{
    "cveId": "CVE-2013-5465",
    "version": "1.0.0",
    "timestamp": "2024-12-10T17:54:04.992951+00:00",
    "description": "IBM Maximo Asset Management 7.x before 7.1.1.7 LAFIX.20140319-0837, 7.1.1.11 before IFIX.20140323-0749, 7.1.1.12 before IFIX.20140321-1336, 7.5.x before 7.5.0.3 IFIX027, and 7.5.0.4 before IFIX011 SmartCloud Control Desk 7.x before 7.5.0.3 and 7.5.1.x before 7.5.1.2 and Tivoli IT Asset Management for IT, Tivoli Service Request Manager, Maximo Service Desk, and Change and Configuration Management Database (CCMDB) 7.x before 7.1.1.7 LAFIX.20140319-0837, 7.1.1.11 before IFIX.20140207-1801, and 7.1.1.12 before IFIX.20140218-1510 do not properly restrict file types during uploads, which allows remote authenticated users to have an unspecified impact via an invalid type.",
    "keyphrases": {
        "rootcause": "do not properly restrict file types during uploads",
        "weakness": "",
        "impact": "unspecified impact",
        "vector": "invalid type",
        "attacker": "remote authenticated users",
        "product": "IBM Maximo Asset Management",
        "version": "7.x before 7.1.1.7 LAFIX.20140319-0837",
        "component": ""
    }
}
