{
    "cveId": "CVE-2021-3044",
    "version": "1.0.0",
    "timestamp": "2024-12-15T20:24:27.876763+00:00",
    "description": "An improper authorization vulnerability in Palo Alto Networks Cortex XSOAR enables a remote unauthenticated attacker with network access to the Cortex XSOAR server to perform unauthorized actions through the REST API. This issue impacts Cortex XSOAR 6.1.0 builds later than 1016923 and earlier than 1271064 Cortex XSOAR 6.2.0 builds earlier than 1271065. This issue does not impact Cortex XSOAR 5.5.0, Cortex XSOAR 6.0.0, Cortex XSOAR 6.0.1, or Cortex XSOAR 6.0.2 versions. All Cortex XSOAR instances hosted by Palo Alto Networks are upgraded to resolve this vulnerability. No additional action is required for these instances.",
    "keyphrases": {
        "rootcause": "improper authorization",
        "weakness": "",
        "impact": "perform unauthorized actions",
        "vector": "network access to the Cortex XSOAR server",
        "attacker": "remote unauthenticated attacker",
        "product": "Palo Alto Networks Cortex XSOAR",
        "version": "6.1.0 builds later than 1016923 and earlier than 1271064, 6.2.0 builds earlier than 1271065",
        "component": "REST API"
    }
}
