{
    "cveId": "CVE-2012-6440",
    "version": "1.0.0",
    "timestamp": "2024-12-10T17:54:04.992951+00:00",
    "description": "The web-server password-authentication functionality in Rockwell Automation EtherNet/IP products 1756-ENBT, 1756-EWEB, 1768-ENBT, and 1768-EWEB communication modules CompactLogix L32E and L35E controllers 1788-ENBT FLEXLogix adapter 1794-AENTR FLEX I/O EtherNet/IP adapter ControlLogix 18 and earlier CompactLogix 18 and earlier GuardLogix 18 and earlier SoftLogix 18 and earlier CompactLogix controllers 19 and earlier SoftLogix controllers 19 and earlier ControlLogix controllers 20 and earlier GuardLogix controllers 20 and earlier and MicroLogix 1100 and 1400 allows man-in-the-middle attackers to conduct replay attacks via HTTP traffic.",
    "keyphrases": {
        "rootcause": "",
        "weakness": "",
        "impact": "conduct replay attacks",
        "vector": "man-in-the-middle attack",
        "attacker": "man-in-the-middle attackers",
        "product": [
            "Rockwell Automation EtherNet/IP products",
            "CompactLogix",
            "ControlLogix",
            "GuardLogix",
            "SoftLogix",
            "MicroLogix"
        ],
        "version": [
            "18 and earlier",
            "19 and earlier",
            "20 and earlier"
        ],
        "component": "web-server password-authentication functionality"
    }
}
