{
    "cveId": "CVE-2018-13404",
    "version": "1.0.0",
    "timestamp": "2024-12-12T22:08:52.294043+00:00",
    "description": "The VerifyPopServerConnection resource in Atlassian Jira before version 7.6.10, from version 7.7.0 before version 7.7.5, from version 7.8.0 before version 7.8.5, from version 7.9.0 before version 7.9.3, from version 7.10.0 before version 7.10.3, from version 7.11.0 before version 7.11.3, from version 7.12.0 before version 7.12.3, and from version 7.13.0 before version 7.13.1 allows remote attackers who have administrator rights to determine the existence of internal hosts & open ports and in some cases obtain service information from internal network resources via a Server Side Request Forgery (SSRF) vulnerability.",
    "keyphrases": {
        "rootcause": "",
        "weakness": "Server Side Request Forgery (SSRF)",
        "impact": [
            "determine the existence of internal hosts & open ports",
            "obtain service information from internal network resources"
        ],
        "vector": "",
        "attacker": "remote attackers who have administrator rights",
        "product": "Atlassian Jira",
        "version": [
            "before version 7.6.10",
            "from version 7.7.0 before version 7.7.5",
            "from version 7.8.0 before version 7.8.5",
            "from version 7.9.0 before version 7.9.3",
            "from version 7.10.0 before version 7.10.3",
            "from version 7.11.0 before version 7.11.3",
            "from version 7.12.0 before version 7.12.3",
            "from version 7.13.0 before version 7.13.1"
        ],
        "component": "VerifyPopServerConnection resource"
    }
}
