{
    "cveId": "CVE-2019-10915",
    "version": "1.0.0",
    "timestamp": "2024-12-12T22:08:52.294043+00:00",
    "description": "A vulnerability has been identified in TIA Administrator (All versions < V1.0 SP1 Upd1). The integrated configuration web application (TIA Administrator) allows to execute certain application commands without proper authentication. The vulnerability could be exploited by an attacker with local access to the affected system. Successful exploitation requires no privileges and no user interaction. An attacker could use the vulnerability to compromise confidentiality and integrity and availability of the affected system. At the time of advisory publication no public exploitation of this security vulnerability was known.",
    "keyphrases": {
        "rootcause": "",
        "weakness": "",
        "impact": [
            "execute certain application commands",
            "compromise confidentiality and integrity and availability"
        ],
        "vector": "",
        "attacker": "attacker with local access",
        "product": "TIA Administrator",
        "version": "All versions < V1.0 SP1 Upd1",
        "component": "integrated configuration web application"
    }
}
