{
  "cveId": "CVE-2024-7250",
  "version": "1.0.0",
  "timestamp": "2024-12-06T11:32:07.789868+00:00",
  "description": "Comodo Internet Security Pro cmdagent Link Following Local Privilege Escalation Vulnerability. This vulnerability allows local attackers to escalate privileges on affected installations of Comodo Internet Security Pro. An attacker must first obtain the ability to execute low-privileged code on the target system in order to exploit this vulnerability. The specific flaw exists within the cmdagent executable. By creating a symbolic link, an attacker can abuse the agent to delete a file. An attacker can leverage this vulnerability to escalate privileges and execute arbitrary code in the context of SYSTEM. Was ZDI-CAN-22829.",
  "keyphrases": {
    "rootcause": "",
    "weakness": [
      "Local Privilege Escalation",
      "Privilege Escalation Vulnerability"
    ],
    "impact": [
      "Privilege Escalation",
      "escalate privileges and execute arbitrary code in the context of SYSTEM"
    ],
    "vector": "creating a symbolic link",
    "attacker": "local attackers",
    "product": "Comodo Internet Security Pro",
    "version": "",
    "component": "cmdagent"
  },
  "mitreTechnicalImpacts": []
}