{
    "cveId": "CVE-2024-7537",
    "version": "1.0.0",
    "timestamp": "2024-12-06T11:32:07.789868+00:00",
    "description": "oFono QMI SMS Handling Out-Of-Bounds Read Information Disclosure Vulnerability. This vulnerability allows local attackers to disclose sensitive information on affected installations of oFono. Authentication is not required to exploit this vulnerability. The specific flaw exists within the processing of SMS message lists. The issue results from the lack of proper validation of user-supplied data, which can result in a read past the end of an allocated buffer. An attacker can leverage this in conjunction with other vulnerabilities to execute arbitrary code in the context of root. Was ZDI-CAN-23157.",
    "keyphrases": {
        "rootcause": "lack of proper validation of user-supplied data",
        "weakness": "Out-Of-Bounds Read",
        "impact": "Information Disclosure",
        "vector": "",
        "attacker": "local attackers",
        "product": "oFono",
        "version": "",
        "component": "QMI SMS Handling"
    }
}
