{
  "cveId": "CVE-2020-9529",
  "version": "1.0.0",
  "timestamp": "2024-12-13T17:34:55.850537+00:00",
  "description": "Firmware developed by Shenzhen Hichip Vision Technology (V6 through V20), as used by many different vendors in millions of Internet of Things devices, suffers from a privilege escalation vulnerability that allows attackers on the local network to reset the devices administrator password. This affects products marketed under the following brand names Accfly, Alptop, Anlink, Besdersec, BOAVISION, COOAU, CPVAN, Ctronics, D3D Security, Dericam, Elex System, Elite Security, ENSTER, ePGes, Escam, FLOUREON, GENBOLT, Hongjingtian (HJT), ICAMI, Iegeek, Jecurity, Jennov, KKMoon, LEFTEK, Loosafe, Luowice, Nesuniq, Nettoly, ProElite, QZT, Royallite, SDETER, SV3C, SY2L, Tenvis, ThinkValue, TOMLOV, TPTEK, WGCC, and ZILINK.",
  "keyphrases": {
    "rootcause": "",
    "weakness": "privilege escalation vulnerability",
    "impact": [
      "privilege escalation",
      "reset the devices administrator password"
    ],
    "vector": "",
    "attacker": "attackers on the local network",
    "product": "Firmware developed by Shenzhen Hichip Vision Technology",
    "version": "V6 through V20",
    "component": ""
  },
  "mitreTechnicalImpacts": []
}