{
    "cveId": "CVE-2020-9409",
    "version": "1.0.0",
    "timestamp": "2024-12-13T17:34:55.850537+00:00",
    "description": "The administrative UI component of TIBCO Software Inc.s TIBCO JasperReports Server, TIBCO JasperReports Server for AWS Marketplace, and TIBCO JasperReports Server for ActiveMatrix BPM contains a vulnerability that theoretically allows an unauthenticated attacker to obtain the permissions of a JasperReports Server superuser for the affected systems. The attacker can theoretically exploit the vulnerability consistently, remotely, and without authenticating. Affected releases are TIBCO Software Inc.s TIBCO JasperReports Server versions 7.1.1 and below, TIBCO JasperReports Server for AWS Marketplace versions 7.1.1 and below, and TIBCO JasperReports Server for ActiveMatrix BPM versions 7.1.1 and below.",
    "keyphrases": {
        "rootcause": "",
        "weakness": "",
        "impact": "obtain the permissions of a JasperReports Server superuser",
        "vector": "",
        "attacker": "unauthenticated attacker",
        "product": [
            "TIBCO JasperReports Server",
            "TIBCO JasperReports Server for AWS Marketplace",
            "TIBCO JasperReports Server for ActiveMatrix BPM"
        ],
        "version": "7.1.1 and below",
        "component": "administrative UI component"
    }
}
