{
    "cveId": "CVE-2020-9414",
    "version": "1.0.0",
    "timestamp": "2024-12-13T17:34:55.850537+00:00",
    "description": "The MFT admin service component of TIBCO Software Inc.s TIBCO Managed File Transfer Command Center and TIBCO Managed File Transfer Internet Server contains a vulnerability that theoretically allows an authenticated user with specific permissions to obtain the session identifier of another user. The session identifier when replayed could provide administrative rights or file transfer permissions to the affected system. Affected releases are TIBCO Software Inc.s TIBCO Managed File Transfer Command Center versions 8.2.1 and below and TIBCO Managed File Transfer Internet Server versions 8.2.1 and below.",
    "keyphrases": {
        "rootcause": "",
        "weakness": "",
        "impact": "obtain the session identifier of another user",
        "vector": "",
        "attacker": "authenticated user with specific permissions",
        "product": [
            "TIBCO Managed File Transfer Command Center",
            "TIBCO Managed File Transfer Internet Server"
        ],
        "version": "8.2.1 and below",
        "component": "MFT admin service component"
    }
}
