{
    "cveId": "CVE-2024-37360",
    "version": "1.0.0",
    "timestamp": "2025-07-04T16:12:41.853043+00:00",
    "description": "Hitachi Vantara Pentaho Business Analytics Server - Improper Neutralization of Input During Web Page Generation (Cross-site Scripting) The software does not neutralize or incorrectly neutralize user-controllable input before it is placed in output that is used as a web page that is served to other users. (CWE-79) Hitachi Vantara Pentaho Business Analytics Server prior to versions 10.2.0.0 and 9.3.0.9, including 8.3.x, allow a malicious URL to inject content into the Analyzer plugin interface. Once the malicious script is injected, the attacker can perform a variety of malicious activities. The attacker could transfer private information, such as cookies that may include session information, from the victims machine to the attacker. The attacker could send malicious requests to a web site on behalf of the victim, which could be especially dangerous to the site if the victim has administrator privileges to manage that site.",
    "keyphrases": {
        "component": "Analyzer plugin interface",
        "rootcause": "Improper Neutralization of Input During Web Page Generation",
        "vector": "malicious URL",
        "weakness": "cross-site scripting",
        "product": "Hitachi Vantara Pentaho Business Analytics Server",
        "impact": "transfer private information, send malicious requests",
        "attacker": "",
        "version": "prior to versions 10.2.0.0 and 9.3.0.9, including 8.3.x"
    }
}
