{
    "cveId": "CVE-2007-5641",
    "version": "1.0.0",
    "timestamp": "2024-12-10T17:54:04.992951+00:00",
    "description": "Multiple PHP remote file inclusion vulnerabilities in PHP Project Management 0.8.10 and earlier allow remote attackers to execute arbitrary PHP code via a URL in the full_path parameter to (1) certinfo/index.php, (2) emails/index.php, (3) events/index.php, (4) fax/index.php, (5) files/index.php, (6) files/list.php, (7) groupadm/index.php, (8) history/index.php, (9) info/index.php, (10) log/index.php, (11) mail/index.php, (12) messages/index.php, (13) organizations/index.php, (14) phones/index.php, (15) presence/index.php, (16) projects/index.php, (17) projects/summary.inc.php, (18) projects/list.php, (19) reports/index.php, (20) search/index.php, (21) snf/index.php, (22) syslog/index.php, (23) tasks/searchsimilar.php, (24) tasks/index.php, (25) tasks/summary.inc.php, and (26) useradm/index.php in modules (27) /ajax/loadsplash.php (28) /blocks/birthday.php (29) /blocks/events.php and (30) /blocks/help.php.",
    "keyphrases": {
        "rootcause": "Multiple PHP remote file inclusion vulnerabilities",
        "weakness": "",
        "impact": "execute arbitrary PHP code",
        "vector": "URL in the full_path parameter",
        "attacker": "remote attackers",
        "product": "PHP Project Management",
        "version": "0.8.10 and earlier",
        "component": [
            "certinfo/index.php",
            "emails/index.php",
            "events/index.php",
            "fax/index.php",
            "files/index.php",
            "files/list.php",
            "groupadm/index.php",
            "history/index.php",
            "info/index.php",
            "log/index.php",
            "mail/index.php",
            "messages/index.php",
            "organizations/index.php",
            "phones/index.php",
            "presence/index.php",
            "projects/index.php",
            "projects/summary.inc.php",
            "projects/list.php",
            "reports/index.php",
            "search/index.php",
            "snf/index.php",
            "syslog/index.php",
            "tasks/searchsimilar.php",
            "tasks/index.php",
            "tasks/summary.inc.php",
            "useradm/index.php",
            "ajax/loadsplash.php",
            "blocks/birthday.php",
            "blocks/events.php",
            "blocks/help.php"
        ]
    }
}
