{
    "cveId": "CVE-2007-5147",
    "version": "1.0.0",
    "timestamp": "2024-12-10T17:54:04.992951+00:00",
    "description": "Multiple PHP remote file inclusion vulnerabilities in Puzzle Apps CMS 2.2.1 allow remote attackers to execute arbitrary PHP code via a URL in the MODULEDIR parameter to (1) core/modules/my/my.module.php or (2) core/modules/xml/xml.module.php the COREROOT parameter to (3) config.loader.php, (4) platform.loader.php, (5) core.loader.php, (6) person.loader.php, or (7) module.loader.php in core/ or (8) install/steps/step_3.php or the THISDIR parameter to (9) people.lib.php, (10) general.lib.php, (11) content.lib.php, or (12) templates.lib.php in core/modules/admin/libs/ or (13) core/modules/webstat/MEC/index.php.",
    "keyphrases": {
        "rootcause": "Multiple PHP remote file inclusion vulnerabilities",
        "weakness": "",
        "impact": "execute arbitrary PHP code",
        "vector": [
            "URL in the MODULEDIR parameter",
            "COREROOT parameter",
            "THISDIR parameter"
        ],
        "attacker": "remote attackers",
        "product": "Puzzle Apps CMS",
        "version": "2.2.1",
        "component": [
            "core/modules/my/my.module.php",
            "core/modules/xml/xml.module.php",
            "config.loader.php",
            "platform.loader.php",
            "core.loader.php",
            "person.loader.php",
            "module.loader.php",
            "install/steps/step_3.php",
            "people.lib.php",
            "general.lib.php",
            "content.lib.php",
            "templates.lib.php",
            "core/modules/webstat/MEC/index.php"
        ]
    }
}
