{
    "cveId": "CVE-2008-0877",
    "version": "1.0.0",
    "timestamp": "2024-12-10T17:54:04.992951+00:00",
    "description": "Multiple cross-site scripting (XSS) vulnerabilities in Jinzora Media Jukebox 2.7.5 allow remote attackers to inject arbitrary web script or HTML via the (1) frontend, (2) set_frontend, (3) jz_path, (4) theme, and (5) set_theme parameters to (a) index.php the frontend, theme, and (6) language parameters to (b) ajax_request.php the jz_path parameter to (c) slim.php the frontend, theme, and jz_path parameters to (d) popup.php the (13) PATH_INFO to index.php and (e) slim.php and the (14) query parameter in a playlistedit action and (15) siteNewsData parameter in a sitenews action to (f) popup.php.",
    "keyphrases": {
        "rootcause": "",
        "weakness": "cross-site scripting",
        "impact": "",
        "vector": [
            "frontend",
            "set_frontend",
            "jz_path",
            "theme",
            "set_theme",
            "language parameters",
            "PATH_INFO to index.php",
            "query parameter in a playlistedit action",
            "siteNewsData parameter in a sitenews action"
        ],
        "attacker": "remote attackers",
        "product": "Jinzora Media Jukebox",
        "version": "2.7.5",
        "component": [
            "index.php",
            "ajax_request.php",
            "slim.php",
            "popup.php"
        ]
    }
}
