{
    "cveId": "CVE-2005-4366",
    "version": "1.0.0",
    "timestamp": "2024-12-10T17:54:04.992951+00:00",
    "description": "Multiple SQL injection vulnerabilities in DRZES HMS 3.2 allow remote attackers to execute arbitrary SQL commands via the (1) plan_id parameter to (a) domains.php, (b) viewusage.php, (c) pop_accounts.php, (d) databases.php, (e) ftp_users.php, (f) crons.php, (g) pass_dirs.php, (h) zone_files.php, (i) htaccess.php, and (j) software.php (2) the customerPlanID parameter to viewplan.php (3) the ref_id parameter to referred_plans.php (4) customerPlanID parameter to listcharges.php and (5) the domain parameter to (k) pop_accounts.php, (d) databases.php, (e) ftp_users.php, (f) crons.php, (g) pass_dirs.php, (h) zone_files.php, (i) htaccess.php, and (j) software.php. NOTE the viewinvoice.php invoiceID vector is already covered by CVE-2005-4137.",
    "keyphrases": {
        "rootcause": "improper input sanitization",
        "weakness": "SQL injection",
        "impact": "execute arbitrary SQL commands",
        "vector": [
            "plan_id parameter",
            "customerPlanID parameter",
            "ref_id parameter",
            "customerPlanID parameter",
            "domain parameter"
        ],
        "attacker": "remote attackers",
        "product": "DRZES HMS",
        "version": "3.2",
        "component": [
            "domains.php",
            "viewusage.php",
            "pop_accounts.php",
            "databases.php",
            "ftp_users.php",
            "crons.php",
            "pass_dirs.php",
            "zone_files.php",
            "htaccess.php",
            "software.php",
            "viewplan.php",
            "referred_plans.php",
            "listcharges.php"
        ]
    }
}
