{
    "cveId": "CVE-2017-6745",
    "version": "1.0.0",
    "timestamp": "2024-12-11T16:08:24.783251+00:00",
    "description": "A vulnerability in the cache server within Cisco Videoscape Distribution Suite (VDS) for Television 3.2(5)ES1 could allow an unauthenticated, remote attacker to cause a denial of service (DoS) condition on a targeted appliance. The vulnerability is due to excessive mapped connections exhausting the allotted resources within the system. An attacker could exploit this vulnerability by sending large amounts of inbound traffic to a device with the intention of overloading certain resources. A successful exploit could cause the device to reload, resulting in a DoS condition. Cisco Bug IDs CSCvc39260.",
    "keyphrases": {
        "rootcause": "",
        "weakness": "",
        "impact": "denial of service (DoS)",
        "vector": "large amounts of inbound traffic",
        "attacker": "unauthenticated, remote attacker",
        "product": "Cisco Videoscape Distribution Suite (VDS) for Television",
        "version": "3.2(5)ES1",
        "component": "cache server"
    }
}
