{
    "cveId": "CVE-2021-1502",
    "version": "1.0.0",
    "timestamp": "2024-12-15T20:24:27.876763+00:00",
    "description": "A vulnerability in Cisco Webex Network Recording Player for Windows and MacOS and Cisco Webex Player for Windows and MacOS could allow an attacker to execute arbitrary code on an affected system. The vulnerability is due to insufficient validation of values within Webex recording files formatted as either Advanced Recording Format (ARF) or Webex Recording Format (WRF). An attacker could exploit the vulnerability by sending a user a malicious ARF or WRF file through a link or email attachment and persuading the user to open the file. A successful exploit could allow the attacker to execute arbitrary code on the affected system with the privileges of the targeted user.",
    "keyphrases": {
        "rootcause": "insufficient validation",
        "weakness": "",
        "impact": "execute arbitrary code",
        "vector": "malicious ARF or WRF file",
        "attacker": "attacker",
        "product": [
            "Cisco Webex Network Recording Player",
            "Cisco Webex Player"
        ],
        "version": "",
        "component": ""
    }
}
