{
    "cveId": "CVE-2021-1144",
    "version": "1.0.0",
    "timestamp": "2024-12-13T17:34:55.850537+00:00",
    "description": "A vulnerability in Cisco Connected Mobile Experiences (CMX) could allow a remote, authenticated attacker without administrative privileges to alter the password of any user on an affected system. The vulnerability is due to incorrect handling of authorization checks for changing a password. An authenticated attacker without administrative privileges could exploit this vulnerability by sending a modified HTTP request to an affected device. A successful exploit could allow the attacker to alter the passwords of any user on the system, including an administrative user, and then impersonate that user.",
    "keyphrases": {
        "rootcause": "incorrect handling of authorization checks for changing a password",
        "weakness": "",
        "impact": [
            "alter the passwords of any user on the system",
            "impersonate that user"
        ],
        "vector": "modified HTTP request",
        "attacker": "remote, authenticated attacker without administrative privileges",
        "product": "Cisco Connected Mobile Experiences",
        "version": "",
        "component": ""
    }
}
