{
    "cveId": "CVE-2021-1993",
    "version": "1.0.0",
    "timestamp": "2024-12-06T11:32:07.789868+00:00",
    "description": "Vulnerability in the Java VM component of Oracle Database Server. Supported versions that are affected are 12.1.0.2, 12.2.0.1, 18c and 19c. Difficult to exploit vulnerability allows low privileged attacker having Create Session privilege with network access via Oracle Net to compromise Java VM. Successful attacks require human interaction from a person other than the attacker. Successful attacks of this vulnerability can result in unauthorized creation, deletion or modification access to critical data or all Java VM accessible data. CVSS 3.1 Base Score 4.8 (Integrity impacts). CVSS Vector (CVSS3.1/AVN/ACH/PRL/UIR/SU/CN/IH/AN).",
    "keyphrases": {
        "rootcause": "",
        "weakness": "",
        "impact": "unauthorized creation, deletion or modification access to critical data or all Java VM accessible data",
        "vector": "",
        "attacker": "low privileged attacker having Create Session privilege with network access via Oracle Net",
        "product": "Oracle Database Server",
        "version": "12.1.0.2, 12.2.0.1, 18c and 19c",
        "component": "Java VM component"
    }
}
