{
  "cveId": "CVE-2020-16921",
  "version": "1.0.0",
  "timestamp": "2024-12-13T17:34:55.850537+00:00",
  "description": "An information disclosure vulnerability exists in Text Services Framework when it fails to properly handle objects in memory. An attacker who successfully exploited this vulnerability could potentially read data that was not intended to be disclosed. Note that this vulnerability would not allow an attacker to execute code or to elevate their user rights directly, but it could be used to obtain information that could be used to try to further compromise the affected system.To exploit this vulnerability, an attacker would have to log on to an affected system and open a specially crafted file.The update addresses the vulnerability by correcting how Text Services Framework handles objects in memory.",
  "keyphrases": {
    "rootcause": "fails to properly handle objects in memory",
    "weakness": "information disclosure vulnerability",
    "impact": [
      "compromise the affected system",
      "execute code",
      "information disclosure",
      "obtain information"
    ],
    "vector": "open a specially crafted file",
    "attacker": "attacker",
    "product": "Text Services Framework",
    "version": "",
    "component": ""
  },
  "mitreTechnicalImpacts": []
}