{
  "cveId": "CVE-2021-2010",
  "version": "1.0.0",
  "timestamp": "2024-12-06T11:32:07.789868+00:00",
  "description": "Vulnerability in the MySQL Client product of Oracle MySQL (component C API). Supported versions that are affected are 5.6.50 and prior, 5.7.32 and prior and 8.0.22 and prior. Difficult to exploit vulnerability allows low privileged attacker with network access via multiple protocols to compromise MySQL Client. Successful attacks of this vulnerability can result in unauthorized update, insert or delete access to some of MySQL Client accessible data and unauthorized ability to cause a partial denial of service (partial DOS) of MySQL Client. CVSS 3.1 Base Score 4.2 (Integrity and Availability impacts). CVSS Vector (CVSS3.1/AVN/ACH/PRL/UIN/SU/CN/IL/AL).",
  "keyphrases": {
    "rootcause": "",
    "weakness": "",
    "impact": [
      "Availability",
      "DOS",
      "denial of service",
      "insert or delete access",
      "unauthorized update"
    ],
    "vector": "multiple protocols",
    "attacker": "low privileged attacker with network access",
    "product": "MySQL Client",
    "version": [
      "5.6.50 and prior",
      "5.7.32 and prior and 8.0.22 and prior"
    ],
    "component": "C API"
  },
  "mitreTechnicalImpacts": []
}