{
    "cveId": "CVE-2021-2000",
    "version": "1.0.0",
    "timestamp": "2024-12-06T11:32:07.789868+00:00",
    "description": "Vulnerability in the Unified Audit component of Oracle Database Server. Supported versions that are affected are 12.1.0.2, 12.2.0.1, 18c and 19c. Easily exploitable vulnerability allows high privileged attacker having SYS Account privilege with network access via Oracle Net to compromise Unified Audit. Successful attacks require human interaction from a person other than the attacker. Successful attacks of this vulnerability can result in unauthorized update, insert or delete access to some of Unified Audit accessible data. CVSS 3.1 Base Score 2.4 (Integrity impacts). CVSS Vector (CVSS3.1/AVN/ACL/PRH/UIR/SU/CN/IL/AN).",
    "keyphrases": {
        "rootcause": "",
        "weakness": "",
        "impact": "unauthorized update, insert or delete access to some of Unified Audit accessible data",
        "vector": "",
        "attacker": "high privileged attacker having SYS Account privilege with network access via Oracle Net",
        "product": "Oracle Database Server",
        "version": "12.1.0.2, 12.2.0.1, 18c and 19c",
        "component": "Unified Audit component"
    }
}
