{
    "cveId": "CVE-2021-2005",
    "version": "1.0.0",
    "timestamp": "2024-12-06T11:32:07.789868+00:00",
    "description": "Vulnerability in the Oracle Business Intelligence Enterprise Edition product of Oracle Fusion Middleware (component BI Platform Security). Supported versions that are affected are 12.2.1.3.0 and 12.2.1.4.0. Easily exploitable vulnerability allows unauthenticated attacker with network access via HTTP to compromise Oracle Business Intelligence Enterprise Edition. Successful attacks require human interaction from a person other than the attacker and while the vulnerability is in Oracle Business Intelligence Enterprise Edition, attacks may significantly impact additional products. Successful attacks of this vulnerability can result in unauthorized read access to a subset of Oracle Business Intelligence Enterprise Edition accessible data. CVSS 3.1 Base Score 4.7 (Confidentiality impacts). CVSS Vector (CVSS3.1/AVN/ACL/PRN/UIR/SC/CL/IN/AN).",
    "keyphrases": {
        "rootcause": "",
        "weakness": "",
        "impact": "unauthorized read access",
        "vector": "network access via HTTP",
        "attacker": "unauthenticated attacker",
        "product": "Oracle Business Intelligence Enterprise Edition",
        "version": "12.2.1.3.0 and 12.2.1.4.0",
        "component": "BI Platform Security"
    }
}
