{
  "cveId": "CVE-2021-2041",
  "version": "1.0.0",
  "timestamp": "2024-12-06T11:32:07.789868+00:00",
  "description": "Vulnerability in the Oracle Business Intelligence Enterprise Edition product of Oracle Fusion Middleware (component Installation). Supported versions that are affected are 12.2.1.3.0 and 12.2.1.4.0. Difficult to exploit vulnerability allows unauthenticated attacker with network access via HTTP to compromise Oracle Business Intelligence Enterprise Edition. Successful attacks of this vulnerability can result in takeover of Oracle Business Intelligence Enterprise Edition. CVSS 3.1 Base Score 8.1 (Confidentiality, Integrity and Availability impacts). CVSS Vector (CVSS3.1/AVN/ACH/PRN/UIN/SU/CH/IH/AH).",
  "keyphrases": {
    "rootcause": "",
    "weakness": "",
    "impact": [
      "Integrity and Availability impacts",
      "takeover of Oracle Business Intelligence Enterprise Edition"
    ],
    "vector": "network access via HTTP",
    "attacker": "unauthenticated attacker",
    "product": "Oracle Business Intelligence Enterprise Edition",
    "version": "12.2.1.3.0 and 12.2.1.4.0",
    "component": "Installation"
  },
  "mitreTechnicalImpacts": []
}