{
    "cveId": "CVE-2021-2256",
    "version": "1.0.0",
    "timestamp": "2024-12-06T11:32:07.789868+00:00",
    "description": "Vulnerability in the Oracle Storage Cloud Software Appliance product of Oracle Storage Gateway (component Management Console). The supported version that is affected is Prior to 16.3.1.4.2. Easily exploitable vulnerability allows unauthenticated attacker with network access via HTTP to compromise Oracle Storage Cloud Software Appliance. While the vulnerability is in Oracle Storage Cloud Software Appliance, attacks may significantly impact additional products. Successful attacks of this vulnerability can result in takeover of Oracle Storage Cloud Software Appliance. Note Updating the Oracle Storage Cloud Software Appliance to version 16.3.1.4.2 or later will address these vulnerabilities. Download the latest version of Oracle Storage Cloud Software Appliance from here. Refer to Document 2768897.1 for more details. CVSS 3.1 Base Score 10.0 (Confidentiality, Integrity and Availability impacts). CVSS Vector (CVSS3.1/AVN/ACL/PRN/UIN/SC/CH/IH/AH).",
    "keyphrases": {
        "rootcause": "",
        "weakness": "",
        "impact": "takeover of Oracle Storage Cloud Software Appliance",
        "vector": "unauthenticated attacker with network access via HTTP",
        "attacker": "unauthenticated attacker",
        "product": "Oracle Storage Cloud Software Appliance",
        "version": "Prior to 16.3.1.4.2",
        "component": "Management Console"
    }
}
