{
    "cveId": "CVE-2021-2311",
    "version": "1.0.0",
    "timestamp": "2024-12-06T11:32:07.789868+00:00",
    "description": "Vulnerability in the Oracle Hospitality Inventory Management product of Oracle Food and Beverage Applications (component Export to Reporting and Analytics). The supported version that is affected is 9.1.0. Easily exploitable vulnerability allows low privileged attacker with network access via HTTP to compromise Oracle Hospitality Inventory Management. Successful attacks of this vulnerability can result in unauthorized access to critical data or complete access to all Oracle Hospitality Inventory Management accessible data. CVSS 3.1 Base Score 6.5 (Confidentiality impacts). CVSS Vector (CVSS3.1/AVN/ACL/PRL/UIN/SU/CH/IN/AN).",
    "keyphrases": {
        "rootcause": "",
        "weakness": "",
        "impact": [
            "unauthorized access to critical data",
            "complete access to all Oracle Hospitality Inventory Management accessible data"
        ],
        "vector": "",
        "attacker": "low privileged attacker with network access via HTTP",
        "product": "Oracle Hospitality Inventory Management",
        "version": "9.1.0",
        "component": "Export to Reporting and Analytics"
    }
}
