{
    "cveId": "CVE-2021-2348",
    "version": "1.0.0",
    "timestamp": "2024-12-06T11:32:07.789868+00:00",
    "description": "Vulnerability in the Oracle Commerce Guided Search / Oracle Commerce Experience Manager product of Oracle Commerce (component Tools and Frameworks). The supported version that is affected is 11.3.1.5. Easily exploitable vulnerability allows low privileged attacker with network access via HTTP to compromise Oracle Commerce Guided Search / Oracle Commerce Experience Manager. Successful attacks of this vulnerability can result in unauthorized read access to a subset of Oracle Commerce Guided Search / Oracle Commerce Experience Manager accessible data. CVSS 3.1 Base Score 4.3 (Confidentiality impacts). CVSS Vector (CVSS3.1/AVN/ACL/PRL/UIN/SU/CL/IN/AN).",
    "keyphrases": {
        "rootcause": "",
        "weakness": "",
        "impact": "unauthorized read access",
        "vector": "",
        "attacker": "low privileged attacker",
        "product": "Oracle Commerce",
        "version": "11.3.1.5",
        "component": "Tools and Frameworks"
    }
}
