{
    "cveId": "CVE-2021-2153",
    "version": "1.0.0",
    "timestamp": "2024-12-06T11:32:07.789868+00:00",
    "description": "Vulnerability in the Oracle Internet Expenses product of Oracle E-Business Suite (component Mobile Expenses). Supported versions that are affected are 12.2.3-12.2.10. Easily exploitable vulnerability allows unauthenticated attacker with network access via HTTP to compromise Oracle Internet Expenses. Successful attacks require human interaction from a person other than the attacker. Successful attacks of this vulnerability can result in unauthorized update, insert or delete access to some of Oracle Internet Expenses accessible data. CVSS 3.1 Base Score 4.3 (Integrity impacts). CVSS Vector (CVSS3.1/AVN/ACL/PRN/UIR/SU/CN/IL/AN).",
    "keyphrases": {
        "rootcause": "",
        "weakness": "",
        "impact": "unauthorized update, insert or delete access to some of Oracle Internet Expenses accessible data",
        "vector": "",
        "attacker": "unauthenticated attacker with network access via HTTP",
        "product": "Oracle Internet Expenses",
        "version": "12.2.3-12.2.10",
        "component": "Mobile Expenses"
    }
}
