{
    "cveId": "CVE-2021-2406",
    "version": "1.0.0",
    "timestamp": "2024-12-18T22:42:50.929578+00:00",
    "description": "Vulnerability in the Oracle Collaborative Planning product of Oracle E-Business Suite (component User Interface). Supported versions that are affected are 12.1.1-12.1.3. Easily exploitable vulnerability allows low privileged attacker with network access via HTTP to compromise Oracle Collaborative Planning. Successful attacks of this vulnerability can result in unauthorized creation, deletion or modification access to critical data or all Oracle Collaborative Planning accessible data as well as unauthorized access to critical data or complete access to all Oracle Collaborative Planning accessible data. CVSS 3.1 Base Score 8.1 (Confidentiality and Integrity impacts). CVSS Vector (CVSS3.1/AVN/ACL/PRL/UIN/SU/CH/IH/AN).",
    "keyphrases": {
        "rootcause": "",
        "weakness": "",
        "impact": [
            "unauthorized creation",
            "deletion or modification access to critical data",
            "unauthorized access to critical data"
        ],
        "vector": "",
        "attacker": "low privileged attacker",
        "product": "Oracle Collaborative Planning product of Oracle E-Business Suite",
        "version": "12.1.1-12.1.3",
        "component": "User Interface"
    }
}
