{
    "cveId": "CVE-2021-2338",
    "version": "1.0.0",
    "timestamp": "2024-12-06T11:32:07.789868+00:00",
    "description": "Vulnerability in the Siebel Apps - Marketing product of Oracle Siebel CRM (component Email Marketing Stand-Alone). Supported versions that are affected are 21.5 and Prior. Easily exploitable vulnerability allows unauthenticated attacker with network access via HTTP to compromise Siebel Apps - Marketing. Successful attacks require human interaction from a person other than the attacker and while the vulnerability is in Siebel Apps - Marketing, attacks may significantly impact additional products. Successful attacks of this vulnerability can result in unauthorized update, insert or delete access to some of Siebel Apps - Marketing accessible data as well as unauthorized read access to a subset of Siebel Apps - Marketing accessible data. CVSS 3.1 Base Score 6.1 (Confidentiality and Integrity impacts). CVSS Vector (CVSS3.1/AVN/ACL/PRN/UIR/SC/CL/IL/AN).",
    "keyphrases": {
        "rootcause": "",
        "weakness": "",
        "impact": "unauthorized update, insert or delete access to some of Siebel Apps - Marketing accessible data as well as unauthorized read access to a subset of Siebel Apps - Marketing accessible data",
        "vector": "unauthenticated attacker with network access via HTTP",
        "attacker": "unauthenticated attacker",
        "product": "Siebel Apps - Marketing product of Oracle Siebel CRM",
        "version": "21.5 and Prior",
        "component": "Email Marketing Stand-Alone"
    }
}
