{
    "cveId": "CVE-2021-2462",
    "version": "1.0.0",
    "timestamp": "2024-12-06T11:32:07.789868+00:00",
    "description": "Vulnerability in the Oracle Commerce Service Center product of Oracle Commerce (component Commerce Service Center). Supported versions that are affected are 11.0.0, 11.1.0, 11.2.0 and 11.3.0-11.3.2. Easily exploitable vulnerability allows unauthenticated attacker with network access via HTTP to compromise Oracle Commerce Service Center. Successful attacks require human interaction from a person other than the attacker and while the vulnerability is in Oracle Commerce Service Center, attacks may significantly impact additional products. Successful attacks of this vulnerability can result in unauthorized update, insert or delete access to some of Oracle Commerce Service Center accessible data as well as unauthorized read access to a subset of Oracle Commerce Service Center accessible data. CVSS 3.1 Base Score 6.1 (Confidentiality and Integrity impacts). CVSS Vector (CVSS3.1/AVN/ACL/PRN/UIR/SC/CL/IL/AN).",
    "keyphrases": {
        "rootcause": "",
        "weakness": "",
        "impact": "unauthorized update, insert or delete access",
        "vector": "unauthenticated network access via HTTP",
        "attacker": "unauthenticated attacker",
        "product": "Oracle Commerce",
        "version": "11.0.0, 11.1.0, 11.2.0 and 11.3.0-11.3.2",
        "component": "Commerce Service Center"
    }
}
