{
    "cveId": "CVE-2021-2312",
    "version": "1.0.0",
    "timestamp": "2024-12-06T11:32:07.789868+00:00",
    "description": "Vulnerability in the Oracle VM VirtualBox product of Oracle Virtualization (component Core). The supported version that is affected is Prior to 6.1.20. Easily exploitable vulnerability allows high privileged attacker with logon to the infrastructure where Oracle VM VirtualBox executes to compromise Oracle VM VirtualBox. Successful attacks of this vulnerability can result in unauthorized ability to cause a hang or frequently repeatable crash (complete DOS) of Oracle VM VirtualBox. Note This vulnerability applies to Windows systems only. CVSS 3.1 Base Score 4.4 (Availability impacts). CVSS Vector (CVSS3.1/AVL/ACL/PRH/UIN/SU/CN/IN/AH).",
    "keyphrases": {
        "rootcause": "",
        "weakness": "",
        "impact": "cause a hang or frequently repeatable crash (complete DOS) of Oracle VM VirtualBox",
        "vector": "",
        "attacker": "high privileged attacker",
        "product": "Oracle VM VirtualBox",
        "version": "Prior to 6.1.20",
        "component": "Core"
    }
}
