{
    "cveId": "CVE-2021-2416",
    "version": "1.0.0",
    "timestamp": "2024-12-06T11:32:07.789868+00:00",
    "description": "Vulnerability in the Oracle Communications Session Border Controller product of Oracle Communications (component Routing). Supported versions that are affected are 8.4 and 9.0. Easily exploitable vulnerability allows high privileged attacker with network access via HTTP to compromise Oracle Communications Session Border Controller. Successful attacks of this vulnerability can result in unauthorized ability to cause a hang or frequently repeatable crash (complete DOS) of Oracle Communications Session Border Controller. CVSS 3.1 Base Score 4.9 (Availability impacts). CVSS Vector (CVSS3.1/AVN/ACL/PRH/UIN/SU/CN/IN/AH).",
    "keyphrases": {
        "rootcause": "",
        "weakness": "",
        "impact": "hang or frequently repeatable crash (complete DOS)",
        "vector": "",
        "attacker": "high privileged attacker with network access via HTTP",
        "product": "Oracle Communications Session Border Controller",
        "version": "8.4 and 9.0",
        "component": "Routing"
    }
}
