{
    "cveId": "CVE-2021-2257",
    "version": "1.0.0",
    "timestamp": "2024-12-06T11:32:07.789868+00:00",
    "description": "Vulnerability in the Oracle Storage Cloud Software Appliance product of Oracle Storage Gateway (component Management Console). The supported version that is affected is Prior to 16.3.1.4.2. Easily exploitable vulnerability allows high privileged attacker with network access via HTTP to compromise Oracle Storage Cloud Software Appliance. While the vulnerability is in Oracle Storage Cloud Software Appliance, attacks may significantly impact additional products. Successful attacks of this vulnerability can result in unauthorized read access to a subset of Oracle Storage Cloud Software Appliance accessible data. Note Updating the Oracle Storage Cloud Software Appliance to version 16.3.1.4.2 or later will address these vulnerabilities. Download the latest version of Oracle Storage Cloud Software Appliance from here. Refer to Document 2768897.1 for more details. CVSS 3.1 Base Score 4.1 (Confidentiality impacts). CVSS Vector (CVSS3.1/AVN/ACL/PRH/UIN/SC/CL/IN/AN).",
    "keyphrases": {
        "rootcause": "",
        "weakness": "",
        "impact": "unauthorized read access",
        "vector": "high privileged attacker with network access via HTTP",
        "attacker": "",
        "product": "Oracle Storage Cloud Software Appliance",
        "version": "Prior to 16.3.1.4.2",
        "component": "Management Console"
    }
}
