{
  "cveId": "CVE-2021-2034",
  "version": "1.0.0",
  "timestamp": "2024-12-06T11:32:07.789868+00:00",
  "description": "Vulnerability in the Oracle Common Applications Calendar product of Oracle E-Business Suite (component Tasks). Supported versions that are affected are 12.1.1-12.1.3. Easily exploitable vulnerability allows unauthenticated attacker with network access via HTTP to compromise Oracle Common Applications Calendar. Successful attacks require human interaction from a person other than the attacker and while the vulnerability is in Oracle Common Applications Calendar, attacks may significantly impact additional products. Successful attacks of this vulnerability can result in unauthorized access to critical data or complete access to all Oracle Common Applications Calendar accessible data as well as unauthorized update, insert or delete access to some of Oracle Common Applications Calendar accessible data. CVSS 3.1 Base Score 8.2 (Confidentiality and Integrity impacts). CVSS Vector (CVSS3.1/AVN/ACL/PRN/UIR/SC/CH/IL/AN).",
  "keyphrases": {
    "rootcause": "",
    "weakness": "",
    "impact": [
      "Integrity",
      "complete access to all Oracle Common Applications Calendar accessible data",
      "insert or delete access",
      "unauthorized access to critical data",
      "unauthorized update"
    ],
    "vector": "",
    "attacker": "unauthenticated attacker with network access via HTTP",
    "product": "Oracle Common Applications Calendar",
    "version": "12.1.1-12.1.3",
    "component": "Tasks"
  },
  "mitreTechnicalImpacts": []
}