{
  "cveId": "CVE-2021-2445",
  "version": "1.0.0",
  "timestamp": "2024-12-06T11:32:07.789868+00:00",
  "description": "Vulnerability in the Hyperion Infrastructure Technology product of Oracle Hyperion (component Lifecycle Management). The supported version that is affected is 11.2.5.0. Difficult to exploit vulnerability allows high privileged attacker with network access via HTTP to compromise Hyperion Infrastructure Technology. Successful attacks require human interaction from a person other than the attacker. Successful attacks of this vulnerability can result in unauthorized creation, deletion or modification access to critical data or all Hyperion Infrastructure Technology accessible data as well as unauthorized access to critical data or complete access to all Hyperion Infrastructure Technology accessible data. CVSS 3.1 Base Score 5.7 (Confidentiality and Integrity impacts). CVSS Vector (CVSS3.1/AVN/ACH/PRH/UIR/SU/CH/IH/AN).",
  "keyphrases": {
    "rootcause": "",
    "weakness": "",
    "impact": [
      "Integrity",
      "deletion or modification access to critical data",
      "unauthorized access to critical data",
      "unauthorized creation"
    ],
    "vector": "",
    "attacker": "high privileged attacker with network access via HTTP",
    "product": "Oracle Hyperion",
    "version": "11.2.5.0",
    "component": "Lifecycle Management"
  },
  "mitreTechnicalImpacts": []
}