{
    "cveId": "CVE-2021-2161",
    "version": "1.0.0",
    "timestamp": "2024-12-06T11:32:07.789868+00:00",
    "description": "Vulnerability in the Java SE, Java SE Embedded, Oracle GraalVM Enterprise Edition product of Oracle Java SE (component Libraries). Supported versions that are affected are Java SE 7u291, 8u281, 11.0.10, 16 Java SE Embedded 8u281 Oracle GraalVM Enterprise Edition 19.3.5, 20.3.1.2 and 21.0.0.2. Difficult to exploit vulnerability allows unauthenticated attacker with network access via multiple protocols to compromise Java SE, Java SE Embedded, Oracle GraalVM Enterprise Edition. Successful attacks of this vulnerability can result in unauthorized creation, deletion or modification access to critical data or all Java SE, Java SE Embedded, Oracle GraalVM Enterprise Edition accessible data. Note This vulnerability applies to Java deployments that load and run untrusted code (e.g., code that comes from the internet) and rely on the Java sandbox for security. It can also be exploited by supplying untrusted data to APIs in the specified Component. CVSS 3.1 Base Score 5.9 (Integrity impacts). CVSS Vector (CVSS3.1/AVN/ACH/PRN/UIN/SU/CN/IH/AN).",
    "keyphrases": {
        "rootcause": "",
        "weakness": "",
        "impact": "unauthorized creation, deletion or modification access to critical data or all Java SE, Java SE Embedded, Oracle GraalVM Enterprise Edition accessible data",
        "vector": "multiple protocols",
        "attacker": "unauthenticated attacker with network access",
        "product": "Oracle Java SE, Java SE Embedded, Oracle GraalVM Enterprise Edition",
        "version": "Java SE 7u291, 8u281, 11.0.10, 16 Java SE Embedded 8u281 Oracle GraalVM Enterprise Edition 19.3.5, 20.3.1.2 and 21.0.0.2",
        "component": "Libraries"
    }
}
