{
  "cveId": "CVE-2021-2356",
  "version": "1.0.0",
  "timestamp": "2024-12-06T11:32:07.789868+00:00",
  "description": "Vulnerability in the MySQL Server product of Oracle MySQL (component Server Replication). Supported versions that are affected are 5.7.34 and prior and 8.0.25 and prior. Difficult to exploit vulnerability allows low privileged attacker with network access via multiple protocols to compromise MySQL Server. Successful attacks of this vulnerability can result in unauthorized ability to cause a hang or frequently repeatable crash (complete DOS) of MySQL Server as well as unauthorized update, insert or delete access to some of MySQL Server accessible data. CVSS 3.1 Base Score 5.9 (Integrity and Availability impacts). CVSS Vector (CVSS3.1/AVN/ACH/PRL/UIN/SU/CN/IL/AH).",
  "keyphrases": {
    "rootcause": "",
    "weakness": "",
    "impact": [
      "Availability",
      "cause a hang or frequently repeatable crash (complete DOS) of MySQL Server as well as unauthorized update",
      "insert or delete access to some of MySQL Server accessible data"
    ],
    "vector": "multiple protocols",
    "attacker": "low privileged attacker with network access",
    "product": "MySQL Server",
    "version": "5.7.34 and prior and 8.0.25 and prior",
    "component": "Server Replication"
  },
  "mitreTechnicalImpacts": []
}