{
    "cveId": "CVE-2021-2432",
    "version": "1.0.0",
    "timestamp": "2024-12-06T11:32:07.789868+00:00",
    "description": "Vulnerability in the Java SE product of Oracle Java SE (component JNDI). The supported version that is affected is Java SE 7u301. Difficult to exploit vulnerability allows unauthenticated attacker with network access via multiple protocols to compromise Java SE. Successful attacks of this vulnerability can result in unauthorized ability to cause a partial denial of service (partial DOS) of Java SE. Note This vulnerability applies to Java deployments, typically in clients running sandboxed Java Web Start applications or sandboxed Java applets, that load and run untrusted code (e.g., code that comes from the internet) and rely on the Java sandbox for security. This vulnerability can also be exploited by using APIs in the specified Component, e.g., through a web service which supplies data to the APIs. CVSS 3.1 Base Score 3.7 (Availability impacts). CVSS Vector (CVSS3.1/AVN/ACH/PRN/UIN/SU/CN/IN/AL).",
    "keyphrases": {
        "rootcause": "",
        "weakness": "",
        "impact": "partial denial of service (partial DOS)",
        "vector": "multiple protocols",
        "attacker": "unauthenticated attacker with network access",
        "product": "Oracle Java SE",
        "version": "Java SE 7u301",
        "component": "JNDI"
    }
}
