{
  "cveId": "CVE-2021-2219",
  "version": "1.0.0",
  "timestamp": "2024-12-06T11:32:07.789868+00:00",
  "description": "Vulnerability in the PeopleSoft Enterprise PeopleTools product of Oracle PeopleSoft (component SQR). Supported versions that are affected are 8.56, 8.57 and 8.58. Easily exploitable vulnerability allows low privileged attacker with network access via HTTP to compromise PeopleSoft Enterprise PeopleTools. While the vulnerability is in PeopleSoft Enterprise PeopleTools, attacks may significantly impact additional products. Successful attacks of this vulnerability can result in unauthorized update, insert or delete access to some of PeopleSoft Enterprise PeopleTools accessible data as well as unauthorized read access to a subset of PeopleSoft Enterprise PeopleTools accessible data and unauthorized ability to cause a partial denial of service (partial DOS) of PeopleSoft Enterprise PeopleTools. CVSS 3.1 Base Score 7.4 (Confidentiality, Integrity and Availability impacts). CVSS Vector (CVSS3.1/AVN/ACL/PRL/UIN/SC/CL/IL/AL).",
  "keyphrases": {
    "rootcause": "",
    "weakness": "",
    "impact": [
      "DOS",
      "Integrity and Availability impacts",
      "insert or delete access to some of PeopleSoft Enterprise PeopleTools accessible data as well as unauthorized read access to a subset of PeopleSoft Enterprise PeopleTools accessible data",
      "partial denial of service",
      "unauthorized update"
    ],
    "vector": "network access via HTTP",
    "attacker": "low privileged attacker",
    "product": "PeopleSoft Enterprise PeopleTools",
    "version": [
      "8.56",
      "8.57 and 8.58"
    ],
    "component": "SQR"
  },
  "mitreTechnicalImpacts": []
}