{
  "cveId": "CVE-2021-2443",
  "version": "1.0.0",
  "timestamp": "2024-12-06T11:32:07.789868+00:00",
  "description": "Vulnerability in the Oracle VM VirtualBox product of Oracle Virtualization (component Core). The supported version that is affected is Prior to 6.1.24. Easily exploitable vulnerability allows high privileged attacker with logon to the infrastructure where Oracle VM VirtualBox executes to compromise Oracle VM VirtualBox. While the vulnerability is in Oracle VM VirtualBox, attacks may significantly impact additional products. Successful attacks of this vulnerability can result in unauthorized ability to cause a hang or frequently repeatable crash (complete DOS) of Oracle VM VirtualBox as well as unauthorized update, insert or delete access to some of Oracle VM VirtualBox accessible data and unauthorized read access to a subset of Oracle VM VirtualBox accessible data. Note This vulnerability applies to Solaris x86 and Linux systems only. CVSS 3.1 Base Score 7.3 (Confidentiality, Integrity and Availability impacts). CVSS Vector (CVSS3.1/AVL/ACL/PRH/UIN/SC/CL/IL/AH).",
  "keyphrases": {
    "rootcause": "",
    "weakness": "",
    "impact": [
      "Integrity and Availability impacts",
      "cause a hang or frequently repeatable crash (complete DOS) of Oracle VM VirtualBox",
      "insert or delete access to some of Oracle VM VirtualBox accessible data",
      "unauthorized read access to a subset of Oracle VM VirtualBox accessible data",
      "unauthorized update"
    ],
    "vector": "",
    "attacker": "high privileged attacker",
    "product": "Oracle VM VirtualBox",
    "version": "Prior to 6.1.24",
    "component": "Core"
  },
  "mitreTechnicalImpacts": []
}