{
    "cveId": "CVE-2021-2414",
    "version": "1.0.0",
    "timestamp": "2024-12-06T11:32:07.789868+00:00",
    "description": "Vulnerability in the Oracle Communications Session Border Controller product of Oracle Communications (component Routing). Supported versions that are affected are 8.4 and 9.0. Easily exploitable vulnerability allows high privileged attacker with network access via HTTP to compromise Oracle Communications Session Border Controller. While the vulnerability is in Oracle Communications Session Border Controller, attacks may significantly impact additional products. Successful attacks of this vulnerability can result in unauthorized access to critical data or complete access to all Oracle Communications Session Border Controller accessible data. CVSS 3.1 Base Score 6.8 (Confidentiality impacts). CVSS Vector (CVSS3.1/AVN/ACL/PRH/UIN/SC/CH/IN/AN).",
    "keyphrases": {
        "rootcause": "",
        "weakness": "",
        "impact": "unauthorized access to critical data or complete access to all Oracle Communications Session Border Controller accessible data",
        "vector": "",
        "attacker": "high privileged attacker with network access via HTTP",
        "product": "Oracle Communications Session Border Controller",
        "version": "8.4 and 9.0",
        "component": "Routing"
    }
}
