{
  "cveId": "CVE-2021-2008",
  "version": "1.0.0",
  "timestamp": "2024-12-06T11:32:07.789868+00:00",
  "description": "Vulnerability in the Enterprise Manager for Fusion Middleware product of Oracle Enterprise Manager (component FMW Control Plugin). The supported version that is affected are 11.1.1.9 and 12.2.1.3 Easily exploitable vulnerability allows unauthenticated attacker with network access via HTTP to compromise Enterprise Manager for Fusion Middleware. Successful attacks of this vulnerability can result in unauthorized update, insert or delete access to some of Enterprise Manager for Fusion Middleware accessible data as well as unauthorized read access to a subset of Enterprise Manager for Fusion Middleware accessible data and unauthorized ability to cause a partial denial of service (partial DOS) of Enterprise Manager for Fusion Middleware. CVSS 3.1 Base Score 7.3 (Confidentiality, Integrity and Availability impacts). CVSS Vector (CVSS3.1/AVN/ACL/PRN/UIN/SU/CL/IL/AL).",
  "keyphrases": {
    "rootcause": "",
    "weakness": "",
    "impact": [
      "DOS",
      "Integrity and Availability impacts",
      "insert or delete access",
      "partial denial of service",
      "unauthorized read access",
      "unauthorized update"
    ],
    "vector": "",
    "attacker": "unauthenticated attacker with network access via HTTP",
    "product": "Enterprise Manager for Fusion Middleware",
    "version": "11.1.1.9 and 12.2.1.3",
    "component": "FMW Control Plugin"
  },
  "mitreTechnicalImpacts": []
}