{
    "cveId": "CVE-2021-2335",
    "version": "1.0.0",
    "timestamp": "2024-12-06T11:32:07.789868+00:00",
    "description": "Vulnerability in the Oracle Database - Enterprise Edition Data Redaction component of Oracle Database Server. Supported versions that are affected are 12.1.0.2, 12.2.0.1 and 19c. Easily exploitable vulnerability allows low privileged attacker having Create Session privilege with network access via Oracle Net to compromise Oracle Database - Enterprise Edition Data Redaction. Successful attacks require human interaction from a person other than the attacker. Successful attacks of this vulnerability can result in unauthorized update, insert or delete access to some of Oracle Database - Enterprise Edition Data Redaction accessible data. CVSS 3.1 Base Score 3.5 (Integrity impacts). CVSS Vector (CVSS3.1/AVN/ACL/PRL/UIR/SU/CN/IL/AN).",
    "keyphrases": {
        "rootcause": "",
        "weakness": "",
        "impact": "unauthorized update, insert or delete access",
        "vector": "Oracle Net",
        "attacker": "low privileged attacker",
        "product": "Oracle Database - Enterprise Edition",
        "version": "12.1.0.2, 12.2.0.1 and 19c",
        "component": "Data Redaction"
    }
}
