{
    "cveId": "CVE-2021-2159",
    "version": "1.0.0",
    "timestamp": "2024-12-06T11:32:07.789868+00:00",
    "description": "Vulnerability in the PeopleSoft Enterprise CS Campus Community product of Oracle PeopleSoft (component Frameworks). The supported version that is affected is 9.2. Easily exploitable vulnerability allows low privileged attacker with network access via HTTP to compromise PeopleSoft Enterprise CS Campus Community. Successful attacks require human interaction from a person other than the attacker. Successful attacks of this vulnerability can result in unauthorized read access to a subset of PeopleSoft Enterprise CS Campus Community accessible data. CVSS 3.1 Base Score 3.5 (Confidentiality impacts). CVSS Vector (CVSS3.1/AVN/ACL/PRL/UIR/SU/CL/IN/AN).",
    "keyphrases": {
        "rootcause": "",
        "weakness": "",
        "impact": "unauthorized read access",
        "vector": "",
        "attacker": "low privileged attacker",
        "product": "Oracle PeopleSoft",
        "version": "9.2",
        "component": "Frameworks"
    }
}
