{
    "cveId": "CVE-2021-2040",
    "version": "1.0.0",
    "timestamp": "2024-12-06T11:32:07.789868+00:00",
    "description": "Vulnerability in the Oracle Argus Safety product of Oracle Health Sciences Applications (component Case Form, Local Affiliate Form). The supported version that is affected is 8.2.2. Easily exploitable vulnerability allows unauthenticated attacker with network access via HTTP to compromise Oracle Argus Safety. Successful attacks require human interaction from a person other than the attacker and while the vulnerability is in Oracle Argus Safety, attacks may significantly impact additional products. Successful attacks of this vulnerability can result in unauthorized update, insert or delete access to some of Oracle Argus Safety accessible data as well as unauthorized read access to a subset of Oracle Argus Safety accessible data. CVSS 3.1 Base Score 6.1 (Confidentiality and Integrity impacts). CVSS Vector (CVSS3.1/AVN/ACL/PRN/UIR/SC/CL/IL/AN).",
    "keyphrases": {
        "rootcause": "",
        "weakness": "",
        "impact": "unauthorized update, insert or delete access",
        "vector": "network access via HTTP",
        "attacker": "unauthenticated attacker",
        "product": "Oracle Argus Safety",
        "version": "8.2.2",
        "component": "Case Form, Local Affiliate Form"
    }
}
