{
  "cveId": "CVE-2021-2366",
  "version": "1.0.0",
  "timestamp": "2024-12-06T11:32:07.789868+00:00",
  "description": "Vulnerability in the Primavera P6 Enterprise Project Portfolio Management product of Oracle Construction and Engineering (component Web Access). Supported versions that are affected are 17.12.0-17.12.20, 18.8.0-18.8.23, 19.12.0-19.12.14 and 20.12.0-20.12.3. Easily exploitable vulnerability allows low privileged attacker with network access via HTTP to compromise Primavera P6 Enterprise Project Portfolio Management. While the vulnerability is in Primavera P6 Enterprise Project Portfolio Management, attacks may significantly impact additional products. Successful attacks of this vulnerability can result in unauthorized update, insert or delete access to some of Primavera P6 Enterprise Project Portfolio Management accessible data as well as unauthorized read access to a subset of Primavera P6 Enterprise Project Portfolio Management accessible data. CVSS 3.1 Base Score 6.4 (Confidentiality and Integrity impacts). CVSS Vector (CVSS3.1/AVN/ACL/PRL/UIN/SC/CL/IL/AN).",
  "keyphrases": {
    "rootcause": "",
    "weakness": "",
    "impact": [
      "Integrity",
      "insert or delete access",
      "unauthorized read access",
      "unauthorized update"
    ],
    "vector": "low privileged attacker with network access via HTTP",
    "attacker": "",
    "product": "Primavera P6 Enterprise Project Portfolio Management",
    "version": [
      "17.12.0-17.12.20",
      "18.8.0-18.8.23",
      "19.12.0-19.12.14 and 20.12.0-20.12.3"
    ],
    "component": "Web Access"
  },
  "mitreTechnicalImpacts": []
}