{
    "cveId": "CVE-2017-16776",
    "version": "1.0.0",
    "timestamp": "2024-12-11T16:08:24.783251+00:00",
    "description": "Security researchers discovered an authentication bypass vulnerability in version 2.0.2 of the Conserus Workflow Intelligence application by McKesson Medical Imaging Company, which is now a Change Healthcare company. The attacker must send a malicious HTTP GET request to exploit the vulnerability. The vulnerability allows an attacker to bypass authentication and escalate privileges of valid users. An unauthenticated attacker can exploit the vulnerability and be granted limited access to other accounts. An authenticated attacker can exploit the vulnerability and be granted access reserved for higher privilege users.",
    "keyphrases": {
        "rootcause": "",
        "weakness": "authentication bypass",
        "impact": [
            "bypass authentication",
            "escalate privileges"
        ],
        "vector": "malicious HTTP GET request",
        "attacker": [
            "unauthenticated attacker",
            "authenticated attacker"
        ],
        "product": "Conserus Workflow Intelligence",
        "version": "2.0.2",
        "component": ""
    }
}
