{
    "cveId": "CVE-2004-2571",
    "version": "1.0.0",
    "timestamp": "2024-12-10T17:54:04.992951+00:00",
    "description": "Multiple buffer overflows in EnderUNIX isoqlog 2.1.1 allow remote attackers to execute arbitrary code via the (1) parseQmailFromBytesLine, (2) parseQmailToRemoteLine, (3) parseQmailToLocalLine, (4) parseSendmailFromBytesLine, (5) parseSendmailToLine, (6) parseEximFromBytesLine, and (7) parseEximToLine functions in Parser.c allow local users to execute arbitrary code via the (8) lowercase and (9) check_syslog_date functions in Parser.c, and (10) unspecified functions in Dir.c and allow unspecified attackers to execute arbitrary code via the (11) loadconfig and (12) removespaces functions in loadconfig.c, the (13) loadLang function in LangCfg.c, and (14) unspecified functions in Html.c.",
    "keyphrases": {
        "rootcause": "buffer overflows",
        "weakness": "",
        "impact": "execute arbitrary code",
        "vector": "",
        "attacker": "",
        "product": "EnderUNIX isoqlog",
        "version": "2.1.1",
        "component": [
            "parseQmailFromBytesLine",
            "parseQmailToRemoteLine",
            "parseQmailToLocalLine",
            "parseSendmailFromBytesLine",
            "parseSendmailToLine",
            "parseEximFromBytesLine",
            "parseEximToLine functions in Parser.c",
            "lowercase",
            "check_syslog_date functions in Parser.c",
            "unspecified functions in Dir.c",
            "loadconfig",
            "removespaces functions in loadconfig.c",
            "loadLang function in LangCfg.c",
            "unspecified functions in Html.c"
        ]
    }
}
