{
    "cveId": "CVE-2017-2704",
    "version": "1.0.0",
    "timestamp": "2024-12-11T16:08:24.783251+00:00",
    "description": "Smarthome 1.0.2.364 and earlier versions,HiAPP 7.3.0.303 and earlier versions,HwParentControl 2.0.0 and earlier versions,HwParentControlParent 5.1.0.12 and earlier versions,Crowdtest 1.5.3 and earlier versions,HiWallet 8.0.0.301 and earlier versions,Huawei Pay 8.0.0.300 and earlier versions,Skytone 8.1.2.300 and earlier versions,HwCloudDrive(EMUI6.0) 8.0.0.307 and earlier versions,HwPhoneFinder(EMUI6.0) 9.3.0.310 and earlier versions,HwPhoneFinder(EMUI5.1) 9.2.2.303 and earlier versions,HiCinema 8.0.2.300 and earlier versions,HuaweiWear 21.0.0.360 and earlier versions,HiHealthApp 3.0.3.300 and earlier versions have an information exposure vulnerability. Encryption keys are stored in the system. The attacker can implement reverse engineering to obtain the encryption keys, causing information exposure.",
    "keyphrases": {
        "rootcause": "encryption keys stored in system",
        "weakness": "",
        "impact": "information exposure",
        "vector": "reverse engineering",
        "attacker": "attacker",
        "product": [
            "Smarthome",
            "HiAPP",
            "HwParentControl",
            "HwParentControlParent",
            "Crowdtest",
            "HiWallet",
            "Huawei Pay",
            "Skytone",
            "HwCloudDrive",
            "HwPhoneFinder",
            "HiCinema",
            "HuaweiWear",
            "HiHealthApp"
        ],
        "version": [
            "1.0.2.364 and earlier",
            "7.3.0.303 and earlier",
            "2.0.0 and earlier",
            "5.1.0.12 and earlier",
            "1.5.3 and earlier",
            "8.0.0.301 and earlier",
            "8.0.0.300 and earlier",
            "8.1.2.300 and earlier",
            "8.0.0.307 and earlier",
            "9.3.0.310 and earlier",
            "9.2.2.303 and earlier",
            "8.0.2.300 and earlier",
            "21.0.0.360 and earlier",
            "3.0.3.300 and earlier"
        ],
        "component": ""
    }
}
