{
    "cveId": "CVE-2012-4821",
    "version": "1.0.0",
    "timestamp": "2024-12-10T17:54:04.992951+00:00",
    "description": "Multiple unspecified vulnerabilities in the JRE component in IBM Java 7 SR2 and earlier, Java 6.0.1 SR3 and earlier, Java 6 SR11 and earlier, Java 5 SR14 and earlier, and Java 142 SR13 FP13 and earlier as used in IBM Rational Host On-Demand, Rational Change, Tivoli Monitoring, Smart Analytics System 5600, Tivoli Remote Control 5.1.2, WebSphere Real Time, Lotus Notes & Domino, Tivoli Storage Productivity Center, and Service Deliver Manager and other products from other vendors such as Red Hat, allow remote attackers to execute arbitrary code via insecure use of the (1) java.lang.Class getDeclaredMethods or nd (2) java.lang.reflect.AccessibleObject setAccessible() methods.",
    "keyphrases": {
        "rootcause": "insecure use of the java.lang.Class getDeclaredMethods or nd java.lang.reflect.AccessibleObject setAccessible() methods",
        "weakness": "unspecified vulnerabilities",
        "impact": "execute arbitrary code",
        "vector": "",
        "attacker": "remote attackers",
        "product": [
            "IBM Java 7",
            "Java 6.0.1",
            "Java 6",
            "Java 5",
            "Java 142"
        ],
        "version": [
            "SR2 and earlier",
            "SR3 and earlier",
            "SR11 and earlier",
            "SR14 and earlier",
            "SR13 FP13 and earlier"
        ],
        "component": ""
    }
}
