{
  "cveId": "CVE-2024-11946",
  "version": "1.0.0",
  "timestamp": "2025-07-04T16:12:41.853043+00:00",
  "description": "iXsystems TrueNAS CORE fetch_plugin_packagesites tar Cleartext Transmission of Sensitive Information Vulnerability. This vulnerability allows network-adjacent attackers to tamper with firmware update files on affected installations of iXsystems TrueNAS devices. Authentication is not required to exploit this vulnerability. The specific flaw exists within the handling of firmware updates. The issue results from the use of an insecure protocol to deliver updates. An attacker can leverage this in conjunction with other vulnerabilities to execute arbitrary code in the context of root. Was ZDI-CAN-25668.",
  "keyphrases": {
    "rootcause": "use of an insecure protocol to deliver updates",
    "weakness": "Cleartext Transmission of Sensitive Information",
    "impact": [
      "tamper with firmware update files",
      "execute arbitrary code"
    ],
    "vector": "",
    "attacker": "network-adjacent attackers",
    "product": "iXsystems TrueNAS CORE",
    "version": "",
    "component": ""
  },
  "mitreTechnicalImpacts": []
}