{
  "cveId": "CVE-2024-11201",
  "version": "1.0.0",
  "timestamp": "2024-12-17T08:36:27.567979+00:00",
  "description": "The myCred Loyalty Points and Rewards plugin for WordPress and WooCommerce Give Points, Ranks, Badges, Cashback, WooCommerce rewards, and WooCommerce credits for Gamification plugin for WordPress is vulnerable to Stored Cross-Site Scripting via the plugins mycred_send shortcode in all versions up to, and including, 2.7.5.2 due to insufficient input sanitization and output escaping on user supplied attributes. This makes it possible for authenticated attackers, with contributor-level access and above, to inject arbitrary web scripts in pages that will execute whenever a user accesses an injected page.",
  "keyphrases": {
    "rootcause": "insufficient input sanitization and output escaping on user supplied attributes",
    "weakness": "cross-site scripting",
    "impact": "inject arbitrary web scripts",
    "vector": "",
    "attacker": "authenticated attackers",
    "product": "myCred Loyalty Points and Rewards plugin",
    "version": "up to 2.7.5.2",
    "component": "mycred_send shortcode"
  },
  "mitreTechnicalImpacts": []
}