{
    "cveId": "CVE-2009-3179",
    "version": "1.0.0",
    "timestamp": "2024-12-10T17:54:04.992951+00:00",
    "description": "Multiple unspecified vulnerabilities in Symantec Altiris Deployment Solution 6.9 might allow remote attackers to execute arbitrary code via unknown client-side attack vectors, as demonstrated by a certain module in VulnDisco Pack Professional 7.17, as identified by (1) Symantec Altiris Deployment Solution 6.9 exploit, (2) Symantec Altiris Deployment Solution 6.9 exploit (II), and (3) Symantec Altiris Deployment Solution 6.9 exploit (III). NOTE as of 20090909, this disclosure has no actionable information. However, because the VulnDisco Pack author is a reliable researcher, the issue is being assigned a CVE identifier for tracking purposes.",
    "keyphrases": {
        "rootcause": "",
        "weakness": "unspecified vulnerabilities",
        "impact": "execute arbitrary code",
        "vector": "unknown client-side attack vectors",
        "attacker": "remote attackers",
        "product": "Symantec Altiris Deployment Solution",
        "version": "6.9",
        "component": ""
    }
}
