{
    "cveId": "CVE-2009-3555",
    "version": "1.0.0",
    "timestamp": "2024-12-10T17:54:04.992951+00:00",
    "description": "The TLS protocol, and the SSL protocol 3.0 and possibly earlier, as used in Microsoft Internet Information Services (IIS) 7.0, mod_ssl in the Apache HTTP Server 2.2.14 and earlier, OpenSSL before 0.9.8l, GnuTLS 2.8.5 and earlier, Mozilla Network Security Services (NSS) 3.12.4 and earlier, multiple Cisco products, and other products, does not properly associate renegotiation handshakes with an existing connection, which allows man-in-the-middle attackers to insert data into HTTPS sessions, and possibly other types of sessions protected by TLS or SSL, by sending an unauthenticated request that is processed retroactively by a server in a post-renegotiation context, related to a plaintext injection attack, aka the Project Mogul issue.",
    "keyphrases": {
        "rootcause": "does not properly associate renegotiation handshakes with an existing connection",
        "weakness": "",
        "impact": "insert data into HTTPS sessions",
        "vector": "sending an unauthenticated request that is processed retroactively by a server in a post-renegotiation context",
        "attacker": "man-in-the-middle attackers",
        "product": [
            "Microsoft Internet Information Services",
            "Apache HTTP Server",
            "OpenSSL",
            "GnuTLS",
            "Mozilla Network Security Services",
            "Cisco products"
        ],
        "version": [
            "IIS 7.0",
            "mod_ssl in 2.2.14 and earlier",
            "before 0.9.8l",
            "2.8.5 and earlier",
            "3.12.4 and earlier",
            "multiple"
        ],
        "component": [
            "TLS protocol",
            "SSL protocol 3.0 and possibly earlier"
        ]
    }
}
