{
    "cveId": "CVE-2009-3015",
    "version": "1.0.0",
    "timestamp": "2024-12-10T17:54:04.992951+00:00",
    "description": "QtWeb 3.0 Builds 001 and 003 does not properly block javascript and data URIs in Refresh and Location headers in HTTP responses, which allows remote attackers to conduct cross-site scripting (XSS) attacks via vectors related to (1) injecting a Refresh header that contains a javascript URI, (2) entering a javascript URI when specifying the content of a Refresh header, (3) injecting a Refresh header that contains JavaScript sequences in a datatext/html URI, (4) entering a datatext/html URI with JavaScript sequences when specifying the content of a Refresh header, (5) injecting a Location header that contains JavaScript sequences in a datatext/html URI, or (6) entering a datatext/html URI with JavaScript sequences when specifying the content of a Location header.",
    "keyphrases": {
        "rootcause": "improper blocking of javascript and data URIs",
        "weakness": "cross-site scripting",
        "impact": "",
        "vector": [
            "injecting a Refresh header that contains a javascript URI",
            "entering a javascript URI when specifying the content of a Refresh header",
            "injecting a Refresh header that contains JavaScript sequences in a datatext/html URI",
            "entering a datatext/html URI with JavaScript sequences when specifying the content of a Refresh header",
            "injecting a Location header that contains JavaScript sequences in a datatext/html URI",
            "entering a datatext/html URI with JavaScript sequences when specifying the content of a Location header"
        ],
        "attacker": "remote attackers",
        "product": "QtWeb",
        "version": "3.0 Builds 001 and 003",
        "component": ""
    }
}
