{
    "cveId": "CVE-2023-27387",
    "version": "1.0.0",
    "timestamp": "2024-12-15T20:24:27.876763+00:00",
    "description": "Cross-site request forgery (CSRF) in T&D Corporation and ESPEC MIC CORP. data logger products allows a remote unauthenticated attacker to conduct an arbitrary operation by having a logged-in user view a malicious page. Affected products and versions are as follows T&D Corporation data logger products (TR-71W/72W all firmware versions, RTR-5W all firmware versions, WDR-7 all firmware versions, WDR-3 all firmware versions, and WS-2 all firmware versions), and ESPEC MIC CORP. data logger products (RT-12N/RS-12N all firmware versions, RT-22BN all firmware versions, and TEU-12N all firmware versions).",
    "keyphrases": {
        "rootcause": "Cross-site request forgery (CSRF)",
        "weakness": "",
        "impact": "conduct an arbitrary operation",
        "vector": "",
        "attacker": "remote unauthenticated attacker",
        "product": [
            "T&D Corporation data logger products",
            "ESPEC MIC CORP. data logger products"
        ],
        "version": [
            "all firmware versions",
            "all firmware versions",
            "all firmware versions"
        ],
        "component": ""
    }
}
