{
    "cveId": "CVE-2023-27334",
    "version": "1.0.0",
    "timestamp": "2024-12-06T11:32:07.789868+00:00",
    "description": "Softing edgeConnector Siemens ConditionRefresh Resource Exhaustion Denial-of-Service Vulnerability. This vulnerability allows remote attackers to create a denial-of-service condition on affected installations of Softing edgeConnector Siemens. Authentication is not required to exploit this vulnerability. The specific flaw exists within the handling of OPC UA ConditionRefresh requests. By sending a large number of requests, an attacker can consume all available resources on the server. An attacker can leverage this vulnerability to create a denial-of-service condition on the system. Was ZDI-CAN-20498.",
    "keyphrases": {
        "rootcause": "",
        "weakness": "Resource Exhaustion",
        "impact": "Denial-of-Service",
        "vector": "large number of requests",
        "attacker": "remote attackers",
        "product": "Softing edgeConnector Siemens",
        "version": "",
        "component": "OPC UA ConditionRefresh requests"
    }
}
