{
    "cveId": "CVE-2019-15405",
    "version": "1.0.0",
    "timestamp": "2024-12-12T22:08:52.294043+00:00",
    "description": "The Asus ASUS_X00K_1 Android device with a build fingerprint of asus/CN_X00K/ASUS_X00K_17.0/NRD90M/CN_X00K-14.01.1711.27-20180420user/release-keys contains a pre-installed app with a package name of com.asus.loguploaderproxy app (versionCode=1570000015, versionName=7.0.0.3_161222) that allows other pre-installed apps to perform command execution via an accessible app component. This capability can be accessed by any pre-installed app on the device which can obtain signatureOrSystem permissions that are required by other other pre-installed apps that exported their capabilities to other pre-installed app.",
    "keyphrases": {
        "rootcause": "accessible app component",
        "weakness": "",
        "impact": "command execution",
        "vector": "",
        "attacker": "other pre-installed apps",
        "product": "Asus ASUS_X00K_1 Android device",
        "version": "build fingerprint of asus/CN_X00K/ASUS_X00K_17.0/NRD90M/CN_X00K-14.01.1711.27-20180420user/release-keys",
        "component": "com.asus.loguploaderproxy app"
    }
}
