{
    "cveId": "CVE-2019-15396",
    "version": "1.0.0",
    "timestamp": "2024-12-12T22:08:52.294043+00:00",
    "description": "The Asus ZenFone 3 Android device with a build fingerprint of asus/WW_Phone/ASUS_Z012D7.0/NRD90M/14.2020.1708.56-20170719user/release-keys contains a pre-installed app with a package name of com.asus.loguploaderproxy app (versionCode=1570000015, versionName=7.0.0.3_161222) that allows other pre-installed apps to perform command execution via an accessible app component. This capability can be accessed by any pre-installed app on the device which can obtain signatureOrSystem permissions that are required by other other pre-installed apps that exported their capabilities to other pre-installed app.",
    "keyphrases": {
        "rootcause": "",
        "weakness": "",
        "impact": "command execution",
        "vector": "accessible app component",
        "attacker": "any pre-installed app",
        "product": "Asus ZenFone 3",
        "version": "",
        "component": "com.asus.loguploaderproxy app"
    }
}
