{
    "cveId": "CVE-2019-15450",
    "version": "1.0.0",
    "timestamp": "2024-12-12T22:08:52.294043+00:00",
    "description": "The Samsung j3popeltecan Android device with a build fingerprint of samsung/j3popeltevl/j3popeltecan8.1.0/M1AJQ/J327WVLS3BSA2user/release-keys contains a pre-installed app with a package name of com.samsung.android.themecenter app (versionCode=7000100, versionName=7.0.1.0) that allows other pre-installed apps to perform app installation via an accessible app component. This capability can be accessed by any pre-installed app on the device which can obtain signatureOrSystem permissions that are required by other other pre-installed apps that exported their capabilities to other pre-installed app.",
    "keyphrases": {
        "rootcause": "",
        "weakness": "accessible app component",
        "impact": "perform app installation",
        "vector": "",
        "attacker": "pre-installed apps",
        "product": "Samsung j3popeltecan Android device",
        "version": "8.1.0",
        "component": "pre-installed app"
    }
}
