{
    "cveId": "CVE-2019-15402",
    "version": "1.0.0",
    "timestamp": "2024-12-12T22:08:52.294043+00:00",
    "description": "The Asus ASUS_A002_2 Android device with a build fingerprint of asus/WW_ASUS_A002_2/ASUS_A002_27.0/NRD90M/14.1610.1802.18-20180321user/release-keys contains a pre-installed app with a package name of com.asus.loguploaderproxy app (versionCode=1570000020, versionName=7.0.0.4_170901) that allows other pre-installed apps to perform command execution via an accessible app component. This capability can be accessed by any pre-installed app on the device which can obtain signatureOrSystem permissions that are required by other other pre-installed apps that exported their capabilities to other pre-installed app.",
    "keyphrases": {
        "rootcause": "",
        "weakness": "accessible app component",
        "impact": "command execution",
        "vector": "",
        "attacker": "pre-installed apps",
        "product": "Asus ASUS_A002_2 Android device",
        "version": "7.0.0.4_170901",
        "component": "com.asus.loguploaderproxy app"
    }
}
