{
    "cveId": "CVE-2006-0259",
    "version": "1.0.0",
    "timestamp": "2024-12-10T17:54:04.992951+00:00",
    "description": "Multiple unspecified vulnerabilities in Oracle Database server 10.1.0.5 have unspecified impact and attack vectors, as identified by Oracle Vuln# (1) DB04 and (2) DB06 in the (a) Data Pump component (3) DB10 in the (b) Net Listener component and (4) DB16 in the (c) Oracle Text component. NOTE details are unavailable from Oracle, but they have not publicly disputed a claim by a reliable independent researcher that states that DB06 is SQL injection in the GENERATE_JOB_NAME, GET_WORKERSTATUSLIST1010, GET_PARAMVALUES1010, GET_DUMPFILESET1010, GET_JOBSTATUS1010, ATTACH, and ESTABLISH_REMOTE_CONTEXT functions in DBMS_DATAPUMP.",
    "keyphrases": {
        "rootcause": "",
        "weakness": "Multiple unspecified vulnerabilities",
        "impact": "unspecified",
        "vector": "unspecified",
        "attacker": "",
        "product": "Oracle Database server",
        "version": "10.1.0.5",
        "component": [
            "Data Pump component",
            "Net Listener component",
            "Oracle Text component"
        ]
    }
}
