{
    "cveId": "CVE-2022-23165",
    "version": "1.0.0",
    "timestamp": "2024-12-15T20:24:27.876763+00:00",
    "description": "Sysaid Sysaid 14.2.0 Reflected Cross-Site Scripting (XSS) - The parameter helpPageName used by the page /help/treecontent.jsp suffers from a Reflected Cross-Site Scripting vulnerability. For an attacker to exploit this Cross-Site Scripting vulnerability, its necessary for the affected product to expose the Offline Help Pages. An attacker may gain access to sensitive information or execute client-side code in the browser session of the victim user. Furthermore, an attacker would require the victim to open a malicious link. An attacker may exploit this vulnerability in order to perform phishing attacks. The attacker can receive sensitive data like server details, usernames, workstations, etc. He can also perform actions such as uploading files, deleting calls from the system",
    "keyphrases": {
        "rootcause": "",
        "weakness": "cross-site scripting",
        "impact": [
            "gain access to sensitive information",
            "execute client-side code"
        ],
        "vector": "",
        "attacker": "attacker",
        "product": "Sysaid Sysaid",
        "version": "14.2.0",
        "component": "/help/treecontent.jsp"
    }
}
