{
    "cveId": "CVE-2022-39407",
    "version": "1.0.0",
    "timestamp": "2024-12-06T11:32:07.789868+00:00",
    "description": "Vulnerability in the PeopleSoft Enterprise PeopleTools product of Oracle PeopleSoft (component Security). Supported versions that are affected are 8.58, 8.59 and 8.60. Easily exploitable vulnerability allows low privileged attacker with logon to the infrastructure where PeopleSoft Enterprise PeopleTools executes to compromise PeopleSoft Enterprise PeopleTools. Successful attacks of this vulnerability can result in unauthorized access to critical data or complete access to all PeopleSoft Enterprise PeopleTools accessible data. CVSS 3.1 Base Score 5.5 (Confidentiality impacts). CVSS Vector (CVSS3.1/AVL/ACL/PRL/UIN/SU/CH/IN/AN).",
    "keyphrases": {
        "rootcause": "",
        "weakness": "",
        "impact": [
            "unauthorized access to critical data",
            "complete access to all PeopleSoft Enterprise PeopleTools accessible data"
        ],
        "vector": "",
        "attacker": "low privileged attacker",
        "product": "Oracle PeopleSoft",
        "version": "8.58, 8.59 and 8.60",
        "component": "Security"
    }
}
