{
    "cveId": "CVE-2022-39402",
    "version": "1.0.0",
    "timestamp": "2024-12-06T11:32:07.789868+00:00",
    "description": "Vulnerability in the MySQL Shell product of Oracle MySQL (component Shell Core Client). Supported versions that are affected are 8.0.30 and prior. Easily exploitable vulnerability allows unauthenticated attacker with logon to the infrastructure where MySQL Shell executes to compromise MySQL Shell. While the vulnerability is in MySQL Shell, attacks may significantly impact additional products (scope change). Successful attacks of this vulnerability can result in unauthorized read access to a subset of MySQL Shell accessible data. CVSS 3.1 Base Score 4.3 (Confidentiality impacts). CVSS Vector (CVSS3.1/AVL/ACL/PRN/UIN/SC/CL/IN/AN).",
    "keyphrases": {
        "rootcause": "",
        "weakness": "",
        "impact": "unauthorized read access to a subset of MySQL Shell accessible data",
        "vector": "",
        "attacker": "unauthenticated attacker",
        "product": "MySQL Shell",
        "version": "8.0.30 and prior",
        "component": "Shell Core Client"
    }
}
