{
    "cveId": "CVE-2022-39420",
    "version": "1.0.0",
    "timestamp": "2024-12-06T11:32:07.789868+00:00",
    "description": "Vulnerability in the Oracle Transportation Management product of Oracle Supply Chain (component Data, Functional Security). Supported versions that are affected are 6.4.3 and 6.5.1. Easily exploitable vulnerability allows low privileged attacker with network access via HTTP to compromise Oracle Transportation Management. Successful attacks of this vulnerability can result in unauthorized update, insert or delete access to some of Oracle Transportation Management accessible data as well as unauthorized read access to a subset of Oracle Transportation Management accessible data. CVSS 3.1 Base Score 5.4 (Confidentiality and Integrity impacts). CVSS Vector (CVSS3.1/AVN/ACL/PRL/UIN/SU/CL/IL/AN).",
    "keyphrases": {
        "rootcause": "",
        "weakness": "",
        "impact": "unauthorized update, insert or delete access",
        "vector": "low privileged attacker with network access via HTTP",
        "attacker": "",
        "product": "Oracle Transportation Management",
        "version": "6.4.3 and 6.5.1",
        "component": "Data, Functional Security"
    }
}
