{
    "cveId": "CVE-2024-47716",
    "version": "1.0.0",
    "timestamp": "2024-12-06T11:32:07.789868+00:00",
    "description": "In the Linux kernel, the following vulnerability has been resolved ARM 9410/1 vfp Use asm volatile in fmrx/fmxr macros Floating point instructions in userspace can crash some arm kernels built with clang/LLD 17.0.6 BUG unsupported FP instruction in kernel mode FPEXC == 0xc0000780 Internal error Oops - undefined instruction 0 [#1] ARM CPU 0 PID 196 Comm vfp-reproducer Not tainted 6.10.0 #1 Hardware name BCM2835 PC is at vfp_support_entry+0xc8/0x2cc LR is at do_undefinstr+0xa8/0x250 pc [] lr [] psr a0000013 sp dc8d1f68 ip 60000013 fp bedea19c r10 ec532b17 r9 00000010 r8 0044766c r7 c0000780 r6 ec532b17 r5 c1c13800 r4 dc8d1fb0 r3 c10072c4 r2 c0101c88 r1 ec532b17 r0 0044766c Flags NzCv IRQs on FIQs on Mode SVC_32 ISA ARM Segment none Control 00c5387d Table 0251c008 DAC 00000051 Register r0 information non-paged memory Register r1 information vmalloc memory Register r2 information non-slab/vmalloc memory Register r3 information non-slab/vmalloc memory Register r4 information 2-page vmalloc region Register r5 information slab kmalloc-cg-2k Register r6 information vmalloc memory Register r7 information non-slab/vmalloc memory Register r8 information non-paged memory Register r9 information zero-size pointer Register r10 information vmalloc memory Register r11 information non-p",
    "keyphrases": {
        "rootcause": "floating point instructions in userspace",
        "weakness": "unsupported FP instruction in kernel mode",
        "impact": "crash",
        "vector": "",
        "attacker": "",
        "product": "Linux kernel",
        "version": "6.10.0",
        "component": "ARM 9410/1 vfp"
    }
}
