{
    "cveId": "CVE-2014-4752",
    "version": "1.0.0",
    "timestamp": "2024-12-10T17:54:04.992951+00:00",
    "description": "IBM System Networking G8052, G8124, G8124-E, G8124-ER, G8264, G8316, and G8264-T switches before 7.9.10.0 EN4093, EN4093R, CN4093, SI4093, EN2092, and G8264CS switches before 7.8.6.0 Flex System Interconnect Fabric before 7.8.6.0 1G L2-7 SLB switch for Bladecenter before 21.0.21.0 10G VFSM for Bladecenter before 7.8.14.0 110G switch for Bladecenter before 7.4.8.0 1G switch for Bladecenter before 5.3.5.0 Server Connectivity Module before 1.1.3.4 System Networking RackSwitch G8332 before 7.7.17.0 and System Networking RackSwitch G8000 before 7.1.7.0 have hardcoded credentials, which makes it easier for remote attackers to obtain access via unspecified vectors.",
    "keyphrases": {
        "rootcause": "hardcoded credentials",
        "weakness": "",
        "impact": "obtain access",
        "vector": "unspecified vectors",
        "attacker": "remote attackers",
        "product": [
            "IBM System Networking G8052",
            "G8124",
            "G8124-E",
            "G8124-ER",
            "G8264",
            "G8316",
            "G8264-T switches",
            "EN4093",
            "EN4093R",
            "CN4093",
            "SI4093",
            "EN2092",
            "G8264CS switches",
            "Flex System Interconnect Fabric",
            "1G L2-7 SLB switch for Bladecenter",
            "10G VFSM for Bladecenter",
            "110G switch for Bladecenter",
            "1G switch for Bladecenter",
            "Server Connectivity Module",
            "System Networking RackSwitch G8332",
            "System Networking RackSwitch G8000"
        ],
        "version": [
            "before 7.9.10.0",
            "before 7.8.6.0",
            "before 7.8.6.0",
            "before 21.0.21.0",
            "before 7.8.14.0",
            "before 7.4.8.0",
            "before 5.3.5.0",
            "before 1.1.3.4",
            "before 7.7.17.0",
            "before 7.1.7.0"
        ],
        "component": ""
    }
}
