{
    "cveId": "CVE-2016-1606",
    "version": "1.0.0",
    "timestamp": "2024-12-10T17:54:04.992951+00:00",
    "description": "Multiple stack-based buffer overflows in COM objects in Micro Focus Rumba 9.4.x before 9.4 HF 13960 allow remote attackers to execute arbitrary code via (1) the NetworkName property value to ObjectXSNAConfig.ObjectXSNAConfig in iconfig.dll, (2) the CPName property value to ObjectXSNAConfig.ObjectXSNAConfig in iconfig.dll, (3) the PrinterName property value to ProfileEditor.PrintPasteControl in ProfEdit.dll, (4) the Data argument to the WriteRecords function in FTXBIFFLib.AS400FtxBIFF in FtxBIFF.dll, (5) the Serialized property value to NMSECCOMPARAMSLib.SSL3 in NMSecComParams.dll, (6) the UserName property value to NMSECCOMPARAMSLib.FirewallProxy in NMSecComParams.dll, (7) the LUName property value to ProfileEditor.MFSNAControl in ProfEdit.dll, (8) the newVal argument to the Load function in FTPSFTPLib.SFtpSession in FTPSFtp.dll, or (9) a long Host field in the FTP Client.",
    "keyphrases": {
        "rootcause": "Multiple stack-based buffer overflows",
        "weakness": "",
        "impact": "execute arbitrary code",
        "vector": "(1) the NetworkName property value to ObjectXSNAConfig.ObjectXSNAConfig in iconfig.dll",
        "attacker": "remote attackers",
        "product": "Micro Focus Rumba",
        "version": "9.4.x before 9.4 HF 13960",
        "component": [
            "NetworkName property value to ObjectXSNAConfig.ObjectXSNAConfig in iconfig.dll",
            "CPName property value to ObjectXSNAConfig.ObjectXSNAConfig in iconfig.dll",
            "PrinterName property value to ProfileEditor.PrintPasteControl in ProfEdit.dll",
            "Data argument to the WriteRecords function in FTXBIFFLib.AS400FtxBIFF in FtxBIFF.dll",
            "Serialized property value to NMSECCOMPARAMSLib.SSL3 in NMSecComParams.dll",
            "UserName property value to NMSECCOMPARAMSLib.FirewallProxy in NMSecComParams.dll",
            "LUName property value to ProfileEditor.MFSNAControl in ProfEdit.dll",
            "newVal argument to the Load function in FTPSFTPLib.SFtpSession in FTPSFtp.dll",
            "long Host field in the FTP Client"
        ]
    }
}
