{
    "cveId": "CVE-2021-35603",
    "version": "1.0.0",
    "timestamp": "2024-12-06T11:32:07.789868+00:00",
    "description": "Vulnerability in the Java SE, Oracle GraalVM Enterprise Edition product of Oracle Java SE (component JSSE). Supported versions that are affected are Java SE 7u311, 8u301, 11.0.12, 17 Oracle GraalVM Enterprise Edition 20.3.3 and 21.2.0. Difficult to exploit vulnerability allows unauthenticated attacker with network access via TLS to compromise Java SE, Oracle GraalVM Enterprise Edition. Successful attacks of this vulnerability can result in unauthorized read access to a subset of Java SE, Oracle GraalVM Enterprise Edition accessible data. Note This vulnerability applies to Java deployments, typically in clients running sandboxed Java Web Start applications or sandboxed Java applets, that load and run untrusted code (e.g., code that comes from the internet) and rely on the Java sandbox for security. This vulnerability can also be exploited by using APIs in the specified Component, e.g., through a web service which supplies data to the APIs. CVSS 3.1 Base Score 3.7 (Confidentiality impacts). CVSS Vector (CVSS3.1/AVN/ACH/PRN/UIN/SU/CL/IN/AN).",
    "keyphrases": {
        "rootcause": "",
        "weakness": "",
        "impact": "unauthorized read access",
        "vector": "network access via TLS",
        "attacker": "unauthenticated attacker",
        "product": "Java SE",
        "version": "7u311, 8u301, 11.0.12, 17",
        "component": "JSSE"
    }
}
