{
  "cveId": "CVE-2021-35571",
  "version": "1.0.0",
  "timestamp": "2024-12-06T11:32:07.789868+00:00",
  "description": "Vulnerability in the PeopleSoft Enterprise CS Academic Advisement product of Oracle PeopleSoft (component Advising Notes). The supported version that is affected is 9.2. Easily exploitable vulnerability allows low privileged attacker with network access via HTTP to compromise PeopleSoft Enterprise CS Academic Advisement. Successful attacks of this vulnerability can result in unauthorized update, insert or delete access to some of PeopleSoft Enterprise CS Academic Advisement accessible data as well as unauthorized read access to a subset of PeopleSoft Enterprise CS Academic Advisement accessible data. CVSS 3.1 Base Score 5.4 (Confidentiality and Integrity impacts). CVSS Vector (CVSS3.1/AVN/ACL/PRL/UIN/SU/CL/IL/AN).",
  "keyphrases": {
    "rootcause": "",
    "weakness": "",
    "impact": [
      "Integrity",
      "insert or delete access",
      "unauthorized read access",
      "unauthorized update"
    ],
    "vector": "low privileged attacker with network access via HTTP",
    "attacker": "",
    "product": "Oracle PeopleSoft",
    "version": "9.2",
    "component": "PeopleSoft Enterprise CS Academic Advisement"
  },
  "mitreTechnicalImpacts": []
}