{
    "cveId": "CVE-2021-35606",
    "version": "1.0.0",
    "timestamp": "2024-12-06T11:32:07.789868+00:00",
    "description": "Vulnerability in the PeopleSoft Enterprise CS Campus Community product of Oracle PeopleSoft (component Notification Framework). Supported versions that are affected are 9.0 and 9.2. Easily exploitable vulnerability allows low privileged attacker with access to the physical communication segment attached to the hardware where the PeopleSoft Enterprise CS Campus Community executes to compromise PeopleSoft Enterprise CS Campus Community. Successful attacks of this vulnerability can result in unauthorized access to critical data or complete access to all PeopleSoft Enterprise CS Campus Community accessible data. CVSS 3.1 Base Score 5.7 (Confidentiality impacts). CVSS Vector (CVSS3.1/AVA/ACL/PRL/UIN/SU/CH/IN/AN).",
    "keyphrases": {
        "rootcause": "",
        "weakness": "",
        "impact": "unauthorized access to critical data or complete access to all PeopleSoft Enterprise CS Campus Community accessible data",
        "vector": "",
        "attacker": "low privileged attacker with access to the physical communication segment attached to the hardware where the PeopleSoft Enterprise CS Campus Community executes",
        "product": "Oracle PeopleSoft",
        "version": "9.0 and 9.2",
        "component": "Notification Framework"
    }
}
