{
    "cveId": "CVE-2021-35541",
    "version": "1.0.0",
    "timestamp": "2024-12-06T11:32:07.789868+00:00",
    "description": "Vulnerability in the PeopleSoft Enterprise SCM product of Oracle PeopleSoft (component Supplier Portal). The supported version that is affected is 9.2. Easily exploitable vulnerability allows low privileged attacker with network access via HTTP to compromise PeopleSoft Enterprise SCM. Successful attacks require human interaction from a person other than the attacker and while the vulnerability is in PeopleSoft Enterprise SCM, attacks may significantly impact additional products. Successful attacks of this vulnerability can result in unauthorized update, insert or delete access to some of PeopleSoft Enterprise SCM accessible data as well as unauthorized read access to a subset of PeopleSoft Enterprise SCM accessible data. CVSS 3.1 Base Score 5.4 (Confidentiality and Integrity impacts). CVSS Vector (CVSS3.1/AVN/ACL/PRL/UIR/SC/CL/IL/AN).",
    "keyphrases": {
        "rootcause": "",
        "weakness": "",
        "impact": [
            "unauthorized update",
            "insert or delete access",
            "unauthorized read access"
        ],
        "vector": "",
        "attacker": "low privileged attacker",
        "product": "Oracle PeopleSoft",
        "version": "9.2",
        "component": "Supplier Portal"
    }
}
