{
    "cveId": "CVE-2021-35686",
    "version": "1.0.0",
    "timestamp": "2024-12-06T11:32:07.789868+00:00",
    "description": "Vulnerability in the Oracle Financial Services Analytical Applications Infrastructure product of Oracle Financial Services Applications (component Unified Metadata Manager). Supported versions that are affected are 8.0.7-8.1.1. Easily exploitable vulnerability allows low privileged attacker with network access via HTTP to compromise Oracle Financial Services Analytical Applications Infrastructure. Successful attacks of this vulnerability can result in unauthorized read access to a subset of Oracle Financial Services Analytical Applications Infrastructure accessible data. CVSS 3.1 Base Score 4.3 (Confidentiality impacts). CVSS Vector (CVSS3.1/AVN/ACL/PRL/UIN/SU/CL/IN/AN).",
    "keyphrases": {
        "rootcause": "",
        "weakness": "",
        "impact": "unauthorized read access",
        "vector": "low privileged attacker with network access via HTTP",
        "attacker": "",
        "product": "Oracle Financial Services Analytical Applications Infrastructure",
        "version": "8.0.7-8.1.1",
        "component": "Unified Metadata Manager"
    }
}
