{
    "cveId": "CVE-2021-35653",
    "version": "1.0.0",
    "timestamp": "2024-12-06T11:32:07.789868+00:00",
    "description": "Vulnerability in the Essbase Administration Services product of Oracle Essbase (component EAS Console). The supported versions that are affected are Prior to 11.1.2.4.046 and Prior to 21.3. Easily exploitable vulnerability allows low privileged attacker with network access via HTTP to compromise Essbase Administration Services. While the vulnerability is in Essbase Administration Services, attacks may significantly impact additional products. Successful attacks of this vulnerability can result in unauthorized access to critical data or complete access to all Essbase Administration Services accessible data. CVSS 3.1 Base Score 7.7 (Confidentiality impacts). CVSS Vector (CVSS3.1/AVN/ACL/PRL/UIN/SC/CH/IN/AN).",
    "keyphrases": {
        "rootcause": "",
        "weakness": "",
        "impact": [
            "unauthorized access to critical data",
            "complete access to all Essbase Administration Services accessible data"
        ],
        "vector": "",
        "attacker": "low privileged attacker with network access via HTTP",
        "product": "Oracle Essbase",
        "version": "Prior to 11.1.2.4.046 and Prior to 21.3",
        "component": "Essbase Administration Services"
    }
}
