{
    "cveId": "CVE-2021-35651",
    "version": "1.0.0",
    "timestamp": "2024-12-06T11:32:07.789868+00:00",
    "description": "Vulnerability in the Essbase Administration Services product of Oracle Essbase (component EAS Console). The supported versions that are affected are Prior to 11.1.2.4.046 and Prior to 21.3. Easily exploitable vulnerability allows low privileged attacker with network access via HTTP to compromise Essbase Administration Services. While the vulnerability is in Essbase Administration Services, attacks may significantly impact additional products. Successful attacks of this vulnerability can result in unauthorized access to critical data or complete access to all Essbase Administration Services accessible data as well as unauthorized update, insert or delete access to some of Essbase Administration Services accessible data. CVSS 3.1 Base Score 8.5 (Confidentiality and Integrity impacts). CVSS Vector (CVSS3.1/AVN/ACL/PRL/UIN/SC/CH/IL/AN).",
    "keyphrases": {
        "rootcause": "",
        "weakness": "",
        "impact": "unauthorized access to critical data",
        "vector": "",
        "attacker": "low privileged attacker with network access via HTTP",
        "product": "Essbase Administration Services",
        "version": "Prior to 11.1.2.4.046 and Prior to 21.3",
        "component": "EAS Console"
    }
}
