{
    "cveId": "CVE-2021-35618",
    "version": "1.0.0",
    "timestamp": "2024-12-06T11:32:07.789868+00:00",
    "description": "Vulnerability in the MySQL Cluster product of Oracle MySQL (component Cluster General). Supported versions that are affected are 8.0.26 and prior. Difficult to exploit vulnerability allows high privileged attacker with access to the physical communication segment attached to the hardware where the MySQL Cluster executes to compromise MySQL Cluster. Successful attacks require human interaction from a person other than the attacker. Successful attacks of this vulnerability can result in unauthorized ability to cause a partial denial of service (partial DOS) of MySQL Cluster. CVSS 3.1 Base Score 1.8 (Availability impacts). CVSS Vector (CVSS3.1/AVA/ACH/PRH/UIR/SU/CN/IN/AL).",
    "keyphrases": {
        "rootcause": "",
        "weakness": "",
        "impact": "partial denial of service",
        "vector": "",
        "attacker": "high privileged attacker",
        "product": "MySQL Cluster",
        "version": "8.0.26 and prior",
        "component": "Cluster General"
    }
}
