{
    "cveId": "CVE-2021-35556",
    "version": "1.0.0",
    "timestamp": "2024-12-15T20:24:27.876763+00:00",
    "description": "Vulnerability in the Java SE, Oracle GraalVM Enterprise Edition product of Oracle Java SE (component Swing). Supported versions that are affected are Java SE 7u311, 8u301, 11.0.12, 17 Oracle GraalVM Enterprise Edition 20.3.3 and 21.2.0. Easily exploitable vulnerability allows unauthenticated attacker with network access via multiple protocols to compromise Java SE, Oracle GraalVM Enterprise Edition. Successful attacks of this vulnerability can result in unauthorized ability to cause a partial denial of service (partial DOS) of Java SE, Oracle GraalVM Enterprise Edition. Note This vulnerability applies to Java deployments, typically in clients running sandboxed Java Web Start applications or sandboxed Java applets, that load and run untrusted code (e.g., code that comes from the internet) and rely on the Java sandbox for security. This vulnerability does not apply to Java deployments, typically in servers, that load and run only trusted code (e.g., code installed by an administrator). CVSS 3.1 Base Score 5.3 (Availability impacts). CVSS Vector (CVSS3.1/AVN/ACL/PRN/UIN/SU/CN/IN/AL).",
    "keyphrases": {
        "rootcause": "",
        "weakness": "",
        "impact": "partial denial of service",
        "vector": "multiple protocols",
        "attacker": "unauthenticated attacker",
        "product": [
            "Java SE",
            "Oracle GraalVM Enterprise Edition"
        ],
        "version": [
            "Java SE 7u311",
            "8u301",
            "11.0.12",
            "17"
        ],
        "component": "Swing"
    }
}
