{
    "cveId": "CVE-2021-35493",
    "version": "1.0.0",
    "timestamp": "2024-12-15T20:24:27.876763+00:00",
    "description": "The WebFOCUS Reporting Server and WebFOCUS Client components of TIBCO Software Inc.s TIBCO WebFOCUS Client, TIBCO WebFOCUS Installer, and TIBCO WebFOCUS Reporting Server contain easily exploitable Stored and Reflected Cross Site Scripting (XSS) vulnerabilities that allow a low privileged attacker to social engineer a legitimate user with network access to execute scripts targeting the affected system or the victims local system. A successful attack using this vulnerability requires human interaction from a person other than the attacker. Affected releases are TIBCO Software Inc.s TIBCO WebFOCUS Client versions 8207.27.0 and below, TIBCO WebFOCUS Installer versions 8207.27.0 and below, and TIBCO WebFOCUS Reporting Server versions 8207.27.0 and below.",
    "keyphrases": {
        "rootcause": "",
        "weakness": "Stored and Reflected Cross Site Scripting (XSS)",
        "impact": "social engineer a legitimate user with network access to execute scripts",
        "vector": "",
        "attacker": "low privileged attacker",
        "product": [
            "TIBCO WebFOCUS Client",
            "TIBCO WebFOCUS Installer",
            "TIBCO WebFOCUS Reporting Server"
        ],
        "version": "8207.27.0 and below",
        "component": ""
    }
}
