{
    "cveId": "CVE-2021-35652",
    "version": "1.0.0",
    "timestamp": "2024-12-06T11:32:07.789868+00:00",
    "description": "Vulnerability in the Essbase Administration Services product of Oracle Essbase (component EAS Console). The supported versions that are affected are Prior to 11.1.2.4.046 and Prior to 21.3. Easily exploitable vulnerability allows unauthenticated attacker with network access via HTTP to compromise Essbase Administration Services. While the vulnerability is in Essbase Administration Services, attacks may significantly impact additional products. Successful attacks of this vulnerability can result in takeover of Essbase Administration Services. CVSS 3.1 Base Score 10.0 (Confidentiality, Integrity and Availability impacts). CVSS Vector (CVSS3.1/AVN/ACL/PRN/UIN/SC/CH/IH/AH).",
    "keyphrases": {
        "rootcause": "",
        "weakness": "",
        "impact": "takeover of Essbase Administration Services",
        "vector": "",
        "attacker": "unauthenticated attacker with network access via HTTP",
        "product": "Oracle Essbase",
        "version": [
            "Prior to 11.1.2.4.046",
            "Prior to 21.3"
        ],
        "component": "Essbase Administration Services"
    }
}
