{
    "cveId": "CVE-2006-4089",
    "version": "1.0.0",
    "timestamp": "2024-12-10T17:54:04.992951+00:00",
    "description": "Multiple buffer overflows in Andy Lo-A-Foe AlsaPlayer 0.99.76 and earlier allow remote attackers to cause a denial of service (application crash), or have other unknown impact, via (1) a long Location field sent by a web server, which triggers an overflow in the reconnect function in reader/http/http.c (2) a long URL sent by a web server when AlsaPlayer is seeking a media file for the playlist, which triggers overflows in new_list_item and CbUpdated in interface/gtk/PlaylistWindow.cpp and (3) a long response sent by a CDDB server, which triggers an overflow in cddb_lookup in input/ccda/cdda_engine.c.",
    "keyphrases": {
        "rootcause": "multiple buffer overflows",
        "weakness": "",
        "impact": "denial of service (application crash)",
        "vector": [
            "long Location field sent by a web server",
            "long URL sent by a web server",
            "long response sent by a CDDB server"
        ],
        "attacker": "remote attackers",
        "product": "Andy Lo-A-Foe AlsaPlayer",
        "version": "0.99.76 and earlier",
        "component": [
            "reconnect function",
            "new_list_item and CbUpdated",
            "cddb_lookup"
        ]
    }
}
