{
  "cveId": "CVE-2018-2942",
  "version": "1.0.0",
  "timestamp": "2024-12-15T20:24:27.876763+00:00",
  "description": "Vulnerability in the Java SE component of Oracle Java SE (subcomponent Windows DLL). Supported versions that are affected are Java SE 7u181 and 8u172. Difficult to exploit vulnerability allows unauthenticated attacker with network access via multiple protocols to compromise Java SE. Successful attacks require human interaction from a person other than the attacker and while the vulnerability is in Java SE, attacks may significantly impact additional products. Successful attacks of this vulnerability can result in takeover of Java SE. Note Applies to client and server deployment of Java. This vulnerability can be exploited through sandboxed Java Web Start applications and sandboxed Java applets. It can also be exploited by supplying data to APIs in the specified Component without using sandboxed Java Web Start applications or sandboxed Java applets, such as through a web service. CVSS 3.0 Base Score 8.3 (Confidentiality, Integrity and Availability impacts). CVSS Vector (CVSS3.0/AVN/ACH/PRN/UIR/SC/CH/IH/AH).",
  "keyphrases": {
    "rootcause": "",
    "weakness": "",
    "impact": [
      "Integrity and Availability impacts",
      "takeover of Java SE"
    ],
    "vector": "multiple protocols",
    "attacker": "unauthenticated attacker with network access",
    "product": "Oracle Java SE",
    "version": "Java SE 7u181 and 8u172",
    "component": "Windows DLL"
  },
  "mitreTechnicalImpacts": []
}