{
  "cveId": "CVE-2018-2689",
  "version": "1.0.0",
  "timestamp": "2024-12-11T16:08:24.783251+00:00",
  "description": "Vulnerability in the Oracle VM VirtualBox component of Oracle Virtualization (subcomponent Core). Supported versions that are affected are Prior to 5.1.32 and Prior to 5.2.6. Easily exploitable vulnerability allows unauthenticated attacker with logon to the infrastructure where Oracle VM VirtualBox executes to compromise Oracle VM VirtualBox. Successful attacks require human interaction from a person other than the attacker and while the vulnerability is in Oracle VM VirtualBox, attacks may significantly impact additional products. Successful attacks of this vulnerability can result in takeover of Oracle VM VirtualBox. CVSS 3.0 Base Score 8.6 (Confidentiality, Integrity and Availability impacts). CVSS Vector (CVSS3.0/AVL/ACL/PRN/UIR/SC/CH/IH/AH).",
  "keyphrases": {
    "rootcause": "",
    "weakness": "",
    "impact": [
      "Integrity and Availability impacts",
      "takeover of Oracle VM VirtualBox"
    ],
    "vector": "",
    "attacker": "unauthenticated attacker",
    "product": "Oracle VM VirtualBox",
    "version": "Prior to 5.1.32 and Prior to 5.2.6",
    "component": "Oracle Virtualization"
  },
  "mitreTechnicalImpacts": []
}