{
    "cveId": "CVE-2018-2755",
    "version": "1.0.0",
    "timestamp": "2024-12-06T11:32:07.789868+00:00",
    "description": "Vulnerability in the MySQL Server component of Oracle MySQL (subcomponent Server Replication). Supported versions that are affected are 5.5.59 and prior, 5.6.39 and prior and 5.7.21 and prior. Difficult to exploit vulnerability allows unauthenticated attacker with logon to the infrastructure where MySQL Server executes to compromise MySQL Server. Successful attacks require human interaction from a person other than the attacker and while the vulnerability is in MySQL Server, attacks may significantly impact additional products. Successful attacks of this vulnerability can result in takeover of MySQL Server. CVSS 3.0 Base Score 7.7 (Confidentiality, Integrity and Availability impacts). CVSS Vector (CVSS3.0/AVL/ACH/PRN/UIR/SC/CH/IH/AH).",
    "keyphrases": {
        "rootcause": "",
        "weakness": "",
        "impact": "takeover of MySQL Server",
        "vector": "",
        "attacker": "unauthenticated attacker",
        "product": "Oracle MySQL",
        "version": "5.5.59 and prior, 5.6.39 and prior and 5.7.21 and prior",
        "component": "MySQL Server"
    }
}
