{
    "cveId": "CVE-2018-2583",
    "version": "1.0.0",
    "timestamp": "2024-12-11T16:08:24.783251+00:00",
    "description": "Vulnerability in the MySQL Server component of Oracle MySQL (subcomponent Stored Procedure). Supported versions that are affected are 5.6.38 and prior and 5.7.20 and prior. Easily exploitable vulnerability allows high privileged attacker with network access via multiple protocols to compromise MySQL Server. While the vulnerability is in MySQL Server, attacks may significantly impact additional products. Successful attacks of this vulnerability can result in unauthorized ability to cause a hang or frequently repeatable crash (complete DOS) of MySQL Server. CVSS 3.0 Base Score 6.8 (Availability impacts). CVSS Vector (CVSS3.0/AVN/ACL/PRH/UIN/SC/CN/IN/AH).",
    "keyphrases": {
        "rootcause": "",
        "weakness": "",
        "impact": "cause a hang or frequently repeatable crash (complete DOS) of MySQL Server",
        "vector": "multiple protocols",
        "attacker": "high privileged attacker with network access",
        "product": "Oracle MySQL",
        "version": "5.6.38 and prior and 5.7.20 and prior",
        "component": "MySQL Server"
    }
}
