{
  "cveId": "CVE-2018-2599",
  "version": "1.0.0",
  "timestamp": "2024-12-11T16:08:24.783251+00:00",
  "description": "Vulnerability in the Java SE, Java SE Embedded, JRockit component of Oracle Java SE (subcomponent JNDI). Supported versions that are affected are Java SE 6u171, 7u161, 8u152 and 9.0.1 Java SE Embedded 8u151 JRockit R28.3.16. Difficult to exploit vulnerability allows unauthenticated attacker with network access via multiple protocols to compromise Java SE, Java SE Embedded, JRockit. Successful attacks of this vulnerability can result in unauthorized update, insert or delete access to some of Java SE, Java SE Embedded, JRockit accessible data and unauthorized ability to cause a partial denial of service (partial DOS) of Java SE, Java SE Embedded, JRockit. Note This vulnerability applies to client and server deployment of Java. This vulnerability can be exploited through sandboxed Java Web Start applications and sandboxed Java applets. It can also be exploited by supplying data to APIs in the specified Component without using sandboxed Java Web Start applications or sandboxed Java applets, such as through a web service. CVSS 3.0 Base Score 4.8 (Integrity and Availability impacts). CVSS Vector (CVSS3.0/AVN/ACH/PRN/UIN/SU/CN/IL/AL).",
  "keyphrases": {
    "rootcause": "",
    "weakness": "",
    "impact": [
      "Availability",
      "JRockit accessible data",
      "Java SE Embedded",
      "insert or delete access to some of Java SE",
      "partial denial of service (partial DOS)",
      "unauthorized update"
    ],
    "vector": "multiple protocols",
    "attacker": "unauthenticated attacker with network access",
    "product": [
      "['Java SE'",
      "'Java SE Embedded'",
      "'JRockit']"
    ],
    "version": [
      "Java SE 6u171",
      "7u161",
      "8u152 and 9.0.1 Java SE Embedded 8u151 JRockit R28.3.16"
    ],
    "component": "JNDI"
  },
  "mitreTechnicalImpacts": []
}