{
  "cveId": "CVE-2018-2876",
  "version": "1.0.0",
  "timestamp": "2024-12-11T16:08:24.783251+00:00",
  "description": "Vulnerability in the Oracle Retail Integration Bus component of Oracle Retail Applications (subcomponent RIB Kernal(Apache Commons Collections)). The supported version that is affected is 13.2. Easily exploitable vulnerability allows unauthenticated attacker with network access via HTTP to compromise Oracle Retail Integration Bus. Successful attacks require human interaction from a person other than the attacker and while the vulnerability is in Oracle Retail Integration Bus, attacks may significantly impact additional products. Successful attacks of this vulnerability can result in unauthorized update, insert or delete access to some of Oracle Retail Integration Bus accessible data as well as unauthorized read access to a subset of Oracle Retail Integration Bus accessible data and unauthorized ability to cause a partial denial of service (partial DOS) of Oracle Retail Integration Bus. CVSS 3.0 Base Score 7.1 (Confidentiality, Integrity and Availability impacts). CVSS Vector (CVSS3.0/AVN/ACL/PRN/UIR/SC/CL/IL/AL).",
  "keyphrases": {
    "rootcause": "",
    "weakness": "",
    "impact": [
      "DOS",
      "Integrity and Availability impacts",
      "insert or delete access",
      "partial denial of service",
      "unauthorized read access",
      "unauthorized update"
    ],
    "vector": "HTTP",
    "attacker": "unauthenticated attacker",
    "product": "Oracle Retail Integration Bus",
    "version": "13.2",
    "component": "RIB Kernal(Apache Commons Collections)"
  },
  "mitreTechnicalImpacts": []
}