{
  "cveId": "CVE-2018-2960",
  "version": "1.0.0",
  "timestamp": "2024-12-06T11:32:07.789868+00:00",
  "description": "Vulnerability in the Primavera P6 Enterprise Project Portfolio Management component of Oracle Construction and Engineering Suite (subcomponent Web Access). Supported versions that are affected are 8.4, 15.x, 16.x and 17.x. Easily exploitable vulnerability allows unauthenticated attacker with network access via HTTP to compromise Primavera P6 Enterprise Project Portfolio Management. Successful attacks require human interaction from a person other than the attacker and while the vulnerability is in Primavera P6 Enterprise Project Portfolio Management, attacks may significantly impact additional products. Successful attacks of this vulnerability can result in unauthorized update, insert or delete access to some of Primavera P6 Enterprise Project Portfolio Management accessible data as well as unauthorized read access to a subset of Primavera P6 Enterprise Project Portfolio Management accessible data. CVSS 3.0 Base Score 6.1 (Confidentiality and Integrity impacts). CVSS Vector (CVSS3.0/AVN/ACL/PRN/UIR/SC/CL/IL/AN).",
  "keyphrases": {
    "rootcause": "",
    "weakness": "",
    "impact": [
      "Integrity",
      "insert or delete access to some of Primavera P6 Enterprise Project Portfolio Management accessible data",
      "unauthorized read access to a subset of Primavera P6 Enterprise Project Portfolio Management accessible data",
      "unauthorized update"
    ],
    "vector": "network access via HTTP",
    "attacker": "unauthenticated attacker",
    "product": "Oracle Construction and Engineering Suite",
    "version": [
      "8.4",
      "15.x",
      "16.x and 17.x"
    ],
    "component": "Primavera P6 Enterprise Project Portfolio Management"
  },
  "mitreTechnicalImpacts": []
}