{
  "cveId": "CVE-2018-2635",
  "version": "1.0.0",
  "timestamp": "2024-12-06T11:32:07.789868+00:00",
  "description": "Vulnerability in the Oracle Application Object Library component of Oracle E-Business Suite (subcomponent Login). Supported versions that are affected are 12.1.3, 12.2.3, 12.2.4, 12.2.5, 12.2.6 and 12.2.7. Difficult to exploit vulnerability allows unauthenticated attacker with network access via HTTP to compromise Oracle Application Object Library. Successful attacks of this vulnerability can result in unauthorized update, insert or delete access to some of Oracle Application Object Library accessible data as well as unauthorized read access to a subset of Oracle Application Object Library accessible data. CVSS 3.0 Base Score 4.8 (Confidentiality and Integrity impacts). CVSS Vector (CVSS3.0/AVN/ACH/PRN/UIN/SU/CL/IL/AN).",
  "keyphrases": {
    "rootcause": "",
    "weakness": "Difficult to exploit vulnerability",
    "impact": [
      "Integrity",
      "insert or delete access to some of Oracle Application Object Library accessible data as well as unauthorized read access to a subset of Oracle Application Object Library accessible data",
      "unauthorized update"
    ],
    "vector": "network access via HTTP",
    "attacker": "unauthenticated attacker",
    "product": "Oracle E-Business Suite",
    "version": [
      "12.1.3",
      "12.2.3",
      "12.2.4",
      "12.2.5",
      "12.2.6 and 12.2.7"
    ],
    "component": "Oracle Application Object Library component"
  },
  "mitreTechnicalImpacts": []
}