{
  "cveId": "CVE-2018-2756",
  "version": "1.0.0",
  "timestamp": "2024-12-11T16:08:24.783251+00:00",
  "description": "Vulnerability in the Oracle Communications Order and Service Management component of Oracle Communications Applications (subcomponent WebUI). Supported versions that are affected are 7.2.4.3.0, 7.3.0.1.x, 7.3.1.0.7 and 7.3.5.0.x. Easily exploitable vulnerability allows low privileged attacker with network access via HTTP to compromise Oracle Communications Order and Service Management. Successful attacks require human interaction from a person other than the attacker. Successful attacks of this vulnerability can result in unauthorized access to critical data or complete access to all Oracle Communications Order and Service Management accessible data as well as unauthorized update, insert or delete access to some of Oracle Communications Order and Service Management accessible data. CVSS 3.0 Base Score 6.3 (Confidentiality and Integrity impacts). CVSS Vector (CVSS3.0/AVN/ACL/PRL/UIR/SU/CH/IL/AN).",
  "keyphrases": {
    "rootcause": "",
    "weakness": "",
    "impact": [
      "Integrity",
      "insert or delete access",
      "unauthorized access to critical data",
      "unauthorized update"
    ],
    "vector": "",
    "attacker": "low privileged attacker with network access via HTTP",
    "product": "Oracle Communications Applications",
    "version": [
      "7.2.4.3.0",
      "7.3.0.1.x",
      "7.3.1.0.7",
      "7.3.5.0.x"
    ],
    "component": "Oracle Communications Order and Service Management component"
  },
  "mitreTechnicalImpacts": []
}