{
    "cveId": "CVE-2018-2624",
    "version": "1.0.0",
    "timestamp": "2024-12-06T11:32:07.789868+00:00",
    "description": "Vulnerability in the Sun ZFS Storage Appliance Kit (AK) component of Oracle Sun Systems Products Suite (subcomponent User Interface). The supported version that is affected is Prior to 8.7.13. Easily exploitable vulnerability allows unauthenticated attacker with network access via HTTP to compromise Sun ZFS Storage Appliance Kit (AK). While the vulnerability is in Sun ZFS Storage Appliance Kit (AK), attacks may significantly impact additional products. Successful attacks of this vulnerability can result in unauthorized access to critical data or complete access to all Sun ZFS Storage Appliance Kit (AK) accessible data. CVSS 3.0 Base Score 8.6 (Confidentiality impacts). CVSS Vector (CVSS3.0/AVN/ACL/PRN/UIN/SC/CH/IN/AN).",
    "keyphrases": {
        "rootcause": "",
        "weakness": "",
        "impact": "unauthorized access to critical data or complete access to all Sun ZFS Storage Appliance Kit (AK) accessible data",
        "vector": "",
        "attacker": "unauthenticated attacker with network access via HTTP",
        "product": "Sun ZFS Storage Appliance Kit (AK)",
        "version": "Prior to 8.7.13",
        "component": "User Interface"
    }
}
