{
  "cveId": "CVE-2018-2727",
  "version": "1.0.0",
  "timestamp": "2024-12-11T16:08:24.783251+00:00",
  "description": "Vulnerability in the Oracle Financial Services Market Risk Measurement and Management component of Oracle Financial Services Applications (subcomponent User Interface). The supported version that is affected is 8.0.5. Easily exploitable vulnerability allows low privileged attacker with network access via HTTP to compromise Oracle Financial Services Market Risk Measurement and Management. Successful attacks of this vulnerability can result in unauthorized creation, deletion or modification access to critical data or all Oracle Financial Services Market Risk Measurement and Management accessible data as well as unauthorized access to critical data or complete access to all Oracle Financial Services Market Risk Measurement and Management accessible data. CVSS 3.0 Base Score 8.1 (Confidentiality and Integrity impacts). CVSS Vector (CVSS3.0/AVN/ACL/PRL/UIN/SU/CH/IH/AN).",
  "keyphrases": {
    "rootcause": "",
    "weakness": "",
    "impact": [
      "Integrity",
      "deletion or modification access to critical data or all Oracle Financial Services Market Risk Measurement and Management accessible data as well as unauthorized access to critical data or complete access to all Oracle Financial Services Market Risk Measurement and Management accessible data",
      "unauthorized creation"
    ],
    "vector": "",
    "attacker": "low privileged attacker",
    "product": "Oracle Financial Services Market Risk Measurement and Management",
    "version": "8.0.5",
    "component": "User Interface"
  },
  "mitreTechnicalImpacts": []
}