{
  "cveId": "CVE-2018-2711",
  "version": "1.0.0",
  "timestamp": "2024-12-11T16:08:24.783251+00:00",
  "description": "Vulnerability in the Oracle JDeveloper component of Oracle Fusion Middleware (subcomponent Security Framework). Supported versions that are affected are 11.1.1.2.4, 11.1.1.7.0, 11.1.1.7.1, 11.1.1.9.0 and 12.1.3.0.0. Easily exploitable vulnerability allows unauthenticated attacker with network access via HTTP to compromise Oracle JDeveloper. Successful attacks require human interaction from a person other than the attacker and while the vulnerability is in Oracle JDeveloper, attacks may significantly impact additional products. Successful attacks of this vulnerability can result in unauthorized access to critical data or complete access to all Oracle JDeveloper accessible data as well as unauthorized update, insert or delete access to some of Oracle JDeveloper accessible data. CVSS 3.0 Base Score 8.2 (Confidentiality and Integrity impacts). CVSS Vector (CVSS3.0/AVN/ACL/PRN/UIR/SC/CH/IL/AN).",
  "keyphrases": {
    "rootcause": "",
    "weakness": "",
    "impact": [
      "Integrity",
      "insert or delete access",
      "unauthorized access to critical data or complete access to all Oracle JDeveloper accessible data as well as unauthorized update"
    ],
    "vector": "network access via HTTP",
    "attacker": "unauthenticated attacker",
    "product": "Oracle JDeveloper",
    "version": [
      "11.1.1.2.4",
      "11.1.1.7.0",
      "11.1.1.7.1",
      "11.1.1.9.0 and 12.1.3.0.0"
    ],
    "component": ""
  },
  "mitreTechnicalImpacts": []
}