{
  "cveId": "CVE-2018-2742",
  "version": "1.0.0",
  "timestamp": "2024-12-11T16:08:24.783251+00:00",
  "description": "Vulnerability in the Enterprise Manager Ops Center component of Oracle Enterprise Manager Products Suite (subcomponent Framework). Supported versions that are affected are 12.2.2 and 12.3.3. Easily exploitable vulnerability allows unauthenticated attacker with network access via HTTP to compromise Enterprise Manager Ops Center. Successful attacks of this vulnerability can result in unauthorized update, insert or delete access to some of Enterprise Manager Ops Center accessible data as well as unauthorized read access to a subset of Enterprise Manager Ops Center accessible data and unauthorized ability to cause a partial denial of service (partial DOS) of Enterprise Manager Ops Center. CVSS 3.0 Base Score 7.3 (Confidentiality, Integrity and Availability impacts). CVSS Vector (CVSS3.0/AVN/ACL/PRN/UIN/SU/CL/IL/AL).",
  "keyphrases": {
    "rootcause": "",
    "weakness": "",
    "impact": [
      "Integrity and Availability impacts",
      "insert or delete access to some of Enterprise Manager Ops Center accessible data",
      "unauthorized ability to cause a partial denial of service (partial DOS) of Enterprise Manager Ops Center",
      "unauthorized read access to a subset of Enterprise Manager Ops Center accessible data",
      "unauthorized update"
    ],
    "vector": "network access via HTTP",
    "attacker": "unauthenticated attacker",
    "product": "Oracle Enterprise Manager Products Suite",
    "version": "12.2.2 and 12.3.3",
    "component": "Enterprise Manager Ops Center component"
  },
  "mitreTechnicalImpacts": []
}