{
  "cveId": "CVE-2018-2750",
  "version": "1.0.0",
  "timestamp": "2024-12-11T16:08:24.783251+00:00",
  "description": "Vulnerability in the Enterprise Manager Base Platform component of Oracle Enterprise Manager Products Suite (subcomponent UI Framework). The supported version that is affected is 12.1.0.5. Easily exploitable vulnerability allows unauthenticated attacker with network access via HTTP to compromise Enterprise Manager Base Platform. Successful attacks require human interaction from a person other than the attacker and while the vulnerability is in Enterprise Manager Base Platform, attacks may significantly impact additional products. Successful attacks of this vulnerability can result in unauthorized update, insert or delete access to some of Enterprise Manager Base Platform accessible data as well as unauthorized read access to a subset of Enterprise Manager Base Platform accessible data and unauthorized ability to cause a partial denial of service (partial DOS) of Enterprise Manager Base Platform. CVSS 3.0 Base Score 7.1 (Confidentiality, Integrity and Availability impacts). CVSS Vector (CVSS3.0/AVN/ACL/PRN/UIR/SC/CL/IL/AL).",
  "keyphrases": {
    "rootcause": "",
    "weakness": "",
    "impact": [
      "DOS",
      "Integrity and Availability impacts",
      "insert or delete access",
      "partial denial of service",
      "unauthorized read access",
      "unauthorized update"
    ],
    "vector": "unauthenticated attacker with network access via HTTP",
    "attacker": "",
    "product": "Oracle Enterprise Manager Products Suite",
    "version": "12.1.0.5",
    "component": "Enterprise Manager Base Platform"
  },
  "mitreTechnicalImpacts": []
}