{
    "cveId": "CVE-2018-2567",
    "version": "1.0.0",
    "timestamp": "2024-12-06T11:32:07.789868+00:00",
    "description": "Vulnerability in the Oracle Communications Order and Service Management component of Oracle Communications Applications (subcomponent Portal). Supported versions that are affected are 7.2.4.1.x, 7.2.4.2.x, 7.3.0.x.x and 7.3.0.1.x. Easily exploitable vulnerability allows unauthenticated attacker with network access via HTTP to compromise Oracle Communications Order and Service Management. Successful attacks require human interaction from a person other than the attacker and while the vulnerability is in Oracle Communications Order and Service Management, attacks may significantly impact additional products. Successful attacks of this vulnerability can result in unauthorized update, insert or delete access to some of Oracle Communications Order and Service Management accessible data as well as unauthorized read access to a subset of Oracle Communications Order and Service Management accessible data. CVSS 3.0 Base Score 6.1 (Confidentiality and Integrity impacts). CVSS Vector (CVSS3.0/AVN/ACL/PRN/UIR/SC/CL/IL/AN).",
    "keyphrases": {
        "rootcause": "",
        "weakness": "",
        "impact": "unauthorized update, insert or delete access",
        "vector": "",
        "attacker": "unauthenticated attacker",
        "product": "Oracle Communications Order and Service Management",
        "version": "7.2.4.1.x, 7.2.4.2.x, 7.3.0.x.x and 7.3.0.1.x",
        "component": "Portal"
    }
}
