{
    "cveId": "CVE-2018-2704",
    "version": "1.0.0",
    "timestamp": "2024-12-06T11:32:07.789868+00:00",
    "description": "Vulnerability in the Oracle Banking Payments component of Oracle Financial Services Applications (subcomponent Payments Core). Supported versions that are affected are 12.3.0 and 12.4.0. Easily exploitable vulnerability allows low privileged attacker with network access via HTTP to compromise Oracle Banking Payments. Successful attacks of this vulnerability can result in unauthorized creation, deletion or modification access to critical data or all Oracle Banking Payments accessible data and unauthorized ability to cause a hang or frequently repeatable crash (complete DOS) of Oracle Banking Payments. CVSS 3.0 Base Score 8.1 (Integrity and Availability impacts). CVSS Vector (CVSS3.0/AVN/ACL/PRL/UIN/SU/CN/IH/AH).",
    "keyphrases": {
        "rootcause": "",
        "weakness": "",
        "impact": "unauthorized creation, deletion or modification access to critical data or all Oracle Banking Payments accessible data",
        "vector": "",
        "attacker": "low privileged attacker with network access via HTTP",
        "product": "Oracle Banking Payments",
        "version": "12.3.0 and 12.4.0",
        "component": "Payments Core"
    }
}
