{
    "cveId": "CVE-2018-2747",
    "version": "1.0.0",
    "timestamp": "2024-12-11T16:08:24.783251+00:00",
    "description": "Vulnerability in the Oracle Banking Corporate Lending component of Oracle Financial Services Applications (subcomponent Core module). Supported versions that are affected are 12.3.0, 12.4.0, 12.5.0 and 14.0.0. Easily exploitable vulnerability allows low privileged attacker with network access via HTTP to compromise Oracle Banking Corporate Lending. Successful attacks of this vulnerability can result in unauthorized access to critical data or complete access to all Oracle Banking Corporate Lending accessible data. CVSS 3.0 Base Score 6.5 (Confidentiality impacts). CVSS Vector (CVSS3.0/AVN/ACL/PRL/UIN/SU/CH/IN/AN).",
    "keyphrases": {
        "rootcause": "",
        "weakness": "",
        "impact": [
            "unauthorized access to critical data",
            "complete access to all Oracle Banking Corporate Lending accessible data"
        ],
        "vector": "low privileged attacker with network access via HTTP",
        "attacker": "low privileged attacker",
        "product": "Oracle Banking Corporate Lending",
        "version": "12.3.0, 12.4.0, 12.5.0 and 14.0.0",
        "component": "Core module"
    }
}
