{
    "cveId": "CVE-2018-2918",
    "version": "1.0.0",
    "timestamp": "2024-12-06T11:32:07.789868+00:00",
    "description": "Vulnerability in the Sun ZFS Storage Appliance Kit (AK) component of Oracle Sun Systems Products Suite (subcomponent API frameworks). The supported version that is affected is Prior to 8.7.18. Difficult to exploit vulnerability allows unauthenticated attacker with network access via multiple protocols to compromise Sun ZFS Storage Appliance Kit (AK). Successful attacks require human interaction from a person other than the attacker. Successful attacks of this vulnerability can result in takeover of Sun ZFS Storage Appliance Kit (AK). CVSS 3.0 Base Score 7.5 (Confidentiality, Integrity and Availability impacts). CVSS Vector (CVSS3.0/AVN/ACH/PRN/UIR/SU/CH/IH/AH).",
    "keyphrases": {
        "rootcause": "",
        "weakness": "",
        "impact": "takeover of Sun ZFS Storage Appliance Kit (AK)",
        "vector": "multiple protocols",
        "attacker": "unauthenticated attacker with network access",
        "product": "Oracle Sun Systems Products Suite",
        "version": "Prior to 8.7.18",
        "component": "Sun ZFS Storage Appliance Kit (AK)"
    }
}
