{
    "cveId": "CVE-2018-2792",
    "version": "1.0.0",
    "timestamp": "2024-12-06T11:32:07.789868+00:00",
    "description": "Vulnerability in the Hardware Management Pack component of Oracle Sun Systems Products Suite (subcomponent Ipmitool). The supported version that is affected is Prior to 2.4.3. Easily exploitable vulnerability allows high privileged attacker with network access via multiple protocols to compromise Hardware Management Pack. Successful attacks of this vulnerability can result in unauthorized update, insert or delete access to some of Hardware Management Pack accessible data as well as unauthorized read access to a subset of Hardware Management Pack accessible data. CVSS 3.0 Base Score 3.8 (Confidentiality and Integrity impacts). CVSS Vector (CVSS3.0/AVN/ACL/PRH/UIN/SU/CL/IL/AN).",
    "keyphrases": {
        "rootcause": "",
        "weakness": "",
        "impact": [
            "unauthorized update",
            "insert or delete access",
            "unauthorized read access"
        ],
        "vector": "multiple protocols",
        "attacker": "high privileged attacker with network access",
        "product": "Hardware Management Pack",
        "version": "Prior to 2.4.3",
        "component": "Ipmitool"
    }
}
