{
  "cveId": "CVE-2018-2948",
  "version": "1.0.0",
  "timestamp": "2024-12-06T11:32:07.789868+00:00",
  "description": "Vulnerability in the JD Edwards EnterpriseOne Tools component of Oracle JD Edwards Products (subcomponent Web Runtime). The supported version that is affected is 9.2. Easily exploitable vulnerability allows unauthenticated attacker with network access via HTTP to compromise JD Edwards EnterpriseOne Tools. Successful attacks require human interaction from a person other than the attacker and while the vulnerability is in JD Edwards EnterpriseOne Tools, attacks may significantly impact additional products. Successful attacks of this vulnerability can result in unauthorized update, insert or delete access to some of JD Edwards EnterpriseOne Tools accessible data as well as unauthorized read access to a subset of JD Edwards EnterpriseOne Tools accessible data. CVSS 3.0 Base Score 6.1 (Confidentiality and Integrity impacts). CVSS Vector (CVSS3.0/AVN/ACL/PRN/UIR/SC/CL/IL/AN).",
  "keyphrases": {
    "rootcause": "",
    "weakness": "",
    "impact": [
      "Integrity",
      "insert or delete access",
      "unauthorized read access",
      "unauthorized update"
    ],
    "vector": "HTTP",
    "attacker": "unauthenticated attacker",
    "product": "Oracle JD Edwards Products",
    "version": "9.2",
    "component": "JD Edwards EnterpriseOne Tools"
  },
  "mitreTechnicalImpacts": []
}