{
  "cveId": "CVE-2018-2739",
  "version": "1.0.0",
  "timestamp": "2024-12-11T16:08:24.783251+00:00",
  "description": "Vulnerability in the Oracle Access Manager component of Oracle Fusion Middleware (subcomponent Web Server Plugin). Supported versions that are affected are 10.1.4.3.0, 11.1.2.3.0 and 12.2.1.3.0. Easily exploitable vulnerability allows unauthenticated attacker with network access via HTTP to compromise Oracle Access Manager. Successful attacks require human interaction from a person other than the attacker and while the vulnerability is in Oracle Access Manager, attacks may significantly impact additional products. Successful attacks of this vulnerability can result in unauthorized creation, deletion or modification access to critical data or all Oracle Access Manager accessible data as well as unauthorized access to critical data or complete access to all Oracle Access Manager accessible data. CVSS 3.0 Base Score 9.3 (Confidentiality and Integrity impacts). CVSS Vector (CVSS3.0/AVN/ACL/PRN/UIR/SC/CH/IH/AN).",
  "keyphrases": {
    "rootcause": "",
    "weakness": "",
    "impact": [
      "Integrity",
      "deletion or modification access to critical data or all Oracle Access Manager accessible data as well as unauthorized access to critical data or complete access to all Oracle Access Manager accessible data",
      "unauthorized creation"
    ],
    "vector": "HTTP",
    "attacker": "unauthenticated attacker with network access",
    "product": "Oracle Access Manager",
    "version": [
      "10.1.4.3.0",
      "11.1.2.3.0 and 12.2.1.3.0"
    ],
    "component": "Web Server Plugin"
  },
  "mitreTechnicalImpacts": []
}