{
    "cveId": "CVE-2018-2908",
    "version": "1.0.0",
    "timestamp": "2024-12-06T11:32:07.789868+00:00",
    "description": "Vulnerability in the Solaris component of Oracle Sun Systems Products Suite (subcomponent Kernel). The supported version that is affected is 11.3. Easily exploitable vulnerability allows low privileged attacker with network access via RPC to compromise Solaris. While the vulnerability is in Solaris, attacks may significantly impact additional products. Successful attacks of this vulnerability can result in unauthorized ability to cause a hang or frequently repeatable crash (complete DOS) of Solaris. CVSS 3.0 Base Score 7.7 (Availability impacts). CVSS Vector (CVSS3.0/AVN/ACL/PRL/UIN/SC/CN/IN/AH).",
    "keyphrases": {
        "rootcause": "",
        "weakness": "",
        "impact": "cause a hang or frequently repeatable crash (complete DOS)",
        "vector": "network access via RPC",
        "attacker": "low privileged attacker",
        "product": "Oracle Sun Systems Products Suite",
        "version": "11.3",
        "component": "Solaris component"
    }
}
