{
    "cveId": "CVE-2018-2972",
    "version": "1.0.0",
    "timestamp": "2024-12-06T11:32:07.789868+00:00",
    "description": "Vulnerability in the Java SE component of Oracle Java SE (subcomponent Security). The supported version that is affected is Java SE 10.0.1. Difficult to exploit vulnerability allows unauthenticated attacker with network access via multiple protocols to compromise Java SE. Successful attacks of this vulnerability can result in unauthorized access to critical data or complete access to all Java SE accessible data. Note Applies to client and server deployment of Java. This vulnerability can be exploited through sandboxed Java Web Start applications and sandboxed Java applets. It can also be exploited by supplying data to APIs in the specified Component without using sandboxed Java Web Start applications or sandboxed Java applets, such as through a web service. CVSS 3.0 Base Score 5.9 (Confidentiality impacts). CVSS Vector (CVSS3.0/AVN/ACH/PRN/UIN/SU/CH/IN/AN).",
    "keyphrases": {
        "rootcause": "",
        "weakness": "",
        "impact": [
            "unauthorized access to critical data",
            "complete access to all Java SE accessible data"
        ],
        "vector": "multiple protocols",
        "attacker": "unauthenticated attacker with network access",
        "product": "Oracle Java SE",
        "version": "Java SE 10.0.1",
        "component": "Java SE"
    }
}
