{
  "cveId": "CVE-2018-2984",
  "version": "1.0.0",
  "timestamp": "2024-12-06T11:32:07.789868+00:00",
  "description": "Vulnerability in the Oracle Hospitality Cruise Fleet Management System component of Oracle Hospitality Applications (subcomponent Gangway Activity Web App). The supported version that is affected is 9.x. Easily exploitable vulnerability allows low privileged attacker with network access via HTTP to compromise Oracle Hospitality Cruise Fleet Management System. Successful attacks of this vulnerability can result in unauthorized creation, deletion or modification access to critical data or all Oracle Hospitality Cruise Fleet Management System accessible data as well as unauthorized access to critical data or complete access to all Oracle Hospitality Cruise Fleet Management System accessible data. CVSS 3.0 Base Score 8.1 (Confidentiality and Integrity impacts). CVSS Vector (CVSS3.0/AVN/ACL/PRL/UIN/SU/CH/IH/AN).",
  "keyphrases": {
    "rootcause": "",
    "weakness": "",
    "impact": [
      "Integrity",
      "deletion or modification access to critical data or all Oracle Hospitality Cruise Fleet Management System accessible data as well as unauthorized access to critical data or complete access to all Oracle Hospitality Cruise Fleet Management System accessible data",
      "unauthorized creation"
    ],
    "vector": "low privileged attacker with network access via HTTP",
    "attacker": "",
    "product": "Oracle Hospitality Cruise Fleet Management System",
    "version": "9.x",
    "component": "Gangway Activity Web App"
  },
  "mitreTechnicalImpacts": []
}