{
    "cveId": "CVE-2018-2957",
    "version": "1.0.0",
    "timestamp": "2024-12-06T11:32:07.789868+00:00",
    "description": "Vulnerability in the Oracle Hospitality OPERA 5 Property Services component of Oracle Hospitality Applications (subcomponent Logging). The supported version that is affected is 5.5.x. Easily exploitable vulnerability allows unauthenticated attacker with network access via HTTP to compromise Oracle Hospitality OPERA 5 Property Services. Successful attacks of this vulnerability can result in unauthorized access to critical data or complete access to all Oracle Hospitality OPERA 5 Property Services accessible data. CVSS 3.0 Base Score 7.5 (Confidentiality impacts). CVSS Vector (CVSS3.0/AVN/ACL/PRN/UIN/SU/CH/IN/AN).",
    "keyphrases": {
        "rootcause": "",
        "weakness": "",
        "impact": [
            "unauthorized access to critical data",
            "complete access to all Oracle Hospitality OPERA 5 Property Services accessible data"
        ],
        "vector": "network access via HTTP",
        "attacker": "unauthenticated attacker",
        "product": "Oracle Hospitality OPERA 5 Property Services",
        "version": "5.5.x",
        "component": "Logging"
    }
}
