{
    "cveId": "CVE-2018-2855",
    "version": "1.0.0",
    "timestamp": "2024-12-06T11:32:07.789868+00:00",
    "description": "Vulnerability in the Oracle Financial Services Basel Regulatory Capital Basic component of Oracle Financial Services Applications (subcomponent Portfolio, Attribution). The supported version that is affected is 8.0.x. Easily exploitable vulnerability allows low privileged attacker with network access via HTTP to compromise Oracle Financial Services Basel Regulatory Capital Basic. Successful attacks of this vulnerability can result in unauthorized creation, deletion or modification access to critical data or all Oracle Financial Services Basel Regulatory Capital Basic accessible data as well as unauthorized access to critical data or complete access to all Oracle Financial Services Basel Regulatory Capital Basic accessible data. CVSS 3.0 Base Score 8.1 (Confidentiality and Integrity impacts). CVSS Vector (CVSS3.0/AVN/ACL/PRL/UIN/SU/CH/IH/AN).",
    "keyphrases": {
        "rootcause": "",
        "weakness": "",
        "impact": "unauthorized creation, deletion or modification access to critical data",
        "vector": "low privileged attacker with network access via HTTP",
        "attacker": "",
        "product": "Oracle Financial Services Basel Regulatory Capital Basic",
        "version": "8.0.x",
        "component": "Portfolio, Attribution"
    }
}
