{
  "cveId": "CVE-2018-2680",
  "version": "1.0.0",
  "timestamp": "2024-12-11T16:08:24.783251+00:00",
  "description": "Vulnerability in the Java VM component of Oracle Database Server. Supported versions that are affected are 11.2.0.4, 12.1.0.2 and 12.2.0.1. Difficult to exploit vulnerability allows unauthenticated attacker with network access via multiple protocols to compromise Java VM. Successful attacks require human interaction from a person other than the attacker and while the vulnerability is in Java VM, attacks may significantly impact additional products. Successful attacks of this vulnerability can result in takeover of Java VM. CVSS 3.0 Base Score 8.3 (Confidentiality, Integrity and Availability impacts). CVSS Vector (CVSS3.0/AVN/ACH/PRN/UIR/SC/CH/IH/AH).",
  "keyphrases": {
    "rootcause": "",
    "weakness": "",
    "impact": [
      "Integrity and Availability impacts",
      "takeover of Java VM"
    ],
    "vector": "multiple protocols",
    "attacker": "unauthenticated attacker with network access",
    "product": "Oracle Database Server",
    "version": [
      "11.2.0.4",
      "12.1.0.2 and 12.2.0.1"
    ],
    "component": "Java VM"
  },
  "mitreTechnicalImpacts": []
}