{
  "cveId": "CVE-2018-2699",
  "version": "1.0.0",
  "timestamp": "2024-12-11T16:08:24.783251+00:00",
  "description": "Vulnerability in the Application Express component of Oracle Database Server. The supported version that is affected is Prior to 5.1.4.00.08. Easily exploitable vulnerability allows unauthenticated attacker with network access via HTTP to compromise Application Express. Successful attacks require human interaction from a person other than the attacker and while the vulnerability is in Application Express, attacks may significantly impact additional products. Successful attacks of this vulnerability can result in unauthorized update, insert or delete access to some of Application Express accessible data as well as unauthorized read access to a subset of Application Express accessible data. CVSS 3.0 Base Score 6.1 (Confidentiality and Integrity impacts). CVSS Vector (CVSS3.0/AVN/ACL/PRN/UIR/SC/CL/IL/AN).",
  "keyphrases": {
    "rootcause": "",
    "weakness": "",
    "impact": [
      "Integrity",
      "insert or delete access to some of Application Express accessible data as well as unauthorized read access to a subset of Application Express accessible data",
      "unauthorized update"
    ],
    "vector": "",
    "attacker": "unauthenticated attacker",
    "product": "Oracle Database Server",
    "version": "Prior to 5.1.4.00.08",
    "component": "Application Express"
  },
  "mitreTechnicalImpacts": []
}