{
    "cveId": "CVE-2018-2904",
    "version": "1.0.0",
    "timestamp": "2024-12-06T11:32:07.789868+00:00",
    "description": "Vulnerability in the Oracle Communications EAGLE LNP Application Processor component of Oracle Communications Applications (subcomponent GUI). The supported version that is affected is 10.x. Easily exploitable vulnerability allows unauthenticated attacker with network access via HTTP to compromise Oracle Communications EAGLE LNP Application Processor. Successful attacks of this vulnerability can result in unauthorized update, insert or delete access to some of Oracle Communications EAGLE LNP Application Processor accessible data as well as unauthorized read access to a subset of Oracle Communications EAGLE LNP Application Processor accessible data. CVSS 3.0 Base Score 6.5 (Confidentiality and Integrity impacts). CVSS Vector (CVSS3.0/AVN/ACL/PRN/UIN/SU/CL/IL/AN).",
    "keyphrases": {
        "rootcause": "",
        "weakness": "",
        "impact": "unauthorized update, insert or delete access",
        "vector": "network access via HTTP",
        "attacker": "unauthenticated attacker",
        "product": "Oracle Communications Applications",
        "version": "10.x",
        "component": "Oracle Communications EAGLE LNP Application Processor component"
    }
}
