{
  "cveId": "CVE-2018-2953",
  "version": "1.0.0",
  "timestamp": "2025-07-04T16:12:41.853043+00:00",
  "description": "Vulnerability in the Oracle One-to-One Fulfillment component of Oracle E-Business Suite (subcomponent Print Server). Supported versions that are affected are 12.1.1, 12.1.2, 12.1.3, 12.2.3, 12.2.4, 12.2.5, 12.2.6 and 12.2.7. Easily exploitable vulnerability allows unauthenticated attacker with network access via HTTP to compromise Oracle One-to-One Fulfillment. Successful attacks require human interaction from a person other than the attacker and while the vulnerability is in Oracle One-to-One Fulfillment, attacks may significantly impact additional products. Successful attacks of this vulnerability can result in unauthorized access to critical data or complete access to all Oracle One-to-One Fulfillment accessible data as well as unauthorized update, insert or delete access to some of Oracle One-to-One Fulfillment accessible data. CVSS 3.0 Base Score 8.2 (Confidentiality and Integrity impacts). CVSS Vector (CVSS3.0/AVN/ACL/PRN/UIR/SC/CH/IL/AN).",
  "keyphrases": {
    "rootcause": "",
    "weakness": "",
    "impact": [
      "unauthorized access to critical data",
      "insert or delete access",
      "unauthorized update",
      "integrity"
    ],
    "vector": "HTTP",
    "attacker": "unauthenticated attacker with network access",
    "product": [
      "Oracle One-to-One Fulfillment",
      "Oracle E-Business Suite"
    ],
    "version": [
      "12.1.1",
      "12.1.2",
      "12.1.3",
      "12.2.3",
      "12.2.4",
      "12.2.5",
      "12.2.6",
      "12.2.7"
    ],
    "component": "Oracle One-to-One Fulfillment component"
  },
  "mitreTechnicalImpacts": []
}