{
  "cveId": "CVE-2018-2926",
  "version": "1.0.0",
  "timestamp": "2024-12-06T11:32:07.789868+00:00",
  "description": "Vulnerability in the Solaris component of Oracle Sun Systems Products Suite (subcomponent NVIDIA-GFX Kernel driver). The supported version that is affected is 11.3. Easily exploitable vulnerability allows low privileged attacker with network access via ISCSI to compromise Solaris. Successful attacks of this vulnerability can result in unauthorized ability to cause a hang or frequently repeatable crash (complete DOS) of Solaris as well as unauthorized update, insert or delete access to some of Solaris accessible data and unauthorized read access to a subset of Solaris accessible data. CVSS 3.0 Base Score 7.6 (Confidentiality, Integrity and Availability impacts). CVSS Vector (CVSS3.0/AVN/ACL/PRL/UIN/SU/CL/IL/AH).",
  "keyphrases": {
    "rootcause": "",
    "weakness": "",
    "impact": [
      "Integrity and Availability impacts",
      "cause a hang or frequently repeatable crash (complete DOS) of Solaris",
      "insert or delete access",
      "unauthorized read access",
      "unauthorized update"
    ],
    "vector": "",
    "attacker": "low privileged attacker with network access via ISCSI",
    "product": "Oracle Sun Systems Products Suite",
    "version": "11.3",
    "component": "NVIDIA-GFX Kernel driver"
  },
  "mitreTechnicalImpacts": []
}