{
    "cveId": "CVE-2023-6943",
    "version": "1.0.0",
    "timestamp": "2024-12-17T08:36:27.567979+00:00",
    "description": "Use of Externally-Controlled Input to Select Classes or Code (Unsafe Reflection) vulnerability in Mitsubishi Electric Corporation EZSocket versions 3.0 and later, FR Configurator2 all versions, GT Designer3 Version1(GOT1000) all versions, GT Designer3 Version1(GOT2000) all versions, GX Works2 versions 1.11M and later, GX Works3 all versions, MELSOFT Navigator versions 1.04E and later, MT Works2 all versions, MX Component versions 4.00A and later and MX OPC Server DA/UA all versions allows a remote unauthenticated attacker to execute a malicious code by RPC with a path to a malicious library while connected to the products.",
    "keyphrases": {
        "rootcause": "Use of Externally-Controlled Input to Select Classes or Code",
        "weakness": "Unsafe Reflection",
        "impact": "execute malicious code",
        "vector": "RPC with path to malicious library",
        "attacker": "remote unauthenticated attacker",
        "product": [
            "Mitsubishi Electric Corporation EZSocket",
            "GT Designer3",
            "GX Works2",
            "GX Works3",
            "MELSOFT Navigator",
            "MT Works2",
            "MX Component",
            "MX OPC Server DA/UA"
        ],
        "version": [
            "3.0 and later",
            "all versions",
            "all versions",
            "1.11M and later",
            "1.106L and prior",
            "1.04E and later",
            "all versions",
            "4.00A and later",
            "all versions"
        ],
        "component": ""
    }
}
