{
    "cveId": "CVE-2017-9492",
    "version": "1.0.0",
    "timestamp": "2024-12-11T16:08:24.783251+00:00",
    "description": "The Comcast firmware on Cisco DPC3939 (firmware version dpc3939-P20-18-v303r20421733-160420a-CMCST) Cisco DPC3939 (firmware version dpc3939-P20-18-v303r20421746-170221a-CMCST) Cisco DPC3939B (firmware version dpc3939b-v303r204217-150321a-CMCST) Cisco DPC3941T (firmware version DPC3941_2.5s3_PROD_sey) and Arris TG1682G (eMTA&DOCSIS version 10.0.132.SIP.PC20.CT, software version TG1682_2.2p7s2_PROD_sey) devices does not include the HTTPOnly flag in a Set-Cookie header for administration applications, which makes it easier for remote attackers to obtain potentially sensitive information via script access to cookies.",
    "keyphrases": {
        "rootcause": "does not include the HTTPOnly flag in a Set-Cookie header",
        "weakness": "",
        "impact": "obtain potentially sensitive information",
        "vector": "script access to cookies",
        "attacker": "remote attackers",
        "product": [
            "Cisco DPC3939",
            "Cisco DPC3939B",
            "Cisco DPC3941T",
            "Arris TG1682G"
        ],
        "version": [
            "dpc3939-P20-18-v303r20421733-160420a-CMCST",
            "dpc3939-P20-18-v303r20421746-170221a-CMCST",
            "dpc3939b-v303r204217-150321a-CMCST",
            "DPC3941_2.5s3_PROD_sey",
            "10.0.132.SIP.PC20.CT",
            "TG1682_2.2p7s2_PROD_sey"
        ],
        "component": "administration applications"
    }
}
