{
    "cveId": "CVE-2020-2673",
    "version": "1.0.0",
    "timestamp": "2024-12-06T11:32:07.789868+00:00",
    "description": "Vulnerability in the Oracle Application Testing Suite product of Oracle Enterprise Manager (component Oracle Flow Builder). Supported versions that are affected are 12.5.0.3, 13.1.0.1, 13.2.0.1 and 13.3.0.1. Easily exploitable vulnerability allows unauthenticated attacker with network access via HTTP to compromise Oracle Application Testing Suite. Successful attacks of this vulnerability can result in unauthorized access to critical data or complete access to all Oracle Application Testing Suite accessible data. CVSS 3.0 Base Score 7.5 (Confidentiality impacts). CVSS Vector (CVSS3.0/AVN/ACL/PRN/UIN/SU/CH/IN/AN).",
    "keyphrases": {
        "rootcause": "",
        "weakness": "",
        "impact": "unauthorized access to critical data or complete access to all Oracle Application Testing Suite accessible data",
        "vector": "",
        "attacker": "unauthenticated attacker with network access via HTTP",
        "product": "Oracle Application Testing Suite",
        "version": [
            "12.5.0.3",
            "13.1.0.1",
            "13.2.0.1",
            "13.3.0.1"
        ],
        "component": "Oracle Flow Builder"
    }
}
