{
    "cveId": "CVE-2020-2544",
    "version": "1.0.0",
    "timestamp": "2024-12-06T11:32:07.789868+00:00",
    "description": "Vulnerability in the Oracle WebLogic Server product of Oracle Fusion Middleware (component Console). Supported versions that are affected are 10.3.6.0.0, 12.1.3.0.0, 12.2.1.3.0 and 12.2.1.4.0. Easily exploitable vulnerability allows unauthenticated attacker with network access via HTTP to compromise Oracle WebLogic Server. Successful attacks require human interaction from a person other than the attacker. Successful attacks of this vulnerability can result in unauthorized update, insert or delete access to some of Oracle WebLogic Server accessible data. CVSS 3.0 Base Score 4.3 (Integrity impacts). CVSS Vector (CVSS3.0/AVN/ACL/PRN/UIR/SU/CN/IL/AN).",
    "keyphrases": {
        "rootcause": "",
        "weakness": "",
        "impact": "unauthorized update, insert or delete access",
        "vector": "network access via HTTP",
        "attacker": "unauthenticated attacker",
        "product": "Oracle WebLogic Server",
        "version": "10.3.6.0.0, 12.1.3.0.0, 12.2.1.3.0 and 12.2.1.4.0",
        "component": "Console"
    }
}
