{
    "cveId": "CVE-2020-2527",
    "version": "1.0.0",
    "timestamp": "2024-12-06T11:32:07.789868+00:00",
    "description": "Vulnerability in the Core RDBMS component of Oracle Database Server. Supported versions that are affected are 12.1.0.2, 12.2.0.1, 18c and 19c. Easily exploitable vulnerability allows high privileged attacker having Create Index, Create Table privilege with network access via OracleNet to compromise Core RDBMS. While the vulnerability is in Core RDBMS, attacks may significantly impact additional products. Successful attacks of this vulnerability can result in unauthorized read access to a subset of Core RDBMS accessible data. CVSS 3.0 Base Score 4.1 (Confidentiality impacts). CVSS Vector (CVSS3.0/AVN/ACL/PRH/UIN/SC/CL/IN/AN).",
    "keyphrases": {
        "rootcause": "",
        "weakness": "",
        "impact": "unauthorized read access to a subset of Core RDBMS accessible data",
        "vector": "network access via OracleNet",
        "attacker": "high privileged attacker",
        "product": "Oracle Database Server",
        "version": [
            "12.1.0.2",
            "12.2.0.1",
            "18c",
            "19c"
        ],
        "component": "Core RDBMS"
    }
}
