{
  "cveId": "CVE-2020-2799",
  "version": "1.0.0",
  "timestamp": "2024-12-06T11:32:07.789868+00:00",
  "description": "Vulnerability in the Oracle GraalVM Enterprise Edition product of Oracle GraalVM (component GraalVM Compiler). Supported versions that are affected are 19.3.1 and 20.0.0. Difficult to exploit vulnerability allows low privileged attacker with network access via multiple protocols to compromise Oracle GraalVM Enterprise Edition. While the vulnerability is in Oracle GraalVM Enterprise Edition, attacks may significantly impact additional products. Successful attacks of this vulnerability can result in unauthorized creation, deletion or modification access to critical data or all Oracle GraalVM Enterprise Edition accessible data. CVSS 3.0 Base Score 6.3 (Integrity impacts). CVSS Vector (CVSS3.0/AVN/ACH/PRL/UIN/SC/CN/IH/AN).",
  "keyphrases": {
    "rootcause": "",
    "weakness": "",
    "impact": [
      "Oracle GraalVM Enterprise Edition accessible data",
      "deletion or modification access to critical data",
      "unauthorized creation"
    ],
    "vector": "multiple protocols",
    "attacker": "low privileged attacker with network access",
    "product": "Oracle GraalVM Enterprise Edition",
    "version": "19.3.1 and 20.0.0",
    "component": "GraalVM Compiler"
  },
  "mitreTechnicalImpacts": []
}