{
    "cveId": "CVE-2020-2647",
    "version": "1.0.0",
    "timestamp": "2024-12-06T11:32:07.789868+00:00",
    "description": "Vulnerability in the Oracle Solaris product of Oracle Systems (component Kernel). Supported versions that are affected are 10 and 11. Easily exploitable vulnerability allows low privileged attacker with logon to the infrastructure where Oracle Solaris executes to compromise Oracle Solaris. Successful attacks require human interaction from a person other than the attacker. Successful attacks of this vulnerability can result in unauthorized ability to cause a hang or frequently repeatable crash (complete DOS) of Oracle Solaris. CVSS 3.0 Base Score 5.0 (Availability impacts). CVSS Vector (CVSS3.0/AVL/ACL/PRL/UIR/SU/CN/IN/AH).",
    "keyphrases": {
        "rootcause": "",
        "weakness": "",
        "impact": "hang or frequently repeatable crash (complete DOS) of Oracle Solaris",
        "vector": "",
        "attacker": "low privileged attacker",
        "product": "Oracle Solaris",
        "version": "10 and 11",
        "component": "Kernel"
    }
}
