{
    "cveId": "CVE-2020-2875",
    "version": "1.0.0",
    "timestamp": "2024-12-06T11:32:07.789868+00:00",
    "description": "Vulnerability in the MySQL Connectors product of Oracle MySQL (component Connector/J). Supported versions that are affected are 8.0.14 and prior and 5.1.48 and prior. Difficult to exploit vulnerability allows unauthenticated attacker with network access via multiple protocols to compromise MySQL Connectors. Successful attacks require human interaction from a person other than the attacker and while the vulnerability is in MySQL Connectors, attacks may significantly impact additional products. Successful attacks of this vulnerability can result in unauthorized update, insert or delete access to some of MySQL Connectors accessible data as well as unauthorized read access to a subset of MySQL Connectors accessible data. CVSS 3.0 Base Score 4.7 (Confidentiality and Integrity impacts). CVSS Vector (CVSS3.0/AVN/ACH/PRN/UIR/SC/CL/IL/AN).",
    "keyphrases": {
        "rootcause": "",
        "weakness": "",
        "impact": "unauthorized update, insert or delete access to some of MySQL Connectors accessible data as well as unauthorized read access to a subset of MySQL Connectors accessible data",
        "vector": "multiple protocols",
        "attacker": "unauthenticated attacker with network access",
        "product": "MySQL Connectors",
        "version": "8.0.14 and prior and 5.1.48 and prior",
        "component": ""
    }
}
