{
    "cveId": "CVE-2020-2553",
    "version": "1.0.0",
    "timestamp": "2024-12-06T11:32:07.789868+00:00",
    "description": "Vulnerability in the Oracle Knowledge product of Oracle Knowledge (component Information Manager Console). Supported versions that are affected are 8.6.0-8.6.3. Difficult to exploit vulnerability allows unauthenticated attacker with network access via HTTP to compromise Oracle Knowledge. Successful attacks of this vulnerability can result in unauthorized update, insert or delete access to some of Oracle Knowledge accessible data as well as unauthorized read access to a subset of Oracle Knowledge accessible data. CVSS 3.0 Base Score 4.8 (Confidentiality and Integrity impacts). CVSS Vector (CVSS3.0/AVN/ACH/PRN/UIN/SU/CL/IL/AN).",
    "keyphrases": {
        "rootcause": "",
        "weakness": "",
        "impact": "unauthorized update, insert or delete access to some of Oracle Knowledge accessible data as well as unauthorized read access to a subset of Oracle Knowledge accessible data",
        "vector": "",
        "attacker": "unauthenticated attacker with network access via HTTP",
        "product": "Oracle Knowledge",
        "version": "8.6.0-8.6.3",
        "component": "Information Manager Console"
    }
}
