{
  "cveId": "CVE-2020-2620",
  "version": "1.0.0",
  "timestamp": "2024-12-12T22:08:52.294043+00:00",
  "description": "Vulnerability in the Enterprise Manager Base Platform product of Oracle Enterprise Manager (component Enterprise Config Management). Supported versions that are affected are 12.1.0.5, 13.2.0.0 and 13.3.0.0. Easily exploitable vulnerability allows high privileged attacker with network access via HTTP to compromise Enterprise Manager Base Platform. Successful attacks of this vulnerability can result in unauthorized access to critical data or complete access to all Enterprise Manager Base Platform accessible data as well as unauthorized update, insert or delete access to some of Enterprise Manager Base Platform accessible data and unauthorized ability to cause a partial denial of service (partial DOS) of Enterprise Manager Base Platform. CVSS 3.0 Base Score 6.0 (Confidentiality, Integrity and Availability impacts). CVSS Vector (CVSS3.0/AVN/ACL/PRH/UIN/SU/CH/IL/AL).",
  "keyphrases": {
    "rootcause": "",
    "weakness": "",
    "impact": [
      "DOS",
      "Integrity and Availability impacts",
      "complete access to all Enterprise Manager Base Platform accessible data",
      "insert or delete access",
      "partial denial of service",
      "unauthorized access to critical data",
      "unauthorized delete",
      "unauthorized insert",
      "unauthorized update"
    ],
    "vector": "high privileged attacker with network access via HTTP",
    "attacker": "high privileged attacker",
    "product": "Enterprise Manager Base Platform",
    "version": [
      "12.1.0.5",
      "13.2.0.0 and 13.3.0.0"
    ],
    "component": "Enterprise Config Management"
  },
  "mitreTechnicalImpacts": []
}