{
    "cveId": "CVE-2020-2789",
    "version": "1.0.0",
    "timestamp": "2024-12-06T11:32:07.789868+00:00",
    "description": "Vulnerability in the Oracle iSupport product of Oracle E-Business Suite (component User Interface). Supported versions that are affected are 12.1.1-12.1.3 and 12.2.3-12.2.8. Easily exploitable vulnerability allows unauthenticated attacker with network access via HTTP to compromise Oracle iSupport. Successful attacks require human interaction from a person other than the attacker and while the vulnerability is in Oracle iSupport, attacks may significantly impact additional products. Successful attacks of this vulnerability can result in unauthorized update, insert or delete access to some of Oracle iSupport accessible data. CVSS 3.0 Base Score 4.7 (Integrity impacts). CVSS Vector (CVSS3.0/AVN/ACL/PRN/UIR/SC/CN/IL/AN).",
    "keyphrases": {
        "rootcause": "",
        "weakness": "",
        "impact": "unauthorized update, insert or delete access",
        "vector": "network access via HTTP",
        "attacker": "unauthenticated attacker",
        "product": "Oracle E-Business Suite",
        "version": "12.1.1-12.1.3 and 12.2.3-12.2.8",
        "component": "Oracle iSupport"
    }
}
