{
    "cveId": "CVE-2020-2771",
    "version": "1.0.0",
    "timestamp": "2024-12-15T20:24:27.876763+00:00",
    "description": "Vulnerability in the Oracle Solaris product of Oracle Systems (component Whodo). Supported versions that are affected are 10 and 11. Difficult to exploit vulnerability allows low privileged attacker with logon to the infrastructure where Oracle Solaris executes to compromise Oracle Solaris. Successful attacks require human interaction from a person other than the attacker and while the vulnerability is in Oracle Solaris, attacks may significantly impact additional products. Successful attacks of this vulnerability can result in unauthorized read access to a subset of Oracle Solaris accessible data. CVSS 3.0 Base Score 2.5 (Confidentiality impacts). CVSS Vector (CVSS3.0/AVL/ACH/PRL/UIR/SC/CL/IN/AN).",
    "keyphrases": {
        "rootcause": "",
        "weakness": "",
        "impact": "unauthorized read access to a subset of Oracle Solaris accessible data",
        "vector": "",
        "attacker": "low privileged attacker",
        "product": "Oracle Solaris",
        "version": "10 and 11",
        "component": "Whodo"
    }
}
