{
    "cveId": "CVE-2020-2734",
    "version": "1.0.0",
    "timestamp": "2024-12-06T11:32:07.789868+00:00",
    "description": "Vulnerability in the RDBMS/Optimizer component of Oracle Database Server. Supported versions that are affected are 12.1.0.2, 12.2.0.1, 18c and 19c. Easily exploitable vulnerability allows high privileged attacker having Execute on DBMS_SQLTUNE privilege with network access via Oracle Net to compromise RDBMS/Optimizer. Successful attacks require human interaction from a person other than the attacker. Successful attacks of this vulnerability can result in unauthorized read access to a subset of RDBMS/Optimizer accessible data. CVSS 3.0 Base Score 2.4 (Confidentiality impacts). CVSS Vector (CVSS3.0/AVN/ACL/PRH/UIR/SU/CL/IN/AN).",
    "keyphrases": {
        "rootcause": "",
        "weakness": "",
        "impact": "unauthorized read access to a subset of RDBMS/Optimizer accessible data",
        "vector": "",
        "attacker": "high privileged attacker having Execute on DBMS_SQLTUNE privilege",
        "product": "Oracle Database Server",
        "version": "12.1.0.2, 12.2.0.1, 18c and 19c",
        "component": "RDBMS/Optimizer"
    }
}
