{
    "cveId": "CVE-2020-2538",
    "version": "1.0.0",
    "timestamp": "2024-12-06T11:32:07.789868+00:00",
    "description": "Vulnerability in the Oracle WebCenter Sites product of Oracle Fusion Middleware (component Advanced UI). The supported version that is affected is 12.2.1.3.0. Easily exploitable vulnerability allows unauthenticated attacker with network access via HTTP to compromise Oracle WebCenter Sites. Successful attacks require human interaction from a person other than the attacker and while the vulnerability is in Oracle WebCenter Sites, attacks may significantly impact additional products. Successful attacks of this vulnerability can result in unauthorized update, insert or delete access to some of Oracle WebCenter Sites accessible data as well as unauthorized read access to a subset of Oracle WebCenter Sites accessible data and unauthorized ability to cause a partial denial of service (partial DOS) of Oracle WebCenter Sites. CVSS 3.0 Base Score 7.1 (Confidentiality, Integrity and Availability impacts). CVSS Vector (CVSS3.0/AVN/ACL/PRN/UIR/SC/CL/IL/AL).",
    "keyphrases": {
        "rootcause": "",
        "weakness": "",
        "impact": [
            "unauthorized update",
            "insert or delete access",
            "unauthorized read access",
            "partial denial of service (partial DOS)"
        ],
        "vector": "unauthenticated attacker with network access via HTTP",
        "attacker": "unauthenticated attacker",
        "product": "Oracle WebCenter Sites",
        "version": "12.2.1.3.0",
        "component": "Advanced UI"
    }
}
