{
    "cveId": "CVE-2020-2654",
    "version": "1.0.0",
    "timestamp": "2024-12-06T11:32:07.789868+00:00",
    "description": "Vulnerability in the Java SE product of Oracle Java SE (component Libraries). Supported versions that are affected are Java SE 7u241, 8u231, 11.0.5 and 13.0.1. Difficult to exploit vulnerability allows unauthenticated attacker with network access via multiple protocols to compromise Java SE. Successful attacks of this vulnerability can result in unauthorized ability to cause a partial denial of service (partial DOS) of Java SE. Note This vulnerability can only be exploited by supplying data to APIs in the specified Component without using Untrusted Java Web Start applications or Untrusted Java applets, such as through a web service. CVSS 3.0 Base Score 3.7 (Availability impacts). CVSS Vector (CVSS3.0/AVN/ACH/PRN/UIN/SU/CN/IN/AL).",
    "keyphrases": {
        "rootcause": "",
        "weakness": "",
        "impact": "partial denial of service (partial DOS)",
        "vector": "",
        "attacker": "unauthenticated attacker with network access",
        "product": "Oracle Java SE",
        "version": "Java SE 7u241, 8u231, 11.0.5 and 13.0.1",
        "component": "Libraries"
    }
}
