{
    "cveId": "CVE-2020-2910",
    "version": "1.0.0",
    "timestamp": "2024-12-06T11:32:07.789868+00:00",
    "description": "Vulnerability in the Oracle VM VirtualBox product of Oracle Virtualization (component Core). Supported versions that are affected are Prior to 6.0.20 and prior to 6.1.6. Easily exploitable vulnerability allows low privileged attacker with logon to the infrastructure where Oracle VM VirtualBox executes to compromise Oracle VM VirtualBox. While the vulnerability is in Oracle VM VirtualBox, attacks may significantly impact additional products. Successful attacks of this vulnerability can result in unauthorized creation, deletion or modification access to critical data or all Oracle VM VirtualBox accessible data. CVSS 3.0 Base Score 6.5 (Integrity impacts). CVSS Vector (CVSS3.0/AVL/ACL/PRL/UIN/SC/CN/IH/AN).",
    "keyphrases": {
        "rootcause": "",
        "weakness": "",
        "impact": "unauthorized creation, deletion or modification access to critical data",
        "vector": "",
        "attacker": "low privileged attacker",
        "product": "Oracle VM VirtualBox",
        "version": "Prior to 6.0.20 and prior to 6.1.6",
        "component": "Core"
    }
}
