{
    "cveId": "CVE-2020-2646",
    "version": "1.0.0",
    "timestamp": "2024-12-06T11:32:07.789868+00:00",
    "description": "Vulnerability in the Enterprise Manager Base Platform product of Oracle Enterprise Manager (component Command Line Interface). Supported versions that are affected are 12.1.0.5, 13.2.0.0 and 13.3.0.0. Easily exploitable vulnerability allows low privileged attacker with network access via HTTP to compromise Enterprise Manager Base Platform. Successful attacks require human interaction from a person other than the attacker and while the vulnerability is in Enterprise Manager Base Platform, attacks may significantly impact additional products. Successful attacks of this vulnerability can result in unauthorized update, insert or delete access to some of Enterprise Manager Base Platform accessible data as well as unauthorized read access to a subset of Enterprise Manager Base Platform accessible data. CVSS 3.0 Base Score 5.4 (Confidentiality and Integrity impacts). CVSS Vector (CVSS3.0/AVN/ACL/PRL/UIR/SC/CL/IL/AN).",
    "keyphrases": {
        "rootcause": "",
        "weakness": "",
        "impact": "unauthorized update, insert or delete access",
        "vector": "network access via HTTP",
        "attacker": "low privileged attacker",
        "product": "Oracle Enterprise Manager",
        "version": "12.1.0.5, 13.2.0.0 and 13.3.0.0",
        "component": "Command Line Interface"
    }
}
