{
    "cveId": "CVE-2020-2912",
    "version": "1.0.0",
    "timestamp": "2024-12-06T11:32:07.789868+00:00",
    "description": "Vulnerability in the PeopleSoft Enterprise CS Campus Community product of Oracle PeopleSoft (component Self-Service). The supported version that is affected is 9.2. Easily exploitable vulnerability allows low privileged attacker with network access via HTTP to compromise PeopleSoft Enterprise CS Campus Community. While the vulnerability is in PeopleSoft Enterprise CS Campus Community, attacks may significantly impact additional products. Successful attacks of this vulnerability can result in unauthorized read access to a subset of PeopleSoft Enterprise CS Campus Community accessible data. CVSS 3.0 Base Score 5.0 (Confidentiality impacts). CVSS Vector (CVSS3.0/AVN/ACL/PRL/UIN/SC/CL/IN/AN).",
    "keyphrases": {
        "rootcause": "",
        "weakness": "",
        "impact": "unauthorized read access",
        "vector": "",
        "attacker": "low privileged attacker",
        "product": "Oracle PeopleSoft",
        "version": "9.2",
        "component": "PeopleSoft Enterprise CS Campus Community"
    }
}
