{
    "cveId": "CVE-2020-2745",
    "version": "1.0.0",
    "timestamp": "2024-12-06T11:32:07.789868+00:00",
    "description": "Vulnerability in the Oracle Access Manager product of Oracle Fusion Middleware (component Federation). Supported versions that are affected are 11.1.2.3.0 and 12.2.1.3.0. Easily exploitable vulnerability allows unauthenticated attacker with network access via HTTP to compromise Oracle Access Manager. Successful attacks require human interaction from a person other than the attacker. Successful attacks of this vulnerability can result in unauthorized ability to cause a partial denial of service (partial DOS) of Oracle Access Manager. CVSS 3.0 Base Score 4.3 (Availability impacts). CVSS Vector (CVSS3.0/AVN/ACL/PRN/UIR/SU/CN/IN/AL).",
    "keyphrases": {
        "rootcause": "",
        "weakness": "",
        "impact": "partial denial of service (partial DOS)",
        "vector": "network access via HTTP",
        "attacker": "unauthenticated attacker",
        "product": "Oracle Access Manager",
        "version": "11.1.2.3.0 and 12.2.1.3.0",
        "component": "Federation"
    }
}
