{
    "cveId": "CVE-2020-2560",
    "version": "1.0.0",
    "timestamp": "2024-12-06T11:32:07.789868+00:00",
    "description": "Vulnerability in the Siebel UI Framework product of Oracle Siebel CRM (component SWSE Server). Supported versions that are affected are 19.10 and prior. Easily exploitable vulnerability allows unauthenticated attacker with network access via HTTP to compromise Siebel UI Framework. Successful attacks require human interaction from a person other than the attacker and while the vulnerability is in Siebel UI Framework, attacks may significantly impact additional products. Successful attacks of this vulnerability can result in unauthorized read access to a subset of Siebel UI Framework accessible data. CVSS 3.0 Base Score 4.7 (Confidentiality impacts). CVSS Vector (CVSS3.0/AVN/ACL/PRN/UIR/SC/CL/IN/AN).",
    "keyphrases": {
        "rootcause": "",
        "weakness": "",
        "impact": "unauthorized read access to a subset of Siebel UI Framework accessible data",
        "vector": "",
        "attacker": "unauthenticated attacker",
        "product": "Oracle Siebel CRM",
        "version": "19.10 and prior",
        "component": "Siebel UI Framework"
    }
}
