{
  "cveId": "CVE-2020-2688",
  "version": "1.0.0",
  "timestamp": "2024-12-06T11:32:07.789868+00:00",
  "description": "Vulnerability in the Oracle Financial Services Analytical Applications Infrastructure product of Oracle Financial Services Applications (component Object Migration). Supported versions that are affected are 8.0.4-8.0.8. Easily exploitable vulnerability allows low privileged attacker with network access via HTTP to compromise Oracle Financial Services Analytical Applications Infrastructure. Successful attacks of this vulnerability can result in unauthorized access to critical data or complete access to all Oracle Financial Services Analytical Applications Infrastructure accessible data as well as unauthorized update, insert or delete access to some of Oracle Financial Services Analytical Applications Infrastructure accessible data. CVSS 3.0 Base Score 7.1 (Confidentiality and Integrity impacts). CVSS Vector (CVSS3.0/AVN/ACL/PRL/UIN/SU/CH/IL/AN).",
  "keyphrases": {
    "rootcause": "",
    "weakness": "",
    "impact": [
      "Integrity",
      "complete access to all Oracle Financial Services Analytical Applications Infrastructure accessible data",
      "insert or delete access to some of Oracle Financial Services Analytical Applications Infrastructure accessible data",
      "unauthorized access to critical data",
      "unauthorized update"
    ],
    "vector": "low privileged attacker with network access via HTTP",
    "attacker": "",
    "product": "Oracle Financial Services Analytical Applications Infrastructure",
    "version": "8.0.4-8.0.8",
    "component": "Object Migration"
  },
  "mitreTechnicalImpacts": []
}