{
    "cveId": "CVE-2006-6731",
    "version": "1.0.0",
    "timestamp": "2024-12-10T17:54:04.992951+00:00",
    "description": "Multiple buffer overflows in Sun Java Development Kit (JDK) and Java Runtime Environment (JRE) 5.0 Update 7 and earlier, Java System Development Kit (SDK) and JRE 1.4.2_12 and earlier 1.4.x versions, and SDK and JRE 1.3.1_18 and earlier allow attackers to develop Java applets that read, write, or execute local files, possibly related to (1) integer overflows in the Java_sun_awt_image_ImagingLib_convolveBI, awt_parseRaster, and awt_parseColorModel functions (2) a stack overflow in the Java_sun_awt_image_ImagingLib_lookupByteRaster function and (3) improper handling of certain negative values in the Java_sun_font_SunLayoutEngine_nativeLayout function. NOTE some of these details are obtained from third party information.",
    "keyphrases": {
        "rootcause": [
            "integer overflows",
            "stack overflow",
            "improper handling of certain negative values"
        ],
        "weakness": [
            "time of check time of use race condition",
            "buffer overflows"
        ],
        "impact": "read, write, or execute local files",
        "vector": "",
        "attacker": "attackers",
        "product": [
            "Sun Java Development Kit",
            "Java Runtime Environment",
            "Java System Development Kit"
        ],
        "version": "5.0 Update 7 and earlier, 1.4.2_12 and earlier 1.4.x versions, 1.3.1_18 and earlier",
        "component": [
            "Java_sun_awt_image_ImagingLib_convolveBI",
            "awt_parseRaster",
            "awt_parseColorModel functions",
            "Java_sun_awt_image_ImagingLib_lookupByteRaster function",
            "Java_sun_font_SunLayoutEngine_nativeLayout function"
        ]
    }
}
