{
    "cveId": "CVE-2013-3770",
    "version": "1.0.0",
    "timestamp": "2024-12-10T17:54:04.992951+00:00",
    "description": "Unspecified vulnerability in the Oracle WebCenter Content component in Oracle Fusion Middleware 10.1.3.5.1, 11.1.1.6.0, and 11.1.1.7.0 allows remote authenticated users to affect confidentiality and integrity via unknown vectors related to Content Server. NOTE the previous information is from the October 2013 CPU. Oracle has not commented on claims from a third party that the issue is related to iDoc script injection in the (1) cs and (2) urm components, which allows attackers to read sensitive files, as demonstrated by obtaining the AES encryption key and encrypted credentials of the weblogic user.",
    "keyphrases": {
        "rootcause": "unspecified vulnerability",
        "weakness": "script injection",
        "impact": [
            "read sensitive files",
            "obtain AES encryption key",
            "obtain encrypted credentials"
        ],
        "vector": "iDoc script injection",
        "attacker": "remote authenticated users",
        "product": "Oracle WebCenter Content",
        "version": [
            "10.1.3.5.1",
            "11.1.1.6.0",
            "11.1.1.7.0"
        ],
        "component": [
            "cs",
            "urm components"
        ]
    }
}
