{
  "cveId": "CVE-2023-32134",
  "version": "1.0.0",
  "timestamp": "2024-12-06T11:32:07.789868+00:00",
  "description": "Sante DICOM Viewer Pro DCM File Parsing Use-After-Free Remote Code Execution Vulnerability. This vulnerability allows remote attackers to execute arbitrary code on affected installations of Sante DICOM Viewer Pro. User interaction is required to exploit this vulnerability in that the target must visit a malicious page or open a malicious file. The specific flaw exists within the parsing of DCM images. The issue results from the lack of validating the existence of an object prior to performing operations on the object. An attacker can leverage this vulnerability to execute code in the context of the current process. Was ZDI-CAN-15629.",
  "keyphrases": {
    "rootcause": "lack of validating the existence of an object prior to performing operations on the object",
    "weakness": "Use-After-Free",
    "impact": [
      "execute arbitrary code",
      "execute code in the context of the current process",
      "remote code execution"
    ],
    "vector": "",
    "attacker": "remote attackers",
    "product": "Sante DICOM Viewer Pro",
    "version": "",
    "component": "DCM File Parsing"
  },
  "mitreTechnicalImpacts": []
}