{
  "cveId": "CVE-2023-32175",
  "version": "1.0.0",
  "timestamp": "2024-12-06T11:32:07.789868+00:00",
  "description": "VIPRE Antivirus Plus Link Following Local Privilege Escalation Vulnerability. This vulnerability allows local attackers to escalate privileges on affected installations of VIPRE Antivirus Plus. An attacker must first obtain the ability to execute low-privileged code on the target system in order to exploit this vulnerability. The specific flaw exists within the Anti Malware Service. By creating a symbolic link, an attacker can abuse the service to create arbitrary files. An attacker can leverage this vulnerability to escalate privileges and execute arbitrary code in the context of SYSTEM. Was ZDI-CAN-18899.",
  "keyphrases": {
    "rootcause": "",
    "weakness": "Privilege Escalation Vulnerability",
    "impact": [
      "Privilege Escalation",
      "escalate privileges and execute arbitrary code"
    ],
    "vector": "create a symbolic link",
    "attacker": "local attackers",
    "product": "VIPRE Antivirus Plus",
    "version": "",
    "component": "Anti Malware Service"
  },
  "mitreTechnicalImpacts": []
}