{
  "cveId": "CVE-2023-22102",
  "version": "1.0.0",
  "timestamp": "2024-12-17T08:36:27.567979+00:00",
  "description": "Vulnerability in the MySQL Connectors product of Oracle MySQL (component Connector/J). Supported versions that are affected are 8.1.0 and prior. Difficult to exploit vulnerability allows unauthenticated attacker with network access via multiple protocols to compromise MySQL Connectors. Successful attacks require human interaction from a person other than the attacker and while the vulnerability is in MySQL Connectors, attacks may significantly impact additional products (scope change). Successful attacks of this vulnerability can result in takeover of MySQL Connectors. CVSS 3.1 Base Score 8.3 (Confidentiality, Integrity and Availability impacts). CVSS Vector (CVSS3.1/AVN/ACH/PRN/UIR/SC/CH/IH/AH).",
  "keyphrases": {
    "rootcause": "",
    "weakness": "",
    "impact": [
      "Integrity and Availability impacts",
      "takeover of MySQL Connectors"
    ],
    "vector": "multiple protocols",
    "attacker": "unauthenticated attacker with network access",
    "product": "Oracle MySQL",
    "version": "8.1.0 and prior",
    "component": "Connector/J"
  },
  "mitreTechnicalImpacts": []
}