{
  "cveId": "CVE-2023-22117",
  "version": "1.0.0",
  "timestamp": "2024-12-06T11:32:07.789868+00:00",
  "description": "Vulnerability in the Oracle FLEXCUBE Universal Banking product of Oracle Financial Services Applications (component Infrastructure). Supported versions that are affected are 12.3, 12.4, 14.0-14.3 and 14.5-14.7. Easily exploitable vulnerability allows low privileged attacker with network access via HTTP to compromise Oracle FLEXCUBE Universal Banking. Successful attacks require human interaction from a person other than the attacker and while the vulnerability is in Oracle FLEXCUBE Universal Banking, attacks may significantly impact additional products (scope change). Successful attacks of this vulnerability can result in unauthorized update, insert or delete access to some of Oracle FLEXCUBE Universal Banking accessible data as well as unauthorized read access to a subset of Oracle FLEXCUBE Universal Banking accessible data. CVSS 3.1 Base Score 5.4 (Confidentiality and Integrity impacts). CVSS Vector (CVSS3.1/AVN/ACL/PRL/UIR/SC/CL/IL/AN).",
  "keyphrases": {
    "rootcause": "",
    "weakness": "",
    "impact": [
      "Integrity",
      "insert or delete access",
      "unauthorized read access",
      "unauthorized update"
    ],
    "vector": "",
    "attacker": "low privileged attacker with network access via HTTP",
    "product": "Oracle FLEXCUBE Universal Banking",
    "version": [
      "12.3",
      "12.4",
      "14.0-14.3 and 14.5-14.7"
    ],
    "component": "Infrastructure"
  },
  "mitreTechnicalImpacts": []
}