{
    "cveId": "CVE-2023-22106",
    "version": "1.0.0",
    "timestamp": "2024-12-06T11:32:07.789868+00:00",
    "description": "Vulnerability in the Oracle Enterprise Command Center Framework product of Oracle E-Business Suite (component API). Supported versions that are affected are ECC 8, 9 and 10. Easily exploitable vulnerability allows low privileged attacker with network access via HTTP to compromise Oracle Enterprise Command Center Framework. Successful attacks of this vulnerability can result in unauthorized access to critical data or complete access to all Oracle Enterprise Command Center Framework accessible data. CVSS 3.1 Base Score 6.5 (Confidentiality impacts). CVSS Vector (CVSS3.1/AVN/ACL/PRL/UIN/SU/CH/IN/AN).",
    "keyphrases": {
        "rootcause": "",
        "weakness": "",
        "impact": "unauthorized access to critical data",
        "vector": "low privileged attacker with network access via HTTP",
        "attacker": "",
        "product": "Oracle Enterprise Command Center Framework",
        "version": "ECC 8, 9 and 10",
        "component": "API"
    }
}
