{
    "cveId": "CVE-2023-22003",
    "version": "1.0.0",
    "timestamp": "2024-12-06T11:32:07.789868+00:00",
    "description": "Vulnerability in the Oracle Solaris product of Oracle Systems (component Utility). Supported versions that are affected are 10 and 11. Easily exploitable vulnerability allows unauthenticated attacker with logon to the infrastructure where Oracle Solaris executes to compromise Oracle Solaris. Successful attacks require human interaction from a person other than the attacker. Successful attacks of this vulnerability can result in unauthorized update, insert or delete access to some of Oracle Solaris accessible data. CVSS 3.1 Base Score 3.3 (Integrity impacts). CVSS Vector (CVSS3.1/AVL/ACL/PRN/UIR/SU/CN/IL/AN).",
    "keyphrases": {
        "rootcause": "",
        "weakness": "",
        "impact": "unauthorized update, insert or delete access to some of Oracle Solaris accessible data",
        "vector": "",
        "attacker": "unauthenticated attacker with logon to the infrastructure where Oracle Solaris executes",
        "product": "Oracle Solaris",
        "version": "10 and 11",
        "component": "Utility"
    }
}
