{
  "cveId": "CVE-2023-22060",
  "version": "1.0.0",
  "timestamp": "2024-12-06T11:32:07.789868+00:00",
  "description": "Vulnerability in the Oracle Hyperion Workspace product of Oracle Hyperion (component UI and Visualization). The supported version that is affected is 11.2.13.0.000. Easily exploitable vulnerability allows low privileged attacker with network access via HTTP to compromise Oracle Hyperion Workspace. Successful attacks require human interaction from a person other than the attacker. Successful attacks of this vulnerability can result in unauthorized creation, deletion or modification access to critical data or all Oracle Hyperion Workspace accessible data as well as unauthorized access to critical data or complete access to all Oracle Hyperion Workspace accessible data and unauthorized ability to cause a partial denial of service (partial DOS) of Oracle Hyperion Workspace. CVSS 3.1 Base Score 7.6 (Confidentiality, Integrity and Availability impacts). CVSS Vector (CVSS3.1/AVN/ACL/PRL/UIR/SU/CH/IH/AL).",
  "keyphrases": {
    "rootcause": "",
    "weakness": "",
    "impact": [
      "Integrity and Availability impacts",
      "deletion or modification access to critical data or all Oracle Hyperion Workspace accessible data as well as unauthorized access to critical data or complete access to all Oracle Hyperion Workspace accessible data and unauthorized ability to cause a partial denial of service (partial DOS) of Oracle Hyperion Workspace",
      "unauthorized creation"
    ],
    "vector": "",
    "attacker": "low privileged attacker",
    "product": "Oracle Hyperion Workspace",
    "version": "11.2.13.0.000",
    "component": "UI and Visualization"
  },
  "mitreTechnicalImpacts": []
}