{
    "cveId": "CVE-2023-22053",
    "version": "1.0.0",
    "timestamp": "2024-12-06T11:32:07.789868+00:00",
    "description": "Vulnerability in the MySQL Server product of Oracle MySQL (component Client programs). Supported versions that are affected are 5.7.42 and prior and 8.0.33 and prior. Difficult to exploit vulnerability allows low privileged attacker with network access via multiple protocols to compromise MySQL Server. Successful attacks of this vulnerability can result in unauthorized ability to cause a hang or frequently repeatable crash (complete DOS) of MySQL Server and unauthorized read access to a subset of MySQL Server accessible data. CVSS 3.1 Base Score 5.9 (Confidentiality and Availability impacts). CVSS Vector (CVSS3.1/AVN/ACH/PRL/UIN/SU/CL/IN/AH).",
    "keyphrases": {
        "rootcause": "",
        "weakness": "",
        "impact": [
            "cause a hang or frequently repeatable crash (complete DOS) of MySQL Server",
            "unauthorized read access to a subset of MySQL Server accessible data"
        ],
        "vector": "multiple protocols",
        "attacker": "low privileged attacker with network access",
        "product": "MySQL Server",
        "version": [
            "5.7.42 and prior",
            "8.0.33 and prior"
        ],
        "component": "Client programs"
    }
}
