{
  "cveId": "CVE-2023-22067",
  "version": "1.0.0",
  "timestamp": "2024-12-17T08:36:27.567979+00:00",
  "description": "Vulnerability in the Oracle Java SE, Oracle GraalVM Enterprise Edition product of Oracle Java SE (component CORBA). Supported versions that are affected are Oracle Java SE 8u381, 8u381-perf Oracle GraalVM Enterprise Edition 20.3.11 and 21.3.7. Easily exploitable vulnerability allows unauthenticated attacker with network access via CORBA to compromise Oracle Java SE, Oracle GraalVM Enterprise Edition. Successful attacks of this vulnerability can result in unauthorized update, insert or delete access to some of Oracle Java SE, Oracle GraalVM Enterprise Edition accessible data. Note This vulnerability can only be exploited by supplying data to APIs in the specified Component without using Untrusted Java Web Start applications or Untrusted Java applets, such as through a web service. CVSS 3.1 Base Score 5.3 (Integrity impacts). CVSS Vector (CVSS3.1/AVN/ACL/PRN/UIN/SU/CN/IL/AN).",
  "keyphrases": {
    "rootcause": "",
    "weakness": "",
    "impact": [
      "Oracle GraalVM Enterprise Edition accessible data",
      "insert or delete access",
      "unauthorized update"
    ],
    "vector": "network access via CORBA",
    "attacker": "unauthenticated attacker",
    "product": [
      "['Oracle Java SE'",
      "'Oracle GraalVM Enterprise Edition']"
    ],
    "version": [
      "8u381",
      "8u381-perf",
      "20.3.11",
      "21.3.7"
    ],
    "component": "CORBA"
  },
  "mitreTechnicalImpacts": []
}