{
  "cveId": "CVE-2023-22074",
  "version": "1.0.0",
  "timestamp": "2024-12-18T22:42:50.929578+00:00",
  "description": "Vulnerability in the Oracle Database Sharding component of Oracle Database Server. Supported versions that are affected are 19.3-19.20 and 21.3-21.11. Easily exploitable vulnerability allows high privileged attacker having Create Session, Select Any Dictionary privilege with network access via Oracle Net to compromise Oracle Database Sharding. Successful attacks require human interaction from a person other than the attacker. Successful attacks of this vulnerability can result in unauthorized ability to cause a partial denial of service (partial DOS) of Oracle Database Sharding. CVSS 3.1 Base Score 2.4 (Availability impacts). CVSS Vector (CVSS3.1/AVN/ACL/PRH/UIR/SU/CN/IN/AL).",
  "keyphrases": {
    "rootcause": "",
    "weakness": "",
    "impact": [
      "DOS",
      "partial denial of service"
    ],
    "vector": "Oracle Net",
    "attacker": "high privileged attacker",
    "product": "Oracle Database Server",
    "version": "19.3-19.20 and 21.3-21.11",
    "component": "Oracle Database Sharding"
  },
  "mitreTechnicalImpacts": []
}