{
    "cveId": "CVE-2023-22016",
    "version": "1.0.0",
    "timestamp": "2024-12-06T11:32:07.789868+00:00",
    "description": "Vulnerability in the Oracle VM VirtualBox product of Oracle Virtualization (component Core). Supported versions that are affected are Prior to 6.1.46 and Prior to 7.0.10. Easily exploitable vulnerability allows high privileged attacker with logon to the infrastructure where Oracle VM VirtualBox executes to compromise Oracle VM VirtualBox. Successful attacks require human interaction from a person other than the attacker. Successful attacks of this vulnerability can result in unauthorized ability to cause a hang or frequently repeatable crash (complete DOS) of Oracle VM VirtualBox. CVSS 3.1 Base Score 4.2 (Availability impacts). CVSS Vector (CVSS3.1/AVL/ACL/PRH/UIR/SU/CN/IN/AH).",
    "keyphrases": {
        "rootcause": "",
        "weakness": "",
        "impact": "cause a hang or frequently repeatable crash (complete DOS) of Oracle VM VirtualBox",
        "vector": "",
        "attacker": "high privileged attacker",
        "product": "Oracle VM VirtualBox",
        "version": "Prior to 6.1.46 and Prior to 7.0.10",
        "component": "Core"
    }
}
