{
    "cveId": "CVE-2023-22022",
    "version": "1.0.0",
    "timestamp": "2024-12-06T11:32:07.789868+00:00",
    "description": "Vulnerability in the Oracle Health Sciences Sciences Data Management Workbench product of Oracle Health Sciences Applications (component Blinding Functionality). Supported versions that are affected are 3.1.0.2, 3.1.1.3 and 3.2.0.0. Easily exploitable vulnerability allows low privileged attacker with network access via HTTP to compromise Oracle Health Sciences Sciences Data Management Workbench. Successful attacks of this vulnerability can result in unauthorized access to critical data or complete access to all Oracle Health Sciences Sciences Data Management Workbench accessible data. CVSS 3.1 Base Score 6.5 (Confidentiality impacts). CVSS Vector (CVSS3.1/AVN/ACL/PRL/UIN/SU/CH/IN/AN).",
    "keyphrases": {
        "rootcause": "",
        "weakness": "",
        "impact": [
            "unauthorized access to critical data",
            "complete access to all Oracle Health Sciences Sciences Data Management Workbench accessible data"
        ],
        "vector": "network access via HTTP",
        "attacker": "low privileged attacker",
        "product": "Oracle Health Sciences Sciences Data Management Workbench",
        "version": "3.1.0.2, 3.1.1.3 and 3.2.0.0",
        "component": "Blinding Functionality"
    }
}
