{
    "cveId": "CVE-2022-36363",
    "version": "1.0.0",
    "timestamp": "2024-11-03T18:37:50.907685+00:00",
    "description": "A vulnerability has been identified in LOGO! 12/24RCE (All versions), LOGO! 12/24RCEo (All versions), LOGO! 230RCE (All versions), LOGO! 230RCEo (All versions), LOGO! 24CE (All versions), LOGO! 24CEo (All versions), LOGO! 24RCE (All versions), LOGO! 24RCEo (All versions), SIPLUS LOGO! 12/24RCE (All versions), SIPLUS LOGO! 12/24RCEo (All versions), SIPLUS LOGO! 230RCE (All versions), SIPLUS LOGO! 230RCEo (All versions), SIPLUS LOGO! 24CE (All versions), SIPLUS LOGO! 24CEo (All versions), SIPLUS LOGO! 24RCE (All versions), SIPLUS LOGO! 24RCEo (All versions). Affected devices do not properly validate an offset value which can be defined in TCP packets when calling a method. This could allow an attacker to retrieve parts of the content of the memory.",
    "keyphrases": {
        "rootcause": "do not properly validate an offset value",
        "weakness": "",
        "impact": "retrieve parts of the content of the memory",
        "vector": "TCP packets",
        "attacker": "attacker",
        "product": [
            "LOGO!",
            "SIPLUS LOGO!"
        ],
        "version": "All versions",
        "component": ""
    },
    "mitreTechnicalImpacts": [
        "Read data"
    ]
}
