{
    "cveId": "CVE-2021-40335",
    "version": "1.0.0",
    "timestamp": "2024-12-15T20:24:27.876763+00:00",
    "description": "A vulnerability exists in the HTTP web interface where the web interface does not sufficiently verify if a well-formed, valid, consistent request was intentionally provided by the user who submitted the request. This cause a Cross Site Request Forgery (CSRF), which if exploited could lead an attacker to gain unauthorized access to the web application and perform an unwanted operation on it without the knowledge of the legitimate user. An attacker, who successfully makes an MSM user who has already established a session to MSM web interface clicks a forged link to the MSM web interface, e.g., link is sent per E-Mail, could perform harmful command on MSM through its web server interface. This issue affects Hitachi Energy MSM V2.2 and prior versions.",
    "keyphrases": {
        "rootcause": "does not sufficiently verify if a well-formed, valid, consistent request was intentionally provided",
        "weakness": "Cross Site Request Forgery",
        "impact": "gain unauthorized access",
        "vector": "",
        "attacker": "attacker",
        "product": "Hitachi Energy MSM",
        "version": "V2.2 and prior versions",
        "component": "HTTP web interface"
    }
}
