{
    "cveId": "CVE-2018-0086",
    "version": "1.0.0",
    "timestamp": "2024-12-11T16:08:24.783251+00:00",
    "description": "A vulnerability in the application server of the Cisco Unified Customer Voice Portal (CVP) could allow an unauthenticated, remote attacker to cause a denial of service (DoS) condition on the affected device. The vulnerability is due to malformed SIP INVITE traffic received on the CVP during communications with the Cisco Virtualized Voice Browser (VVB). An attacker could exploit this vulnerability by sending malformed SIP INVITE traffic to the targeted appliance. An exploit could allow the attacker to impact the availability of services and data on the device, causing a DoS condition. This vulnerability affects Cisco Unified CVP running any software release prior to 11.6(1). Cisco Bug IDs CSCve85840.",
    "keyphrases": {
        "rootcause": "",
        "weakness": "",
        "impact": "denial of service (DoS)",
        "vector": "malformed SIP INVITE traffic",
        "attacker": "unauthenticated, remote attacker",
        "product": "Cisco Unified Customer Voice Portal",
        "version": "prior to 11.6(1)",
        "component": "application server"
    }
}
