{
    "cveId": "CVE-2018-0318",
    "version": "1.0.0",
    "timestamp": "2024-12-11T16:08:24.783251+00:00",
    "description": "A vulnerability in the password reset function of Cisco Prime Collaboration Provisioning (PCP) could allow an unauthenticated, remote attacker to gain unauthorized access to an affected device. The vulnerability is due to insufficient validation of a password reset request. An attacker could exploit this vulnerability by submitting a password reset request and changing the password for any user on an affected system. An exploit could allow the attacker to gain administrative-level privileges on the affected system. This vulnerability affects Cisco Prime Collaboration Provisioning (PCP) Releases 11.6 and prior. Cisco Bug IDs CSCvd07245.",
    "keyphrases": {
        "rootcause": "insufficient validation of a password reset request",
        "weakness": "",
        "impact": "gain administrative-level privileges",
        "vector": "password reset request",
        "attacker": "unauthenticated remote attacker",
        "product": "Cisco Prime Collaboration Provisioning",
        "version": "Releases 11.6 and prior",
        "component": "password reset function"
    }
}
