{
    "cveId": "CVE-2023-38433",
    "version": "1.0.0",
    "timestamp": "2024-12-06T11:32:07.789868+00:00",
    "description": "Fujitsu Real-time Video Transmission Gear IP series use hard-coded credentials, which may allow a remote unauthenticated attacker to initialize or reboot the products, and as a result, terminate the video transmission. Affected products and versions are as follows IP-HE950E firmware versions V01L001 to V01L053, IP-HE950D firmware versions V01L001 to V01L053, IP-HE900E firmware versions V01L001 to V01L010, IP-HE900D firmware versions V01L001 to V01L004, IP-900E / IP-920E firmware versions V01L001 to V02L061, IP-900D / IP-900IID / IP-920D firmware versions V01L001 to V02L061, IP-90 firmware versions V01L001 to V01L013, and IP-9610 firmware versions V01L001 to V02L007.",
    "keyphrases": {
        "rootcause": "hard-coded credentials",
        "weakness": "",
        "impact": [
            "initialize or reboot the products",
            "terminate the video transmission"
        ],
        "vector": "",
        "attacker": "remote unauthenticated attacker",
        "product": [
            "Fujitsu Real-time Video Transmission Gear IP series",
            "IP-HE950E",
            "IP-HE950D",
            "IP-HE900E",
            "IP-HE900D",
            "IP-900E",
            "IP-920E",
            "IP-900D",
            "IP-900IID",
            "IP-920D",
            "IP-90",
            "IP-9610"
        ],
        "version": [
            "V01L001 to V01L053",
            "V01L001 to V01L053",
            "V01L001 to V01L010",
            "V01L001 to V01L004",
            "V01L001 to V02L061",
            "V01L001 to V02L061",
            "V01L001 to V01L013",
            "V01L001 to V02L007"
        ],
        "component": ""
    }
}
