{
    "cveId": "CVE-2023-38101",
    "version": "1.0.0",
    "timestamp": "2024-12-06T11:32:07.789868+00:00",
    "description": "NETGEAR ProSAFE Network Management System SettingConfigController Exposed Dangerous Function Remote Code Execution Vulnerability. This vulnerability allows remote attackers to execute arbitrary code on affected installations of NETGEAR ProSAFE Network Management System. Although authentication is required to exploit this vulnerability, the existing authentication mechanism can be bypassed. The specific flaw exists within the SettingConfigController class. The issue results from an exposed dangerous function. An attacker can leverage this vulnerability to execute code in the context of SYSTEM. . Was ZDI-CAN-19725.",
    "keyphrases": {
        "rootcause": "exposed dangerous function",
        "weakness": "",
        "impact": "remote code execution",
        "vector": "",
        "attacker": "remote attackers",
        "product": "NETGEAR ProSAFE Network Management System",
        "version": "",
        "component": "SettingConfigController class"
    }
}
