{
  "cveId": "CVE-2024-6260",
  "version": "1.0.0",
  "timestamp": "2024-12-17T08:36:27.567979+00:00",
  "description": "Malwarebytes Antimalware Link Following Local Privilege Escalation Vulnerability. This vulnerability allows local attackers to escalate privileges on affected installations of Malwarebytes Antimalware. An attacker must first obtain the ability to execute low-privileged code on the target system in order to exploit this vulnerability. The specific flaw exists within the Malwarebytes service. By creating a symbolic link, an attacker can abuse the service to delete a file. An attacker can leverage this vulnerability to escalate privileges and execute arbitrary code in the context of SYSTEM. Was ZDI-CAN-22321.",
  "keyphrases": {
    "rootcause": "",
    "weakness": [
      "Local Privilege Escalation",
      "Privilege Escalation Vulnerability"
    ],
    "impact": [
      "Privilege Escalation",
      "delete file",
      "escalate privileges and execute arbitrary code"
    ],
    "vector": "creating a symbolic link",
    "attacker": "local attackers",
    "product": "Malwarebytes Antimalware",
    "version": "",
    "component": "Malwarebytes service"
  },
  "mitreTechnicalImpacts": []
}