{
  "cveId": "CVE-2024-6233",
  "version": "1.0.0",
  "timestamp": "2024-12-17T08:36:27.567979+00:00",
  "description": "Check Point ZoneAlarm Extreme Security Link Following Local Privilege Escalation Vulnerability. This vulnerability allows local attackers to escalate privileges on affected installations of Check Point ZoneAlarm Extreme Security. An attacker must first obtain the ability to execute low-privileged code on the target system in order to exploit this vulnerability. The specific flaw exists within the Forensic Recorder service. By creating a symbolic link, an attacker can abuse the service to overwrite arbitrary files. An attacker can leverage this vulnerability to escalate privileges and execute arbitrary code in the context of SYSTEM. Was ZDI-CAN-21677.",
  "keyphrases": {
    "rootcause": "",
    "weakness": "Privilege Escalation Vulnerability",
    "impact": [
      "Privilege Escalation",
      "escalate privileges and execute arbitrary code"
    ],
    "vector": "create symbolic link",
    "attacker": "local attackers",
    "product": "Check Point ZoneAlarm Extreme Security",
    "version": "",
    "component": "Forensic Recorder service"
  },
  "mitreTechnicalImpacts": []
}