{
  "cveId": "CVE-2023-39484",
  "version": "1.0.0",
  "timestamp": "2024-12-06T11:32:07.789868+00:00",
  "description": "PDF-XChange Editor PDF File Parsing Uninitialized Variable Information Disclosure Vulnerability. This vulnerability allows remote attackers to disclose sensitive information on affected installations of PDF-XChange Editor. User interaction is required to exploit this vulnerability in that the target must visit a malicious page or open a malicious file. The specific flaw exists within the parsing of PDF files. The issue results from the lack of proper initialization of memory prior to accessing it. An attacker can leverage this in conjunction with other vulnerabilities to execute arbitrary code in the context of the current process. Was ZDI-CAN-18493.",
  "keyphrases": {
    "rootcause": "lack of proper initialization of memory prior to accessing it",
    "weakness": [
      "Information Disclosure Vulnerability",
      "Uninitialized Variable Information Disclosure"
    ],
    "impact": [
      "Information Disclosure",
      "disclose sensitive information",
      "execute arbitrary code"
    ],
    "vector": "",
    "attacker": "remote attackers",
    "product": "PDF-XChange Editor",
    "version": "",
    "component": "parsing of PDF files"
  },
  "mitreTechnicalImpacts": []
}