{
  "cveId": "CVE-2023-39480",
  "version": "1.0.0",
  "timestamp": "2024-12-06T11:32:07.789868+00:00",
  "description": "Softing Secure Integration Server FileDirectory OPC UA Object Arbitrary File Creation Vulnerability. This vulnerability allows remote attackers to create arbitrary files on affected installations of Softing Secure Integration Server. Although authentication is required to exploit this vulnerability, the existing authentication mechanism can be bypassed. The specific flaw exists within the handling of FileDirectory OPC UA Objects. The issue results from allowing unauthorized access to the filesystem. An attacker can leverage this in conjunction with other vulnerabilities to execute arbitrary code in the context of root. Was ZDI-CAN-20549.",
  "keyphrases": {
    "rootcause": "allowing unauthorized access to the filesystem",
    "weakness": "",
    "impact": [
      "arbitrary file creation",
      "execute arbitrary code"
    ],
    "vector": "FileDirectory OPC UA Objects",
    "attacker": "remote attackers",
    "product": "Softing Secure Integration Server",
    "version": "",
    "component": ""
  },
  "mitreTechnicalImpacts": []
}