{
    "cveId": "CVE-2023-52334",
    "version": "1.0.0",
    "timestamp": "2024-12-17T08:36:27.567979+00:00",
    "description": "Allegra downloadAttachmentGlobal Directory Traversal Information Disclosure Vulnerability. This vulnerability allows remote attackers to disclose sensitive information on affected installations of Allegra. Although authentication is required to exploit this vulnerability, product implements a registration mechanism that can be used to create a user with a sufficient privilege level. The specific flaw exists within the downloadAttachmentGlobal action. The issue results from the lack of proper validation of a user-supplied path prior to using it in file operations. An attacker can leverage this vulnerability to disclose stored credentials, leading to further compromise. Was ZDI-CAN-22507.",
    "keyphrases": {
        "rootcause": "lack of proper validation of a user-supplied path",
        "weakness": "directory traversal",
        "impact": "information disclosure",
        "vector": "",
        "attacker": "remote attackers",
        "product": "Allegra",
        "version": "",
        "component": "downloadAttachmentGlobal action"
    }
}
