{
  "cveId": "CVE-2025-20307",
  "version": "1.0.0",
  "timestamp": "2025-07-05T08:16:57.403025+00:00",
  "description": "A vulnerability in the web-based management interface of Cisco BroadWorks Application Delivery Platform could allow an authenticated, remote attacker to to conduct cross-site scripting (XSS) attacks against a user of the interface. This vulnerability is due to insufficient validation of user-supplied input by the web-based management interface of an affected system. An attacker could exploit this vulnerability by injecting malicious code into specific pages of the interface. A successful exploit could allow the attacker to execute arbitrary script code in the context of the affected interface or access sensitive, browser-based information. To exploit this vulnerability, the attacker must have valid administrative credentials.",
  "keyphrases": {
    "rootcause": "insufficient validation of user-supplied input",
    "weakness": "cross-site scripting",
    "impact": "execute arbitrary script code in the context of the affected interface",
    "vector": "injecting malicious code into specific pages of the interface",
    "attacker": "authenticated remote attacker",
    "product": "Cisco BroadWorks Application Delivery Platform",
    "version": "",
    "component": "web-based management interface"
  },
  "mitreTechnicalImpacts": []
}