{
    "cveId": "CVE-2024-20955",
    "version": "1.0.0",
    "timestamp": "2024-12-06T11:32:07.789868+00:00",
    "description": "Vulnerability in the Oracle GraalVM for JDK, Oracle GraalVM Enterprise Edition product of Oracle Java SE (component Compiler). Supported versions that are affected are Oracle GraalVM for JDK 17.0.9, 21.0.1 Oracle GraalVM Enterprise Edition 20.3.12, 21.3.8 and 22.3.4. Difficult to exploit vulnerability allows unauthenticated attacker with network access via multiple protocols to compromise Oracle GraalVM for JDK, Oracle GraalVM Enterprise Edition. Successful attacks of this vulnerability can result in unauthorized read access to a subset of Oracle GraalVM for JDK, Oracle GraalVM Enterprise Edition accessible data. CVSS 3.1 Base Score 3.7 (Confidentiality impacts). CVSS Vector (CVSS3.1/AVN/ACH/PRN/UIN/SU/CL/IN/AN).",
    "keyphrases": {
        "rootcause": "",
        "weakness": "",
        "impact": "unauthorized read access",
        "vector": "multiple protocols",
        "attacker": "unauthenticated attacker with network access",
        "product": "Oracle Java SE",
        "version": "Oracle GraalVM for JDK 17.0.9, 21.0.1 Oracle GraalVM Enterprise Edition 20.3.12, 21.3.8 and 22.3.4",
        "component": "Compiler"
    }
}
