{
    "cveId": "CVE-2024-20448",
    "version": "1.0.0",
    "timestamp": "2024-12-06T11:32:07.789868+00:00",
    "description": "A vulnerability in the Cisco Nexus Dashboard Fabric Controller (NDFC) software, formerly Cisco Data Center Network Manager (DCNM), could allow an attacker with access to a backup file to view sensitive information. This vulnerability is due to the improper storage of sensitive information within config only and full backup files. An attacker could exploit this vulnerability by parsing the contents of a backup file that is generated from an affected device. A successful exploit could allow the attacker to access sensitive information, including NDFC-connected device credentials, the NDFC site manager private key, and the scheduled backup file encryption key.",
    "keyphrases": {
        "rootcause": "improper storage of sensitive information",
        "weakness": "",
        "impact": "view sensitive information",
        "vector": "parsing the contents of a backup file",
        "attacker": "attacker with access to a backup file",
        "product": "Cisco Nexus Dashboard Fabric Controller (NDFC)",
        "version": "",
        "component": ""
    }
}
