{
  "cveId": "CVE-2024-20942",
  "version": "1.0.0",
  "timestamp": "2024-12-17T08:36:27.567979+00:00",
  "description": "Vulnerability in the Oracle Complex Maintenance, Repair, and Overhaul product of Oracle Supply Chain (component LOV). Supported versions that are affected are 11.5, 12.1 and 12.2. Easily exploitable vulnerability allows unauthenticated attacker with network access via HTTP to compromise Oracle Complex Maintenance, Repair, and Overhaul. Successful attacks require human interaction from a person other than the attacker and while the vulnerability is in Oracle Complex Maintenance, Repair, and Overhaul, attacks may significantly impact additional products (scope change). Successful attacks of this vulnerability can result in unauthorized update, insert or delete access to some of Oracle Complex Maintenance, Repair, and Overhaul accessible data as well as unauthorized read access to a subset of Oracle Complex Maintenance, Repair, and Overhaul accessible data. CVSS 3.1 Base Score 6.1 (Confidentiality and Integrity impacts). CVSS Vector (CVSS3.1/AVN/ACL/PRN/UIR/SC/CL/IL/AN).",
  "keyphrases": {
    "rootcause": "",
    "weakness": "",
    "impact": [
      "Integrity",
      "and Overhaul accessible data as well as unauthorized read access to a subset of Oracle Complex Maintenance",
      "insert or delete access to some of Oracle Complex Maintenance",
      "unauthorized update"
    ],
    "vector": "unauthenticated attacker with network access via HTTP",
    "attacker": "unauthenticated attacker",
    "product": [
      "Oracle Complex Maintenance",
      "Repair",
      "and Overhaul"
    ],
    "version": [
      "11.5",
      "12.1 and 12.2"
    ],
    "component": ""
  },
  "mitreTechnicalImpacts": []
}