{
  "cveId": "CVE-2024-20940",
  "version": "1.0.0",
  "timestamp": "2024-12-17T08:36:27.567979+00:00",
  "description": "Vulnerability in the Oracle Knowledge Management product of Oracle E-Business Suite (component Create, Update, Authoring Flow). Supported versions that are affected are 12.2.3-12.2.13. Easily exploitable vulnerability allows unauthenticated attacker with network access via HTTP to compromise Oracle Knowledge Management. Successful attacks require human interaction from a person other than the attacker and while the vulnerability is in Oracle Knowledge Management, attacks may significantly impact additional products (scope change). Successful attacks of this vulnerability can result in unauthorized update, insert or delete access to some of Oracle Knowledge Management accessible data as well as unauthorized read access to a subset of Oracle Knowledge Management accessible data. CVSS 3.1 Base Score 6.1 (Confidentiality and Integrity impacts). CVSS Vector (CVSS3.1/AVN/ACL/PRN/UIR/SC/CL/IL/AN).",
  "keyphrases": {
    "rootcause": "",
    "weakness": "",
    "impact": [
      "Integrity",
      "insert or delete access to some of Oracle Knowledge Management accessible data as well as unauthorized read access to a subset of Oracle Knowledge Management accessible data",
      "unauthorized update"
    ],
    "vector": "",
    "attacker": "unauthenticated attacker",
    "product": "Oracle Knowledge Management",
    "version": "12.2.3-12.2.13",
    "component": [
      "Create",
      "Update",
      "Authoring Flow"
    ]
  },
  "mitreTechnicalImpacts": []
}