{
  "cveId": "CVE-2024-20929",
  "version": "1.0.0",
  "timestamp": "2024-12-06T11:32:07.789868+00:00",
  "description": "Vulnerability in the Oracle Application Object Library product of Oracle E-Business Suite (component DB Privileges). Supported versions that are affected are 12.2.3-12.2.13. Easily exploitable vulnerability allows unauthenticated attacker with network access via HTTP to compromise Oracle Application Object Library. Successful attacks of this vulnerability can result in unauthorized update, insert or delete access to some of Oracle Application Object Library accessible data as well as unauthorized read access to a subset of Oracle Application Object Library accessible data. CVSS 3.1 Base Score 6.5 (Confidentiality and Integrity impacts). CVSS Vector (CVSS3.1/AVN/ACL/PRN/UIN/SU/CL/IL/AN).",
  "keyphrases": {
    "rootcause": "",
    "weakness": "",
    "impact": [
      "Integrity",
      "insert or delete access",
      "unauthorized read access",
      "unauthorized update"
    ],
    "vector": "network access via HTTP",
    "attacker": "unauthenticated attacker",
    "product": "Oracle Application Object Library",
    "version": "12.2.3-12.2.13",
    "component": "DB Privileges"
  },
  "mitreTechnicalImpacts": []
}