{
    "cveId": "CVE-2020-5574",
    "version": "1.0.0",
    "timestamp": "2024-12-13T17:34:55.850537+00:00",
    "description": "HTML attribute value injection vulnerability in Movable Type series (Movable Type 7 r.4606 (7.2.1) and earlier (Movable Type 7), Movable Type Advanced 7 r.4606 (7.2.1) and earlier (Movable Type Advanced 7), Movable Type for AWS 7 r.4606 (7.2.1) and earlier (Movable Type for AWS 7), Movable Type 6.5.3 and earlier (Movable Type 6.5), Movable Type Advanced 6.5.3 and earlier (Movable Type Advanced 6.5), Movable Type 6.3.11 and earlier (Movable Type 6.3), Movable Type Advanced 6.3.11 and earlier (Movable Type 6.3), Movable Type Premium 1.29 and earlier, and Movable Type Premium Advanced 1.29 and earlier) allows remote attackers to inject arbitrary HTML attribute value via unspecified vectors.",
    "keyphrases": {
        "rootcause": "",
        "weakness": "HTML attribute value injection",
        "impact": "inject arbitrary HTML attribute value",
        "vector": "unspecified vectors",
        "attacker": "remote attackers",
        "product": [
            "Movable Type",
            "Movable Type Advanced",
            "Movable Type for AWS"
        ],
        "version": "7.2.1 and earlier",
        "component": ""
    }
}
