{
    "cveId": "CVE-2015-2142",
    "version": "1.0.0",
    "timestamp": "2024-12-11T16:08:24.783251+00:00",
    "description": "Multiple cross-site request forgery (CSRF) vulnerabilities in Issuetracker phpBugTracker before 1.7.0 allow remote authenticated users to (1) hijack the authentication of users for requests that cause an unspecified impact via the id parameter to project.php, (2) hijack the authentication of users for requests that cause an unspecified impact via the group_id parameter to group.php, (3) hijack the authentication of users for requests that delete statuses via the status_id parameter to status.php, (4) hijack the authentication of users for requests that delete severities via the severity_id parameter to severity.php, (5) hijack the authentication of users for requests that cause an unspecified impact via the priority_id parameter to priority.php, (6) hijack the authentication of users for requests that delete the operating system via the os_id parameter to os.php, (7) hijack the authentication of users for requests that delete databases via the database_id parameter to database.php, or (8) hijack the authentication of users for requests that delete sites via the site_id parameter to sites.php.",
    "keyphrases": {
        "rootcause": "cross-site request forgery",
        "weakness": "",
        "impact": "hijack authentication",
        "vector": "CSRF",
        "attacker": "remote authenticated users",
        "product": "Issuetracker phpBugTracker",
        "version": "before 1.7.0",
        "component": [
            "project.php",
            "group.php",
            "status.php",
            "severity.php",
            "priority.php",
            "os.php",
            "database.php",
            "sites.php"
        ]
    }
}
