{
    "cveId": "CVE-2015-2098",
    "version": "1.0.0",
    "timestamp": "2024-12-15T20:24:27.876763+00:00",
    "description": "Multiple stack-based buffer overflows in WebGate eDVR Manager allow remote attackers to execute arbitrary code via unspecified vectors to the (1) Connect, (2) ConnectEx, or (3) ConnectEx2 function in the WESPEvent.WESPEventCtrl.1 control (4) AudioOnlySiteChannel function in the WESPPlayback.WESPPlaybackCtrl.1 control (5) Connect or (6) ConnectEx function in the WESPPTZ.WESPPTZCtrl.1 control (7) SiteChannel property in the WESPPlayback.WESPPlaybackCtrl.1 control (8) SiteName property in the WESPPlayback.WESPPlaybackCtrl.1 control or (9) OpenDVrSSite function in the WESPPTZ.WESPPTZCtrl.1 control.",
    "keyphrases": {
        "rootcause": "stack-based buffer overflows",
        "weakness": "",
        "impact": "execute arbitrary code",
        "vector": "unspecified vectors",
        "attacker": "remote attackers",
        "product": "WebGate eDVR Manager",
        "version": "",
        "component": [
            "Connect",
            "ConnectEx",
            "ConnectEx2 function in the WESPEvent.WESPEventCtrl.1 control",
            "AudioOnlySiteChannel function in the WESPPlayback.WESPPlaybackCtrl.1 control",
            "Connect or ConnectEx function in the WESPPTZ.WESPPTZCtrl.1 control",
            "SiteChannel property in the WESPPlayback.WESPPlaybackCtrl.1 control",
            "SiteName property in the WESPPlayback.WESPPlaybackCtrl.1 control",
            "OpenDVrSSite function in the WESPPTZ.WESPPTZCtrl.1 control"
        ]
    }
}
