{
    "cveId": "CVE-2022-42973",
    "version": "1.0.0",
    "timestamp": "2024-12-19T08:32:02.878079+00:00",
    "description": "A CWE-798 Use of Hard-coded Credentials vulnerability exists that could cause local privilege escalation when local attacker connects to the database. Affected Products APC Easy UPS Online Monitoring Software (Windows 7, 10, 11 & Windows Server 2016, 2019, 2022 - Versions prior to V2.5-GA), APC Easy UPS Online Monitoring Software (Windows 11, Windows Server 2019, 2022 - Versions prior to V2.5-GA-01-22261), Schneider Electric Easy UPS Online Monitoring Software (Windows 7, 10, 11 & Windows Server 2016, 2019, 2022 - Versions prior to V2.5-GS), Schneider Electric Easy UPS Online Monitoring Software (Windows 11, Windows Server 2019, 2022 - Versions prior to V2.5-GS-01-22261)",
    "keyphrases": {
        "rootcause": "Use of Hard-coded Credentials",
        "weakness": "",
        "impact": "local privilege escalation",
        "vector": "",
        "attacker": "local attacker",
        "product": [
            "APC Easy UPS Online Monitoring Software",
            "Schneider Electric Easy UPS Online Monitoring Software"
        ],
        "version": [
            "prior to V2.5-GA",
            "prior to V2.5-GA-01-22261",
            "prior to V2.5-GS",
            "prior to V2.5-GS-01-22261"
        ],
        "component": ""
    }
}
