{
    "cveId": "CVE-2023-24544",
    "version": "1.0.0",
    "timestamp": "2024-12-15T20:24:27.876763+00:00",
    "description": "Improper access control vulnerability in Buffalo network devices allows a network-adjacent attacker to obtain specific files of the product. As a result, the product settings may be altered. The affected products and versions are as follows BS-GSL2024 firmware Ver. 1.10-0.03 and earlier, BS-GSL2016P firmware Ver. 1.10-0.03 and earlier, BS-GSL2016 firmware Ver. 1.10-0.03 and earlier, BS-GS2008 firmware Ver. 1.0.10.01 and earlier, BS-GS2016 firmware Ver. 1.0.10.01 and earlier, BS-GS2024 firmware Ver. 1.0.10.01 and earlier, BS-GS2048 firmware Ver. 1.0.10.01 and earlier, BS-GS2008P firmware Ver. 1.0.10.01 and earlier, BS-GS2016P firmware Ver. 1.0.10.01 and earlier, and BS-GS2024P firmware Ver. 1.0.10.01 and earlier",
    "keyphrases": {
        "rootcause": "Improper access control",
        "weakness": "",
        "impact": "obtain specific files",
        "vector": "",
        "attacker": "network-adjacent attacker",
        "product": [
            "BS-GSL2024",
            "BS-GSL2016P",
            "BS-GSL2016",
            "BS-GS2008",
            "BS-GS2016",
            "BS-GS2024",
            "BS-GS2048",
            "BS-GS2008P",
            "BS-GS2016P",
            "BS-GS2024P"
        ],
        "version": [
            "firmware Ver. 1.10-0.03 and earlier",
            "firmware Ver. 1.10-0.03 and earlier",
            "firmware Ver. 1.10-0.03 and earlier",
            "firmware Ver. 1.0.10.01 and earlier",
            "firmware Ver. 1.0.10.01 and earlier",
            "firmware Ver. 1.0.10.01 and earlier",
            "firmware Ver. 1.0.10.01 and earlier",
            "firmware Ver. 1.0.10.01 and earlier",
            "firmware Ver. 1.0.10.01 and earlier",
            "firmware Ver. 1.0.10.01 and earlier"
        ],
        "component": ""
    }
}
