{
    "cveId": "CVE-2016-0477",
    "version": "1.0.0",
    "timestamp": "2024-12-10T17:54:04.992951+00:00",
    "description": "Unspecified vulnerability in the Oracle Application Testing Suite component in Oracle Enterprise Manager Grid Control 12.4.0.2 and 12.5.0.2 allows remote attackers to affect confidentiality via unknown vectors related to Load Testing for Web Apps, a different vulnerability than CVE-2016-0476 and CVE-2016-0478. NOTE the previous information is from the January 2016 CPU. Oracle has not commented on third-party claims that this is a directory traversal vulnerability in the DownloadServlet servlet, which allows remote attackers to read arbitrary files via directory traversal sequences in the (1) repository, (2) workspace, or (3) scenario parameter.",
    "keyphrases": {
        "rootcause": "unspecified vulnerability",
        "weakness": "directory traversal",
        "impact": "read arbitrary files",
        "vector": "directory traversal sequences",
        "attacker": "remote attackers",
        "product": "Oracle Application Testing Suite",
        "version": "12.4.0.2 and 12.5.0.2",
        "component": "DownloadServlet servlet"
    }
}
