{
    "cveId": "CVE-2016-5551",
    "version": "1.0.0",
    "timestamp": "2024-12-06T11:32:07.789868+00:00",
    "description": "Vulnerability in the Solaris Cluster component of Oracle Sun Systems Products Suite (subcomponent NAS device addition). The supported version that is affected is 4.3. Easily exploitable vulnerability allows unauthenticated attacker with logon to the infrastructure where Solaris Cluster executes to compromise Solaris Cluster. Successful attacks require human interaction from a person other than the attacker. Successful attacks of this vulnerability can result in unauthorized read access to a subset of Solaris Cluster accessible data. CVSS 3.0 Base Score 3.3 (Confidentiality impacts). CVSS Vector (CVSS3.0/AVL/ACL/PRN/UIR/SU/CL/IN/AN).",
    "keyphrases": {
        "rootcause": "",
        "weakness": "",
        "impact": "unauthorized read access to a subset of Solaris Cluster accessible data",
        "vector": "",
        "attacker": "unauthenticated attacker",
        "product": "Oracle Sun Systems Products Suite",
        "version": "4.3",
        "component": "Solaris Cluster component"
    }
}
