{
    "cveId": "CVE-2021-28821",
    "version": "1.0.0",
    "timestamp": "2024-12-15T20:24:27.876763+00:00",
    "description": "The Windows Installation component of TIBCO Software Inc.s TIBCO Enterprise Message Service, TIBCO Enterprise Message Service - Community Edition, and TIBCO Enterprise Message Service - Developer Edition contains a vulnerability that theoretically allows a low privileged attacker with local access on some versions of the Windows operating system to insert malicious software. The affected component can be abused to execute the malicious software inserted by the attacker with the elevated privileges of the component. This vulnerability results from a lack of access restrictions on certain files and/or folders in the installation. Affected releases are TIBCO Software Inc.s TIBCO Enterprise Message Service versions 8.5.1 and below, TIBCO Enterprise Message Service - Community Edition versions 8.5.1 and below, and TIBCO Enterprise Message Service - Developer Edition versions 8.5.1 and below.",
    "keyphrases": {
        "rootcause": "lack of access restrictions on certain files and/or folders",
        "weakness": "",
        "impact": "execute malicious software",
        "vector": "",
        "attacker": "low privileged attacker with local access",
        "product": [
            "TIBCO Enterprise Message Service",
            "TIBCO Enterprise Message Service - Community Edition",
            "TIBCO Enterprise Message Service - Developer Edition"
        ],
        "version": "8.5.1 and below",
        "component": "Windows Installation component"
    }
}
