{
    "cveId": "CVE-2021-22788",
    "version": "1.0.0",
    "timestamp": "2024-12-15T20:24:27.876763+00:00",
    "description": "A CWE-787 Out-of-bounds Write vulnerability exists that could cause denial of service when an attacker sends a specially crafted HTTP request to the web server of the device. Affected Product Modicon M340 CPUs BMXP34 (Versions prior to V3.40), Modicon M340 X80 Ethernet Communication Modules BMXNOE0100 (H), BMXNOE0110 (H), BMXNOC0401, BMXNOR0200H RTU (All Versions), Modicon Premium Processors with integrated Ethernet (Copro) TSXP574634, TSXP575634, TSXP576634 (All Versions), Modicon Quantum Processors with Integrated Ethernet (Copro) 140CPU65xxxxx (All Versions), Modicon Quantum Communication Modules 140NOE771x1, 140NOC78x00, 140NOC77101 (All Versions), Modicon Premium Communication Modules TSXETY4103, TSXETY5103 (All Versions)",
    "keyphrases": {
        "rootcause": "CWE-787 Out-of-bounds Write",
        "weakness": "",
        "impact": "denial of service",
        "vector": "specially crafted HTTP request",
        "attacker": "attacker",
        "product": [
            "Modicon M340 CPUs BMXP34",
            "Modicon M340 X80 Ethernet Communication Modules",
            "Modicon Premium Processors with integrated Ethernet",
            "Modicon Quantum Processors with Integrated Ethernet",
            "Modicon Quantum Communication Modules",
            "Modicon Premium Communication Modules"
        ],
        "version": "",
        "component": ""
    }
}
