{
    "cveId": "CVE-2024-21192",
    "version": "1.0.0",
    "timestamp": "2024-12-06T11:32:07.789868+00:00",
    "description": "Vulnerability in the Oracle Enterprise Manager for Fusion Middleware product of Oracle Fusion Middleware (component WebLogic Mgmt). The supported version that is affected is 12.2.1.4.0. Easily exploitable vulnerability allows high privileged attacker with logon to the infrastructure where Oracle Enterprise Manager for Fusion Middleware executes to compromise Oracle Enterprise Manager for Fusion Middleware. Successful attacks of this vulnerability can result in unauthorized access to critical data or complete access to all Oracle Enterprise Manager for Fusion Middleware accessible data. CVSS 3.1 Base Score 4.4 (Confidentiality impacts). CVSS Vector (CVSS3.1/AVL/ACL/PRH/UIN/SU/CH/IN/AN).",
    "keyphrases": {
        "rootcause": "",
        "weakness": "",
        "impact": [
            "unauthorized access to critical data",
            "complete access to all Oracle Enterprise Manager for Fusion Middleware accessible data"
        ],
        "vector": "",
        "attacker": "high privileged attacker with logon to the infrastructure where Oracle Enterprise Manager for Fusion Middleware executes",
        "product": "Oracle Enterprise Manager for Fusion Middleware",
        "version": "12.2.1.4.0",
        "component": "WebLogic Mgmt"
    }
}
