{
  "cveId": "CVE-2024-21110",
  "version": "1.0.0",
  "timestamp": "2024-12-06T11:32:07.789868+00:00",
  "description": "Vulnerability in the Oracle VM VirtualBox product of Oracle Virtualization (component Core). Supported versions that are affected are Prior to 7.0.16. Easily exploitable vulnerability allows low privileged attacker with logon to the infrastructure where Oracle VM VirtualBox executes to compromise Oracle VM VirtualBox. Successful attacks require human interaction from a person other than the attacker. Successful attacks of this vulnerability can result in takeover of Oracle VM VirtualBox. CVSS 3.1 Base Score 7.3 (Confidentiality, Integrity and Availability impacts). CVSS Vector (CVSS3.1/AVL/ACL/PRL/UIR/SU/CH/IH/AH).",
  "keyphrases": {
    "rootcause": "",
    "weakness": "",
    "impact": [
      "Integrity and Availability impacts",
      "takeover of Oracle VM VirtualBox"
    ],
    "vector": "",
    "attacker": "low privileged attacker",
    "product": "Oracle VM VirtualBox",
    "version": "Prior to 7.0.16",
    "component": "Core"
  },
  "mitreTechnicalImpacts": []
}