{
    "cveId": "CVE-2024-21170",
    "version": "1.0.0",
    "timestamp": "2024-12-06T11:32:07.789868+00:00",
    "description": "Vulnerability in the MySQL Connectors product of Oracle MySQL (component Connector/Python). Supported versions that are affected are 8.4.0 and prior. Easily exploitable vulnerability allows low privileged attacker with network access via multiple protocols to compromise MySQL Connectors. Successful attacks of this vulnerability can result in unauthorized update, insert or delete access to some of MySQL Connectors accessible data as well as unauthorized read access to a subset of MySQL Connectors accessible data and unauthorized ability to cause a partial denial of service (partial DOS) of MySQL Connectors. CVSS 3.1 Base Score 6.3 (Confidentiality, Integrity and Availability impacts). CVSS Vector (CVSS3.1/AVN/ACL/PRL/UIN/SU/CL/IL/AL).",
    "keyphrases": {
        "rootcause": "",
        "weakness": "",
        "impact": [
            "unauthorized update",
            "insert or delete access",
            "unauthorized read access",
            "partial denial of service"
        ],
        "vector": "multiple protocols",
        "attacker": "low privileged attacker",
        "product": "Oracle MySQL",
        "version": "8.4.0 and prior",
        "component": "Connector/Python"
    }
}
