{
    "cveId": "CVE-2024-21257",
    "version": "1.0.0",
    "timestamp": "2024-12-06T11:32:07.789868+00:00",
    "description": "Vulnerability in the Oracle Hyperion BI+ product of Oracle Hyperion (component UI and Visualization). The supported version that is affected is 11.2.18.0.000. Easily exploitable vulnerability allows low privileged attacker with access to the physical communication segment attached to the hardware where the Oracle Hyperion BI+ executes to compromise Oracle Hyperion BI+. Successful attacks require human interaction from a person other than the attacker. Successful attacks of this vulnerability can result in unauthorized read access to a subset of Oracle Hyperion BI+ accessible data. CVSS 3.1 Base Score 3.0 (Confidentiality impacts). CVSS Vector (CVSS3.1/AVA/ACL/PRL/UIR/SU/CL/IN/AN).",
    "keyphrases": {
        "rootcause": "",
        "weakness": "",
        "impact": "unauthorized read access to a subset of Oracle Hyperion BI+ accessible data",
        "vector": "",
        "attacker": "low privileged attacker",
        "product": "Oracle Hyperion BI+",
        "version": "11.2.18.0.000",
        "component": "UI and Visualization"
    }
}
