{
    "cveId": "CVE-2024-21091",
    "version": "1.0.0",
    "timestamp": "2024-12-06T11:32:07.789868+00:00",
    "description": "Vulnerability in the Oracle Agile Product Lifecycle Management for Process product of Oracle Supply Chain (component Data Import). The supported version that is affected is 6.2.4.2. Easily exploitable vulnerability allows low privileged attacker with network access via HTTP to compromise Oracle Agile Product Lifecycle Management for Process. Successful attacks of this vulnerability can result in unauthorized access to critical data or complete access to all Oracle Agile Product Lifecycle Management for Process accessible data. CVSS 3.1 Base Score 6.5 (Confidentiality impacts). CVSS Vector (CVSS3.1/AVN/ACL/PRL/UIN/SU/CH/IN/AN).",
    "keyphrases": {
        "rootcause": "",
        "weakness": "",
        "impact": [
            "unauthorized access to critical data",
            "complete access to all Oracle Agile Product Lifecycle Management for Process accessible data"
        ],
        "vector": "",
        "attacker": "low privileged attacker with network access via HTTP",
        "product": "Oracle Agile Product Lifecycle Management for Process",
        "version": "6.2.4.2",
        "component": "Data Import"
    }
}
