{
    "cveId": "CVE-2024-21164",
    "version": "1.0.0",
    "timestamp": "2024-12-06T11:32:07.789868+00:00",
    "description": "Vulnerability in the Oracle VM VirtualBox product of Oracle Virtualization (component Core). Supported versions that are affected are Prior to 7.0.20. Difficult to exploit vulnerability allows high privileged attacker with logon to the infrastructure where Oracle VM VirtualBox executes to compromise Oracle VM VirtualBox. While the vulnerability is in Oracle VM VirtualBox, attacks may significantly impact additional products (scope change). Successful attacks of this vulnerability can result in unauthorized read access to a subset of Oracle VM VirtualBox accessible data. CVSS 3.1 Base Score 2.5 (Confidentiality impacts). CVSS Vector (CVSS3.1/AVL/ACH/PRH/UIN/SC/CL/IN/AN).",
    "keyphrases": {
        "rootcause": "",
        "weakness": "",
        "impact": "unauthorized read access to a subset of Oracle VM VirtualBox accessible data",
        "vector": "",
        "attacker": "high privileged attacker",
        "product": "Oracle VM VirtualBox",
        "version": "Prior to 7.0.20",
        "component": "Core"
    }
}
