{
  "cveId": "CVE-2024-21096",
  "version": "1.0.0",
  "timestamp": "2024-12-06T11:32:07.789868+00:00",
  "description": "Vulnerability in the MySQL Server product of Oracle MySQL (component Client mysqldump). Supported versions that are affected are 8.0.36 and prior and 8.3.0 and prior. Difficult to exploit vulnerability allows unauthenticated attacker with logon to the infrastructure where MySQL Server executes to compromise MySQL Server. Successful attacks of this vulnerability can result in unauthorized update, insert or delete access to some of MySQL Server accessible data as well as unauthorized read access to a subset of MySQL Server accessible data and unauthorized ability to cause a partial denial of service (partial DOS) of MySQL Server. CVSS 3.1 Base Score 4.9 (Confidentiality, Integrity and Availability impacts). CVSS Vector (CVSS3.1/AVL/ACH/PRN/UIN/SU/CL/IL/AL).",
  "keyphrases": {
    "rootcause": "",
    "weakness": "",
    "impact": [
      "DOS",
      "Integrity and Availability impacts",
      "insert or delete access to some of MySQL Server accessible data",
      "partial denial of service",
      "unauthorized read access to a subset of MySQL Server accessible data",
      "unauthorized update"
    ],
    "vector": "",
    "attacker": "unauthenticated attacker",
    "product": "Oracle MySQL",
    "version": "8.0.36 and prior and 8.3.0 and prior",
    "component": "Client mysqldump"
  },
  "mitreTechnicalImpacts": []
}