{
    "cveId": "CVE-2024-21597",
    "version": "1.0.0",
    "timestamp": "2024-12-17T08:36:27.567979+00:00",
    "description": "An Exposure of Resource to Wrong Sphere vulnerability in the Packet Forwarding Engine (PFE) of Juniper Networks Junos OS on MX Series allows an unauthenticated, network-based attacker to bypass the intended access restrictions.In an Abstracted Fabric (AF) scenario if routing-instances (RI) are configured, specific valid traffic destined to the device can bypass the configured lo0 firewall filters as its received in the wrong RI context.This issue affects Juniper Networks Junos OS on MX Series * All versions earlier than 20.4R3-S9 * 21.2 versions earlier than 21.2R3-S3 * 21.4 versions earlier than 21.4R3-S5 * 22.1 versions earlier than 22.1R3 * 22.2 versions earlier than 22.2R3 * 22.3 versions earlier than 22.3R2.",
    "keyphrases": {
        "rootcause": "",
        "weakness": "Exposure of Resource to Wrong Sphere",
        "impact": "bypass the configured lo0 firewall filters",
        "vector": "",
        "attacker": "unauthenticated network-based attacker",
        "product": "Juniper Networks Junos OS",
        "version": [
            "All versions earlier than 20.4R3-S9",
            "21.2 versions earlier than 21.2R3-S3",
            "21.4 versions earlier than 21.4R3-S5",
            "22.1 versions earlier than 22.1R3",
            "22.2 versions earlier than 22.2R3",
            "22.3 versions earlier than 22.3R2"
        ],
        "component": "Packet Forwarding Engine (PFE)"
    }
}
