{
    "cveId": "CVE-2024-21071",
    "version": "1.0.0",
    "timestamp": "2024-12-06T11:32:07.789868+00:00",
    "description": "Vulnerability in the Oracle Workflow product of Oracle E-Business Suite (component Admin Screens and Grants UI). Supported versions that are affected are 12.2.3-12.2.13. Easily exploitable vulnerability allows high privileged attacker with network access via HTTP to compromise Oracle Workflow. While the vulnerability is in Oracle Workflow, attacks may significantly impact additional products (scope change). Successful attacks of this vulnerability can result in takeover of Oracle Workflow. CVSS 3.1 Base Score 9.1 (Confidentiality, Integrity and Availability impacts). CVSS Vector (CVSS3.1/AVN/ACL/PRH/UIN/SC/CH/IH/AH).",
    "keyphrases": {
        "rootcause": "",
        "weakness": "",
        "impact": "takeover of Oracle Workflow",
        "vector": "HTTP",
        "attacker": "high privileged attacker with network access",
        "product": "Oracle Workflow",
        "version": "12.2.3-12.2.13",
        "component": "Admin Screens and Grants UI"
    }
}
