{
    "cveId": "CVE-2024-21066",
    "version": "1.0.0",
    "timestamp": "2024-12-06T11:32:07.789868+00:00",
    "description": "Vulnerability in the RDBMS component of Oracle Database Server. Supported versions that are affected are 19.3-19.22 and 21.3-21.13. Easily exploitable vulnerability allows high privileged attacker having Authenticated User privilege with logon to the infrastructure where RDBMS executes to compromise RDBMS. Successful attacks require human interaction from a person other than the attacker. Successful attacks of this vulnerability can result in unauthorized access to critical data or complete access to all RDBMS accessible data. CVSS 3.1 Base Score 4.2 (Confidentiality impacts). CVSS Vector (CVSS3.1/AVL/ACL/PRH/UIR/SU/CH/IN/AN).",
    "keyphrases": {
        "rootcause": "",
        "weakness": "",
        "impact": "unauthorized access to critical data or complete access to all RDBMS accessible data",
        "vector": "",
        "attacker": "high privileged attacker having Authenticated User privilege with logon to the infrastructure where RDBMS executes",
        "product": "Oracle Database Server",
        "version": "19.3-19.22 and 21.3-21.13",
        "component": "RDBMS component"
    }
}
