{
  "cveId": "CVE-2024-21261",
  "version": "1.0.0",
  "timestamp": "2024-12-06T11:32:07.789868+00:00",
  "description": "Vulnerability in Oracle Application Express (component General). Supported versions that are affected are 23.2 and 24.1. Difficult to exploit vulnerability allows low privileged attacker with network access via HTTP to compromise Oracle Application Express. While the vulnerability is in Oracle Application Express, attacks may significantly impact additional products (scope change). Successful attacks of this vulnerability can result in unauthorized update, insert or delete access to some of Oracle Application Express accessible data as well as unauthorized read access to a subset of Oracle Application Express accessible data. CVSS 3.1 Base Score 4.9 (Confidentiality and Integrity impacts). CVSS Vector (CVSS3.1/AVN/ACH/PRL/UIN/SC/CL/IL/AN).",
  "keyphrases": {
    "rootcause": "",
    "weakness": "",
    "impact": [
      "Integrity",
      "insert or delete access",
      "unauthorized read access",
      "unauthorized update"
    ],
    "vector": "network access via HTTP",
    "attacker": "low privileged attacker",
    "product": "Oracle Application Express",
    "version": "23.2 and 24.1",
    "component": "General"
  },
  "mitreTechnicalImpacts": []
}