{
  "cveId": "CVE-2024-21283",
  "version": "1.0.0",
  "timestamp": "2024-12-06T11:32:07.789868+00:00",
  "description": "Vulnerability in the PeopleSoft Enterprise HCM Global Payroll Core product of Oracle PeopleSoft (component Global Payroll for Core). Supported versions that are affected are 9.2.48-9.2.50. Easily exploitable vulnerability allows low privileged attacker with network access via HTTP to compromise PeopleSoft Enterprise HCM Global Payroll Core. Successful attacks of this vulnerability can result in unauthorized creation, deletion or modification access to critical data or all PeopleSoft Enterprise HCM Global Payroll Core accessible data as well as unauthorized access to critical data or complete access to all PeopleSoft Enterprise HCM Global Payroll Core accessible data. CVSS 3.1 Base Score 8.1 (Confidentiality and Integrity impacts). CVSS Vector (CVSS3.1/AVN/ACL/PRL/UIN/SU/CH/IH/AN).",
  "keyphrases": {
    "rootcause": "",
    "weakness": "",
    "impact": [
      "Integrity",
      "deletion or modification access to critical data or all PeopleSoft Enterprise HCM Global Payroll Core accessible data as well as unauthorized access to critical data or complete access to all PeopleSoft Enterprise HCM Global Payroll Core accessible data",
      "unauthorized creation"
    ],
    "vector": "",
    "attacker": "low privileged attacker with network access via HTTP",
    "product": "Oracle PeopleSoft",
    "version": "9.2.48-9.2.50",
    "component": "PeopleSoft Enterprise HCM Global Payroll Core"
  },
  "mitreTechnicalImpacts": []
}