{
    "cveId": "CVE-2024-21084",
    "version": "1.0.0",
    "timestamp": "2024-12-06T11:32:07.789868+00:00",
    "description": "Vulnerability in the Oracle BI Publisher product of Oracle Analytics (component Service Gateway). Supported versions that are affected are 7.0.0.0.0 and 12.2.1.4.0. Easily exploitable vulnerability allows unauthenticated attacker with network access via HTTP to compromise Oracle BI Publisher. While the vulnerability is in Oracle BI Publisher, attacks may significantly impact additional products (scope change). Successful attacks of this vulnerability can result in unauthorized read access to a subset of Oracle BI Publisher accessible data. CVSS 3.1 Base Score 5.8 (Confidentiality impacts). CVSS Vector (CVSS3.1/AVN/ACL/PRN/UIN/SC/CL/IN/AN).",
    "keyphrases": {
        "rootcause": "",
        "weakness": "",
        "impact": "unauthorized read access",
        "vector": "network access via HTTP",
        "attacker": "unauthenticated attacker",
        "product": "Oracle Analytics",
        "version": [
            "7.0.0.0.0",
            "12.2.1.4.0"
        ],
        "component": "Oracle BI Publisher"
    }
}
