{
    "cveId": "CVE-2024-21155",
    "version": "1.0.0",
    "timestamp": "2024-12-06T11:32:07.789868+00:00",
    "description": "Vulnerability in the Oracle ZFS Storage Appliance Kit product of Oracle Systems (component User Interface). The supported version that is affected is 8.8. Easily exploitable vulnerability allows unauthenticated attacker with network access via HTTP to compromise Oracle ZFS Storage Appliance Kit. Successful attacks require human interaction from a person other than the attacker and while the vulnerability is in Oracle ZFS Storage Appliance Kit, attacks may significantly impact additional products (scope change). Successful attacks of this vulnerability can result in unauthorized read access to a subset of Oracle ZFS Storage Appliance Kit accessible data. CVSS 3.1 Base Score 4.7 (Confidentiality impacts). CVSS Vector (CVSS3.1/AVN/ACL/PRN/UIR/SC/CL/IN/AN).",
    "keyphrases": {
        "rootcause": "",
        "weakness": "",
        "impact": "unauthorized read access",
        "vector": "network access via HTTP",
        "attacker": "unauthenticated attacker",
        "product": "Oracle ZFS Storage Appliance Kit",
        "version": "8.8",
        "component": "User Interface"
    }
}
