{
  "cveId": "CVE-2024-21149",
  "version": "1.0.0",
  "timestamp": "2024-12-06T11:32:07.789868+00:00",
  "description": "Vulnerability in the Oracle Enterprise Asset Management product of Oracle E-Business Suite (component Work Definition Issues). Supported versions that are affected are 12.2.11-12.2.13. Easily exploitable vulnerability allows low privileged attacker with network access via HTTP to compromise Oracle Enterprise Asset Management. Successful attacks of this vulnerability can result in unauthorized creation, deletion or modification access to critical data or all Oracle Enterprise Asset Management accessible data as well as unauthorized access to critical data or complete access to all Oracle Enterprise Asset Management accessible data. CVSS 3.1 Base Score 8.1 (Confidentiality and Integrity impacts). CVSS Vector (CVSS3.1/AVN/ACL/PRL/UIN/SU/CH/IH/AN).",
  "keyphrases": {
    "rootcause": "",
    "weakness": "",
    "impact": [
      "Integrity",
      "deletion or modification access to critical data or all Oracle Enterprise Asset Management accessible data as well as unauthorized access to critical data or complete access to all Oracle Enterprise Asset Management accessible data",
      "unauthorized creation"
    ],
    "vector": "",
    "attacker": "low privileged attacker with network access via HTTP",
    "product": "Oracle Enterprise Asset Management",
    "version": "12.2.11-12.2.13",
    "component": "Work Definition Issues"
  },
  "mitreTechnicalImpacts": []
}