{
  "cveId": "CVE-2010-2123",
  "version": "1.0.0",
  "timestamp": "2024-12-10T17:54:04.992951+00:00",
  "description": "Multiple cross-site scripting (XSS) vulnerabilities in the Storm module 5.x and 6.x before 6.x-1.33 for Drupal allow remote authenticated users, with certain module privileges, to inject arbitrary web script or HTML via the (1) fullname, (2) address, (3) city, (4) provstate (aka state), (5) phone, or (6) taxid parameter in a stormorganization action to index.php the (7) name parameter in a stormperson action to index.php the (8) stepno (aka Step no.) or (9) title parameter in a stormtask action to index.php the (10) title (aka Project) parameter in a stormticket action to index.php or (11) unspecified parameters in a stormproject action to index.php. NOTE some of these details are obtained from third party information.",
  "keyphrases": {
    "rootcause": "Multiple cross-site scripting (XSS) vulnerabilities in the Storm module 5.x and 6.x before 6.x-1.33 for Drupal",
    "weakness": "cross-site scripting",
    "impact": "inject arbitrary web script or HTML",
    "vector": "",
    "attacker": "remote authenticated users",
    "product": "Storm module",
    "version": "5.x and 6.x before 6.x-1.33",
    "component": ""
  },
  "mitreTechnicalImpacts": []
}