{
  "cveId": "CVE-2019-17139",
  "version": "1.0.0",
  "timestamp": "2024-12-12T22:08:52.294043+00:00",
  "description": "This vulnerability allows remote attackers to execute arbitrary code on affected installations of Foxit PhantomPDF 9.5.0.20723. User interaction is required to exploit this vulnerability in that the target must visit a malicious page or open a malicious file. The specific flaw exists within the processing of Javascript in the HTML2PDF plugin. The issue results from the lack of proper validation of user-supplied data, which can result in a write past the end of an allocated object. An attacker can leverage this vulnerability to execute code in the context of the current process. Was ZDI-CAN-8692.",
  "keyphrases": {
    "rootcause": "lack of proper validation of user-supplied data",
    "weakness": "write past the end of an allocated object",
    "impact": [
      "execute arbitrary code",
      "execute code in the context of the current process"
    ],
    "vector": "",
    "attacker": "remote attackers",
    "product": "Foxit PhantomPDF",
    "version": "9.5.0.20723",
    "component": "HTML2PDF plugin"
  },
  "mitreTechnicalImpacts": []
}