{
    "cveId": "CVE-2022-20789",
    "version": "1.0.0",
    "timestamp": "2024-12-15T20:24:27.876763+00:00",
    "description": "A vulnerability in the software upgrade process of Cisco Unified Communications Manager (Unified CM) and Cisco Unified Communications Manager Session Management Edition (Unified CM SME) could allow an authenticated, remote attacker to write arbitrary files on the affected system. This vulnerability is due to improper restrictions applied to a system script. An attacker could exploit this vulnerability by using crafted variables during the execution of a system upgrade. A successful exploit could allow the attacker to overwrite or append arbitrary data to system files using root-level privileges.",
    "keyphrases": {
        "rootcause": "improper restrictions",
        "weakness": "",
        "impact": "write arbitrary files",
        "vector": "crafted variables during the execution of a system upgrade",
        "attacker": "authenticated remote attacker",
        "product": [
            "Cisco Unified Communications Manager",
            "Cisco Unified Communications Manager Session Management Edition"
        ],
        "version": "",
        "component": "software upgrade process"
    }
}
