{
    "cveId": "CVE-2016-9159",
    "version": "1.0.0",
    "timestamp": "2024-12-10T17:54:04.992951+00:00",
    "description": "A vulnerability has been identified in SIMATIC S7-300 CPU family (All versions), SIMATIC S7-300 CPU family (incl. related ET200 CPUs and SIPLUS variants) (All versions), SIMATIC S7-400 PN/DP V6 and below CPU family (incl. SIPLUS variants) (All versions), SIMATIC S7-400 PN/DP V7 CPU family (incl. SIPLUS variants) (All versions), SIMATIC S7-400 V6 and earlier CPU family (All versions), SIMATIC S7-400 V7 CPU family (All versions), SIMATIC S7-410 V8 CPU family (All versions), SIMATIC S7-410 V8 CPU family (incl. SIPLUS variants) (All versions). An attacker with network access to port 102/tcp (ISO-TSAP) or via Profibus could obtain credentials from the PLC if protection-level 2 is configured on the affected devices.",
    "keyphrases": {
        "rootcause": "",
        "weakness": "",
        "impact": "obtain credentials",
        "vector": "network access to port 102/tcp (ISO-TSAP) or via Profibus",
        "attacker": "attacker",
        "product": [
            "SIMATIC S7-300 CPU family",
            "SIMATIC S7-300 CPU family (incl. related ET200 CPUs and SIPLUS variants)",
            "SIMATIC S7-400 PN/DP V6 and below CPU family (incl. SIPLUS variants)",
            "SIMATIC S7-400 PN/DP V7 CPU family (incl. SIPLUS variants)",
            "SIMATIC S7-400 V6 and earlier CPU family",
            "SIMATIC S7-400 V7 CPU family",
            "SIMATIC S7-410 V8 CPU family",
            "SIMATIC S7-410 V8 CPU family (incl. SIPLUS variants)"
        ],
        "version": [
            "All versions",
            "All versions",
            "All versions",
            "All versions",
            "All versions",
            "All versions",
            "All versions",
            "All versions"
        ],
        "component": ""
    }
}
