{
    "cveId": "CVE-2022-47375",
    "version": "1.0.0",
    "timestamp": "2024-12-17T08:36:27.567979+00:00",
    "description": "A vulnerability has been identified in SIMATICPC-Station Plus (All versions), SIMATIC S7-400 CPU 412-2 PN V7 (All versions), SIMATIC S7-400 CPU 414-3 PN/DP V7 (All versions), SIMATIC S7-400 CPU 414F-3 PN/DP V7 (All versions), SIMATIC S7-400 CPU 416-3 PN/DP V7 (All versions), SIMATIC S7-400 CPU 416F-3 PN/DP V7 (All versions), SINAMICS S120 (incl. SIPLUS variants) (All versions < V5.2 SP3 HF15), SIPLUS S7-400 CPU 414-3 PN/DP V7 (All versions), SIPLUS S7-400 CPU 416-3 PN/DP V7 (All versions). The affected products do not handle long file names correctly.This could allow an attacker to create a buffer overflow and create a denial of service condition for the device.",
    "keyphrases": {
        "rootcause": "do not handle long file names correctly",
        "weakness": "",
        "impact": "denial of service",
        "vector": "buffer overflow",
        "attacker": "attacker",
        "product": [
            "SIMATICPC-Station Plus",
            "SIMATIC S7-400 CPU 412-2 PN V7",
            "SIMATIC S7-400 CPU 414-3 PN/DP V7",
            "SIMATIC S7-400 CPU 414F-3 PN/DP V7",
            "SIMATIC S7-400 CPU 416-3 PN/DP V7",
            "SIMATIC S7-400 CPU 416F-3 PN/DP V7",
            "SINAMICS S120 (incl. SIPLUS variants)",
            "SIPLUS S7-400 CPU 414-3 PN/DP V7",
            "SIPLUS S7-400 CPU 416-3 PN/DP V7"
        ],
        "version": [
            "All versions",
            "All versions < V5.2 SP3 HF15",
            "All versions",
            "All versions"
        ],
        "component": ""
    }
}
