{
    "cveId": "CVE-2025-0125",
    "version": "1.0.0",
    "timestamp": "2025-07-04T16:12:41.853043+00:00",
    "description": "An improper input neutralization vulnerability in the management web interface of the Palo Alto Networks PAN-OS software enables a malicious authenticated read-write administrator to impersonate another legitimate authenticated PAN-OS administrator. The attacker must have network access to the management web interface to exploit this issue. You greatly reduce the risk of this issue by restricting access to the management web interface to only trusted internal IP addresses according to our recommended critical deployment guidelines https//live.paloaltonetworks.com/t5/community-blogs/tips-amp-tricks-how-to-secure-the-management-access-of-your-palo/ba-p/464431 . This issue does not affect Cloud NGFW and all Prisma Access instances.",
    "keyphrases": {
        "rootcause": "improper input neutralization",
        "weakness": "",
        "impact": "impersonate another legitimate authenticated PAN-OS administrator",
        "vector": "",
        "attacker": "malicious authenticated read-write administrator",
        "product": "Palo Alto Networks PAN-OS",
        "version": "",
        "component": "management web interface"
    }
}
