{
  "cveId": "CVE-2019-2807",
  "version": "1.0.0",
  "timestamp": "2024-12-06T11:32:07.789868+00:00",
  "description": "Vulnerability in the Oracle Solaris component of Oracle Sun Systems Products Suite (subcomponent Zones). The supported version that is affected is 11.4. Easily exploitable vulnerability allows low privileged attacker with logon to the infrastructure where Oracle Solaris executes to compromise Oracle Solaris. Successful attacks require human interaction from a person other than the attacker. Successful attacks of this vulnerability can result in unauthorized update, insert or delete access to some of Oracle Solaris accessible data and unauthorized ability to cause a partial denial of service (partial DOS) of Oracle Solaris. CVSS 3.0 Base Score 3.9 (Integrity and Availability impacts). CVSS Vector (CVSS3.0/AVL/ACL/PRL/UIR/SU/CN/IL/AL).",
  "keyphrases": {
    "rootcause": "",
    "weakness": "",
    "impact": [
      "Availability",
      "insert or delete access",
      "partial denial of service (partial DOS)",
      "unauthorized update"
    ],
    "vector": "",
    "attacker": "low privileged attacker",
    "product": "Oracle Solaris",
    "version": "11.4",
    "component": "Zones"
  },
  "mitreTechnicalImpacts": []
}