{
    "cveId": "CVE-2019-2602",
    "version": "1.0.0",
    "timestamp": "2024-12-06T11:32:07.789868+00:00",
    "description": "Vulnerability in the Java SE, Java SE Embedded component of Oracle Java SE (subcomponent Libraries). Supported versions that are affected are Java SE 7u211, 8u202, 11.0.2 and 12 Java SE Embedded 8u201. Easily exploitable vulnerability allows unauthenticated attacker with network access via multiple protocols to compromise Java SE, Java SE Embedded. Successful attacks of this vulnerability can result in unauthorized ability to cause a hang or frequently repeatable crash (complete DOS) of Java SE, Java SE Embedded. Note This vulnerability can only be exploited by supplying data to APIs in the specified Component without using Untrusted Java Web Start applications or Untrusted Java applets, such as through a web service. CVSS 3.0 Base Score 7.5 (Availability impacts). CVSS Vector (CVSS3.0/AVN/ACL/PRN/UIN/SU/CN/IN/AH).",
    "keyphrases": {
        "rootcause": "",
        "weakness": "",
        "impact": "cause a hang or frequently repeatable crash (complete DOS)",
        "vector": "multiple protocols",
        "attacker": "unauthenticated attacker with network access",
        "product": [
            "Java SE",
            "Java SE Embedded"
        ],
        "version": [
            "7u211",
            "8u202",
            "11.0.2",
            "12"
        ],
        "component": "Libraries"
    }
}
