{
  "cveId": "CVE-2019-2633",
  "version": "1.0.0",
  "timestamp": "2025-07-04T16:12:41.853043+00:00",
  "description": "Vulnerability in the Oracle Work in Process component of Oracle E-Business Suite (subcomponent Messages). Supported versions that are affected are 12.1.1, 12.1.2, 12.1.3, 12.2.3, 12.2.4, 12.2.5, 12.2.6, 12.2.7 and 12.2.8. Easily exploitable vulnerability allows low privileged attacker with network access via HTTP to compromise Oracle Work in Process. Successful attacks of this vulnerability can result in unauthorized creation, deletion or modification access to critical data or all Oracle Work in Process accessible data as well as unauthorized access to critical data or complete access to all Oracle Work in Process accessible data. CVSS 3.0 Base Score 9.9 (Confidentiality, Integrity and Availability impacts). CVSS Vector (CVSS3.0/AVN/ACL/PRL/UIN/SC/CH/IH/AL).",
  "keyphrases": {
    "rootcause": "",
    "weakness": "",
    "impact": [
      "access to critical data or all Oracle Work in Process accessible data",
      "deletion or modification access to critical data",
      "unauthorized access to critical data",
      "Integrity and Availability impacts",
      "unauthorized creation"
    ],
    "vector": "network access via HTTP",
    "attacker": "low privileged attacker with network access",
    "product": "Oracle E-Business Suite",
    "version": [
      "12.2.7 and 12.2.8",
      "12.1.1",
      "12.1.2",
      "12.1.3",
      "12.2.3",
      "12.2.4",
      "12.2.5",
      "12.2.6"
    ],
    "component": "Work in Process"
  },
  "mitreTechnicalImpacts": []
}