{
  "cveId": "CVE-2019-2799",
  "version": "1.0.0",
  "timestamp": "2024-12-06T11:32:07.789868+00:00",
  "description": "Vulnerability in the Oracle ODBC Driver component of Oracle Database Server ***PRIVILEGE CANNOT BE NONE FOR AUTHENTICATED ATTACKS***. Supported versions that are affected are 11.2.0.4, 12.1.0.2, 12.2.0.1 and 18c. Difficult to exploit vulnerability allows low privileged attacker having None privilege with network access via multiple protocols to compromise Oracle ODBC Driver. Successful attacks of this vulnerability can result in takeover of Oracle ODBC Driver. Note The vulnerability affects Windows platforms only. CVSS 3.0 Base Score 7.5 (Confidentiality, Integrity and Availability impacts). CVSS Vector (CVSS3.0/AVN/ACH/PRL/UIN/SU/CH/IH/AH).",
  "keyphrases": {
    "rootcause": "",
    "weakness": "",
    "impact": [
      "Integrity and Availability impacts",
      "takeover of Oracle ODBC Driver"
    ],
    "vector": "multiple protocols",
    "attacker": "low privileged attacker",
    "product": "Oracle Database Server",
    "version": [
      "11.2.0.4",
      "12.1.0.2",
      "12.2.0.1 and 18c"
    ],
    "component": "Oracle ODBC Driver component"
  },
  "mitreTechnicalImpacts": []
}