{
    "cveId": "CVE-2019-2679",
    "version": "1.0.0",
    "timestamp": "2024-12-06T11:32:07.789868+00:00",
    "description": "Vulnerability in the Oracle VM VirtualBox component of Oracle Virtualization (subcomponent Core). Supported versions that are affected are Prior to 5.2.28 and prior to 6.0.6. Easily exploitable vulnerability allows low privileged attacker with logon to the infrastructure where Oracle VM VirtualBox executes to compromise Oracle VM VirtualBox. While the vulnerability is in Oracle VM VirtualBox, attacks may significantly impact additional products. Successful attacks of this vulnerability can result in unauthorized ability to cause a hang or frequently repeatable crash (complete DOS) of Oracle VM VirtualBox and unauthorized read access to a subset of Oracle VM VirtualBox accessible data. CVSS 3.0 Base Score 7.3 (Confidentiality and Availability impacts). CVSS Vector (CVSS3.0/AVL/ACL/PRL/UIN/SC/CL/IN/AH).",
    "keyphrases": {
        "rootcause": "",
        "weakness": "",
        "impact": [
            "crash",
            "read access"
        ],
        "vector": "",
        "attacker": "low privileged attacker",
        "product": "Oracle VM VirtualBox",
        "version": "Prior to 5.2.28 and prior to 6.0.6",
        "component": "Core"
    }
}
