{
  "cveId": "CVE-2019-2878",
  "version": "1.0.0",
  "timestamp": "2024-12-12T22:08:52.294043+00:00",
  "description": "Vulnerability in the Sun ZFS Storage Appliance Kit (AK) component of Oracle Sun Systems Products Suite (subcomponent HTTP data path subsystems). The supported version that is affected is 8.8.3. Easily exploitable vulnerability allows unauthenticated attacker with network access via HTTP to compromise Sun ZFS Storage Appliance Kit (AK). Successful attacks require human interaction from a person other than the attacker and while the vulnerability is in Sun ZFS Storage Appliance Kit (AK), attacks may significantly impact additional products. Successful attacks of this vulnerability can result in unauthorized update, insert or delete access to some of Sun ZFS Storage Appliance Kit (AK) accessible data as well as unauthorized read access to a subset of Sun ZFS Storage Appliance Kit (AK) accessible data. CVSS 3.0 Base Score 6.1 (Confidentiality and Integrity impacts). CVSS Vector (CVSS3.0/AVN/ACL/PRN/UIR/SC/CL/IL/AN).",
  "keyphrases": {
    "rootcause": "",
    "weakness": "",
    "impact": [
      "Integrity",
      "insert or delete access",
      "unauthorized read access",
      "unauthorized update"
    ],
    "vector": "network access via HTTP",
    "attacker": "unauthenticated attacker",
    "product": "Oracle Sun Systems Products Suite",
    "version": "8.8.3",
    "component": "Sun ZFS Storage Appliance Kit (AK) component"
  },
  "mitreTechnicalImpacts": []
}