{
  "cveId": "CVE-2019-2763",
  "version": "1.0.0",
  "timestamp": "2024-12-06T11:32:07.789868+00:00",
  "description": "Vulnerability in the Oracle Hospitality Gift and Loyalty component of Oracle Food and Beverage Applications. Supported versions that are affected are 9.0.0 and 9.1.0. Easily exploitable vulnerability allows unauthenticated attacker with network access via HTTP to compromise Oracle Hospitality Gift and Loyalty. Successful attacks of this vulnerability can result in unauthorized access to critical data or complete access to all Oracle Hospitality Gift and Loyalty accessible data as well as unauthorized update, insert or delete access to some of Oracle Hospitality Gift and Loyalty accessible data. CVSS 3.0 Base Score 8.2 (Confidentiality and Integrity impacts). CVSS Vector (CVSS3.0/AVN/ACL/PRN/UIN/SU/CH/IL/AN).",
  "keyphrases": {
    "rootcause": "",
    "weakness": "",
    "impact": [
      "Integrity",
      "insert or delete access",
      "unauthorized access to critical data",
      "unauthorized update"
    ],
    "vector": "",
    "attacker": "unauthenticated attacker with network access via HTTP",
    "product": "Oracle Food and Beverage Applications",
    "version": "9.0.0 and 9.1.0",
    "component": "Oracle Hospitality Gift and Loyalty"
  },
  "mitreTechnicalImpacts": []
}