{
    "cveId": "CVE-2019-2399",
    "version": "1.0.0",
    "timestamp": "2024-12-06T11:32:07.789868+00:00",
    "description": "Vulnerability in the Oracle Communications Diameter Signaling Router (DSR) component of Oracle Communications Applications (subcomponent Security). The supported version that is affected is prior to 8.3. Easily exploitable vulnerability allows unauthenticated attacker with network access via HTTP to compromise Oracle Communications Diameter Signaling Router (DSR). Successful attacks of this vulnerability can result in unauthorized read access to a subset of Oracle Communications Diameter Signaling Router (DSR) accessible data and unauthorized ability to cause a partial denial of service (partial DOS) of Oracle Communications Diameter Signaling Router (DSR). CVSS 3.0 Base Score 6.5 (Confidentiality and Availability impacts). CVSS Vector (CVSS3.0/AVN/ACL/PRN/UIN/SU/CL/IN/AL).",
    "keyphrases": {
        "rootcause": "",
        "weakness": "",
        "impact": "unauthorized read access to a subset of Oracle Communications Diameter Signaling Router (DSR) accessible data and unauthorized ability to cause a partial denial of service (partial DOS)",
        "vector": "network access via HTTP",
        "attacker": "unauthenticated attacker",
        "product": "Oracle Communications Applications",
        "version": "prior to 8.3",
        "component": "Oracle Communications Diameter Signaling Router (DSR) component"
    }
}
