{
    "cveId": "CVE-2019-2909",
    "version": "1.0.0",
    "timestamp": "2024-12-06T11:32:07.789868+00:00",
    "description": "Vulnerability in the Java VM component of Oracle Database Server. Supported versions that are affected are 11.2.0.4, 12.1.0.2, 12.2.0.1, 18c and 19c. Difficult to exploit vulnerability allows unauthenticated attacker with network access via multiple protocols to compromise Java VM. While the vulnerability is in Java VM, attacks may significantly impact additional products. Successful attacks of this vulnerability can result in unauthorized creation, deletion or modification access to critical data or all Java VM accessible data. CVSS 3.0 Base Score 6.8 (Integrity impacts). CVSS Vector (CVSS3.0/AVN/ACH/PRN/UIN/SC/CN/IH/AN).",
    "keyphrases": {
        "rootcause": "",
        "weakness": "",
        "impact": "unauthorized creation, deletion or modification access to critical data or all Java VM accessible data",
        "vector": "",
        "attacker": "unauthenticated attacker with network access",
        "product": "Oracle Database Server",
        "version": "11.2.0.4, 12.1.0.2, 12.2.0.1, 18c and 19c",
        "component": "Java VM"
    }
}
