{
    "cveId": "CVE-2019-2536",
    "version": "1.0.0",
    "timestamp": "2024-12-06T11:32:07.789868+00:00",
    "description": "Vulnerability in the MySQL Server component of Oracle MySQL (subcomponent Server Packaging). Supported versions that are affected are 8.0.13 and prior. Difficult to exploit vulnerability allows high privileged attacker with logon to the infrastructure where MySQL Server executes to compromise MySQL Server. Successful attacks require human interaction from a person other than the attacker and while the vulnerability is in MySQL Server, attacks may significantly impact additional products. Successful attacks of this vulnerability can result in unauthorized ability to cause a hang or frequently repeatable crash (complete DOS) of MySQL Server. CVSS 3.0 Base Score 5.0 (Availability impacts). CVSS Vector (CVSS3.0/AVL/ACH/PRH/UIR/SC/CN/IN/AH).",
    "keyphrases": {
        "rootcause": "",
        "weakness": "",
        "impact": "cause a hang or frequently repeatable crash (complete DOS) of MySQL Server",
        "vector": "",
        "attacker": "high privileged attacker",
        "product": "Oracle MySQL",
        "version": "8.0.13 and prior",
        "component": "MySQL Server"
    }
}
