{
    "cveId": "CVE-2019-2659",
    "version": "1.0.0",
    "timestamp": "2024-12-06T11:32:07.789868+00:00",
    "description": "Vulnerability in the Oracle Commerce Platform component of Oracle Commerce (subcomponent Dynamo Application Framework). The supported version that is affected is 11.2.0.3. Easily exploitable vulnerability allows unauthenticated attacker with network access via HTTP to compromise Oracle Commerce Platform. Successful attacks require human interaction from a person other than the attacker and while the vulnerability is in Oracle Commerce Platform, attacks may significantly impact additional products. Successful attacks of this vulnerability can result in unauthorized update, insert or delete access to some of Oracle Commerce Platform accessible data as well as unauthorized read access to a subset of Oracle Commerce Platform accessible data. CVSS 3.0 Base Score 6.1 (Confidentiality and Integrity impacts). CVSS Vector (CVSS3.0/AVN/ACL/PRN/UIR/SC/CL/IL/AN).",
    "keyphrases": {
        "rootcause": "",
        "weakness": "",
        "impact": "unauthorized update, insert or delete access to some of Oracle Commerce Platform accessible data as well as unauthorized read access to a subset of Oracle Commerce Platform accessible data",
        "vector": "",
        "attacker": "unauthenticated attacker with network access via HTTP",
        "product": "Oracle Commerce Platform",
        "version": "11.2.0.3",
        "component": "Dynamo Application Framework"
    }
}
