{
  "cveId": "CVE-2019-2561",
  "version": "1.0.0",
  "timestamp": "2024-12-06T11:32:07.789868+00:00",
  "description": "Vulnerability in the Oracle Retail Xstore Office component of Oracle Retail Applications (subcomponent Internal Operations). Supported versions that are affected are 7.0 and 7.1. Easily exploitable vulnerability allows unauthenticated attacker with network access via HTTP to compromise Oracle Retail Xstore Office. Successful attacks of this vulnerability can result in unauthorized access to critical data or complete access to all Oracle Retail Xstore Office accessible data as well as unauthorized update, insert or delete access to some of Oracle Retail Xstore Office accessible data. CVSS 3.0 Base Score 8.2 (Confidentiality and Integrity impacts). CVSS Vector (CVSS3.0/AVN/ACL/PRN/UIN/SU/CH/IL/AN).",
  "keyphrases": {
    "rootcause": "",
    "weakness": "",
    "impact": [
      "Integrity",
      "complete access to all Oracle Retail Xstore Office accessible data",
      "insert or delete access",
      "unauthorized access to critical data",
      "unauthorized update"
    ],
    "vector": "HTTP",
    "attacker": "unauthenticated attacker",
    "product": "Oracle Retail Xstore Office",
    "version": "7.0 and 7.1",
    "component": "Internal Operations"
  },
  "mitreTechnicalImpacts": []
}