{
    "cveId": "CVE-2019-2727",
    "version": "1.0.0",
    "timestamp": "2024-12-12T22:08:52.294043+00:00",
    "description": "Vulnerability in the Oracle Application Testing Suite component of Oracle Enterprise Manager Products Suite (subcomponent Load Testing for Web Apps). The supported version that is affected is 13.3. Easily exploitable vulnerability allows unauthenticated attacker with network access via HTTP to compromise Oracle Application Testing Suite. Successful attacks of this vulnerability can result in unauthorized update, insert or delete access to some of Oracle Application Testing Suite accessible data as well as unauthorized read access to a subset of Oracle Application Testing Suite accessible data and unauthorized ability to cause a partial denial of service (partial DOS) of Oracle Application Testing Suite. CVSS 3.0 Base Score 7.3 (Confidentiality, Integrity and Availability impacts). CVSS Vector (CVSS3.0/AVN/ACL/PRN/UIN/SU/CL/IL/AL).",
    "keyphrases": {
        "rootcause": "",
        "weakness": "",
        "impact": [
            "unauthorized update",
            "insert or delete access to some of Oracle Application Testing Suite accessible data",
            "unauthorized read access to a subset of Oracle Application Testing Suite accessible data",
            "partial denial of service"
        ],
        "vector": "",
        "attacker": "unauthenticated attacker with network access via HTTP",
        "product": "Oracle Application Testing Suite",
        "version": "13.3",
        "component": "Load Testing for Web Apps"
    }
}
