{
    "cveId": "CVE-2019-2898",
    "version": "1.0.0",
    "timestamp": "2024-12-06T11:32:07.789868+00:00",
    "description": "Vulnerability in the BI Publisher (formerly XML Publisher) product of Oracle Fusion Middleware (component BI Publisher Security). Supported versions that are affected are 11.1.1.9.0, 12.2.1.3.0 and 12.2.1.4.0. Easily exploitable vulnerability allows low privileged attacker with network access via HTTP to compromise BI Publisher (formerly XML Publisher). Successful attacks of this vulnerability can result in unauthorized read access to a subset of BI Publisher (formerly XML Publisher) accessible data. CVSS 3.0 Base Score 4.3 (Confidentiality impacts). CVSS Vector (CVSS3.0/AVN/ACL/PRL/UIN/SU/CL/IN/AN).",
    "keyphrases": {
        "rootcause": "",
        "weakness": "",
        "impact": "unauthorized read access",
        "vector": "low privileged attacker with network access via HTTP",
        "attacker": "",
        "product": "Oracle Fusion Middleware",
        "version": "11.1.1.9.0, 12.2.1.3.0 and 12.2.1.4.0",
        "component": "BI Publisher (formerly XML Publisher)"
    }
}
