{
  "cveId": "CVE-2019-2824",
  "version": "1.0.0",
  "timestamp": "2024-12-06T11:32:07.789868+00:00",
  "description": "Vulnerability in the Oracle WebLogic Server component of Oracle Fusion Middleware (subcomponent WLS Core Components). Supported versions that are affected are 10.3.6.0.0, 12.1.3.0.0 and 12.2.1.3.0. Easily exploitable vulnerability allows high privileged attacker with network access via HTTP to compromise Oracle WebLogic Server. Successful attacks of this vulnerability can result in unauthorized access to critical data or complete access to all Oracle WebLogic Server accessible data as well as unauthorized update, insert or delete access to some of Oracle WebLogic Server accessible data. CVSS 3.0 Base Score 5.5 (Confidentiality and Integrity impacts). CVSS Vector (CVSS3.0/AVN/ACL/PRH/UIN/SU/CH/IL/AN).",
  "keyphrases": {
    "rootcause": "",
    "weakness": "",
    "impact": [
      "Integrity",
      "complete access to all Oracle WebLogic Server accessible data",
      "delete access to some of Oracle WebLogic Server accessible data",
      "insert or delete access",
      "unauthorized access to critical data",
      "unauthorized update"
    ],
    "vector": "high privileged attacker with network access via HTTP",
    "attacker": "high privileged attacker",
    "product": "Oracle WebLogic Server",
    "version": [
      "['10.3.6.0.0'",
      "'12.1.3.0.0'",
      "'12.2.1.3.0']"
    ],
    "component": "WLS Core Components"
  },
  "mitreTechnicalImpacts": []
}