{
    "cveId": "CVE-2019-2590",
    "version": "1.0.0",
    "timestamp": "2024-12-06T11:32:07.789868+00:00",
    "description": "Vulnerability in the PeopleSoft Enterprise HCM Talent Acquisition Manager component of Oracle PeopleSoft Products (subcomponent Job Opening). The supported version that is affected is 9.2. Easily exploitable vulnerability allows unauthenticated attacker with network access via HTTP to compromise PeopleSoft Enterprise HCM Talent Acquisition Manager. Successful attacks require human interaction from a person other than the attacker and while the vulnerability is in PeopleSoft Enterprise HCM Talent Acquisition Manager, attacks may significantly impact additional products. Successful attacks of this vulnerability can result in unauthorized access to critical data or complete access to all PeopleSoft Enterprise HCM Talent Acquisition Manager accessible data as well as unauthorized update, insert or delete access to some of PeopleSoft Enterprise HCM Talent Acquisition Manager accessible data. CVSS 3.0 Base Score 8.2 (Confidentiality and Integrity impacts). CVSS Vector (CVSS3.0/AVN/ACL/PRN/UIR/SC/CH/IL/AN).",
    "keyphrases": {
        "rootcause": "",
        "weakness": "",
        "impact": [
            "unauthorized access to critical data",
            "unauthorized update",
            "insert or delete access"
        ],
        "vector": "HTTP",
        "attacker": "unauthenticated attacker",
        "product": "Oracle PeopleSoft Products",
        "version": "9.2",
        "component": "PeopleSoft Enterprise HCM Talent Acquisition Manager"
    }
}
