{
    "cveId": "CVE-2019-2954",
    "version": "1.0.0",
    "timestamp": "2024-12-06T11:32:07.789868+00:00",
    "description": "Vulnerability in the Core RDBMS component of Oracle Database Server. Supported versions that are affected are 11.2.0.4, 12.1.0.2, 12.2.0.1, 18c and 19c. Easily exploitable vulnerability allows low privileged attacker having Create Session, Create Procedure privilege with logon to the infrastructure where Core RDBMS executes to compromise Core RDBMS. Successful attacks require human interaction from a person other than the attacker. Successful attacks of this vulnerability can result in unauthorized update, insert or delete access to some of Core RDBMS accessible data and unauthorized ability to cause a partial denial of service (partial DOS) of Core RDBMS. CVSS 3.0 Base Score 3.9 (Integrity and Availability impacts). CVSS Vector (CVSS3.0/AVL/ACL/PRL/UIR/SU/CN/IL/AL).",
    "keyphrases": {
        "rootcause": "",
        "weakness": "",
        "impact": "unauthorized update, insert or delete access to some of Core RDBMS accessible data and unauthorized ability to cause a partial denial of service (partial DOS) of Core RDBMS",
        "vector": "",
        "attacker": "low privileged attacker having Create Session, Create Procedure privilege with logon to the infrastructure where Core RDBMS executes",
        "product": "Oracle Database Server",
        "version": "11.2.0.4, 12.1.0.2, 12.2.0.1, 18c and 19c",
        "component": "Core RDBMS"
    }
}
