{
    "cveId": "CVE-2019-2944",
    "version": "1.0.0",
    "timestamp": "2024-12-06T11:32:07.789868+00:00",
    "description": "Vulnerability in the Oracle VM VirtualBox product of Oracle Virtualization (component Core). Supported versions that are affected are Prior to 5.2.34 and prior to 6.0.14. Easily exploitable vulnerability allows high privileged attacker with logon to the infrastructure where Oracle VM VirtualBox executes to compromise Oracle VM VirtualBox. While the vulnerability is in Oracle VM VirtualBox, attacks may significantly impact additional products. Successful attacks of this vulnerability can result in unauthorized ability to cause a hang or frequently repeatable crash (complete DOS) of Oracle VM VirtualBox as well as unauthorized update, insert or delete access to some of Oracle VM VirtualBox accessible data and unauthorized read access to a subset of Oracle VM VirtualBox accessible data. CVSS 3.0 Base Score 7.3 (Confidentiality, Integrity and Availability impacts). CVSS Vector (CVSS3.0/AVL/ACL/PRH/UIN/SC/CL/IL/AH).",
    "keyphrases": {
        "rootcause": "",
        "weakness": "",
        "impact": [
            "hang",
            "crash (complete DOS) of Oracle VM VirtualBox",
            "unauthorized update",
            "insert or delete access to some of Oracle VM VirtualBox accessible data",
            "unauthorized read access to a subset of Oracle VM VirtualBox accessible data"
        ],
        "vector": "",
        "attacker": "high privileged attacker with logon to the infrastructure where Oracle VM VirtualBox executes",
        "product": "Oracle VM VirtualBox",
        "version": "Prior to 5.2.34 and prior to 6.0.14",
        "component": "Core"
    }
}
