{
  "cveId": "CVE-2019-2570",
  "version": "1.0.0",
  "timestamp": "2024-12-06T11:32:07.789868+00:00",
  "description": "Vulnerability in the Siebel Core - Server BizLogic Script component of Oracle Siebel CRM (subcomponent Integration - Scripting). The supported version that is affected is 19.3. Easily exploitable vulnerability allows high privileged attacker with network access via HTTP to compromise Siebel Core - Server BizLogic Script. Successful attacks of this vulnerability can result in unauthorized update, insert or delete access to some of Siebel Core - Server BizLogic Script accessible data as well as unauthorized read access to a subset of Siebel Core - Server BizLogic Script accessible data and unauthorized ability to cause a partial denial of service (partial DOS) of Siebel Core - Server BizLogic Script. CVSS 3.0 Base Score 4.7 (Confidentiality, Integrity and Availability impacts). CVSS Vector (CVSS3.0/AVN/ACL/PRH/UIN/SU/CL/IL/AL).",
  "keyphrases": {
    "rootcause": "",
    "weakness": "",
    "impact": [
      "Integrity and Availability impacts",
      "insert or delete access",
      "unauthorized partial denial of service (partial DOS)",
      "unauthorized read access",
      "unauthorized update"
    ],
    "vector": "high privileged attacker with network access via HTTP",
    "attacker": "",
    "product": "Oracle Siebel CRM",
    "version": "19.3",
    "component": "Siebel Core - Server BizLogic Script component"
  },
  "mitreTechnicalImpacts": []
}