{
  "cveId": "CVE-2019-2777",
  "version": "1.0.0",
  "timestamp": "2024-12-06T11:32:07.789868+00:00",
  "description": "Vulnerability in the Siebel Core - Server Framework component of Oracle Siebel CRM (subcomponent Search). Supported versions that are affected are 19.0 and prior. Easily exploitable vulnerability allows unauthenticated attacker with network access via HTTP to compromise Siebel Core - Server Framework. Successful attacks require human interaction from a person other than the attacker and while the vulnerability is in Siebel Core - Server Framework, attacks may significantly impact additional products. Successful attacks of this vulnerability can result in unauthorized update, insert or delete access to some of Siebel Core - Server Framework accessible data as well as unauthorized read access to a subset of Siebel Core - Server Framework accessible data. CVSS 3.0 Base Score 6.1 (Confidentiality and Integrity impacts). CVSS Vector (CVSS3.0/AVN/ACL/PRN/UIR/SC/CL/IL/AN).",
  "keyphrases": {
    "rootcause": "",
    "weakness": "",
    "impact": [
      "Integrity",
      "insert or delete access",
      "unauthorized read access",
      "unauthorized update"
    ],
    "vector": "HTTP",
    "attacker": "unauthenticated attacker",
    "product": "Oracle Siebel CRM",
    "version": "19.0 and prior",
    "component": "Siebel Core - Server Framework"
  },
  "mitreTechnicalImpacts": []
}