{
    "cveId": "CVE-2019-2736",
    "version": "1.0.0",
    "timestamp": "2024-12-06T11:32:07.789868+00:00",
    "description": "Vulnerability in the Oracle FLEXCUBE Investor Servicing component of Oracle Financial Services Applications (subcomponent Infrastructure). Supported versions that are affected are 12.0.1, 12.0.3, 12.0.4, 12.1.0, 12.3.0, 12.4.0, 14.0.0 and 14.1.0. Easily exploitable vulnerability allows unauthenticated attacker with network access via HTTP to compromise Oracle FLEXCUBE Investor Servicing. Successful attacks require human interaction from a person other than the attacker and while the vulnerability is in Oracle FLEXCUBE Investor Servicing, attacks may significantly impact additional products. Successful attacks of this vulnerability can result in unauthorized update, insert or delete access to some of Oracle FLEXCUBE Investor Servicing accessible data as well as unauthorized read access to a subset of Oracle FLEXCUBE Investor Servicing accessible data. CVSS 3.0 Base Score 6.1 (Confidentiality and Integrity impacts). CVSS Vector (CVSS3.0/AVN/ACL/PRN/UIR/SC/CL/IL/AN).",
    "keyphrases": {
        "rootcause": "",
        "weakness": "",
        "impact": "unauthorized update, insert or delete access",
        "vector": "",
        "attacker": "unauthenticated attacker",
        "product": "Oracle FLEXCUBE Investor Servicing",
        "version": "12.0.1, 12.0.3, 12.0.4, 12.1.0, 12.3.0, 12.4.0, 14.0.0 and 14.1.0",
        "component": "Infrastructure"
    }
}
