{
    "cveId": "CVE-2019-2823",
    "version": "1.0.0",
    "timestamp": "2024-12-06T11:32:07.789868+00:00",
    "description": "Vulnerability in the Oracle Financial Services Analytical Applications Infrastructure component of Oracle Financial Services Applications (subcomponent Infrastructure). Supported versions that are affected are 8.0.5-8.0.8. Easily exploitable vulnerability allows low privileged attacker with network access via HTTP to compromise Oracle Financial Services Analytical Applications Infrastructure. Successful attacks of this vulnerability can result in unauthorized update, insert or delete access to some of Oracle Financial Services Analytical Applications Infrastructure accessible data as well as unauthorized read access to a subset of Oracle Financial Services Analytical Applications Infrastructure accessible data. CVSS 3.0 Base Score 5.4 (Confidentiality and Integrity impacts). CVSS Vector (CVSS3.0/AVN/ACL/PRL/UIN/SU/CL/IL/AN).",
    "keyphrases": {
        "rootcause": "",
        "weakness": "",
        "impact": [
            "unauthorized update",
            "insert or delete access",
            "unauthorized read access"
        ],
        "vector": "low privileged attacker with network access via HTTP",
        "attacker": "",
        "product": "Oracle Financial Services Applications",
        "version": "8.0.5-8.0.8",
        "component": "Oracle Financial Services Analytical Applications Infrastructure"
    }
}
