{
  "cveId": "CVE-2019-2438",
  "version": "1.0.0",
  "timestamp": "2024-12-06T11:32:07.789868+00:00",
  "description": "Vulnerability in the Oracle Web Cache component of Oracle Fusion Middleware (subcomponent ESI/Partial Page Caching). The supported version that is affected is 11.1.1.9.0. Difficult to exploit vulnerability allows unauthenticated attacker with network access via HTTP to compromise Oracle Web Cache. Successful attacks require human interaction from a person other than the attacker and while the vulnerability is in Oracle Web Cache, attacks may significantly impact additional products. Successful attacks of this vulnerability can result in unauthorized access to critical data or complete access to all Oracle Web Cache accessible data as well as unauthorized update, insert or delete access to some of Oracle Web Cache accessible data. CVSS 3.0 Base Score 6.9 (Confidentiality and Integrity impacts). CVSS Vector (CVSS3.0/AVN/ACH/PRN/UIR/SC/CH/IL/AN).",
  "keyphrases": {
    "rootcause": "",
    "weakness": "",
    "impact": [
      "Integrity",
      "insert or delete access",
      "unauthorized access to critical data",
      "unauthorized update"
    ],
    "vector": "network access via HTTP",
    "attacker": "unauthenticated attacker with network access",
    "product": "Oracle Web Cache",
    "version": "11.1.1.9.0",
    "component": "ESI/Partial Page Caching"
  },
  "mitreTechnicalImpacts": []
}