{
    "cveId": "CVE-2019-2959",
    "version": "1.0.0",
    "timestamp": "2024-12-06T11:32:07.789868+00:00",
    "description": "Vulnerability in the Hyperion Financial Reporting product of Oracle Hyperion (component Security Models). The supported version that is affected is 11.1.2.4. Difficult to exploit vulnerability allows high privileged attacker with network access via HTTP to compromise Hyperion Financial Reporting. Successful attacks require human interaction from a person other than the attacker. Successful attacks of this vulnerability can result in unauthorized creation, deletion or modification access to critical data or all Hyperion Financial Reporting accessible data. CVSS 3.0 Base Score 4.2 (Integrity impacts). CVSS Vector (CVSS3.0/AVN/ACH/PRH/UIR/SU/CN/IH/AN).",
    "keyphrases": {
        "rootcause": "",
        "weakness": "",
        "impact": "unauthorized creation, deletion or modification access to critical data or all Hyperion Financial Reporting accessible data",
        "vector": "",
        "attacker": "high privileged attacker with network access via HTTP",
        "product": "Hyperion Financial Reporting",
        "version": "11.1.2.4",
        "component": "Security Models"
    }
}
