{
    "cveId": "CVE-2019-2748",
    "version": "1.0.0",
    "timestamp": "2024-12-06T11:32:07.789868+00:00",
    "description": "Vulnerability in the PeopleSoft Enterprise PT PeopleTools component of Oracle PeopleSoft Products (subcomponent Application Server). Supported versions that are affected are 8.55, 8.56 and 8.57. Difficult to exploit vulnerability allows low privileged attacker with network access via HTTP to compromise PeopleSoft Enterprise PT PeopleTools. While the vulnerability is in PeopleSoft Enterprise PT PeopleTools, attacks may significantly impact additional products. Successful attacks of this vulnerability can result in unauthorized creation, deletion or modification access to critical data or all PeopleSoft Enterprise PT PeopleTools accessible data as well as unauthorized read access to a subset of PeopleSoft Enterprise PT PeopleTools accessible data. CVSS 3.0 Base Score 7.1 (Confidentiality and Integrity impacts). CVSS Vector (CVSS3.0/AVN/ACH/PRL/UIN/SC/CL/IH/AN).",
    "keyphrases": {
        "rootcause": "",
        "weakness": "",
        "impact": [
            "unauthorized creation",
            "deletion",
            "modification of critical data",
            "unauthorized read access"
        ],
        "vector": "network access via HTTP",
        "attacker": "low privileged attacker",
        "product": "Oracle PeopleSoft Products",
        "version": "8.55, 8.56 and 8.57",
        "component": "PeopleSoft Enterprise PT PeopleTools"
    }
}
