{
    "cveId": "CVE-2019-2622",
    "version": "1.0.0",
    "timestamp": "2024-12-06T11:32:07.789868+00:00",
    "description": "Vulnerability in the Oracle Service Contracts component of Oracle E-Business Suite (subcomponent Renewals). Supported versions that are affected are 12.1.1, 12.1.2, 12.1.3, 12.2.3, 12.2.4, 12.2.5, 12.2.6, 12.2.7 and 12.2.8. Easily exploitable vulnerability allows unauthenticated attacker with network access via HTTP to compromise Oracle Service Contracts. Successful attacks require human interaction from a person other than the attacker and while the vulnerability is in Oracle Service Contracts, attacks may significantly impact additional products. Successful attacks of this vulnerability can result in unauthorized update, insert or delete access to some of Oracle Service Contracts accessible data. CVSS 3.0 Base Score 4.7 (Integrity impacts). CVSS Vector (CVSS3.0/AVN/ACL/PRN/UIR/SC/CN/IL/AN).",
    "keyphrases": {
        "rootcause": "",
        "weakness": "",
        "impact": "unauthorized update, insert or delete access",
        "vector": "",
        "attacker": "unauthenticated attacker with network access via HTTP",
        "product": "Oracle E-Business Suite",
        "version": "12.1.1, 12.1.2, 12.1.3, 12.2.3, 12.2.4, 12.2.5, 12.2.6, 12.2.7 and 12.2.8",
        "component": "Oracle Service Contracts component"
    }
}
