{
    "cveId": "CVE-2019-2896",
    "version": "1.0.0",
    "timestamp": "2024-12-06T11:32:07.789868+00:00",
    "description": "Vulnerability in the MICROS Relate CRM Software product of Oracle Retail Applications (component Internal Operations). Supported versions that are affected are 7.1.0, 15.0.0, 16.0.0, 17.0.0, and 18.0.0. Difficult to exploit vulnerability allows unauthenticated attacker with network access via HTTP to compromise MICROS Relate CRM Software. Successful attacks of this vulnerability can result in unauthorized access to critical data or complete access to all MICROS Relate CRM Software accessible data. CVSS 3.0 Base Score 5.9 (Confidentiality impacts). CVSS Vector (CVSS3.0/AVN/ACH/PRN/UIN/SU/CH/IN/AN).",
    "keyphrases": {
        "rootcause": "",
        "weakness": "",
        "impact": "unauthorized access to critical data or complete access to all MICROS Relate CRM Software accessible data",
        "vector": "network access via HTTP",
        "attacker": "unauthenticated attacker",
        "product": "MICROS Relate CRM Software",
        "version": [
            "7.1.0",
            "15.0.0",
            "16.0.0",
            "17.0.0",
            "18.0.0"
        ],
        "component": "Internal Operations"
    }
}
