{
    "cveId": "CVE-2019-2828",
    "version": "1.0.0",
    "timestamp": "2024-12-06T11:32:07.789868+00:00",
    "description": "Vulnerability in the Oracle Field Service component of Oracle E-Business Suite (subcomponent Wireless). Supported versions that are affected are 12.1.1 - 12.1.3 and 12.2.3 - 12.2.8. Easily exploitable vulnerability allows unauthenticated attacker with network access via HTTP to compromise Oracle Field Service. Successful attacks require human interaction from a person other than the attacker and while the vulnerability is in Oracle Field Service, attacks may significantly impact additional products. Successful attacks of this vulnerability can result in takeover of Oracle Field Service. CVSS 3.0 Base Score 9.6 (Confidentiality, Integrity and Availability impacts). CVSS Vector (CVSS3.0/AVN/ACL/PRN/UIR/SC/CH/IH/AH).",
    "keyphrases": {
        "rootcause": "",
        "weakness": "",
        "impact": "takeover of Oracle Field Service",
        "vector": "",
        "attacker": "unauthenticated attacker",
        "product": "Oracle E-Business Suite",
        "version": "12.1.1 - 12.1.3 and 12.2.3 - 12.2.8",
        "component": "Oracle Field Service component"
    }
}
