{
    "cveId": "CVE-2019-2550",
    "version": "1.0.0",
    "timestamp": "2024-12-06T11:32:07.789868+00:00",
    "description": "Vulnerability in the Oracle FLEXCUBE Direct Banking component of Oracle Financial Services Applications (subcomponent Logoff Page). The supported version that is affected is 12.0.2. Easily exploitable vulnerability allows unauthenticated attacker with network access via HTTP to compromise Oracle FLEXCUBE Direct Banking. Successful attacks require human interaction from a person other than the attacker. Successful attacks of this vulnerability can result in unauthorized update, insert or delete access to some of Oracle FLEXCUBE Direct Banking accessible data. CVSS 3.0 Base Score 4.3 (Integrity impacts). CVSS Vector (CVSS3.0/AVN/ACL/PRN/UIR/SU/CN/IL/AN).",
    "keyphrases": {
        "rootcause": "",
        "weakness": "",
        "impact": "unauthorized update, insert or delete access to some of Oracle FLEXCUBE Direct Banking accessible data",
        "vector": "unauthenticated attacker with network access via HTTP",
        "attacker": "unauthenticated attacker",
        "product": "Oracle FLEXCUBE Direct Banking",
        "version": "12.0.2",
        "component": "Logoff Page"
    }
}
