{
  "cveId": "CVE-2019-2804",
  "version": "1.0.0",
  "timestamp": "2024-12-06T11:32:07.789868+00:00",
  "description": "Vulnerability in the Oracle Solaris component of Oracle Sun Systems Products Suite (subcomponent Filesystem). Supported versions that are affected are 11.4 and 10. Easily exploitable vulnerability allows low privileged attacker with logon to the infrastructure where Oracle Solaris executes to compromise Oracle Solaris. Successful attacks require human interaction from a person other than the attacker. Successful attacks of this vulnerability can result in takeover of Oracle Solaris. CVSS 3.0 Base Score 7.3 (Confidentiality, Integrity and Availability impacts). CVSS Vector (CVSS3.0/AVL/ACL/PRL/UIR/SU/CH/IH/AH).",
  "keyphrases": {
    "rootcause": "",
    "weakness": "",
    "impact": [
      "Integrity and Availability impacts",
      "takeover of Oracle Solaris"
    ],
    "vector": "",
    "attacker": "low privileged attacker",
    "product": "Oracle Solaris",
    "version": "11.4 and 10",
    "component": "Filesystem"
  },
  "mitreTechnicalImpacts": []
}