{
  "cveId": "CVE-2019-2419",
  "version": "1.0.0",
  "timestamp": "2024-12-06T11:32:07.789868+00:00",
  "description": "Vulnerability in the PeopleSoft Enterprise CC Common Application Objects component of Oracle PeopleSoft Products (subcomponent Form and Approval Builder). The supported version that is affected is 9.2. Easily exploitable vulnerability allows low privileged attacker with network access via HTTP to compromise PeopleSoft Enterprise CC Common Application Objects. Successful attacks require human interaction from a person other than the attacker and while the vulnerability is in PeopleSoft Enterprise CC Common Application Objects, attacks may significantly impact additional products. Successful attacks of this vulnerability can result in unauthorized update, insert or delete access to some of PeopleSoft Enterprise CC Common Application Objects accessible data as well as unauthorized read access to a subset of PeopleSoft Enterprise CC Common Application Objects accessible data. Note This Enterprise Common Component is used by all PeopleSoft Application products. Please refer to the MOS Note Doc ID 2493366.1 for patch information. CVSS 3.0 Base Score 5.4 (Confidentiality and Integrity impacts). CVSS Vector (CVSS3.0/AVN/ACL/PRL/UIR/SC/CL/IL/AN).",
  "keyphrases": {
    "rootcause": "",
    "weakness": "",
    "impact": [
      "Integrity",
      "insert or delete access",
      "unauthorized read access",
      "unauthorized update"
    ],
    "vector": "",
    "attacker": "low privileged attacker",
    "product": "Oracle PeopleSoft Products",
    "version": "9.2",
    "component": "PeopleSoft Enterprise CC Common Application Objects"
  },
  "mitreTechnicalImpacts": []
}