{
  "cveId": "CVE-2019-2411",
  "version": "1.0.0",
  "timestamp": "2024-12-06T11:32:07.789868+00:00",
  "description": "Vulnerability in the Oracle Hospitality Cruise Shipboard Property Management System component of Oracle Hospitality Applications (subcomponent SPMS Suite). The supported version that is affected is 8.0.8. Easily exploitable vulnerability allows low privileged attacker with network access via TCP to compromise Oracle Hospitality Cruise Shipboard Property Management System. Successful attacks require human interaction from a person other than the attacker and while the vulnerability is in Oracle Hospitality Cruise Shipboard Property Management System, attacks may significantly impact additional products. Successful attacks of this vulnerability can result in unauthorized ability to cause a hang or frequently repeatable crash (complete DOS) of Oracle Hospitality Cruise Shipboard Property Management System as well as unauthorized update, insert or delete access to some of Oracle Hospitality Cruise Shipboard Property Management System accessible data. CVSS 3.0 Base Score 7.6 (Integrity and Availability impacts). CVSS Vector (CVSS3.0/AVN/ACL/PRL/UIR/SC/CN/IL/AH).",
  "keyphrases": {
    "rootcause": "",
    "weakness": "",
    "impact": [
      "Availability",
      "insert or delete access",
      "unauthorized ability to cause a hang or frequently repeatable crash (complete DOS)",
      "unauthorized update"
    ],
    "vector": "low privileged attacker with network access via TCP",
    "attacker": "low privileged attacker",
    "product": "Oracle Hospitality Cruise Shipboard Property Management System",
    "version": "8.0.8",
    "component": ""
  },
  "mitreTechnicalImpacts": []
}