{
    "cveId": "CVE-2022-30575",
    "version": "1.0.0",
    "timestamp": "2024-12-15T20:24:27.876763+00:00",
    "description": "The Web Console component of TIBCO Software Inc.s TIBCO Data Science - Workbench, TIBCO Statistica, TIBCO Statistica - Estore Edition, and TIBCO Statistica Trial contains easily exploitable Reflected Cross Site Scripting (XSS) vulnerabilities that allow a low privileged attacker with network access to execute scripts targeting the affected system or the victims local system. Affected releases are TIBCO Software Inc.s TIBCO Data Science - Workbench versions 14.0.0 and below, TIBCO Statistica versions 14.0.0 and below, TIBCO Statistica - Estore Edition versions 14.0.0 and below, and TIBCO Statistica Trial versions 14.0.0 and below.",
    "keyphrases": {
        "rootcause": "",
        "weakness": "cross-site scripting",
        "impact": "execute scripts",
        "vector": "",
        "attacker": "low privileged attacker",
        "product": [
            "TIBCO Data Science - Workbench",
            "TIBCO Statistica",
            "TIBCO Statistica - Estore Edition",
            "TIBCO Statistica Trial"
        ],
        "version": "14.0.0 and below",
        "component": "Web Console component"
    }
}
