{
    "cveId": "CVE-2015-0113",
    "version": "1.0.0",
    "timestamp": "2024-12-10T17:54:04.992951+00:00",
    "description": "The Jazz help system in IBM Rational Collaborative Lifecycle Management 4.0 through 5.0.2, Rational Quality Manager 4.0 through 4.0.7 and 5.0 through 5.0.2, Rational Team Concert 4.0 through 4.0.7 and 5.0 through 5.0.2, Rational Requirements Composer 4.0 through 4.0.7, Rational DOORS Next Generation 4.0 through 4.0.7 and 5.0 through 5.0.2, Rational Engineering Lifecycle Manager 4.0.3 through 4.0.7 and 5.0 through 5.0.2, Rational Rhapsody Design Manager 4.0 through 4.0.7 and 5.0 through 5.0.2, and Rational Software Architect Design Manager 4.0 through 4.0.7 and 5.0 through 5.0.2 allows remote attackers to read JSP source code via a crafted request.",
    "keyphrases": {
        "rootcause": "",
        "weakness": "",
        "impact": "read JSP source code",
        "vector": "crafted request",
        "attacker": "remote attackers",
        "product": "IBM Rational Collaborative Lifecycle Management, Rational Quality Manager, Rational Team Concert, Rational Requirements Composer, Rational DOORS Next Generation, Rational Engineering Lifecycle Manager, Rational Rhapsody Design Manager, Rational Software Architect Design Manager",
        "version": "4.0 through 5.0.2",
        "component": "Jazz help system"
    }
}
