{
    "cveId": "CVE-2016-3014",
    "version": "1.0.0",
    "timestamp": "2024-12-10T17:54:04.992951+00:00",
    "description": "Cross-site scripting (XSS) vulnerability in IBM Rational Collaborative Lifecycle Management 4.0 before 4.0.7 iFix11 and 5.0 before 5.0.2 iFix17, Rational Quality Manager 4.0 before 4.0.7 iFix11 and 5.0 before 5.0.2 iFix17, Rational Team Concert 4.0 before 4.0.7 iFix11 and 5.0 before 5.0.2 iFix17, Rational DOORS Next Generation 4.0 before 4.0.7 iFix11 and 5.0 before 5.0.2 iFix17, Rational Engineering Lifecycle Manager 4.x before 4.0.7 iFix11 and 5.0 before 5.0.2 iFix17, Rational Rhapsody Design Manager 4.0 before 4.0.7 iFix11 and 5.0 before 5.0.2 iFix17, and Rational Software Architect Design Manager 4.0 before 4.0.7 iFix11 and 5.0 before 5.0.2 iFix17 allows remote authenticated users to inject arbitrary web script or HTML via unspecified vectors.",
    "keyphrases": {
        "rootcause": "",
        "weakness": "Cross-site scripting",
        "impact": "inject arbitrary web script or HTML",
        "vector": "unspecified vectors",
        "attacker": "remote authenticated users",
        "product": [
            "IBM Rational Collaborative Lifecycle Management",
            "Rational Quality Manager",
            "Rational Team Concert",
            "Rational DOORS Next Generation",
            "Rational Engineering Lifecycle Manager",
            "Rational Rhapsody Design Manager",
            "Rational Software Architect Design Manager"
        ],
        "version": "4.0 before 4.0.7 iFix11 and 5.0 before 5.0.2 iFix17",
        "component": ""
    }
}
