{
    "cveId": "CVE-2020-15233",
    "version": "1.0.0",
    "timestamp": "2024-12-13T17:34:55.850537+00:00",
    "description": "ORY Fosite is a security first OAuth2 & OpenID Connect framework for Go. In Fosite from version 0.30.2 and before version 0.34.1, there is an issue in which an an attacker can override the registered redirect URL by performing an OAuth flow and requesting a redirect URL that is to the loopback adapter. Attackers can provide both custom URL query parameters to their loopback redirect URL, as well as actually overriding the host of the registered redirect URL. These attacks are only applicable in scenarios where the attacker has access over the loopback interface. This vulnerability has been patched in ORY Fosite v0.34.1.",
    "keyphrases": {
        "rootcause": "",
        "weakness": "",
        "impact": "override the registered redirect URL",
        "vector": "OAuth flow",
        "attacker": "an an attacker",
        "product": "ORY Fosite",
        "version": "from version 0.30.2 and before version 0.34.1",
        "component": ""
    }
}
