{
  "cveId": "CVE-2024-13776",
  "version": "1.0.0",
  "timestamp": "2025-07-04T16:12:41.853043+00:00",
  "description": "The ZoomSounds - WordPress Wave Audio Player with Playlist plugin for WordPress is vulnerable to unauthorized modification of data that can lead to a denial of service due to a missing capability check on the dzsap_delete_notice AJAX action in all versions up to, and including, 6.91. This makes it possible for authenticated attackers, with Subscriber-level access and above, to update option values to seen on the WordPress site. This can be leveraged to update an option that would create an error on the site and deny service to legitimate users or be used to set some values to true such as registration. There are several other functions also vulnerable to missing authorization.",
  "keyphrases": {
    "rootcause": [
      "missing capability check",
      "missing authorization"
    ],
    "weakness": "",
    "impact": [
      "unauthorized modification of data",
      "update option values",
      "denial of service"
    ],
    "vector": "",
    "attacker": "authenticated attackers",
    "product": "ZoomSounds - WordPress Wave Audio Player with Playlist plugin",
    "version": "all versions up to and including 6.91",
    "component": "dzsap_delete_notice AJAX action"
  },
  "mitreTechnicalImpacts": []
}