{
  "cveId": "CVE-2024-13043",
  "version": "1.0.0",
  "timestamp": "2025-07-04T16:12:41.853043+00:00",
  "description": "Panda Security Dome Link Following Local Privilege Escalation Vulnerability. This vulnerability allows local attackers to escalate privileges on affected installations of Panda Security Dome. An attacker must first obtain the ability to execute low-privileged code on the target system in order to exploit this vulnerability. The specific flaw exists within the Hotspot Shield. By creating a junction, an attacker can abuse the application to delete arbitrary files. An attacker can leverage this vulnerability to escalate privileges and execute arbitrary code in the context of SYSTEM. Was ZDI-CAN-23478.",
  "keyphrases": {
    "rootcause": "",
    "weakness": "Privilege Escalation Vulnerability",
    "impact": [
      "escalate privileges and execute arbitrary code",
      "Local Privilege Escalation"
    ],
    "vector": "creating a junction",
    "attacker": "local attackers",
    "product": "Panda Security Dome",
    "version": "",
    "component": "Hotspot Shield"
  },
  "mitreTechnicalImpacts": []
}