{
    "cveId": "CVE-2018-17198",
    "version": "1.0.0",
    "timestamp": "2024-12-12T22:08:52.294043+00:00",
    "description": "Server-side Request Forgery (SSRF) and File Enumeration vulnerability in Apache Roller 5.2.1, 5.2.0 and earlier unsupported versions relies on Java SAX Parser to implement its XML-RPC interface and by default that parser supports external entities in XML DOCTYPE, which opens Roller up to SSRF / File Enumeration vulnerability. Note that this vulnerability exists even if Roller XML-RPC interface is disable via the Roller web admin UI. Mitigation There are a couple of ways you can fix this vulnerability 1) Upgrade to the latest version of Roller, which is now 5.2.2 2) Or, edit the Roller web.xml file and comment out the XML-RPC Servlet mapping as shown below XmlRpcServlet /roller-services/xmlrpc -->",
    "keyphrases": {
        "rootcause": "supports external entities in XML DOCTYPE",
        "weakness": "Server-side Request Forgery",
        "impact": "File Enumeration",
        "vector": "",
        "attacker": "",
        "product": "Apache Roller",
        "version": "5.2.1, 5.2.0 and earlier",
        "component": ""
    }
}
