{
    "cveId": "CVE-2015-6509",
    "version": "1.0.0",
    "timestamp": "2024-12-10T17:54:04.992951+00:00",
    "description": "Multiple cross-site scripting (XSS) vulnerabilities in pfSense before 2.2.3 allow remote attackers to inject arbitrary web script or HTML via the (1) proxypass parameter to system_advanced_misc.php (2) adaptiveend, (3) adaptivestart, (4) maximumstates, (5) maximumtableentries, or (6) aliasesresolveinterval parameter to system_advanced_firewall.php (7) proxyurl, (8) proxyuser, or (9) proxyport parameter to system_advanced_misc.php or (10) name, (11) notification_name, (12) ipaddress, (13) password, (14) smtpipaddress, (15) smtpport, (16) smtpfromaddress, (17) smtpnotifyemailaddress, (18) smtpusername, or (19) smtppassword parameter to system_advanced_notifications.php.",
    "keyphrases": {
        "rootcause": "",
        "weakness": "cross-site scripting",
        "impact": "inject arbitrary web script or HTML",
        "vector": "",
        "attacker": "remote attackers",
        "product": "pfSense",
        "version": "before 2.2.3",
        "component": [
            "proxypass parameter to system_advanced_misc.php",
            "adaptiveend",
            "adaptivestart",
            "maximumstates",
            "maximumtableentries",
            "aliasesresolveinterval parameter to system_advanced_firewall.php",
            "proxyurl",
            "proxyuser",
            "proxyport parameter to system_advanced_misc.php",
            "name",
            "notification_name",
            "ipaddress",
            "password",
            "smtpipaddress",
            "smtpport",
            "smtpfromaddress",
            "smtpnotifyemailaddress",
            "smtpusername",
            "smtppassword parameter to system_advanced_notifications.php"
        ]
    }
}
