{
    "cveId": "CVE-2017-10045",
    "version": "1.0.0",
    "timestamp": "2024-12-06T11:32:07.789868+00:00",
    "description": "Vulnerability in the PeopleSoft Enterprise PeopleTools component of Oracle PeopleSoft Products (subcomponent Integration Broker). Supported versions that are affected are 8.54 and 8.55. Difficult to exploit vulnerability allows unauthenticated attacker with network access via HTTP to compromise PeopleSoft Enterprise PeopleTools. Successful attacks require human interaction from a person other than the attacker. Successful attacks of this vulnerability can result in unauthorized access to critical data or complete access to all PeopleSoft Enterprise PeopleTools accessible data. CVSS 3.0 Base Score 5.3 (Confidentiality impacts). CVSS Vector (CVSS3.0/AVN/ACH/PRN/UIR/SU/CH/IN/AN).",
    "keyphrases": {
        "rootcause": "",
        "weakness": "",
        "impact": [
            "unauthorized access to critical data",
            "complete access to all PeopleSoft Enterprise PeopleTools accessible data"
        ],
        "vector": "",
        "attacker": "unauthenticated attacker with network access via HTTP",
        "product": "Oracle PeopleSoft Products",
        "version": "8.54 and 8.55",
        "component": "PeopleSoft Enterprise PeopleTools"
    }
}
