{
  "cveId": "CVE-2017-10230",
  "version": "1.0.0",
  "timestamp": "2024-12-06T11:32:07.789868+00:00",
  "description": "Vulnerability in the Oracle Hospitality Cruise Dining Room Management component of Oracle Hospitality Applications (subcomponent SilverWhere). The supported version that is affected is 8.0.75. Easily exploitable vulnerability allows low privileged attacker with network access via HTTP to compromise Oracle Hospitality Cruise Dining Room Management. Successful attacks of this vulnerability can result in unauthorized update, insert or delete access to some of Oracle Hospitality Cruise Dining Room Management accessible data as well as unauthorized read access to a subset of Oracle Hospitality Cruise Dining Room Management accessible data. CVSS 3.0 Base Score 5.4 (Confidentiality and Integrity impacts). CVSS Vector (CVSS3.0/AVN/ACL/PRL/UIN/SU/CL/IL/AN).",
  "keyphrases": {
    "rootcause": "",
    "weakness": "",
    "impact": [
      "Integrity",
      "insert or delete access",
      "unauthorized read access",
      "unauthorized update"
    ],
    "vector": "",
    "attacker": "low privileged attacker",
    "product": "Oracle Hospitality Applications",
    "version": "8.0.75",
    "component": "Oracle Hospitality Cruise Dining Room Management"
  },
  "mitreTechnicalImpacts": []
}