{
    "cveId": "CVE-2017-10277",
    "version": "1.0.0",
    "timestamp": "2024-12-06T11:32:07.789868+00:00",
    "description": "Vulnerability in the MySQL Connectors component of Oracle MySQL (subcomponent Connector/Net). Supported versions that are affected are 6.9.9 and earlier. Easily exploitable vulnerability allows unauthenticated attacker with network access via multiple protocols to compromise MySQL Connectors. Successful attacks require human interaction from a person other than the attacker. Successful attacks of this vulnerability can result in unauthorized update, insert or delete access to some of MySQL Connectors accessible data as well as unauthorized read access to a subset of MySQL Connectors accessible data. CVSS 3.0 Base Score 5.4 (Confidentiality and Integrity impacts). CVSS Vector (CVSS3.0/AVN/ACL/PRN/UIR/SU/CL/IL/AN).",
    "keyphrases": {
        "rootcause": "",
        "weakness": "",
        "impact": "unauthorized update, insert or delete access",
        "vector": "multiple protocols",
        "attacker": "unauthenticated attacker",
        "product": "Oracle MySQL",
        "version": "6.9.9 and earlier",
        "component": "MySQL Connectors"
    }
}
