{
  "cveId": "CVE-2017-10190",
  "version": "1.0.0",
  "timestamp": "2024-12-11T16:08:24.783251+00:00",
  "description": "Vulnerability in the Java VM component of Oracle Database Server. Supported versions that are affected are 11.2.0.4, 12.1.0.2 and 12.2.0.1. Easily exploitable vulnerability allows high privileged attacker having Create Session, Create Procedure privilege with logon to the infrastructure where Java VM executes to compromise Java VM. While the vulnerability is in Java VM, attacks may significantly impact additional products. Successful attacks of this vulnerability can result in takeover of Java VM. CVSS 3.0 Base Score 8.2 (Confidentiality, Integrity and Availability impacts). CVSS Vector (CVSS3.0/AVL/ACL/PRH/UIN/SC/CH/IH/AH).",
  "keyphrases": {
    "rootcause": "",
    "weakness": "",
    "impact": [
      "Integrity and Availability impacts",
      "takeover of Java VM"
    ],
    "vector": "",
    "attacker": "high privileged attacker",
    "product": "Oracle Database Server",
    "version": [
      "11.2.0.4",
      "12.1.0.2 and 12.2.0.1"
    ],
    "component": "Java VM"
  },
  "mitreTechnicalImpacts": []
}