{
  "cveId": "CVE-2017-10398",
  "version": "1.0.0",
  "timestamp": "2024-12-06T11:32:07.789868+00:00",
  "description": "Vulnerability in the Oracle Hospitality Cruise Fleet Management component of Oracle Hospitality Applications (subcomponent BaseMasterPage). The supported version that is affected is 9.0.2.0. Easily exploitable vulnerability allows low privileged attacker with logon to the infrastructure where Oracle Hospitality Cruise Fleet Management executes to compromise Oracle Hospitality Cruise Fleet Management. While the vulnerability is in Oracle Hospitality Cruise Fleet Management, attacks may significantly impact additional products. Successful attacks of this vulnerability can result in unauthorized creation, deletion or modification access to critical data or all Oracle Hospitality Cruise Fleet Management accessible data as well as unauthorized access to critical data or complete access to all Oracle Hospitality Cruise Fleet Management accessible data. CVSS 3.0 Base Score 8.4 (Confidentiality and Integrity impacts). CVSS Vector (CVSS3.0/AVL/ACL/PRL/UIN/SC/CH/IH/AN).",
  "keyphrases": {
    "rootcause": "",
    "weakness": "",
    "impact": [
      "Integrity",
      "deletion or modification access to critical data or all Oracle Hospitality Cruise Fleet Management accessible data as well as unauthorized access to critical data or complete access to all Oracle Hospitality Cruise Management accessible data",
      "unauthorized creation"
    ],
    "vector": "",
    "attacker": "low privileged attacker",
    "product": "Oracle Hospitality Cruise Fleet Management",
    "version": "9.0.2.0",
    "component": "BaseMasterPage"
  },
  "mitreTechnicalImpacts": []
}