{
    "cveId": "CVE-2017-10342",
    "version": "1.0.0",
    "timestamp": "2024-12-11T16:08:24.783251+00:00",
    "description": "Vulnerability in the Java Advanced Management Console component of Oracle Java SE (subcomponent Server). The supported version that is affected is Java Advanced Management Console 2.7. Easily exploitable vulnerability allows unauthenticated attacker with network access via multiple protocols to compromise Java Advanced Management Console. Successful attacks of this vulnerability can result in unauthorized ability to cause a partial denial of service (partial DOS) of Java Advanced Management Console. CVSS 3.0 Base Score 5.3 (Availability impacts). CVSS Vector (CVSS3.0/AVN/ACL/PRN/UIN/SU/CN/IN/AL).",
    "keyphrases": {
        "rootcause": "",
        "weakness": "",
        "impact": "partial denial of service (partial DOS)",
        "vector": "multiple protocols",
        "attacker": "unauthenticated attacker with network access",
        "product": "Oracle Java SE",
        "version": "Java Advanced Management Console 2.7",
        "component": "Java Advanced Management Console component"
    }
}
