{
  "cveId": "CVE-2017-10159",
  "version": "1.0.0",
  "timestamp": "2024-12-11T16:08:24.783251+00:00",
  "description": "Vulnerability in the Oracle Communications Policy Management component of Oracle Communications Applications (subcomponent Portal, CMP). Supported versions that are affected are 11.5 and 12.x. Easily exploitable vulnerability allows unauthenticated attacker with network access via HTTP to compromise Oracle Communications Policy Management. Successful attacks require human interaction from a person other than the attacker and while the vulnerability is in Oracle Communications Policy Management, attacks may significantly impact additional products. Successful attacks of this vulnerability can result in unauthorized update, insert or delete access to some of Oracle Communications Policy Management accessible data as well as unauthorized read access to a subset of Oracle Communications Policy Management accessible data. CVSS 3.0 Base Score 6.1 (Confidentiality and Integrity impacts). CVSS Vector (CVSS3.0/AVN/ACL/PRN/UIR/SC/CL/IL/AN).",
  "keyphrases": {
    "rootcause": "",
    "weakness": "",
    "impact": [
      "Integrity",
      "insert or delete access",
      "unauthorized read access",
      "unauthorized update"
    ],
    "vector": "unauthenticated attacker with network access via HTTP",
    "attacker": "unauthenticated attacker",
    "product": "Oracle Communications Policy Management",
    "version": "11.5 and 12.x",
    "component": "Oracle Communications Policy Management component of Oracle Communications Applications"
  },
  "mitreTechnicalImpacts": []
}