{
    "cveId": "CVE-2017-10365",
    "version": "1.0.0",
    "timestamp": "2024-12-06T11:32:07.789868+00:00",
    "description": "Vulnerability in the MySQL Server component of Oracle MySQL (subcomponent Server InnoDB). Supported versions that are affected are 5.7.18 and earlier. Easily exploitable vulnerability allows high privileged attacker with network access via multiple protocols to compromise MySQL Server. Successful attacks of this vulnerability can result in unauthorized update, insert or delete access to some of MySQL Server accessible data and unauthorized ability to cause a partial denial of service (partial DOS) of MySQL Server. CVSS 3.0 Base Score 3.8 (Integrity and Availability impacts). CVSS Vector (CVSS3.0/AVN/ACL/PRH/UIN/SU/CN/IL/AL).",
    "keyphrases": {
        "rootcause": "",
        "weakness": "",
        "impact": "unauthorized update, insert or delete access",
        "vector": "multiple protocols",
        "attacker": "high privileged attacker with network access",
        "product": "Oracle MySQL",
        "version": "5.7.18 and earlier",
        "component": "Server InnoDB"
    }
}
