{
  "cveId": "CVE-2017-10204",
  "version": "1.0.0",
  "timestamp": "2024-12-11T16:08:24.783251+00:00",
  "description": "Vulnerability in the Oracle VM VirtualBox component of Oracle Virtualization (subcomponent Core). The supported version that is affected is Prior to 5.1.24. Easily exploitable vulnerability allows low privileged attacker with logon to the infrastructure where Oracle VM VirtualBox executes to compromise Oracle VM VirtualBox. While the vulnerability is in Oracle VM VirtualBox, attacks may significantly impact additional products. Successful attacks of this vulnerability can result in takeover of Oracle VM VirtualBox. CVSS 3.0 Base Score 8.8 (Confidentiality, Integrity and Availability impacts). CVSS Vector (CVSS3.0/AVL/ACL/PRL/UIN/SC/CH/IH/AH).",
  "keyphrases": {
    "rootcause": "",
    "weakness": "",
    "impact": [
      "Integrity and Availability impacts",
      "takeover of Oracle VM VirtualBox"
    ],
    "vector": "",
    "attacker": "low privileged attacker",
    "product": "Oracle VM VirtualBox",
    "version": "Prior to 5.1.24",
    "component": "Core"
  },
  "mitreTechnicalImpacts": []
}