{
    "cveId": "CVE-2017-10318",
    "version": "1.0.0",
    "timestamp": "2024-12-06T11:32:07.789868+00:00",
    "description": "Vulnerability in the Oracle Hospitality Suite8 component of Oracle Hospitality Applications (subcomponent WebConnect). Supported versions that are affected are 8.10.1 and 8.10.2. Easily exploitable vulnerability allows unauthenticated attacker with network access via HTTP to compromise Oracle Hospitality Suite8. Successful attacks require human interaction from a person other than the attacker and while the vulnerability is in Oracle Hospitality Suite8, attacks may significantly impact additional products. Successful attacks of this vulnerability can result in unauthorized read access to a subset of Oracle Hospitality Suite8 accessible data. CVSS 3.0 Base Score 4.7 (Confidentiality impacts). CVSS Vector (CVSS3.0/AVN/ACL/PRN/UIR/SC/CL/IN/AN).",
    "keyphrases": {
        "rootcause": "",
        "weakness": "",
        "impact": "unauthorized read access to a subset of Oracle Hospitality Suite8 accessible data",
        "vector": "",
        "attacker": "unauthenticated attacker with network access via HTTP",
        "product": "Oracle Hospitality Suite8",
        "version": "8.10.1 and 8.10.2",
        "component": "WebConnect"
    }
}
