{
    "cveId": "CVE-2017-10341",
    "version": "1.0.0",
    "timestamp": "2024-12-06T11:32:07.789868+00:00",
    "description": "Vulnerability in the Java Advanced Management Console component of Oracle Java SE (subcomponent Server). The supported version that is affected is Java Advanced Management Console 2.7. Difficult to exploit vulnerability allows unauthenticated attacker with network access via multiple protocols to compromise Java Advanced Management Console. Successful attacks of this vulnerability can result in unauthorized update, insert or delete access to some of Java Advanced Management Console accessible data. Note This vulnerability applies to Java deployments, typically in clients running sandboxed Java Web Start applications or sandboxed Java applets, that load and run untrusted code (e.g., code that comes from the internet) and rely on the Java sandbox for security. This vulnerability does not apply to Java deployments, typically in servers, that load and run only trusted code (e.g., code installed by an administrator). CVSS 3.0 Base Score 3.7 (Integrity impacts). CVSS Vector (CVSS3.0/AVN/ACH/PRN/UIN/SU/CN/IL/AN).",
    "keyphrases": {
        "rootcause": "",
        "weakness": "",
        "impact": "unauthorized update, insert or delete access to some of Java Advanced Management Console accessible data",
        "vector": "",
        "attacker": "unauthenticated attacker with network access",
        "product": "Oracle Java SE",
        "version": "Java Advanced Management Console 2.7",
        "component": "Java Advanced Management Console component"
    }
}
