{
    "cveId": "CVE-2017-10282",
    "version": "1.0.0",
    "timestamp": "2024-12-11T16:08:24.783251+00:00",
    "description": "Vulnerability in the Core RDBMS component of Oracle Database Server. Supported versions that are affected are 12.1.0.2 and 12.2.0.1. Easily exploitable vulnerability allows high privileged attacker having Create Session, Execute Catalog Role privilege with network access via Oracle Net to compromise Core RDBMS. While the vulnerability is in Core RDBMS, attacks may significantly impact additional products. Successful attacks of this vulnerability can result in takeover of Core RDBMS. CVSS 3.0 Base Score 9.1 (Confidentiality, Integrity and Availability impacts). CVSS Vector (CVSS3.0/AVN/ACL/PRH/UIN/SC/CH/IH/AH).",
    "keyphrases": {
        "rootcause": "",
        "weakness": "",
        "impact": "takeover of Core RDBMS",
        "vector": "network access via Oracle Net",
        "attacker": "high privileged attacker",
        "product": "Oracle Database Server",
        "version": "12.1.0.2 and 12.2.0.1",
        "component": "Core RDBMS"
    }
}
