{
  "cveId": "CVE-2017-10031",
  "version": "1.0.0",
  "timestamp": "2024-12-11T16:08:24.783251+00:00",
  "description": "Vulnerability in the Oracle Communications Convergence component of Oracle Communications Applications (subcomponent Mail Proxy (dojo)). Supported versions that are affected are 3.0 and 3.0.1. Easily exploitable vulnerability allows unauthenticated attacker with network access via HTTP to compromise Oracle Communications Convergence. While the vulnerability is in Oracle Communications Convergence, attacks may significantly impact additional products. Successful attacks of this vulnerability can result in unauthorized update, insert or delete access to some of Oracle Communications Convergence accessible data as well as unauthorized read access to a subset of Oracle Communications Convergence accessible data. CVSS 3.0 Base Score 7.2 (Confidentiality and Integrity impacts). CVSS Vector (CVSS3.0/AVN/ACL/PRN/UIN/SC/CL/IL/AN).",
  "keyphrases": {
    "rootcause": "",
    "weakness": "",
    "impact": [
      "Integrity",
      "insert or delete access",
      "unauthorized read access",
      "unauthorized update"
    ],
    "vector": "network access via HTTP",
    "attacker": "unauthenticated attacker",
    "product": "Oracle Communications Convergence",
    "version": "3.0 and 3.0.1",
    "component": "Mail Proxy (dojo)"
  },
  "mitreTechnicalImpacts": []
}