{
  "cveId": "CVE-2017-10388",
  "version": "1.0.0",
  "timestamp": "2024-12-11T16:08:24.783251+00:00",
  "description": "Vulnerability in the Java SE, Java SE Embedded component of Oracle Java SE (subcomponent Libraries). Supported versions that are affected are Java SE 6u161, 7u151, 8u144 and 9 Java SE Embedded 8u144. Difficult to exploit vulnerability allows unauthenticated attacker with network access via Kerberos to compromise Java SE, Java SE Embedded. Successful attacks require human interaction from a person other than the attacker. Successful attacks of this vulnerability can result in takeover of Java SE, Java SE Embedded. Note Applies to the Java SE Kerberos client. CVSS 3.0 Base Score 7.5 (Confidentiality, Integrity and Availability impacts). CVSS Vector (CVSS3.0/AVN/ACH/PRN/UIR/SU/CH/IH/AH).",
  "keyphrases": {
    "rootcause": "",
    "weakness": "",
    "impact": [
      "Integrity and Availability impacts",
      "Java SE Embedded",
      "takeover of Java SE"
    ],
    "vector": "",
    "attacker": "unauthenticated attacker with network access via Kerberos",
    "product": [
      "Oracle Java SE",
      "Java SE Embedded"
    ],
    "version": [
      "Java SE 6u161",
      "7u151",
      "8u144 and 9 Java SE Embedded 8u144"
    ],
    "component": "Libraries"
  },
  "mitreTechnicalImpacts": []
}