{
  "cveId": "CVE-2017-10258",
  "version": "1.0.0",
  "timestamp": "2024-12-11T16:08:24.783251+00:00",
  "description": "Vulnerability in the PeopleSoft Enterprise PRTL Interaction Hub component of Oracle PeopleSoft Products (subcomponent Add New Image). The supported version that is affected is 9.1.0. Easily exploitable vulnerability allows unauthenticated attacker with network access via HTTP to compromise PeopleSoft Enterprise PRTL Interaction Hub. Successful attacks require human interaction from a person other than the attacker and while the vulnerability is in PeopleSoft Enterprise PRTL Interaction Hub, attacks may significantly impact additional products. Successful attacks of this vulnerability can result in unauthorized update, insert or delete access to some of PeopleSoft Enterprise PRTL Interaction Hub accessible data as well as unauthorized read access to a subset of PeopleSoft Enterprise PRTL Interaction Hub accessible data. CVSS 3.0 Base Score 6.1 (Confidentiality and Integrity impacts). CVSS Vector (CVSS3.0/AVN/ACL/PRN/UIR/SC/CL/IL/AN).",
  "keyphrases": {
    "rootcause": "",
    "weakness": "",
    "impact": [
      "Integrity",
      "insert or delete access",
      "unauthorized read access",
      "unauthorized update"
    ],
    "vector": "HTTP",
    "attacker": "unauthenticated attacker",
    "product": "Oracle PeopleSoft Products",
    "version": "9.1.0",
    "component": "PeopleSoft Enterprise PRTL Interaction Hub"
  },
  "mitreTechnicalImpacts": []
}