{
  "cveId": "CVE-2017-10424",
  "version": "1.0.0",
  "timestamp": "2024-12-11T16:08:24.783251+00:00",
  "description": "Vulnerability in the MySQL Enterprise Monitor component of Oracle MySQL (subcomponent Monitoring Web). Supported versions that are affected are 3.2.8.2223 and earlier, 3.3.4.3247 and earlier and 3.4.2.4181 and earlier. Easily exploitable vulnerability allows unauthenticated attacker with network access via multiple protocols to compromise MySQL Enterprise Monitor. Successful attacks require human interaction from a person other than the attacker. Successful attacks of this vulnerability can result in takeover of MySQL Enterprise Monitor. CVSS 3.0 Base Score 8.8 (Confidentiality, Integrity and Availability impacts). CVSS Vector (CVSS3.0/AVN/ACL/PRN/UIR/SU/CH/IH/AH).",
  "keyphrases": {
    "rootcause": "",
    "weakness": "",
    "impact": [
      "Integrity and Availability impacts",
      "takeover of MySQL Enterprise Monitor"
    ],
    "vector": "multiple protocols",
    "attacker": "unauthenticated attacker",
    "product": "Oracle MySQL",
    "version": [
      "3.2.8.2223 and earlier",
      "3.3.4.3247 and earlier and 3.4.2.4181 and earlier"
    ],
    "component": "MySQL Enterprise Monitor component"
  },
  "mitreTechnicalImpacts": []
}