{
  "cveId": "CVE-2017-10177",
  "version": "1.0.0",
  "timestamp": "2024-12-06T11:32:07.789868+00:00",
  "description": "Vulnerability in the Oracle Application Object Library component of Oracle E-Business Suite (subcomponent Flexfields). The supported version that is affected is 12.2.6. Easily exploitable vulnerability allows low privileged attacker with network access via HTTP to compromise Oracle Application Object Library. Successful attacks of this vulnerability can result in unauthorized creation, deletion or modification access to critical data or all Oracle Application Object Library accessible data as well as unauthorized access to critical data or complete access to all Oracle Application Object Library accessible data. CVSS 3.0 Base Score 8.1 (Confidentiality and Integrity impacts). CVSS Vector (CVSS3.0/AVN/ACL/PRL/UIN/SU/CH/IH/AN).",
  "keyphrases": {
    "rootcause": "",
    "weakness": "",
    "impact": [
      "Integrity",
      "deletion or modification access to critical data or all Oracle Application Object Library accessible data as well as unauthorized access to critical data or complete access to all Oracle Application Object Library accessible data",
      "unauthorized creation"
    ],
    "vector": "",
    "attacker": "low privileged attacker with network access via HTTP",
    "product": "Oracle Application Object Library",
    "version": "12.2.6",
    "component": "Flexfields"
  },
  "mitreTechnicalImpacts": []
}