{
    "cveId": "CVE-2017-10196",
    "version": "1.0.0",
    "timestamp": "2024-12-11T16:08:24.783251+00:00",
    "description": "Vulnerability in the Oracle Outside In Technology component of Oracle Fusion Middleware (subcomponent Outside In Filters). The supported version that is affected is 8.5.3.0. Easily exploitable vulnerability allows unauthenticated attacker with network access via HTTP to compromise Oracle Outside In Technology. Successful attacks of this vulnerability can result in unauthorized ability to cause a hang or frequently repeatable crash (complete DOS) of Oracle Outside In Technology as well as unauthorized update, insert or delete access to some of Oracle Outside In Technology accessible data. CVSS 3.0 Base Score 8.2 (Integrity and Availability impacts). CVSS Vector (CVSS3.0/AVN/ACL/PRN/UIN/SU/CN/IL/AH).",
    "keyphrases": {
        "rootcause": "",
        "weakness": "",
        "impact": "cause a hang or frequently repeatable crash (complete DOS)",
        "vector": "HTTP",
        "attacker": "unauthenticated attacker with network access",
        "product": "Oracle Fusion Middleware",
        "version": "8.5.3.0",
        "component": "Outside In Technology"
    }
}
