{
    "cveId": "CVE-2017-10387",
    "version": "1.0.0",
    "timestamp": "2024-12-06T11:32:07.789868+00:00",
    "description": "Vulnerability in the Oracle CRM Technical Foundation component of Oracle E-Business Suite (subcomponent Preferences). Supported versions that are affected are 12.1.3, 12.2.3, 12.2.4, 12.2.5, 12.2.6 and 12.2.7. Easily exploitable vulnerability allows unauthenticated attacker with network access via HTTP to compromise Oracle CRM Technical Foundation. Successful attacks require human interaction from a person other than the attacker. Successful attacks of this vulnerability can result in unauthorized update, insert or delete access to some of Oracle CRM Technical Foundation accessible data. CVSS 3.0 Base Score 4.3 (Integrity impacts). CVSS Vector (CVSS3.0/AVN/ACL/PRN/UIR/SU/CN/IL/AN).",
    "keyphrases": {
        "rootcause": "",
        "weakness": "",
        "impact": "unauthorized update, insert or delete access to some of Oracle CRM Technical Foundation accessible data",
        "vector": "",
        "attacker": "unauthenticated attacker with network access via HTTP",
        "product": "Oracle CRM Technical Foundation",
        "version": "12.1.3, 12.2.3, 12.2.4, 12.2.5, 12.2.6 and 12.2.7",
        "component": "Preferences"
    }
}
