{
  "cveId": "CVE-2017-10170",
  "version": "1.0.0",
  "timestamp": "2024-12-18T22:42:50.929578+00:00",
  "description": "Vulnerability in the Oracle Field Service component of Oracle E-Business Suite (subcomponent Wireless/WAP). Supported versions that are affected are 12.1.1, 12.1.2 and 12.1.3. Easily exploitable vulnerability allows unauthenticated attacker with network access via HTTP to compromise Oracle Field Service. Successful attacks require human interaction from a person other than the attacker and while the vulnerability is in Oracle Field Service, attacks may significantly impact additional products. Successful attacks of this vulnerability can result in unauthorized access to critical data or complete access to all Oracle Field Service accessible data as well as unauthorized update, insert or delete access to some of Oracle Field Service accessible data. CVSS 3.0 Base Score 8.2 (Confidentiality and Integrity impacts). CVSS Vector (CVSS3.0/AVN/ACL/PRN/UIR/SC/CH/IL/AN).",
  "keyphrases": {
    "rootcause": "",
    "weakness": "",
    "impact": [
      "Integrity",
      "insert or delete access",
      "unauthorized access to critical data",
      "unauthorized update"
    ],
    "vector": "",
    "attacker": "unauthenticated attacker with network access via HTTP",
    "product": "Oracle E-Business Suite",
    "version": [
      "12.1.1",
      "12.1.2 and 12.1.3"
    ],
    "component": "Oracle Field Service component"
  },
  "mitreTechnicalImpacts": []
}