{
  "cveId": "CVE-2017-10344",
  "version": "1.0.0",
  "timestamp": "2024-12-06T11:32:07.789868+00:00",
  "description": "Vulnerability in the Oracle Hospitality Simphony component of Oracle Hospitality Applications (subcomponent Import/Export). Supported versions that are affected are 2.8 and 2.9. Difficult to exploit vulnerability allows unauthenticated attacker with network access via HTTP to compromise Oracle Hospitality Simphony. Successful attacks of this vulnerability can result in unauthorized access to critical data or complete access to all Oracle Hospitality Simphony accessible data as well as unauthorized update, insert or delete access to some of Oracle Hospitality Simphony accessible data. CVSS 3.0 Base Score 6.5 (Confidentiality and Integrity impacts). CVSS Vector (CVSS3.0/AVN/ACH/PRN/UIN/SU/CH/IL/AN).",
  "keyphrases": {
    "rootcause": "",
    "weakness": "",
    "impact": [
      "Integrity",
      "insert or delete access",
      "unauthorized access to critical data",
      "unauthorized update"
    ],
    "vector": "",
    "attacker": "unauthenticated attacker",
    "product": "Oracle Hospitality Simphony",
    "version": "2.8 and 2.9",
    "component": "Import/Export"
  },
  "mitreTechnicalImpacts": []
}