{
    "cveId": "CVE-2017-10394",
    "version": "1.0.0",
    "timestamp": "2024-12-06T11:32:07.789868+00:00",
    "description": "Vulnerability in the PeopleSoft Enterprise PeopleTools component of Oracle PeopleSoft Products (subcomponent Security). Supported versions that are affected are 8.54, 8.55 and 8.56. Easily exploitable vulnerability allows low privileged attacker with network access via HTTP to compromise PeopleSoft Enterprise PeopleTools. Successful attacks of this vulnerability can result in unauthorized update, insert or delete access to some of PeopleSoft Enterprise PeopleTools accessible data and unauthorized ability to cause a partial denial of service (partial DOS) of PeopleSoft Enterprise PeopleTools. CVSS 3.0 Base Score 5.4 (Integrity and Availability impacts). CVSS Vector (CVSS3.0/AVN/ACL/PRL/UIN/SU/CN/IL/AL).",
    "keyphrases": {
        "rootcause": "",
        "weakness": "",
        "impact": [
            "unauthorized update",
            "insert or delete access",
            "partial denial of service"
        ],
        "vector": "",
        "attacker": "low privileged attacker",
        "product": "Oracle PeopleSoft Products",
        "version": "8.54, 8.55 and 8.56",
        "component": "PeopleSoft Enterprise PeopleTools"
    }
}
