{
    "cveId": "CVE-2017-10047",
    "version": "1.0.0",
    "timestamp": "2024-12-11T16:08:24.783251+00:00",
    "description": "Vulnerability in the MICROS BellaVita component of Oracle Hospitality Applications (subcomponent Interface). The supported version that is affected is 2.7.x. Easily exploitable vulnerability allows unauthenticated attacker with network access via HTTP to compromise MICROS BellaVita. Successful attacks of this vulnerability can result in unauthorized update, insert or delete access to some of MICROS BellaVita accessible data as well as unauthorized read access to a subset of MICROS BellaVita accessible data. CVSS 3.0 Base Score 6.5 (Confidentiality and Integrity impacts). CVSS Vector (CVSS3.0/AVN/ACL/PRN/UIN/SU/CL/IL/AN).",
    "keyphrases": {
        "rootcause": "",
        "weakness": "",
        "impact": "unauthorized update, insert or delete access",
        "vector": "",
        "attacker": "unauthenticated attacker",
        "product": "Oracle Hospitality Applications",
        "version": "2.7.x",
        "component": "MICROS BellaVita"
    }
}
