{
  "cveId": "CVE-2017-10361",
  "version": "1.0.0",
  "timestamp": "2024-12-11T16:08:24.783251+00:00",
  "description": "Vulnerability in the Oracle Hospitality Cruise Shipboard Property Management System component of Oracle Hospitality Applications (subcomponent OHC DRS). The supported version that is affected is 8.0.2.0. Easily exploitable vulnerability allows low privileged attacker with network access via HTTP to compromise Oracle Hospitality Cruise Shipboard Property Management System. While the vulnerability is in Oracle Hospitality Cruise Shipboard Property Management System, attacks may significantly impact additional products. Successful attacks of this vulnerability can result in unauthorized read access to a subset of Oracle Hospitality Cruise Shipboard Property Management System accessible data and unauthorized ability to cause a partial denial of service (partial DOS) of Oracle Hospitality Cruise Shipboard Property Management System. CVSS 3.0 Base Score 6.4 (Confidentiality and Availability impacts). CVSS Vector (CVSS3.0/AVN/ACL/PRL/UIN/SC/CL/IN/AL).",
  "keyphrases": {
    "rootcause": "",
    "weakness": "",
    "impact": [
      "Availability",
      "partial denial of service (partial DOS)",
      "unauthorized read access"
    ],
    "vector": "low privileged attacker with network access via HTTP",
    "attacker": "low privileged attacker",
    "product": "Oracle Hospitality Cruise Shipboard Property Management System",
    "version": "8.0.2.0",
    "component": ""
  },
  "mitreTechnicalImpacts": []
}