{
    "cveId": "CVE-2017-10428",
    "version": "1.0.0",
    "timestamp": "2024-12-06T11:32:07.789868+00:00",
    "description": "Vulnerability in the Oracle VM VirtualBox component of Oracle Virtualization (subcomponent Core). The supported version that is affected is Prior to 5.1.30. Difficult to exploit vulnerability allows high privileged attacker with logon to the infrastructure where Oracle VM VirtualBox executes to compromise Oracle VM VirtualBox. While the vulnerability is in Oracle VM VirtualBox, attacks may significantly impact additional products. Successful attacks of this vulnerability can result in unauthorized update, insert or delete access to some of Oracle VM VirtualBox accessible data as well as unauthorized read access to a subset of Oracle VM VirtualBox accessible data and unauthorized ability to cause a partial denial of service (partial DOS) of Oracle VM VirtualBox. CVSS 3.0 Base Score 5.0 (Confidentiality, Integrity and Availability impacts). CVSS Vector (CVSS3.0/AVL/ACH/PRH/UIN/SC/CL/IL/AL).",
    "keyphrases": {
        "rootcause": "",
        "weakness": "",
        "impact": [
            "unauthorized update",
            "insert or delete access to some of Oracle VM VirtualBox accessible data",
            "unauthorized read access to a subset of Oracle VM VirtualBox accessible data",
            "partial denial of service"
        ],
        "vector": "",
        "attacker": "high privileged attacker with logon to the infrastructure where Oracle VM VirtualBox executes",
        "product": "Oracle VM VirtualBox",
        "version": "Prior to 5.1.30",
        "component": "Core"
    }
}
