{
    "cveId": "CVE-2017-10269",
    "version": "1.0.0",
    "timestamp": "2024-12-11T16:08:24.783251+00:00",
    "description": "Vulnerability in the Oracle Tuxedo component of Oracle Fusion Middleware (subcomponent Core). Supported versions that are affected are 11.1.1, 12.1.1, 12.1.3 and 12.2.2. Easily exploitable vulnerability allows unauthenticated attacker with network access via Jolt to compromise Oracle Tuxedo. While the vulnerability is in Oracle Tuxedo, attacks may significantly impact additional products. Successful attacks of this vulnerability can result in unauthorized creation, deletion or modification access to critical data or all Oracle Tuxedo accessible data as well as unauthorized access to critical data or complete access to all Oracle Tuxedo accessible data and unauthorized ability to cause a partial denial of service (partial DOS) of Oracle Tuxedo. CVSS 3.0 Base Score 10.0 (Confidentiality, Integrity and Availability impacts). CVSS Vector (CVSS3.0/AVN/ACL/PRN/UIN/SC/CH/IH/AL).",
    "keyphrases": {
        "rootcause": "",
        "weakness": "",
        "impact": [
            "unauthorized creation, deletion or modification access to critical data or all Oracle Tuxedo accessible data",
            "unauthorized access to critical data or complete access to all Oracle Tuxedo accessible data",
            "unauthorized ability to cause a partial denial of service (partial DOS)"
        ],
        "vector": "Jolt",
        "attacker": "unauthenticated attacker with network access",
        "product": "Oracle Tuxedo",
        "version": [
            "11.1.1",
            "12.1.1",
            "12.1.3",
            "12.2.2"
        ],
        "component": ""
    }
}
