{
    "cveId": "CVE-2017-10055",
    "version": "1.0.0",
    "timestamp": "2024-12-11T16:08:24.783251+00:00",
    "description": "Vulnerability in the Oracle iPlanet Web Server component of Oracle Fusion Middleware (subcomponent Admin Graphical User Interface). The supported version that is affected is 7.0. Easily exploitable vulnerability allows unauthenticated attacker with network access via HTTP to compromise Oracle iPlanet Web Server. Successful attacks require human interaction from a person other than the attacker and while the vulnerability is in Oracle iPlanet Web Server, attacks may significantly impact additional products. Successful attacks of this vulnerability can result in unauthorized update, insert or delete access to some of Oracle iPlanet Web Server accessible data as well as unauthorized read access to a subset of Oracle iPlanet Web Server accessible data. CVSS 3.0 Base Score 6.1 (Confidentiality and Integrity impacts). CVSS Vector (CVSS3.0/AVN/ACL/PRN/UIR/SC/CL/IL/AN).",
    "keyphrases": {
        "rootcause": "",
        "weakness": "",
        "impact": "unauthorized update, insert or delete access to some of Oracle iPlanet Web Server accessible data as well as unauthorized read access to a subset of Oracle iPlanet Web Server accessible data",
        "vector": "",
        "attacker": "unauthenticated attacker with network access via HTTP",
        "product": "Oracle iPlanet Web Server",
        "version": "7.0",
        "component": "Admin Graphical User Interface"
    }
}
