{
    "cveId": "CVE-2017-10056",
    "version": "1.0.0",
    "timestamp": "2024-12-06T11:32:07.789868+00:00",
    "description": "Vulnerability in the Oracle Hospitality 9700 component of Oracle Hospitality Applications (subcomponent Property Management Systems). The supported version that is affected is 4.0. Easily exploitable vulnerability allows low privileged attacker with logon to the infrastructure where Oracle Hospitality 9700 executes to compromise Oracle Hospitality 9700. Successful attacks of this vulnerability can result in unauthorized access to critical data or complete access to all Oracle Hospitality 9700 accessible data. CVSS 3.0 Base Score 5.5 (Confidentiality impacts). CVSS Vector (CVSS3.0/AVL/ACL/PRL/UIN/SU/CH/IN/AN).",
    "keyphrases": {
        "rootcause": "",
        "weakness": "",
        "impact": "unauthorized access to critical data or complete access to all Oracle Hospitality 9700 accessible data",
        "vector": "",
        "attacker": "low privileged attacker",
        "product": "Oracle Hospitality Applications",
        "version": "4.0",
        "component": "Oracle Hospitality 9700"
    }
}
