{
    "cveId": "CVE-2017-10113",
    "version": "1.0.0",
    "timestamp": "2024-12-06T11:32:07.789868+00:00",
    "description": "Vulnerability in the Oracle Common Applications component of Oracle E-Business Suite (subcomponent CRM User Management Framework). Supported versions that are affected are 12.1.3, 12.2.3, 12.2.4, 12.2.5 and 12.2.6. Easily exploitable vulnerability allows unauthenticated attacker with network access via HTTP to compromise Oracle Common Applications. Successful attacks require human interaction from a person other than the attacker and while the vulnerability is in Oracle Common Applications, attacks may significantly impact additional products. Successful attacks of this vulnerability can result in unauthorized access to critical data or complete access to all Oracle Common Applications accessible data as well as unauthorized update, insert or delete access to some of Oracle Common Applications accessible data. CVSS 3.0 Base Score 8.2 (Confidentiality and Integrity impacts). CVSS Vector (CVSS3.0/AVN/ACL/PRN/UIR/SC/CH/IL/AN).",
    "keyphrases": {
        "rootcause": "",
        "weakness": "",
        "impact": [
            "unauthorized access to critical data",
            "complete access to all Oracle Common Applications accessible data",
            "unauthorized update",
            "insert",
            "delete access to some of Oracle Common Applications accessible data"
        ],
        "vector": "",
        "attacker": "unauthenticated attacker with network access via HTTP",
        "product": "Oracle E-Business Suite",
        "version": "12.1.3, 12.2.3, 12.2.4, 12.2.5 and 12.2.6",
        "component": "Oracle Common Applications component"
    }
}
