{
    "cveId": "CVE-2017-10222",
    "version": "1.0.0",
    "timestamp": "2024-12-11T16:08:24.783251+00:00",
    "description": "Vulnerability in the Oracle Hospitality Materials Control component of Oracle Hospitality Applications (subcomponent Production Tool). Supported versions that are affected are 8.31.4 and 8.32.0. Easily exploitable vulnerability allows low privileged attacker with network access via HTTP to compromise Oracle Hospitality Materials Control. Successful attacks of this vulnerability can result in unauthorized update, insert or delete access to some of Oracle Hospitality Materials Control accessible data as well as unauthorized read access to a subset of Oracle Hospitality Materials Control accessible data. CVSS 3.0 Base Score 5.4 (Confidentiality and Integrity impacts). CVSS Vector (CVSS3.0/AVN/ACL/PRL/UIN/SU/CL/IL/AN).",
    "keyphrases": {
        "rootcause": "",
        "weakness": "",
        "impact": [
            "unauthorized update",
            "insert or delete",
            "unauthorized read"
        ],
        "vector": "low privileged attacker with network access via HTTP",
        "attacker": "",
        "product": "Oracle Hospitality Applications",
        "version": "8.31.4 and 8.32.0",
        "component": "Oracle Hospitality Materials Control"
    }
}
