{
    "cveId": "CVE-2017-10039",
    "version": "1.0.0",
    "timestamp": "2024-12-11T16:08:24.783251+00:00",
    "description": "Vulnerability in the Oracle Agile PLM component of Oracle Supply Chain Products Suite (subcomponent Web Client). Supported versions that are affected are 9.3.5 and 9.3.6. Easily exploitable vulnerability allows low privileged attacker with network access via HTTP to compromise Oracle Agile PLM. Successful attacks require human interaction from a person other than the attacker and while the vulnerability is in Oracle Agile PLM, attacks may significantly impact additional products. Successful attacks of this vulnerability can result in unauthorized access to critical data or complete access to all Oracle Agile PLM accessible data. CVSS 3.0 Base Score 6.8 (Confidentiality impacts). CVSS Vector (CVSS3.0/AVN/ACL/PRL/UIR/SC/CH/IN/AN).",
    "keyphrases": {
        "rootcause": "",
        "weakness": "",
        "impact": "unauthorized access to critical data or complete access to all Oracle Agile PLM accessible data",
        "vector": "",
        "attacker": "low privileged attacker with network access via HTTP",
        "product": "Oracle Agile PLM",
        "version": "9.3.5 and 9.3.6",
        "component": "Web Client"
    }
}
