{
    "cveId": "CVE-2017-10268",
    "version": "1.0.0",
    "timestamp": "2024-12-11T16:08:24.783251+00:00",
    "description": "Vulnerability in the MySQL Server component of Oracle MySQL (subcomponent Server Replication). Supported versions that are affected are 5.5.57 and earlier, 5.6.37 and earlier and 5.7.19 and earlier. Difficult to exploit vulnerability allows high privileged attacker with logon to the infrastructure where MySQL Server executes to compromise MySQL Server. Successful attacks of this vulnerability can result in unauthorized access to critical data or complete access to all MySQL Server accessible data. CVSS 3.0 Base Score 4.1 (Confidentiality impacts). CVSS Vector (CVSS3.0/AVL/ACH/PRH/UIN/SU/CH/IN/AN).",
    "keyphrases": {
        "rootcause": "",
        "weakness": "",
        "impact": "unauthorized access to critical data or complete access to all MySQL Server accessible data",
        "vector": "",
        "attacker": "high privileged attacker",
        "product": "Oracle MySQL",
        "version": "5.5.57 and earlier, 5.6.37 and earlier and 5.7.19 and earlier",
        "component": "Server Replication"
    }
}
