{
    "cveId": "CVE-2012-0687",
    "version": "1.0.0",
    "timestamp": "2024-12-10T17:54:04.992951+00:00",
    "description": "TIBCO ActiveMatrix Runtime Platform in Service Grid and Service Bus 2.x before 2.3.2 and BusinessWorks Service Engine before 5.8.2 TIBCO ActiveMatrix Platform in TIBCO Silver Fabric ActiveMatrix Service Grid Distribution 3.1.3, Service Grid and Service Bus 3.x before 3.1.5, BusinessWorks Service Engine 5.9.x before 5.9.3, and BPM before 1.3.0 TIBCO BusinessEvents Runtime in Enterprise and Inference Editions 3.x before 3.0.3, Standard Edition 4.x before 4.0.2, and Standard Edition and Express 5.0.0 and TIBCO BusinessWorks Engine in TIBCO Silver Fabric ActiveMatrix BusinessWorks Distribution 5.9.2 and ActiveMatrix BusinessWorks before 5.9.3 allow remote attackers to obtain sensitive information via a crafted URL.",
    "keyphrases": {
        "rootcause": "improper URL protection",
        "weakness": "information disclosure",
        "impact": "obtain sensitive information",
        "vector": "crafted URL",
        "attacker": "remote attackers",
        "product": [
            "TIBCO ActiveMatrix Runtime Platform",
            "BusinessWorks Service Engine",
            "TIBCO ActiveMatrix Platform",
            "TIBCO Silver Fabric ActiveMatrix Service Grid Distribution",
            "TIBCO BusinessEvents Runtime",
            "TIBCO BusinessWorks Engine",
            "TIBCO Silver Fabric ActiveMatrix BusinessWorks Distribution",
            "ActiveMatrix BusinessWorks"
        ],
        "version": [
            "2.x before 2.3.2",
            "3.1.3",
            "3.x before 3.1.5",
            "before 5.8.2",
            "5.9.x before 5.9.3",
            "before 5.9.3",
            "before 1.3.0",
            "3.x before 3.0.3",
            "4.x before 4.0.2",
            "5.0.0",
            "5.9.2"
        ],
        "component": ""
    }
}
