{
    "cveId": "CVE-2012-0217",
    "version": "1.0.0",
    "timestamp": "2024-12-10T17:54:04.992951+00:00",
    "description": "The x86-64 kernel system-call functionality in Xen 4.1.2 and earlier, as used in Citrix XenServer 6.0.2 and earlier and other products Oracle Solaris 11 and earlier illumos before r13724 Joyent SmartOS before 20120614T184600Z FreeBSD before 9.0-RELEASE-p3 NetBSD 6.0 Beta and earlier Microsoft Windows Server 2008 R2 and R2 SP1 and Windows 7 Gold and SP1 and possibly other operating systems, when running on an Intel processor, incorrectly uses the sysret path in cases where a certain address is not a canonical address, which allows local users to gain privileges via a crafted application. NOTE because this issue is due to incorrect use of the Intel specification, it should have been split into separate identifiers however, there was some value in preserving the original mapping of the multi-codebase coordinated-disclosure effort to a single identifier.",
    "keyphrases": {
        "rootcause": "",
        "weakness": "",
        "impact": "gain privileges",
        "vector": "crafted application",
        "attacker": "local users",
        "product": [
            "Citrix XenServer",
            "Oracle Solaris",
            "Joyent SmartOS",
            "FreeBSD",
            "NetBSD",
            "Microsoft Windows Server",
            "Windows 7"
        ],
        "version": [
            "6.0.2 and earlier",
            "11 and earlier",
            "before 20120614T184600Z",
            "before 9.0-RELEASE-p3",
            "6.0 Beta and earlier",
            "2008 R2 and R2 SP1",
            "Gold and SP1"
        ],
        "component": ""
    }
}
