{
    "cveId": "CVE-2008-3511",
    "version": "1.0.0",
    "timestamp": "2024-12-10T17:54:04.992951+00:00",
    "description": "Multiple cross-site scripting (XSS) vulnerabilities in Softbiz Image Gallery (Photo Gallery) allow remote attackers to inject arbitrary web script or HTML via the (1) latest parameter to (a) index.php, (b) images.php, (c) suggest_image.php, and (d) image_desc.php and the (2) msg parameter to index.php, images.php, and suggest_image.php, and (e) index.php, (f) adminhome.php, (g) config.php, (h) changepassword.php, (i) cleanup.php, (j) browsecats.php, and (k) images.php in admin/. NOTE the image_desc.php/msg vector is covered by CVE-2006-1660. NOTE the provenance of this information is unknown the details are obtained solely from third party information.",
    "keyphrases": {
        "rootcause": "cross-site scripting",
        "weakness": "",
        "impact": "inject arbitrary web script or HTML",
        "vector": [
            "latest parameter to index.php",
            "images.php",
            "suggest_image.php",
            "and image_desc.php",
            "msg parameter to index.php",
            "images.php",
            "and suggest_image.php"
        ],
        "attacker": "remote attackers",
        "product": "Softbiz Image Gallery (Photo Gallery)",
        "version": "",
        "component": [
            "index.php",
            "images.php",
            "suggest_image.php",
            "image_desc.php",
            "adminhome.php",
            "config.php",
            "changepassword.php",
            "cleanup.php",
            "browsecats.php"
        ]
    }
}
