{
    "cveId": "CVE-2008-3081",
    "version": "1.0.0",
    "timestamp": "2024-12-10T17:54:04.992951+00:00",
    "description": "Multiple unspecified input validation vulnerabilities in the Web management interface (aka Messaging Administration interface) in Avaya Message Storage Server (MSS) 3.x and 4.0, and possibly Communication Manager 3.1.x, allow remote authenticated administrators to execute arbitrary commands as user vexvm via vectors related to (1) SFTP Remote Store configuration (2) remote FTP storage settings (3) name server lookup (4) pinging another host (5) TCP/IP Networking parameter configuration (6) the external hosts configuration main page (7) adding and changing external hosts (8) Windows domain parameter configuration (9) date, time, and NTP server configuration (10) alarm settings (11) the command line history form (12) the maintenance form and (13) the server events form.",
    "keyphrases": {
        "rootcause": "Multiple unspecified input validation vulnerabilities",
        "weakness": "command injection",
        "impact": "execute arbitrary commands",
        "vector": [
            "SFTP Remote Store configuration",
            "remote FTP storage settings",
            "name server lookup",
            "pinging another host",
            "TCP/IP Networking parameter configuration",
            "external hosts configuration main page",
            "adding and changing external hosts",
            "Windows domain parameter configuration",
            "date, time, and NTP server configuration",
            "alarm settings",
            "command line history form",
            "maintenance form",
            "server events form"
        ],
        "attacker": "remote authenticated administrators",
        "product": "Avaya Message Storage Server, Communication Manager",
        "version": "3.x, 4.0, 3.1.x",
        "component": "Web management interface"
    }
}
