{
    "cveId": "CVE-2021-20589",
    "version": "1.0.0",
    "timestamp": "2024-12-15T20:24:27.876763+00:00",
    "description": "Buffer access with incorrect length value vulnerability in GOT2000 series GT27 model communication driver versions 01.19.000 through 01.38.000, GT25 model communication driver versions 01.19.000 through 01.38.000, GT23 model communication driver versions 01.19.000 through 01.38.000 and GT21 model communication driver versions 01.21.000 through 01.39.000, GOT SIMPLE series GS21 model communication driver versions 01.21.000 through 01.39.000, GT SoftGOT2000 versions 1.170C through 1.250L and Tension Controller LE7-40GU-L Screen package data for MODBUS/TCP V1.00 allows a remote unauthenticated attacker to stop the communication function of the products via specially crafted packets.",
    "keyphrases": {
        "rootcause": "",
        "weakness": "buffer access with incorrect length value",
        "impact": "stop the communication function",
        "vector": "specially crafted packets",
        "attacker": "remote unauthenticated attacker",
        "product": [
            "GOT2000 series GT27 model",
            "GT25 model",
            "GT23 model",
            "GT21 model",
            "GOT SIMPLE series GS21 model",
            "GT SoftGOT2000",
            "Tension Controller LE7-40GU-L Screen"
        ],
        "version": [
            "01.19.000 through 01.38.000",
            "01.19.000 through 01.38.000",
            "01.19.000 through 01.38.000",
            "01.21.000 through 01.39.000",
            "01.21.000 through 01.39.000",
            "1.170C through 1.250L"
        ],
        "component": [
            "communication driver",
            "communication driver",
            "communication driver",
            "communication driver",
            "communication driver",
            "Screen package data for MODBUS/TCP"
        ]
    }
}
