{
    "cveId": "CVE-2021-20680",
    "version": "1.0.0",
    "timestamp": "2024-12-15T20:24:27.876763+00:00",
    "description": "Cross-site scripting vulnerability in NEC Aterm devices (Aterm WG1900HP2 firmware Ver.1.3.1 and earlier, Aterm WG1900HP firmware Ver.2.5.1 and earlier, Aterm WG1800HP4 firmware Ver.1.3.1 and earlier, Aterm WG1800HP3 firmware Ver.1.5.1 and earlier, Aterm WG1200HS2 firmware Ver.2.5.0 and earlier, Aterm WG1200HP3 firmware Ver.1.3.1 and earlier, Aterm WG1200HP2 firmware Ver.2.5.0 and earlier, Aterm W1200EX firmware Ver.1.3.1 and earlier, Aterm W1200EX-MS firmware Ver.1.3.1 and earlier, Aterm WG1200HS firmware all versions Aterm WG1200HP firmware all versions Aterm WF800HP firmware all versions Aterm WF300HP2 firmware all versions Aterm WR8165N firmware all versions Aterm W500P firmware all versions, and Aterm W300P firmware all versions) allows remote attackers to inject arbitrary script or HTML via unspecified vectors.",
    "keyphrases": {
        "rootcause": "",
        "weakness": "cross-site scripting",
        "impact": "arbitrary script or HTML injection",
        "vector": "unspecified vectors",
        "attacker": "remote attackers",
        "product": "NEC Aterm devices",
        "version": [
            "WG1900HP2 firmware Ver.1.3.1 and earlier",
            "WG1900HP firmware Ver.2.5.1 and earlier",
            "WG1800HP4 firmware Ver.1.3.1 and earlier",
            "WG1800HP3 firmware Ver.1.5.1 and earlier",
            "WG1200HS2 firmware Ver.2.5.0 and earlier",
            "WG1200HP3 firmware Ver.1.3.1 and earlier",
            "WG1200HP2 firmware Ver.2.5.0 and earlier",
            "W1200EX firmware Ver.1.3.1 and earlier",
            "W1200EX-MS firmware Ver.1.3.1 and earlier"
        ],
        "component": ""
    }
}
