{
    "cveId": "CVE-2018-15430",
    "version": "1.0.0",
    "timestamp": "2024-12-12T22:08:52.294043+00:00",
    "description": "A vulnerability in the administrative web interface of Cisco Expressway Series and Cisco TelePresence Video Communication Server (VCS) could allow an authenticated, remote attacker to execute code with user-level privileges on the underlying operating system. The vulnerability is due to insufficient validation of the content of upgrade packages. An attacker could exploit this vulnerability by uploading a malicious archive to the Upgrade page of the administrative web interface. A successful exploit could allow the attacker to execute code with user-level privileges on the underlying operating system.",
    "keyphrases": {
        "rootcause": "insufficient validation of the content of upgrade packages",
        "weakness": "",
        "impact": "execute code with user-level privileges",
        "vector": "uploading a malicious archive",
        "attacker": "authenticated remote attacker",
        "product": [
            "Cisco Expressway Series",
            "Cisco TelePresence Video Communication Server (VCS)"
        ],
        "version": "",
        "component": "administrative web interface"
    }
}
