{
    "cveId": "CVE-2018-15454",
    "version": "1.0.0",
    "timestamp": "2024-12-12T22:08:52.294043+00:00",
    "description": "A vulnerability in the Session Initiation Protocol (SIP) inspection engine of Cisco Adaptive Security Appliance (ASA) Software and Cisco Firepower Threat Defense (FTD) Software could allow an unauthenticated, remote attacker to cause an affected device to reload or trigger high CPU, resulting in a denial of service (DoS) condition. The vulnerability is due to improper handling of SIP traffic. An attacker could exploit this vulnerability by sending SIP requests designed to specifically trigger this issue at a high rate across an affected device. Software updates that address this vulnerability are not yet available.",
    "keyphrases": {
        "rootcause": "improper handling of SIP traffic",
        "weakness": "",
        "impact": "denial of service (DoS)",
        "vector": "SIP requests",
        "attacker": "unauthenticated remote attacker",
        "product": [
            "Cisco Adaptive Security Appliance (ASA) Software",
            "Cisco Firepower Threat Defense (FTD) Software"
        ],
        "version": "",
        "component": "Session Initiation Protocol (SIP) inspection engine"
    }
}
