{
    "cveId": "CVE-2016-10273",
    "version": "1.0.0",
    "timestamp": "2024-12-11T16:08:24.783251+00:00",
    "description": "Multiple stack buffer overflow vulnerabilities in Jensen of Scandinavia AS AirLink 3G (AL3G) version 2.23m (Rev. 3), AirLink 5000AC (AL5000AC) version 1.13, and AirLink 59300 (AL59300) version 1.04 (Rev. 4) devices allow remote attackers to execute arbitrary code or crash the web service via the (1) ateFunc, (2) ateGain, (3) ateTxCount, (4) ateChan, (5) ateRate, (6) ateMacID, (7) e2pTxPower1, (8) e2pTxPower2, (9) e2pTxPower3, (10) e2pTxPower4, (11) e2pTxPower5, (12) e2pTxPower6, (13) e2pTxPower7, (14) e2pTx2Power1, (15) e2pTx2Power2, (16) e2pTx2Power3, (17) e2pTx2Power4, (18) e2pTx2Power5, (19) e2pTx2Power6, (20) e2pTx2Power7, (21) ateTxFreqOffset, (22) ateMode, (23) ateBW, (24) ateAntenna, (25) e2pTxFreqOffset, (26) e2pTxPwDeltaB, (27) e2pTxPwDeltaG, (28) e2pTxPwDeltaMix, (29) e2pTxPwDeltaN, and (30) readE2P parameters of the /goform/formWlanMP endpoint.",
    "keyphrases": {
        "rootcause": "",
        "weakness": "stack buffer overflow",
        "impact": [
            "execute arbitrary code",
            "crash the web service"
        ],
        "vector": [
            "ateFunc",
            "ateGain",
            "ateTxCount",
            "ateChan",
            "ateRate",
            "ateMacID",
            "e2pTxPower1",
            "e2pTxPower2",
            "e2pTxPower3",
            "e2pTxPower4",
            "e2pTxPower5",
            "e2pTxPower6",
            "e2pTxPower7",
            "e2pTx2Power1",
            "e2pTx2Power2",
            "e2pTx2Power3",
            "e2pTx2Power4",
            "e2pTx2Power5",
            "e2pTx2Power6",
            "e2pTx2Power7",
            "ateTxFreqOffset",
            "ateMode",
            "ateBW",
            "ateAntenna",
            "e2pTxFreqOffset",
            "e2pTxPwDeltaB",
            "e2pTxPwDeltaG",
            "e2pTxPwDeltaMix",
            "e2pTxPwDeltaN",
            "readE2P"
        ],
        "attacker": "remote attackers",
        "product": "Jensen of Scandinavia AS AirLink",
        "version": "",
        "component": "/goform/formWlanMP endpoint"
    }
}
