{
  "cveId": "CVE-2024-34693",
  "version": "1.0.0",
  "timestamp": "2024-12-06T11:32:07.789868+00:00",
  "description": "Improper Input Validation vulnerability in Apache Superset, allows for an authenticated attacker to create a MariaDB connection with local_infile enabled. If both the MariaDB server (off by default) and the local mysql client on the web server are set to allow for local infile, its possible for the attacker to execute a specific MySQL/MariaDB SQL command that is able to read files from the server and insert their content on a MariaDB database table.This issue affects Apache Superset before 3.1.3 and version 4.0.0 Users are recommended to upgrade to version 4.0.1 or 3.1.3, which fixes the issue.",
  "keyphrases": {
    "rootcause": [
      "Improper Input Validation",
      "Input Validation vulnerability"
    ],
    "weakness": "",
    "impact": [
      "create a MariaDB connection with local_infile enabled",
      "read files"
    ],
    "vector": "",
    "attacker": "authenticated attacker",
    "product": "Apache Superset",
    "version": "before 3.1.3 and version 4.0.0",
    "component": ""
  },
  "mitreTechnicalImpacts": []
}