{
    "cveId": "CVE-2023-28143",
    "version": "1.0.0",
    "timestamp": "2024-12-15T20:24:27.876763+00:00",
    "description": "Qualys Cloud Agent for macOS (versions 2.5.1-75 before 3.7)installer allows a local escalation of privilege bounded only to the time ofinstallation and only on older macOSX (macOS 10.15 and older) versions.Attackers may exploit incorrect file permissions to give them ROOT commandexecution privileges on the host. During the install of the PKG, a step in theprocess involves extracting the package and copying files to severaldirectories. Attackers may gain writable access to files during the install ofPKG when extraction of the package and copying files to several directories,enabling a local escalation of privilege.",
    "keyphrases": {
        "rootcause": "incorrect file permissions",
        "weakness": "",
        "impact": "local escalation of privilege",
        "vector": "",
        "attacker": "attackers",
        "product": "Qualys Cloud Agent for macOS",
        "version": "2.5.1-75 before 3.7",
        "component": "installer"
    }
}
