{
  "cveId": "CVE-2021-34951",
  "version": "1.0.0",
  "timestamp": "2024-12-06T11:32:07.789868+00:00",
  "description": "Foxit PDF Reader Annotation Use of Uninitialized Variable Information Disclosure Vulnerability. This vulnerability allows remote attackers to disclose sensitive information on affected installations of Foxit PDF Reader. User interaction is required to exploit this vulnerability in that the target must visit a malicious page or open a malicious file. The specific flaw exists within the handling of Annotation objects. The issue results from the lack of proper initialization of a pointer prior to accessing it. An attacker can leverage this in conjunction with other vulnerabilities to execute arbitrary code in the context of the current process. Was ZDI-CAN-14395.",
  "keyphrases": {
    "rootcause": "Use of Uninitialized Variable",
    "weakness": "Information Disclosure Vulnerability",
    "impact": [
      "disclose sensitive information",
      "execute arbitrary code",
      "information disclosure"
    ],
    "vector": "malicious page or file",
    "attacker": "remote attackers",
    "product": "Foxit PDF Reader",
    "version": "",
    "component": "Annotation objects"
  },
  "mitreTechnicalImpacts": []
}