{
  "cveId": "CVE-2021-34697",
  "version": "1.0.0",
  "timestamp": "2024-12-15T20:24:27.876763+00:00",
  "description": "A vulnerability in the Protection Against Distributed Denial of Service Attacks feature of Cisco IOS XE Software could allow an unauthenticated, remote attacker to conduct denial of service (DoS) attacks to or through the affected device. This vulnerability is due to incorrect programming of the half-opened connections limit, TCP SYN flood limit, or TCP SYN cookie features when the features are configured in vulnerable releases of Cisco IOS XE Software. An attacker could exploit this vulnerability by attempting to flood traffic to or through the affected device. A successful exploit could allow the attacker to initiate a DoS attack to or through an affected device.",
  "keyphrases": {
    "rootcause": "",
    "weakness": "incorrect programming",
    "impact": [
      "Denial of Service Attacks",
      "DoS attack",
      "denial of service (DoS)"
    ],
    "vector": "flood traffic",
    "attacker": "unauthenticated remote attacker",
    "product": "Cisco IOS XE Software",
    "version": "",
    "component": "Protection Against Distributed Denial of Service Attacks feature"
  },
  "mitreTechnicalImpacts": []
}