{
    "cveId": "CVE-2021-34729",
    "version": "1.0.0",
    "timestamp": "2024-12-15T20:24:27.876763+00:00",
    "description": "A vulnerability in the CLI of Cisco IOS XE SD-WAN Software and Cisco IOS XE Software could allow an authenticated, local attacker to execute arbitrary commands with elevated privileges on an affected device. This vulnerability is due to insufficient validation of arguments passed to certain CLI commands. An attacker could exploit this vulnerability by including malicious input in the argument of an affected command. A successful exploit could allow the attacker to execute arbitrary commands with elevated privileges on the underlying operating system. An attacker would need valid user credentials to exploit this vulnerability.",
    "keyphrases": {
        "rootcause": "insufficient validation of arguments",
        "weakness": "",
        "impact": "execute arbitrary commands",
        "vector": "malicious input in the argument",
        "attacker": "authenticated local attacker",
        "product": [
            "Cisco IOS XE SD-WAN Software",
            "Cisco IOS XE Software"
        ],
        "version": "",
        "component": "CLI"
    }
}
