{
  "cveId": "CVE-2025-30712",
  "version": "1.0.0",
  "timestamp": "2025-07-04T16:12:41.853043+00:00",
  "description": "Vulnerability in the Oracle VM VirtualBox product of Oracle Virtualization (component Core). The supported version that is affected is 7.1.6. Easily exploitable vulnerability allows high privileged attacker with logon to the infrastructure where Oracle VM VirtualBox executes to compromise Oracle VM VirtualBox. While the vulnerability is in Oracle VM VirtualBox, attacks may significantly impact additional products (scope change). Successful attacks of this vulnerability can result in unauthorized creation, deletion or modification access to critical data or all Oracle VM VirtualBox accessible data as well as unauthorized access to critical data or complete access to all Oracle VM VirtualBox accessible data and unauthorized ability to cause a partial denial of service (partial DOS) of Oracle VM VirtualBox. CVSS 3.1 Base Score 8.1 (Confidentiality, Integrity and Availability impacts). CVSS Vector (CVSS3.1/AVL/ACL/PRH/UIN/SC/CH/IH/AL).",
  "keyphrases": {
    "rootcause": "",
    "weakness": "",
    "impact": [
      "unauthorized access to critical data or complete access to all Oracle VM VirtualBox accessible data",
      "unauthorized access to all Oracle VM VirtualBox accessible data",
      "deletion or modification access to critical data",
      "Integrity and Availability impacts",
      "unauthorized creation",
      "denial of service",
      "DOS"
    ],
    "vector": "",
    "attacker": "high privileged attacker",
    "product": "Oracle VM VirtualBox",
    "version": "7.1.6",
    "component": "Core"
  },
  "mitreTechnicalImpacts": []
}