{
  "cveId": "CVE-2025-30719",
  "version": "1.0.0",
  "timestamp": "2025-07-04T16:12:41.853043+00:00",
  "description": "Vulnerability in the Oracle VM VirtualBox product of Oracle Virtualization (component Core). The supported version that is affected is 7.1.6. Easily exploitable vulnerability allows low privileged attacker with logon to the infrastructure where Oracle VM VirtualBox executes to compromise Oracle VM VirtualBox. Successful attacks of this vulnerability can result in unauthorized ability to cause a hang or frequently repeatable crash (complete DOS) of Oracle VM VirtualBox and unauthorized read access to a subset of Oracle VM VirtualBox accessible data. CVSS 3.1 Base Score 6.1 (Confidentiality and Availability impacts). CVSS Vector (CVSS3.1/AVL/ACL/PRL/UIN/SU/CL/IN/AH).",
  "keyphrases": {
    "rootcause": "",
    "weakness": "",
    "impact": [
      "cause a hang or frequently repeatable crash",
      "unauthorized read access",
      "Availability",
      "complete DOS"
    ],
    "vector": "",
    "attacker": "low privileged attacker",
    "product": "Oracle VM VirtualBox",
    "version": "7.1.6",
    "component": "Core"
  },
  "mitreTechnicalImpacts": []
}