{
  "cveId": "CVE-2025-30694",
  "version": "1.0.0",
  "timestamp": "2025-07-04T16:12:41.853043+00:00",
  "description": "Vulnerability in the XML Database component of Oracle Database Server. Supported versions that are affected are 19.3-19.26, 21.3-21.17 and 23.4-23.7. Easily exploitable vulnerability allows low privileged attacker having User Account privilege with network access via HTTP to compromise XML Database. Successful attacks require human interaction from a person other than the attacker and while the vulnerability is in XML Database, attacks may significantly impact additional products (scope change). Successful attacks of this vulnerability can result in unauthorized update, insert or delete access to some of XML Database accessible data as well as unauthorized read access to a subset of XML Database accessible data. CVSS 3.1 Base Score 5.4 (Confidentiality and Integrity impacts). CVSS Vector (CVSS3.1/AVN/ACL/PRL/UIR/SC/CL/IL/AN).",
  "keyphrases": {
    "rootcause": "",
    "weakness": "",
    "impact": [
      "unauthorized insert or delete access",
      "unauthorized read access",
      "unauthorized update",
      "Integrity"
    ],
    "vector": "network access via HTTP",
    "attacker": "low privileged attacker",
    "product": "Oracle Database Server",
    "version": [
      "21.3-21.17 and 23.4-23.7",
      "19.3-19.26"
    ],
    "component": "XML Database component"
  },
  "mitreTechnicalImpacts": []
}