{
    "cveId": "CVE-2020-7575",
    "version": "1.0.0",
    "timestamp": "2024-12-13T17:34:55.850537+00:00",
    "description": "A vulnerability has been identified in Climatix POL908 (BACnet/IP module) (All versions), Climatix POL909 (AWM module) (All versions < V11.32). A persistent cross-site scripting (XSS) vulnerability exists in the web server access log page of the affected devices that could allow an attacker to inject arbitrary JavaScript code via specially crafted GET requests. The code could be potentially executed later by another (privileged) user. The security vulnerability could be exploited by an attacker with network access to the affected system. Successful exploitation requires no system privileges. An attacker could use the vulnerability to compromise the confidentiality and integrity of other users web sessions.",
    "keyphrases": {
        "rootcause": "",
        "weakness": "cross-site scripting",
        "impact": "inject arbitrary JavaScript code",
        "vector": "specially crafted GET requests",
        "attacker": "",
        "product": [
            "Climatix POL908",
            "Climatix POL909"
        ],
        "version": "All versions, All versions < V11.32",
        "component": "web server access log page"
    }
}
