{
    "cveId": "CVE-2023-1457",
    "version": "1.0.0",
    "timestamp": "2024-12-17T08:36:27.567979+00:00",
    "description": "A vulnerability, which was classified as critical, was found in Ubiquiti EdgeRouter X 2.0.9-hotfix.6. Affected is an unknown function of the component Static Routing Configuration Handler. The manipulation of the argument next-hop-interface leads to command injection. It is possible to launch the attack remotely. The exploit has been disclosed to the public and may be used. The real existence of this vulnerability is still doubted at the moment. VDB-223302 is the identifier assigned to this vulnerability. NOTE The vendor position is that post-authentication issues are not accepted as vulnerabilities.",
    "keyphrases": {
        "rootcause": "",
        "weakness": "command injection",
        "impact": "",
        "vector": "manipulation of the argument next-hop-interface",
        "attacker": "",
        "product": "Ubiquiti EdgeRouter X",
        "version": "2.0.9-hotfix.6",
        "component": "Static Routing Configuration Handler"
    }
}
