{
    "cveId": "CVE-2019-20107",
    "version": "1.0.0",
    "timestamp": "2024-12-13T17:34:55.850537+00:00",
    "description": "Multiple SQL injection vulnerabilities in TestLink through 1.9.19 allows remote authenticated users to execute arbitrary SQL commands via the (1) tproject_id parameter to keywordsView.php the (2) req_spec_id parameter to reqSpecCompareRevisions.php the (3) requirement_id parameter to reqCompareVersions.php the (4) build_id parameter to planUpdateTC.php the (5) tplan_id parameter to newest_tcversions.php the (6) tplan_id parameter to tcCreatedPerUserGUI.php the (7) tcase_id parameter to tcAssign2Tplan.php or the (8) testcase_id parameter to tcCompareVersions.php. Authentication is often easy to achieve a guest account, that can execute this attack, can be created by anyone in the default configuration.",
    "keyphrases": {
        "rootcause": "",
        "weakness": "SQL injection",
        "impact": "execute arbitrary SQL commands",
        "vector": "tproject_id parameter to keywordsView.php",
        "attacker": "remote authenticated users",
        "product": "TestLink",
        "version": "through 1.9.19",
        "component": ""
    }
}
