{
    "cveId": "CVE-2006-5911",
    "version": "1.0.0",
    "timestamp": "2024-12-10T17:54:04.992951+00:00",
    "description": "Multiple PHP remote file inclusion vulnerabilities in Campware Campsite before 2.6.2 allow remote attackers to execute arbitrary PHP code via a URL in the g_documentRoot parameter to (1) Alias.php, (2) Article.php, (3) ArticleAttachment.php, (4) ArticleComment.php, (5) ArticleData.php, (6) ArticleImage.php, (7) ArticleIndex.php, (8) ArticlePublish.php, (9) ArticleTopic.php, (10) ArticleType.php, (11) ArticleTypeField.php, (12) Attachment.php, (13) Country.php, (14) DatabaseObject.php, (15) Event.php, (16) IPAccess.php, (17) Image.php, (18) Issue.php, (19) IssuePublish.php, (20) Language.php, (21) Log.php, (22) LoginAttempts.php, (23) Publication.php, (24) Section.php, (25) ShortURL.php, (26) Subscription.php, (27) SubscriptionDefaultTime.php, (28) SubscriptionSection.php, (29) SystemPref.php, (30) Template.php, (31) TimeUnit.php, (32) Topic.php, (33) UrlType.php, (34) User.php, and (35) UserType.php in implementation/management/classes/ (36) configuration.php and (37) db_connect.php in implementation/management/ and (38) LocalizerConfig.php and (39) LocalizerLanguage.php in implementation/management/priv/localizer/.",
    "keyphrases": {
        "rootcause": "Multiple PHP remote file inclusion vulnerabilities",
        "weakness": "",
        "impact": "execute arbitrary PHP code",
        "vector": "URL in the g_documentRoot parameter",
        "attacker": "remote attackers",
        "product": "Campware Campsite",
        "version": "before 2.6.2",
        "component": [
            "Alias.php",
            "Article.php",
            "ArticleAttachment.php",
            "ArticleComment.php",
            "ArticleData.php",
            "ArticleImage.php",
            "ArticleIndex.php",
            "ArticlePublish.php",
            "ArticleTopic.php",
            "ArticleType.php",
            "ArticleTypeField.php",
            "Attachment.php",
            "Country.php",
            "DatabaseObject.php",
            "Event.php",
            "IPAccess.php",
            "Image.php",
            "Issue.php",
            "IssuePublish.php",
            "Language.php",
            "Log.php",
            "LoginAttempts.php",
            "Publication.php",
            "Section.php",
            "ShortURL.php",
            "Subscription.php",
            "SubscriptionDefaultTime.php",
            "SubscriptionSection.php",
            "SystemPref.php",
            "Template.php",
            "TimeUnit.php",
            "Topic.php",
            "UrlType.php",
            "User.php",
            "UserType.php",
            "configuration.php",
            "db_connect.php",
            "LocalizerConfig.php",
            "LocalizerLanguage.php"
        ]
    }
}
