{
  "cveId": "CVE-2006-5101",
  "version": "1.0.0",
  "timestamp": "2024-12-10T17:54:04.992951+00:00",
  "description": "PHP remote file inclusion vulnerability in include.php in Comdev CSV Importer 3.1 and possibly 4.1, as used in (1) Comdev Contact Form 3.1, (2) Comdev Customer Helpdesk 3.1, (3) Comdev Events Calendar 3.1, (4) Comdev FAQ Support 3.1, (5) Comdev Guestbook 3.1, (6) Comdev Links Directory 3.1, (7) Comdev News Publisher 3.1, (8) Comdev Newsletter 3.1, (9) Comdev Photo Gallery 3.1, (10) Comdev Vote Caster 3.1, (11) Comdev Web Blogger 3.1, and (12) Comdev eCommerce 3.1, allows remote attackers to execute arbitrary PHP code via a URL in the path[docroot] parameter. NOTE it has been reported that 4.1 versions might also be affected.",
  "keyphrases": {
    "rootcause": "",
    "weakness": "remote file inclusion",
    "impact": "execute arbitrary PHP code",
    "vector": "URL in the path[docroot] parameter",
    "attacker": "remote attackers",
    "product": "Comdev CSV Importer",
    "version": "3.1 and possibly 4.1",
    "component": "include.php"
  },
  "mitreTechnicalImpacts": []
}