{
    "cveId": "CVE-2012-1463",
    "version": "1.0.0",
    "timestamp": "2024-12-10T17:54:04.992951+00:00",
    "description": "The ELF file parser in AhnLab V3 Internet Security 2011.01.18.00, Bitdefender 7.2, Quick Heal (aka Cat QuickHeal) 11.00, Command Antivirus 5.2.11.5, Comodo Antivirus 7424, eSafe 7.0.17.0, F-Prot Antivirus 4.6.2.117, F-Secure Anti-Virus 9.0.16160.0, McAfee Anti-Virus Scanning Engine 5.400.0.1158, Norman Antivirus 6.06.12, nProtect Anti-Virus 2011-01-17.01, and Panda Antivirus 10.0.2.7 allows remote attackers to bypass malware detection via an ELF file with a modified endianness field. NOTE this may later be SPLIT into multiple CVEs if additional information is published showing that the error occurred independently in different ELF parser implementations.",
    "keyphrases": {
        "rootcause": "improper endianness handling",
        "weakness": "",
        "impact": "bypass malware detection",
        "vector": "ELF file with a modified endianness field",
        "attacker": "remote attackers",
        "product": [
            "AhnLab V3 Internet Security",
            "Bitdefender",
            "Quick Heal",
            "Command Antivirus",
            "Comodo Antivirus",
            "eSafe",
            "F-Prot Antivirus",
            "F-Secure Anti-Virus",
            "McAfee Anti-Virus Scanning Engine",
            "Norman Antivirus",
            "nProtect Anti-Virus",
            "Panda Antivirus"
        ],
        "version": [
            "2011.01.18.00",
            "7.2",
            "11.00",
            "5.2.11.5",
            "7424",
            "7.0.17.0",
            "4.6.2.117",
            "9.0.16160.0",
            "5.400.0.1158",
            "6.06.12",
            "2011-01-17.01",
            "10.0.2.7"
        ],
        "component": "ELF file parser"
    }
}
