{
    "cveId": "CVE-2022-24368",
    "version": "1.0.0",
    "timestamp": "2024-12-15T20:24:27.876763+00:00",
    "description": "This vulnerability allows remote attackers to disclose sensitive information on affected installations of Foxit PDF Reader 11.1.0.52543. User interaction is required to exploit this vulnerability in that the target must visit a malicious page or open a malicious file. The specific flaw exists within the handling of Doc objects. The issue results from the lack of validating the existence of an object prior to performing operations on the object. An attacker can leverage this in conjunction with other vulnerabilities to execute arbitrary code in the context of the current process. Was ZDI-CAN-16115.",
    "keyphrases": {
        "rootcause": "lack of validating the existence of an object prior to performing operations on the object",
        "weakness": "",
        "impact": "information disclosure",
        "vector": "malicious page or open a malicious file",
        "attacker": "remote attackers",
        "product": "Foxit PDF Reader",
        "version": "11.1.0.52543",
        "component": "Doc objects"
    }
}
