{
    "cveId": "CVE-2013-2455",
    "version": "1.0.0",
    "timestamp": "2024-12-10T17:54:04.992951+00:00",
    "description": "Unspecified vulnerability in the Java Runtime Environment (JRE) component in Oracle Java SE 7 Update 21 and earlier, 6 Update 45 and earlier, and 5.0 Update 45 and earlier, and OpenJDK 7, allows remote attackers to affect confidentiality via unknown vectors related to Libraries, a different vulnerability than CVE-2013-2443 and CVE-2013-2452. NOTE the previous information is from the June 2013 CPU. Oracle has not commented on claims from another vendor that this issue is related to incorrect access checks by the (1) getEnclosingClass, (2) getEnclosingMethod, and (3) getEnclosingConstructor methods.",
    "keyphrases": {
        "rootcause": "unspecified vulnerability",
        "weakness": "",
        "impact": "affect confidentiality",
        "vector": "unknown vectors",
        "attacker": "remote attackers",
        "product": [
            "Oracle Java SE",
            "OpenJDK"
        ],
        "version": [
            "7 Update 21 and earlier",
            "6 Update 45 and earlier",
            "5.0 Update 45 and earlier",
            "7"
        ],
        "component": "Java Runtime Environment (JRE) component"
    }
}
