{
  "cveId": "CVE-2024-9250",
  "version": "1.0.0",
  "timestamp": "2024-12-17T08:36:27.567979+00:00",
  "description": "Foxit PDF Reader AcroForm Use-After-Free Remote Code Execution Vulnerability. This vulnerability allows remote attackers to execute arbitrary code on affected installations of Foxit PDF Reader. User interaction is required to exploit this vulnerability in that the target must visit a malicious page or open a malicious file. The specific flaw exists within the handling of AcroForms. The issue results from the lack of validating the existence of an object prior to performing operations on the object. An attacker can leverage this vulnerability to execute code in the context of the current process. Was ZDI-CAN-24489.",
  "keyphrases": {
    "rootcause": "lack of validating the existence of an object prior to performing operations on the object",
    "weakness": "Use-After-Free",
    "impact": [
      "Remote Code Execution",
      "arbitrary code execution",
      "execute arbitrary code",
      "execute code in the context of the current process"
    ],
    "vector": "malicious page or file",
    "attacker": "remote attackers",
    "product": "Foxit PDF Reader",
    "version": "",
    "component": "AcroForms"
  },
  "mitreTechnicalImpacts": []
}