{
    "cveId": "CVE-2024-9764",
    "version": "1.0.0",
    "timestamp": "2024-12-17T08:36:27.567979+00:00",
    "description": "Tungsten Automation Power PDF PDF File Parsing Use-After-Free Remote Code Execution Vulnerability. This vulnerability allows remote attackers to execute arbitrary code on affected installations of Tungsten Automation Power PDF. User interaction is required to exploit this vulnerability in that the target must visit a malicious page or open a malicious file. The specific flaw exists within the parsing of PDF files. The issue results from the lack of validating the existence of an object prior to performing operations on the object. An attacker can leverage this vulnerability to execute code in the context of the current process. Was ZDI-CAN-24480.",
    "keyphrases": {
        "rootcause": "lack of validating the existence of an object prior to performing operations on the object",
        "weakness": "Use-After-Free",
        "impact": "execute arbitrary code",
        "vector": "",
        "attacker": "remote attackers",
        "product": "Tungsten Automation Power PDF",
        "version": "",
        "component": "parsing of PDF files"
    }
}
