{
  "cveId": "CVE-2024-9244",
  "version": "1.0.0",
  "timestamp": "2024-12-17T08:36:27.567979+00:00",
  "description": "Foxit PDF Reader Update Service Incorrect Permission Assignment Local Privilege Escalation Vulnerability. This vulnerability allows local attackers to escalate privileges on affected installations of Foxit PDF Reader. An attacker must first obtain the ability to execute low-privileged code on the target system in order to exploit this vulnerability. The specific flaw exists within the handling of the configuration files used by the Foxit Reader Update Service. The issue results from incorrect permissions set on a resource used by the service. An attacker can leverage this vulnerability to escalate privileges and execute code in the context of SYSTEM. Was ZDI-CAN-23933.",
  "keyphrases": {
    "rootcause": "Incorrect Permission Assignment",
    "weakness": "Privilege Escalation Vulnerability",
    "impact": [
      "Privilege Escalation",
      "escalate privileges",
      "execute code"
    ],
    "vector": "",
    "attacker": "local attackers",
    "product": "Foxit PDF Reader",
    "version": "",
    "component": "Update Service"
  },
  "mitreTechnicalImpacts": []
}