{
    "cveId": "CVE-2019-25071",
    "version": "1.0.0",
    "timestamp": "2024-12-15T20:24:27.876763+00:00",
    "description": "A vulnerability was found in Apple iPhone up to 12.4.1. It has been declared as critical. Affected by this vulnerability is Siri. Playing an audio or video file might be able to initiate Siri on the same device which makes it possible to execute commands remotely. Exploit details have been disclosed to the public. The existence and implications of this vulnerability are doubted by Apple even though multiple public videos demonstrating the attack exist. Upgrading to version 13.0 migt be able to address this issue. It is recommended to upgrade affected devices. NOTE Apple claims, that after examining the report they do not see any actual security implications.",
    "keyphrases": {
        "rootcause": "",
        "weakness": "",
        "impact": "execute commands remotely",
        "vector": "audio or video file",
        "attacker": "",
        "product": "Apple iPhone",
        "version": "up to 12.4.1",
        "component": "Siri"
    }
}
