{
  "cveId": "CVE-2023-42125",
  "version": "1.0.0",
  "timestamp": "2024-12-06T11:32:07.789868+00:00",
  "description": "Avast Premium Security Sandbox Protection Link Following Privilege Escalation Vulnerability. This vulnerability allows local attackers to escalate privileges on affected installations of Avast Premium Security. An attacker must first obtain the ability to execute low-privileged code on the target system in order to exploit this vulnerability. The specific flaw exists within the implementation of the sandbox feature. By creating a symbolic link, an attacker can abuse the service to create arbitrary namespace objects. An attacker can leverage this vulnerability to escalate privileges and execute arbitrary code in the context of SYSTEM. . Was ZDI-CAN-20383.",
  "keyphrases": {
    "rootcause": "privilege escalation",
    "weakness": "Privilege Escalation Vulnerability",
    "impact": [
      "Privilege Escalation",
      "escalate privileges and execute arbitrary code"
    ],
    "vector": "",
    "attacker": "",
    "product": "Avast Premium Security",
    "version": "",
    "component": "Sandbox Protection Link Following"
  },
  "mitreTechnicalImpacts": []
}