{
    "cveId": "CVE-2023-42033",
    "version": "1.0.0",
    "timestamp": "2024-12-06T11:32:07.789868+00:00",
    "description": "Visualware MyConnection Server doPostUploadfiles Directory Traversal Remote Code Execution Vulnerability. This vulnerability allows remote attackers to execute arbitrary code on affected installations of Visualware MyConnection Server. Although authentication is required to exploit this vulnerability, the existing authentication mechanism can be bypassed. The specific flaw exists within the doPostUploadfiles method. The issue results from the lack of proper validation of a user-supplied path prior to using it in file operations. An attacker can leverage this vulnerability to execute code in the context of root. Was ZDI-CAN-21612.",
    "keyphrases": {
        "rootcause": "lack of proper validation of a user-supplied path",
        "weakness": "directory traversal",
        "impact": "remote code execution",
        "vector": "",
        "attacker": "remote attackers",
        "product": "Visualware MyConnection Server",
        "version": "",
        "component": "doPostUploadfiles method"
    }
}
