{
  "cveId": "CVE-2024-4353",
  "version": "1.0.0",
  "timestamp": "2024-12-06T11:32:07.789868+00:00",
  "description": "Concrete CMS versions 9.0.0 through 9.3.2 are affected by a stored XSS vulnerability in the generate dashboard board instance functionality. The Name input field does not check the input sufficiently letting a rogue administrator have the capability to inject malicious JavaScript code. The Concrete CMS security team gave this vulnerability a CVSS v3.1 score of 3.1 with a vector of AVN/ACH/PRH/UIR/SU/CL/IL/AN https//nvd.nist.gov/vuln-metrics/cvss/v3-calculator and a CVSS v4 score of 1.8 with a vector of CVSS4.0/AVN/ACH/ATN/PRH/UIA/VCL/VIL/VAN/SCN/SIN/SAN Concrete versions below 9 are not affected by this vulnerability. Thanks fhAnso for reporting.",
  "keyphrases": {
    "rootcause": "does not check the input sufficiently",
    "weakness": [
      "XSS vulnerability",
      "cross-site scripting"
    ],
    "impact": "inject malicious JavaScript code",
    "vector": "",
    "attacker": "rogue administrator",
    "product": "Concrete CMS",
    "version": "9.0.0 through 9.3.2",
    "component": "generate dashboard board instance functionality"
  },
  "mitreTechnicalImpacts": []
}