{
    "cveId": "CVE-2024-4839",
    "version": "1.0.0",
    "timestamp": "2024-12-06T11:32:07.789868+00:00",
    "description": "A Cross-Site Request Forgery (CSRF) vulnerability exists in the Servers Configurations function of the parisneo/lollms-webui, versions 9.6 to the latest. The affected functions include Elastic search Service (under construction), XTTS service, Petals service, vLLM service, and Motion Ctrl service, which lack CSRF protection. This vulnerability allows attackers to deceive users into unwittingly installing the XTTS service among other packages by submitting a malicious installation request. Successful exploitation results in attackers tricking users into performing actions without their consent.",
    "keyphrases": {
        "rootcause": "lack CSRF protection",
        "weakness": "Cross-Site Request Forgery",
        "impact": "",
        "vector": "malicious installation request",
        "attacker": "attackers",
        "product": "parisneo/lollms-webui",
        "version": "9.6 to the latest",
        "component": "Servers Configurations function"
    }
}
