{
    "cveId": "CVE-2023-5147",
    "version": "1.0.0",
    "timestamp": "2024-12-06T11:32:07.789868+00:00",
    "description": "** UNSUPPORTED WHEN ASSIGNED ** A vulnerability was found in D-Link DAR-7000 up to 20151231. It has been classified as critical. This affects an unknown part of the file /sysmanage/updateos.php. The manipulation of the argument 1_file_upload leads to unrestricted upload. It is possible to initiate the attack remotely. The exploit has been disclosed to the public and may be used. The associated identifier of this vulnerability is VDB-240243. NOTE This vulnerability only affects products that are no longer supported by the maintainer. NOTE Vendor was contacted early and confirmed immediately that the product is end-of-life. It should be retired and replaced.",
    "keyphrases": {
        "rootcause": "",
        "weakness": "unrestricted upload",
        "impact": "",
        "vector": "manipulation of the argument 1_file_upload",
        "attacker": "",
        "product": "D-Link DAR-7000",
        "version": "up to 20151231",
        "component": "/sysmanage/updateos.php"
    }
}
