{
    "cveId": "CVE-2023-5151",
    "version": "1.0.0",
    "timestamp": "2024-12-06T11:32:07.789868+00:00",
    "description": "** UNSUPPORTED WHEN ASSIGNED ** A vulnerability classified as critical was found in D-Link DAR-8000 up to 20151231. Affected by this vulnerability is an unknown functionality of the file /autheditpwd.php. The manipulation of the argument hid_id leads to sql injection. The attack can be launched remotely. The exploit has been disclosed to the public and may be used. The associated identifier of this vulnerability is VDB-240247. NOTE This vulnerability only affects products that are no longer supported by the maintainer. NOTE Vendor was contacted early and confirmed immediately that the product is end-of-life. It should be retired and replaced.",
    "keyphrases": {
        "rootcause": "",
        "weakness": "sql injection",
        "impact": "",
        "vector": "manipulation of the argument hid_id",
        "attacker": "",
        "product": "D-Link DAR-8000",
        "version": "up to 20151231",
        "component": "/autheditpwd.php"
    }
}
