{
    "cveId": "CVE-2023-5915",
    "version": "1.0.0",
    "timestamp": "2024-12-17T08:36:27.567979+00:00",
    "description": "A vulnerability of Uncontrolled Resource Consumption has been identified in STARDOM provided by Yokogawa Electric Corporation.This vulnerability may allow to a remote attacker to cause a denial-of-service condition to the FCN/FCJ controller by sending a crafted packet. While sending the packet, the maintenance homepage of the controller could not be accessed. Therefore, functions of the maintenance homepage, changing configuration, viewing logs, etc. are not available. But the controllers operation is not stopped by the condition.The affected products and versions are as follows STARDOM FCN/FCJ R1.01 to R4.31.",
    "keyphrases": {
        "rootcause": "",
        "weakness": "Uncontrolled Resource Consumption",
        "impact": "denial-of-service condition",
        "vector": "crafted packet",
        "attacker": "remote attacker",
        "product": "STARDOM FCN/FCJ",
        "version": "R1.01 to R4.31",
        "component": ""
    }
}
