{
    "cveId": "CVE-2017-3479",
    "version": "1.0.0",
    "timestamp": "2024-12-06T11:32:07.789868+00:00",
    "description": "Vulnerability in the Oracle FLEXCUBE Private Banking component of Oracle Financial Services Applications (subcomponent Miscellaneous). Supported versions that are affected are 2.0.0, 2.0.1, 2.2.0.1 and 12.0.1. Easily exploitable vulnerability allows low privileged attacker with network access via HTTP to compromise Oracle FLEXCUBE Private Banking. Successful attacks of this vulnerability can result in unauthorized update, insert or delete access to some of Oracle FLEXCUBE Private Banking accessible data and unauthorized ability to cause a partial denial of service (partial DOS) of Oracle FLEXCUBE Private Banking. CVSS 3.0 Base Score 5.4 (Integrity and Availability impacts). CVSS Vector (CVSS3.0/AVN/ACL/PRL/UIN/SU/CN/IL/AL).",
    "keyphrases": {
        "rootcause": "",
        "weakness": "",
        "impact": [
            "unauthorized update",
            "insert or delete",
            "partial denial of service"
        ],
        "vector": "network access via HTTP",
        "attacker": "low privileged attacker",
        "product": "Oracle FLEXCUBE Private Banking",
        "version": [
            "2.0.0",
            "2.0.1",
            "2.2.0.1",
            "12.0.1"
        ],
        "component": ""
    }
}
