{
  "cveId": "CVE-2017-3531",
  "version": "1.0.0",
  "timestamp": "2024-12-06T11:32:07.789868+00:00",
  "description": "Vulnerability in the Oracle WebLogic Server component of Oracle Fusion Middleware (subcomponent Servlet Runtime). Supported versions that are affected are 12.1.3.0, 12.2.1.0, 12.2.1.1 and 12.2.1.2. Easily exploitable vulnerability allows unauthenticated attacker with network access via HTTP to compromise Oracle WebLogic Server. While the vulnerability is in Oracle WebLogic Server, attacks may significantly impact additional products. Successful attacks of this vulnerability can result in unauthorized update, insert or delete access to some of Oracle WebLogic Server accessible data and unauthorized ability to cause a partial denial of service (partial DOS) of Oracle WebLogic Server. CVSS 3.0 Base Score 7.2 (Integrity and Availability impacts). CVSS Vector (CVSS3.0/AVN/ACL/PRN/UIN/SC/CN/IL/AL).",
  "keyphrases": {
    "rootcause": "",
    "weakness": "",
    "impact": [
      "Availability",
      "DOS",
      "insert or delete access",
      "partial denial of service",
      "unauthorized update"
    ],
    "vector": "unauthenticated attacker with network access via HTTP",
    "attacker": "unauthenticated attacker",
    "product": "Oracle WebLogic Server",
    "version": [
      "12.1.3.0",
      "12.2.1.0",
      "12.2.1.1 and 12.2.1.2"
    ],
    "component": ""
  },
  "mitreTechnicalImpacts": []
}