{
    "description": "Vulnerability in the Oracle WebLogic Server component of Oracle Fusion Middleware (subcomponent: Web Services). Supported versions that are affected are 10.3.6.0, 12.1.3.0, 12.2.1.0, 12.2.1.1 and 12.2.1.2. Difficult to exploit vulnerability allows unauthenticated attacker with network access via HTTP to compromise Oracle WebLogic Server. Successful attacks of this vulnerability can result in unauthorized creation, deletion or modification access to critical data or all Oracle WebLogic Server accessible data as well as unauthorized access to critical data or complete access to all Oracle WebLogic Server accessible data. CVSS 3.0 Base Score 7.4 (Confidentiality and Integrity impacts). CVSS Vector: (CVSS:3.0/AV:N/AC:H/PR:N/UI:N/S:U/C:H/I:H/A:N).",
    "keyphrases": {
        "rootcause": "",
        "weakness": "",
        "impact": [
            "unauthorized creation",
            "deletion or modification access to critical data",
            "unauthorized access to critical data"
        ],
        "vector": "",
        "attacker": "unauthenticated attacker with network access via HTTP",
        "product": "Oracle WebLogic Server",
        "version": [
            "10.3.6.0",
            "12.1.3.0",
            "12.2.1.0",
            "12.2.1.1",
            "12.2.1.2"
        ],
        "component": "Web Services"
    },
    "mitre_technical_impacts": [
        "Gain privileges / assume identity",
        "Bypass protection mechanism",
        "Modify data",
        "Read data"
    ]
}