{
    "cveId": "CVE-2017-3587",
    "version": "1.0.0",
    "timestamp": "2024-12-06T11:32:07.789868+00:00",
    "description": "Vulnerability in the Oracle VM VirtualBox component of Oracle Virtualization (subcomponent Shared Folder). Supported versions that are affected are Prior to 5.0.38 and Prior to 5.1.20. Easily exploitable vulnerability allows low privileged attacker with logon to the infrastructure where Oracle VM VirtualBox executes to compromise Oracle VM VirtualBox. While the vulnerability is in Oracle VM VirtualBox, attacks may significantly impact additional products. Successful attacks of this vulnerability can result in unauthorized creation, deletion or modification access to critical data or all Oracle VM VirtualBox accessible data and unauthorized ability to cause a hang or frequently repeatable crash (complete DOS) of Oracle VM VirtualBox. CVSS 3.0 Base Score 8.4 (Integrity and Availability impacts). CVSS Vector (CVSS3.0/AVL/ACL/PRL/UIN/SC/CN/IH/AH).",
    "keyphrases": {
        "rootcause": "",
        "weakness": "",
        "impact": "unauthorized creation, deletion or modification access to critical data or all Oracle VM VirtualBox accessible data",
        "vector": "",
        "attacker": "low privileged attacker with logon to the infrastructure where Oracle VM VirtualBox executes",
        "product": "Oracle VM VirtualBox",
        "version": "Prior to 5.0.38 and Prior to 5.1.20",
        "component": "Shared Folder"
    }
}
