{
    "cveId": "CVE-2017-3535",
    "version": "1.0.0",
    "timestamp": "2024-12-06T11:32:07.789868+00:00",
    "description": "Vulnerability in the Oracle FLEXCUBE Universal Banking component of Oracle Financial Services Applications (subcomponent Infrastructure). Supported versions that are affected are 11.3.0, 11.4.0, 12.0.1, 12.0.2 and 12.0.3. Easily exploitable vulnerability allows unauthenticated attacker with network access via HTTP to compromise Oracle FLEXCUBE Universal Banking. Successful attacks require human interaction from a person other than the attacker and while the vulnerability is in Oracle FLEXCUBE Universal Banking, attacks may significantly impact additional products. Successful attacks of this vulnerability can result in unauthorized read access to a subset of Oracle FLEXCUBE Universal Banking accessible data. CVSS 3.0 Base Score 4.7 (Confidentiality impacts). CVSS Vector (CVSS3.0/AVN/ACL/PRN/UIR/SC/CL/IN/AN).",
    "keyphrases": {
        "rootcause": "",
        "weakness": "",
        "impact": "unauthorized read access to a subset of Oracle FLEXCUBE Universal Banking accessible data",
        "vector": "",
        "attacker": "unauthenticated attacker",
        "product": "Oracle FLEXCUBE Universal Banking",
        "version": "11.3.0, 11.4.0, 12.0.1, 12.0.2 and 12.0.3",
        "component": "Infrastructure"
    }
}
