{
    "cveId": "CVE-2017-3831",
    "version": "1.0.0",
    "timestamp": "2024-12-11T16:08:24.783251+00:00",
    "description": "A vulnerability in the web-based GUI of Cisco Mobility Express 1800 Series Access Points could allow an unauthenticated, remote attacker to bypass authentication. The attacker could be granted full administrator privileges. The vulnerability is due to improper implementation of authentication for accessing certain web pages using the GUI interface. An attacker could exploit this vulnerability by sending a crafted HTTP request to the web interface of the affected system. A successful exploit could allow the attacker to bypass authentication and perform unauthorized configuration changes or issue control commands to the affected device. This vulnerability affects Cisco Mobility Express 1800 Series Access Points running a software version prior to 8.2.110.0. Cisco Bug IDs CSCuy68219.",
    "keyphrases": {
        "rootcause": "improper implementation of authentication for accessing certain web pages using the GUI interface",
        "weakness": "",
        "impact": [
            "bypass authentication",
            "perform unauthorized configuration changes",
            "issue control commands"
        ],
        "vector": "crafted HTTP request",
        "attacker": "unauthenticated remote attacker",
        "product": "Cisco Mobility Express 1800 Series Access Points",
        "version": "prior to 8.2.110.0",
        "component": "web-based GUI"
    }
}
