{
    "cveId": "CVE-2017-3621",
    "version": "1.0.0",
    "timestamp": "2024-12-06T11:32:07.789868+00:00",
    "description": "Vulnerability in the Sun ZFS Storage Appliance Kit (AK) component of Oracle Sun Systems Products Suite (subcomponent IPC Frameworks). The supported version that is affected is AK 2013. Easily exploitable vulnerability allows unauthenticated attacker with network access via multiple protocols to compromise Sun ZFS Storage Appliance Kit (AK). Successful attacks of this vulnerability can result in unauthorized ability to cause a hang or frequently repeatable crash (complete DOS) of Sun ZFS Storage Appliance Kit (AK). CVSS 3.0 Base Score 7.5 (Availability impacts). CVSS Vector (CVSS3.0/AVN/ACL/PRN/UIN/SU/CN/IN/AH).",
    "keyphrases": {
        "rootcause": "",
        "weakness": "",
        "impact": "cause a hang or frequently repeatable crash (complete DOS) of Sun ZFS Storage Appliance Kit (AK)",
        "vector": "multiple protocols",
        "attacker": "unauthenticated attacker with network access",
        "product": "Oracle Sun Systems Products Suite",
        "version": "",
        "component": "Sun ZFS Storage Appliance Kit (AK)"
    }
}
