{
  "cveId": "CVE-2017-3570",
  "version": "1.0.0",
  "timestamp": "2024-12-06T11:32:07.789868+00:00",
  "description": "Vulnerability in the PeopleSoft Enterprise FSCM component of Oracle PeopleSoft Products (subcomponent eSettlements). The supported version that is affected is 9.1. Easily exploitable vulnerability allows high privileged attacker with network access via HTTP to compromise PeopleSoft Enterprise FSCM. Successful attacks of this vulnerability can result in unauthorized creation, deletion or modification access to critical data or all PeopleSoft Enterprise FSCM accessible data as well as unauthorized access to critical data or complete access to all PeopleSoft Enterprise FSCM accessible data. CVSS 3.0 Base Score 6.5 (Confidentiality and Integrity impacts). CVSS Vector (CVSS3.0/AVN/ACL/PRH/UIN/SU/CH/IH/AN).",
  "keyphrases": {
    "rootcause": "",
    "weakness": "",
    "impact": [
      "Integrity",
      "deletion or modification access to critical data or all PeopleSoft Enterprise FSCM accessible data as well as unauthorized access to critical data or complete access to all PeopleSoft Enterprise FSCM accessible data",
      "unauthorized creation"
    ],
    "vector": "",
    "attacker": "high privileged attacker with network access via HTTP",
    "product": "Oracle PeopleSoft Products",
    "version": "9.1",
    "component": "PeopleSoft Enterprise FSCM component"
  },
  "mitreTechnicalImpacts": []
}