{
  "cveId": "CVE-2017-3583",
  "version": "1.0.0",
  "timestamp": "2024-12-06T11:32:07.789868+00:00",
  "description": "Vulnerability in the Primavera P6 Enterprise Project Portfolio Management component of Oracle Primavera Products Suite (subcomponent Web Access). Supported versions that are affected are 8.3, 8.4, 15.1, 15.2, 16.1 and 16.2. Easily exploitable vulnerability allows unauthenticated attacker with network access via HTTP to compromise Primavera P6 Enterprise Project Portfolio Management. Successful attacks require human interaction from a person other than the attacker. Successful attacks of this vulnerability can result in unauthorized creation, deletion or modification access to critical data or all Primavera P6 Enterprise Project Portfolio Management accessible data as well as unauthorized access to critical data or complete access to all Primavera P6 Enterprise Project Portfolio Management accessible data. CVSS 3.0 Base Score 8.1 (Confidentiality and Integrity impacts). CVSS Vector (CVSS3.0/AVN/ACL/PRN/UIR/SU/CH/IH/AN).",
  "keyphrases": {
    "rootcause": "",
    "weakness": "",
    "impact": [
      "Integrity",
      "deletion or modification access to critical data or all Primavera P6 Enterprise Project Portfolio Management accessible data as well as unauthorized access to critical data or complete access to all Primavera P6 Enterprise Project Portfolio Management accessible data",
      "unauthorized creation"
    ],
    "vector": "",
    "attacker": "unauthenticated attacker",
    "product": "Oracle Primavera Products Suite",
    "version": [
      "8.3",
      "8.4",
      "15.1",
      "15.2",
      "16.1 and 16.2"
    ],
    "component": "Primavera P6 Enterprise Project Portfolio Management component"
  },
  "mitreTechnicalImpacts": []
}