{
    "cveId": "CVE-2017-3305",
    "version": "1.0.0",
    "timestamp": "2024-12-06T11:32:07.789868+00:00",
    "description": "Vulnerability in the MySQL Server component of Oracle MySQL (subcomponent Server C API). Supported versions that are affected are 5.5.55 and earlier and 5.6.35 and earlier. Difficult to exploit vulnerability allows low privileged attacker with network access via multiple protocols to compromise MySQL Server. Successful attacks of this vulnerability can result in unauthorized access to critical data or complete access to all MySQL Server accessible data. CVSS 3.0 Base Score 5.3 (Confidentiality impacts). CVSS Vector (CVSS3.0/AVN/ACH/PRL/UIN/SU/CH/IN/AN). NOTE the previous information is from the April 2017 CPU. Oracle has not commented on third-party claims that this issue allows man-in-the-middle attackers to hijack the authentication of users by leveraging incorrect ordering of security parameter verification in a client, aka, The Riddle.",
    "keyphrases": {
        "rootcause": "incorrect ordering of security parameter verification",
        "weakness": "",
        "impact": [
            "unauthorized access to critical data",
            "complete access to all MySQL Server accessible data"
        ],
        "vector": "multiple protocols",
        "attacker": "low privileged attacker with network access",
        "product": "Oracle MySQL",
        "version": "5.5.55 and earlier, 5.6.35 and earlier",
        "component": "Server C API"
    }
}
