{
  "cveId": "CVE-2017-3253",
  "version": "1.0.0",
  "timestamp": "2024-12-06T11:32:07.789868+00:00",
  "description": "Vulnerability in the Java SE, Java SE Embedded, JRockit component of Oracle Java SE (subcomponent 2D). Supported versions that are affected are Java SE 6u131, 7u121 and 8u112 Java SE Embedded 8u111 JRockit R28.3.12. Easily exploitable vulnerability allows unauthenticated attacker with network access via multiple protocols to compromise Java SE, Java SE Embedded, JRockit. Successful attacks of this vulnerability can result in unauthorized ability to cause a hang or frequently repeatable crash (complete DOS) of Java SE, Java SE Embedded, JRockit. Note Applies to client and server deployment of Java. This vulnerability can be exploited through sandboxed Java Web Start applications and sandboxed Java applets. It can also be exploited by supplying data to APIs in the specified Component without using sandboxed Java Web Start applications or sandboxed Java applets, such as through a web service. CVSS v3.0 Base Score 7.5 (Availability impacts).",
  "keyphrases": {
    "rootcause": "",
    "weakness": "",
    "impact": [
      "Java SE Embedded",
      "cause a hang or frequently repeatable crash (complete DOS)"
    ],
    "vector": "multiple protocols",
    "attacker": "unauthenticated attacker with network access",
    "product": "Java SE",
    "version": [
      "6u131",
      "7u121 and 8u112"
    ],
    "component": ""
  },
  "mitreTechnicalImpacts": []
}