{
  "cveId": "CVE-2017-3569",
  "version": "1.0.0",
  "timestamp": "2024-12-06T11:32:07.789868+00:00",
  "description": "Vulnerability in the Oracle Hospitality OPERA 5 Property Services component of Oracle Hospitality Applications (subcomponent OPERA Business Events). Supported versions that are affected are 5.4.0.x, 5.4.1.x, 5.4.2.x, 5.4.3.x, 5.5.0.x and 5.5.1.x. Easily exploitable vulnerability allows low privileged attacker with network access via HTTP to compromise Oracle Hospitality OPERA 5 Property Services. Successful attacks of this vulnerability can result in unauthorized update, insert or delete access to some of Oracle Hospitality OPERA 5 Property Services accessible data as well as unauthorized read access to a subset of Oracle Hospitality OPERA 5 Property Services accessible data. CVSS 3.0 Base Score 5.4 (Confidentiality and Integrity impacts). CVSS Vector (CVSS3.0/AVN/ACL/PRL/UIN/SU/CL/IL/AN).",
  "keyphrases": {
    "rootcause": "",
    "weakness": "",
    "impact": [
      "Integrity",
      "insert or delete access",
      "unauthorized read access",
      "unauthorized update"
    ],
    "vector": "",
    "attacker": "low privileged attacker",
    "product": "Oracle Hospitality OPERA 5 Property Services",
    "version": [
      "5.4.0.x",
      "5.4.1.x",
      "5.4.2.x",
      "5.4.3.x",
      "5.5.0.x",
      "5.5.1.x"
    ],
    "component": "OPERA Business Events"
  },
  "mitreTechnicalImpacts": []
}