{
    "cveId": "CVE-2017-3304",
    "version": "1.0.0",
    "timestamp": "2024-12-06T11:32:07.789868+00:00",
    "description": "Vulnerability in the MySQL Cluster component of Oracle MySQL (subcomponent Cluster DD). Supported versions that are affected are 7.2.27 and earlier, 7.3.16 and earlier, 7.4.14 and earlier and 7.5.5 and earlier. Easily exploitable vulnerability allows low privileged attacker with network access via multiple protocols to compromise MySQL Cluster. Successful attacks of this vulnerability can result in unauthorized update, insert or delete access to some of MySQL Cluster accessible data and unauthorized ability to cause a partial denial of service (partial DOS) of MySQL Cluster. CVSS 3.0 Base Score 5.4 (Integrity and Availability impacts). CVSS Vector (CVSS3.0/AVN/ACL/PRL/UIN/SU/CN/IL/AL).",
    "keyphrases": {
        "rootcause": "",
        "weakness": "",
        "impact": "unauthorized update, insert or delete access",
        "vector": "multiple protocols",
        "attacker": "low privileged attacker with network access",
        "product": "Oracle MySQL",
        "version": "7.2.27 and earlier, 7.3.16 and earlier, 7.4.14 and earlier and 7.5.5 and earlier",
        "component": "MySQL Cluster component"
    }
}
