{
  "cveId": "CVE-2017-3586",
  "version": "1.0.0",
  "timestamp": "2024-12-06T11:32:07.789868+00:00",
  "description": "Vulnerability in the MySQL Connectors component of Oracle MySQL (subcomponent Connector/J). Supported versions that are affected are 5.1.41 and earlier. Easily exploitable vulnerability allows low privileged attacker with network access via multiple protocols to compromise MySQL Connectors. While the vulnerability is in MySQL Connectors, attacks may significantly impact additional products. Successful attacks of this vulnerability can result in unauthorized update, insert or delete access to some of MySQL Connectors accessible data as well as unauthorized read access to a subset of MySQL Connectors accessible data. CVSS 3.0 Base Score 6.4 (Confidentiality and Integrity impacts). CVSS Vector (CVSS3.0/AVN/ACL/PRL/UIN/SC/CL/IL/AN).",
  "keyphrases": {
    "rootcause": "",
    "weakness": "",
    "impact": [
      "Integrity",
      "insert or delete access",
      "unauthorized read access",
      "unauthorized update"
    ],
    "vector": "multiple protocols",
    "attacker": "low privileged attacker",
    "product": "Oracle MySQL",
    "version": "5.1.41 and earlier",
    "component": "MySQL Connectors"
  },
  "mitreTechnicalImpacts": []
}