{
    "cveId": "CVE-2020-36695",
    "version": "1.0.0",
    "timestamp": "2024-12-06T11:32:07.789868+00:00",
    "description": "Incorrect Default Permissions vulnerability in Hitachi Device Manager on Linux (Device Manager Server component), Hitachi Tiered Storage Manager on Linux, Hitachi Replication Manager on Linux, Hitachi Tuning Manager on Linux (Hitachi Tuning Manager server, Hitachi Tuning Manager - Agent for RAID, Hitachi Tuning Manager - Agent for NAS components), Hitachi Compute Systems Manager on Linux allows File Manipulation.This issue affects Hitachi Device Manager before 8.8.5-02 Hitachi Tiered Storage Manager before 8.8.5-02 Hitachi Replication Manager before 8.8.5-02 Hitachi Tuning Manager before 8.8.5-02 Hitachi Compute Systems Manager before 8.8.3-08.",
    "keyphrases": {
        "rootcause": "Incorrect Default Permissions",
        "weakness": "",
        "impact": "File Manipulation",
        "vector": "",
        "attacker": "",
        "product": [
            "Hitachi Device Manager",
            "Hitachi Tiered Storage Manager",
            "Hitachi Replication Manager",
            "Hitachi Tuning Manager",
            "Hitachi Compute Systems Manager"
        ],
        "version": [
            "before 8.8.5-02",
            "before 8.8.5-02",
            "before 8.8.5-02",
            "before 8.8.5-02",
            "before 8.8.3-08"
        ],
        "component": [
            "Linux (Device Manager Server component)"
        ]
    }
}
