{
    "cveId": "CVE-2020-3259",
    "version": "1.0.0",
    "timestamp": "2024-12-06T11:32:07.789868+00:00",
    "description": "A vulnerability in the web services interface of Cisco Adaptive Security Appliance (ASA) Software and Cisco Firepower Threat Defense (FTD) Software could allow an unauthenticated, remote attacker to retrieve memory contents on an affected device, which could lead to the disclosure of confidential information. The vulnerability is due to a buffer tracking issue when the software parses invalid URLs that are requested from the web services interface. An attacker could exploit this vulnerability by sending a crafted GET request to the web services interface. A successful exploit could allow the attacker to retrieve memory contents, which could lead to the disclosure of confidential information. Note This vulnerability affects only specific AnyConnect and WebVPN configurations. For more information, see the Vulnerable Products section.",
    "keyphrases": {
        "rootcause": "buffer tracking issue when the software parses invalid URLs",
        "weakness": "",
        "impact": "retrieve memory contents, which could lead to the disclosure of confidential information",
        "vector": "crafted GET request",
        "attacker": "unauthenticated remote attacker",
        "product": [
            "Cisco Adaptive Security Appliance (ASA) Software",
            "Cisco Firepower Threat Defense (FTD) Software"
        ],
        "version": "",
        "component": "web services interface"
    }
}
