{
    "cveId": "CVE-2022-22170",
    "version": "1.0.0",
    "timestamp": "2024-12-15T20:24:27.876763+00:00",
    "description": "A Missing Release of Resource after Effective Lifetime vulnerability in the Packet Forwarding Engine (PFE) of Juniper Networks Junos OS allows an unauthenticated networked attacker to cause a Denial of Service (DoS) by sending specific packets over VXLAN which cause heap memory to leak and on exhaustion the PFE to reset. The heap memory utilization can be monitored with the command user@host> show chassis fpc This issue affects Juniper Networks Junos OS 19.4 versions prior to 19.4R2-S6, 19.4R3-S6 20.1 versions prior to 20.1R3-S2 20.2 versions prior to 20.2R3-S3 20.3 versions prior to 20.3R3-S1 20.4 versions prior to 20.4R3 21.1 versions prior to 21.1R3 21.2 versions prior to 21.2R2. This issue does not affect versions of Junos OS prior to 19.4R1.",
    "keyphrases": {
        "rootcause": "Missing Release of Resource after Effective Lifetime",
        "weakness": "",
        "impact": "Denial of Service (DoS)",
        "vector": "sending specific packets over VXLAN",
        "attacker": "unauthenticated networked attacker",
        "product": "Juniper Networks Junos OS",
        "version": "19.4 to 21.2",
        "component": "Packet Forwarding Engine (PFE)"
    }
}
