{
  "cveId": "CVE-2024-12032",
  "version": "1.0.0",
  "timestamp": "2025-07-04T16:12:41.853043+00:00",
  "description": "The Tourfic Ultimate Hotel Booking, Travel Booking & Apartment Booking WordPress Plugin | WooCommerce Booking plugin for WordPress is vulnerable to SQL Injection via the enquiry_id parameter of the tf_enquiry_reply_email_callback function in all versions up to, and including, 2.15.3 due to insufficient escaping on the user supplied parameter and lack of sufficient preparation on the existing SQL query. This makes it possible for authenticated attackers, with Subscriber-level access and above, to append additional SQL queries into already existing queries that can be used to extract sensitive information from the database.",
  "keyphrases": {
    "rootcause": "insufficient escaping on the user supplied parameter and lack of sufficient preparation on the existing SQL query",
    "weakness": "SQL injection",
    "impact": "extract sensitive information from the database",
    "vector": "",
    "attacker": "authenticated attackers",
    "product": [
      "Travel Booking & Apartment Booking WordPress Plugin",
      "Tourfic Ultimate Hotel Booking"
    ],
    "version": "up to and including 2.15.3",
    "component": "tf_enquiry_reply_email_callback function"
  },
  "mitreTechnicalImpacts": []
}