{
    "cveId": "CVE-2024-12832",
    "version": "1.0.0",
    "timestamp": "2025-07-04T16:12:41.853043+00:00",
    "description": "Arista NG Firewall ReportEntry SQL Injection Arbitrary File Read and Write Vulnerability. This vulnerability allows remote attackers to create arbitrary files and disclose sensitive information on affected installations of Arista NG Firewall. Authentication is required to exploit this vulnerability. The specific flaw exists within the ReportEntry class. The issue results from the lack of proper validation of a user-supplied string before using it to construct SQL queries. An attacker can leverage this in conjunction with other vulnerabilities to execute arbitrary code in the context of the www-data user. Was ZDI-CAN-24325.",
    "keyphrases": {
        "rootcause": "lack of proper validation of a user-supplied string before using it to construct SQL queries",
        "weakness": "SQL injection",
        "impact": "create arbitrary files and disclose sensitive information",
        "vector": "",
        "attacker": "remote attackers",
        "product": "Arista NG Firewall",
        "version": "",
        "component": "ReportEntry class"
    }
}
