{
    "cveId": "CVE-2008-1482",
    "version": "1.0.0",
    "timestamp": "2024-12-10T17:54:04.992951+00:00",
    "description": "Multiple integer overflows in xine-lib 1.1.11 and earlier allow remote attackers to trigger heap-based buffer overflows and possibly execute arbitrary code via (1) a crafted .FLV file, which triggers an overflow in demuxers/demux_flv.c (2) a crafted .MOV file, which triggers an overflow in demuxers/demux_qt.c (3) a crafted .RM file, which triggers an overflow in demuxers/demux_real.c (4) a crafted .MVE file, which triggers an overflow in demuxers/demux_wc3movie.c (5) a crafted .MKV file, which triggers an overflow in demuxers/ebml.c or (6) a crafted .CAK file, which triggers an overflow in demuxers/demux_film.c.",
    "keyphrases": {
        "rootcause": "integer overflows",
        "weakness": "heap-based buffer overflows",
        "impact": "arbitrary code execution",
        "vector": [
            "crafted .FLV file",
            "crafted .MOV file",
            "crafted .RM file",
            "crafted .MVE file",
            "crafted .MKV file",
            "crafted .CAK file"
        ],
        "attacker": "remote attackers",
        "product": "xine-lib",
        "version": "1.1.11 and earlier",
        "component": [
            "demuxers/demux_flv.c",
            "demuxers/demux_qt.c",
            "demuxers/demux_real.c",
            "demuxers/demux_wc3movie.c",
            "demuxers/ebml.c",
            "demuxers/demux_film.c"
        ]
    }
}
