{
    "cveId": "CVE-2022-45153",
    "version": "1.0.0",
    "timestamp": "2024-12-15T20:24:27.876763+00:00",
    "description": "An Incorrect Default Permissions vulnerability in saphanabootstrap-formula of SUSE Linux Enterprise Module for SAP Applications 15-SP1, SUSE Linux Enterprise Server for SAP 12-SP5 openSUSE Leap 15.4 allows local attackers to escalate to root by manipulating the sudo configuration that is created. This issue affects SUSE Linux Enterprise Module for SAP Applications 15-SP1 saphanabootstrap-formula versions prior to 0.13.1+git.1667812208.4db963e. SUSE Linux Enterprise Server for SAP 12-SP5 saphanabootstrap-formula versions prior to 0.13.1+git.1667812208.4db963e. openSUSE Leap 15.4 saphanabootstrap-formula versions prior to 0.13.1+git.1667812208.4db963e.",
    "keyphrases": {
        "rootcause": "Incorrect Default Permissions vulnerability",
        "weakness": "",
        "impact": "escalate to root",
        "vector": "manipulating the sudo configuration",
        "attacker": "local attackers",
        "product": [
            "SUSE Linux Enterprise Module for SAP Applications",
            "SUSE Linux Enterprise Server for SAP",
            "openSUSE Leap"
        ],
        "version": "15-SP1",
        "component": "saphanabootstrap-formula"
    }
}
