{
    "cveId": "CVE-2024-3274",
    "version": "1.0.0",
    "timestamp": "2024-12-06T11:32:07.789868+00:00",
    "description": "** UNSUPPORTED WHEN ASSIGNED ** A vulnerability has been found in D-Link DNS-320L, DNS-320LW and DNS-327L up to 20240403 and classified as problematic. Affected by this vulnerability is an unknown functionality of the file /cgi-bin/info.cgi of the component HTTP GET Request Handler. The manipulation leads to information disclosure. The attack can be launched remotely. The exploit has been disclosed to the public and may be used. The identifier VDB-259285 was assigned to this vulnerability. NOTE This vulnerability only affects products that are no longer supported by the maintainer. NOTE Vendor was contacted early and confirmed immediately that the product is end-of-life. It should be retired and replaced.",
    "keyphrases": {
        "rootcause": "",
        "weakness": "",
        "impact": "information disclosure",
        "vector": "HTTP GET Request Handler",
        "attacker": "",
        "product": "D-Link DNS-320L, DNS-320LW and DNS-327L",
        "version": "up to 20240403",
        "component": "/cgi-bin/info.cgi"
    }
}
