{
  "cveId": "CVE-2025-21547",
  "version": "1.0.0",
  "timestamp": "2025-07-04T16:12:41.853043+00:00",
  "description": "Vulnerability in the Oracle Hospitality OPERA 5 product of Oracle Hospitality Applications (component Opera Servlet). Supported versions that are affected are 5.6.19.20, 5.6.25.8, 5.6.26.6 and 5.6.27.1. Easily exploitable vulnerability allows unauthenticated attacker with network access via HTTP to compromise Oracle Hospitality OPERA 5. Successful attacks of this vulnerability can result in unauthorized access to critical data or complete access to all Oracle Hospitality OPERA 5 accessible data and unauthorized ability to cause a hang or frequently repeatable crash (complete DOS) of Oracle Hospitality OPERA 5. CVSS 3.1 Base Score 9.1 (Confidentiality and Availability impacts). CVSS Vector (CVSS3.1/AVN/ACL/PRN/UIN/SU/CH/IN/AH).",
  "keyphrases": {
    "rootcause": "",
    "weakness": "",
    "impact": [
      "cause a hang or frequently repeatable crash",
      "access to critical data or complete access",
      "unauthorized access to critical data",
      "Availability",
      "complete DOS"
    ],
    "vector": "network access via HTTP",
    "attacker": "unauthenticated attacker",
    "product": "Oracle Hospitality OPERA",
    "version": [
      "5.6.26.6 and 5.6.27.1",
      "5.6.19.20",
      "5.6.25.8"
    ],
    "component": "Opera Servlet"
  },
  "mitreTechnicalImpacts": []
}