{
    "cveId": "CVE-2025-21562",
    "version": "1.0.0",
    "timestamp": "2025-07-04T16:12:41.853043+00:00",
    "description": "Vulnerability in the PeopleSoft Enterprise CC Common Application Objects product of Oracle PeopleSoft (component Run Control Management). The supported version that is affected is 9.2. Easily exploitable vulnerability allows low privileged attacker with network access via HTTP to compromise PeopleSoft Enterprise CC Common Application Objects. Successful attacks of this vulnerability can result in unauthorized read access to a subset of PeopleSoft Enterprise CC Common Application Objects accessible data. CVSS 3.1 Base Score 4.3 (Confidentiality impacts). CVSS Vector (CVSS3.1/AVN/ACL/PRL/UIN/SU/CL/IN/AN).",
    "keyphrases": {
        "rootcause": "",
        "weakness": "",
        "impact": "unauthorized read access to a subset of PeopleSoft Enterprise CC Common Application Objects accessible data",
        "vector": "HTTP",
        "attacker": "low privileged attacker with network access",
        "product": "PeopleSoft Enterprise CC Common Application Objects",
        "version": "9.2",
        "component": "Run Control Management"
    }
}
