{
  "cveId": "CVE-2025-21542",
  "version": "1.0.0",
  "timestamp": "2025-07-04T16:12:41.853043+00:00",
  "description": "Vulnerability in the Oracle Communications Order and Service Management product of Oracle Communications Applications (component Security). Supported versions that are affected are 7.4.0, 7.4.1 and 7.5.0. Easily exploitable vulnerability allows low privileged attacker with network access via HTTP to compromise Oracle Communications Order and Service Management. Successful attacks of this vulnerability can result in unauthorized update, insert or delete access to some of Oracle Communications Order and Service Management accessible data as well as unauthorized read access to a subset of Oracle Communications Order and Service Management accessible data and unauthorized ability to cause a partial denial of service (partial DOS) of Oracle Communications Order and Service Management. CVSS 3.1 Base Score 6.3 (Confidentiality, Integrity and Availability impacts). CVSS Vector (CVSS3.1/AVN/ACL/PRL/UIN/SU/CL/IL/AL).",
  "keyphrases": {
    "rootcause": "",
    "weakness": "",
    "impact": [
      "unauthorized read access to some of the accessible data",
      "read access to subset of accessible data",
      "Integrity and Availability impacts",
      "partial denial of service",
      "insert or delete access",
      "unauthorized update",
      "DOS"
    ],
    "vector": "HTTP",
    "attacker": "low privileged attacker with network access",
    "product": "Oracle Communications Order and Service Management",
    "version": [
      "7.4.1 and 7.5.0",
      "7.4.0"
    ],
    "component": ""
  },
  "mitreTechnicalImpacts": []
}