{
  "cveId": "CVE-2025-21550",
  "version": "1.0.0",
  "timestamp": "2025-07-04T16:12:41.853043+00:00",
  "description": "Vulnerability in the Oracle Financial Services Behavior Detection Platform product of Oracle Financial Services Applications (component Web UI). Supported versions that are affected are 8.0.8.1, 8.1.2.7 and 8.1.2.8. Easily exploitable vulnerability allows unauthenticated attacker with network access via HTTP to compromise Oracle Financial Services Behavior Detection Platform. Successful attacks require human interaction from a person other than the attacker and while the vulnerability is in Oracle Financial Services Behavior Detection Platform, attacks may significantly impact additional products (scope change). Successful attacks of this vulnerability can result in unauthorized update, insert or delete access to some of Oracle Financial Services Behavior Detection Platform accessible data as well as unauthorized read access to a subset of Oracle Financial Services Behavior Detection Platform accessible data. CVSS 3.1 Base Score 6.1 (Confidentiality and Integrity impacts). CVSS Vector (CVSS3.1/AVN/ACL/PRN/UIR/SC/CL/IL/AN).",
  "keyphrases": {
    "rootcause": "",
    "weakness": "",
    "impact": [
      "insert or delete access to some of Oracle Financial Services Behavior Detection Platform accessible data",
      "unauthorized read access",
      "unauthorized update",
      "Integrity"
    ],
    "vector": "HTTP",
    "attacker": "unauthenticated attacker",
    "product": "Oracle Financial Services Behavior Detection Platform",
    "version": [
      "8.1.2.7 and 8.1.2.8",
      "8.0.8.1"
    ],
    "component": "Web UI"
  },
  "mitreTechnicalImpacts": []
}