{
    "cveId": "CVE-2025-21582",
    "version": "1.0.0",
    "timestamp": "2025-07-04T16:12:41.853043+00:00",
    "description": "Vulnerability in the Oracle CRM Technical Foundation product of Oracle E-Business Suite (component Preferences). Supported versions that are affected are 12.2.3-12.2.14. Easily exploitable vulnerability allows unauthenticated attacker with network access via HTTP to compromise Oracle CRM Technical Foundation. Successful attacks require human interaction from a person other than the attacker and while the vulnerability is in Oracle CRM Technical Foundation, attacks may significantly impact additional products (scope change). Successful attacks of this vulnerability can result in unauthorized update, insert or delete access to some of Oracle CRM Technical Foundation accessible data as well as unauthorized read access to a subset of Oracle CRM Technical Foundation accessible data. CVSS 3.1 Base Score 6.1 (Confidentiality and Integrity impacts). CVSS Vector (CVSS3.1/AVN/ACL/PRN/UIR/SC/CL/IL/AN).",
    "keyphrases": {
        "rootcause": "",
        "weakness": "",
        "impact": "unauthorized read access to a subset of Oracle CRM Technical Foundation accessible data",
        "vector": "unauthenticated attacker with network access via HTTP",
        "attacker": "",
        "product": "Oracle E-Business Suite",
        "version": "12.2.3-12.2.14",
        "component": "Oracle CRM Technical Foundation product"
    }
}
