{
    "cveId": "CVE-2022-46144",
    "version": "1.0.0",
    "timestamp": "2024-12-15T20:24:27.876763+00:00",
    "description": "A vulnerability has been identified in SCALANCE SC622-2C (6GK5622-2GS00-2AC2) (All versions = V2.3 = V2.3 = V2.3 = V2.3 = V2.3 = V2.3 < V3.0), SCALANCE WAB762-1 (6GK5762-1AJ00-6AA0) (All versions), SCALANCE WAM763-1 (6GK5763-1AL00-7DA0) (All versions), SCALANCE WAM763-1 (ME) (6GK5763-1AL00-7DC0) (All versions), SCALANCE WAM763-1 (US) (6GK5763-1AL00-7DB0) (All versions), SCALANCE WAM766-1 (EU) (6GK5766-1GE00-7DA0) (All versions), SCALANCE WAM766-1 (ME) (6GK5766-1GE00-7DC0) (All versions), SCALANCE WAM766-1 (US) (6GK5766-1GE00-7DB0) (All versions), SCALANCE WAM766-1 EEC (EU) (6GK5766-1GE00-7TA0) (All versions), SCALANCE WAM766-1 EEC (ME) (6GK5766-1GE00-7TC0) (All versions), SCALANCE WAM766-1 EEC (US) (6GK5766-1GE00-7TB0) (All versions), SCALANCE WUB762-1 (6GK5762-1AJ00-1AA0) (All versions), SCALANCE WUB762-1 (6GK5762-1AJ00-2AA0) (All versions), SCALANCE WUM763-1 (6GK5763-1AL00-3AA0) (All versions), SCALANCE WUM763-1 (6GK5763-1AL00-3DA0) (All versions), SCALANCE WUM763-1 (US) (6GK5763-1AL00-3AB0) (All versions), SCALANCE WUM763-1 (US) (6GK5763-1AL00-3DB0) (All versions), SCALANCE WUM766-1 (EU) (6GK5766-1GE00-3DA0) (All versions), SCALANCE WUM766-1 (ME) (6GK5766-1GE00-3DC0) (All versions), SCALANCE WUM766-1 (US) (6GK5766-1GE00-3DB0) (All versions). Affected devices do not properly process CLI commands after a user forcefully quitted the SSH connection. This could allow an authenticated attacker to make the CLI via SSH or serial interface irresponsive.",
    "keyphrases": {
        "rootcause": "",
        "weakness": "do not properly process CLI commands",
        "impact": "make the CLI via SSH or serial interface irresponsive",
        "vector": "forcefully quitted SSH connection",
        "attacker": "authenticated attacker",
        "product": [
            "SCALANCE SC622-2C",
            "SCALANCE WAB762-1",
            "SCALANCE WAM763-1",
            "SCALANCE WAM763-1 (ME)",
            "SCALANCE WAM763-1 (US)",
            "SCALANCE WAM766-1 (EU)",
            "SCALANCE WAM766-1 (ME)",
            "SCALANCE WAM766-1 (US)",
            "SCALANCE WAM766-1 EEC (EU)",
            "SCALANCE WAM766-1 EEC (ME)",
            "SCALANCE WAM766-1 EEC (US)",
            "SCALANCE WUB762-1",
            "SCALANCE WUB762-1",
            "SCALANCE WUM763-1",
            "SCALANCE WUM763-1",
            "SCALANCE WUM763-1 (US)",
            "SCALANCE WUM763-1 (US)",
            "SCALANCE WUM766-1 (EU)",
            "SCALANCE WUM766-1 (ME)",
            "SCALANCE WUM766-1 (US)"
        ],
        "version": "All versions",
        "component": ""
    }
}
