{
    "cveId": "CVE-2010-0593",
    "version": "1.0.0",
    "timestamp": "2024-12-10T17:54:04.992951+00:00",
    "description": "The Cisco RVS4000 4-port Gigabit Security Router before 1.3.2.0, PVC2300 Business Internet Video Camera before 1.1.2.6, WVC200 Wireless-G PTZ Internet Video Camera before 1.1.1.15, WVC210 Wireless-G PTZ Internet Video Camera before 1.1.1.15, and WVC2300 Wireless-G Business Internet Video Camera before 1.1.2.6 do not properly restrict read access to passwords, which allows context-dependent attackers to obtain sensitive information, related to (1) access by remote authenticated users to a PVC2300 or WVC2300 via a crafted URL, (2) leveraging setup privileges on a WVC200 or WVC210, and (3) leveraging administrative privileges on an RVS4000, aka Bug ID CSCte64726.",
    "keyphrases": {
        "rootcause": "improper access restriction",
        "weakness": "",
        "impact": "obtain sensitive information",
        "vector": [
            "crafted URL",
            "setup privileges",
            "administrative privileges"
        ],
        "attacker": "context-dependent attackers",
        "product": [
            "Cisco RVS4000",
            "PVC2300",
            "WVC200",
            "WVC210",
            "WVC2300"
        ],
        "version": [
            "before 1.3.2.0",
            "before 1.1.2.6",
            "before 1.1.1.15",
            "before 1.1.1.15",
            "before 1.1.2.6"
        ],
        "component": ""
    }
}
