{
    "cveId": "CVE-2023-31131",
    "version": "1.0.0",
    "timestamp": "2024-12-15T20:24:27.876763+00:00",
    "description": "Greenplum Database (GPDB) is an open source data warehouse based on PostgreSQL. In versions prior to 6.22.3 Greenplum Database used an unsafe methods to extract tar files within GPPKGs. greenplum-db is vulnerable to path traversal leading to arbitrary file writes. An attacker can use this vulnerability to overwrite data or system files potentially leading to crash or malfunction of the system. Any files which are accessible to the running process are at risk. All users are requested to upgrade to Greenplum Database version 6.23.2 or higher. There are no known workarounds for this vulnerability.",
    "keyphrases": {
        "rootcause": "unsafe methods to extract tar files",
        "weakness": "path traversal",
        "impact": "arbitrary file writes",
        "vector": "",
        "attacker": "attacker",
        "product": "Greenplum Database",
        "version": "prior to 6.22.3",
        "component": ""
    }
}
