{
    "cveId": "CVE-2020-14694",
    "version": "1.0.0",
    "timestamp": "2024-12-06T11:32:07.789868+00:00",
    "description": "Vulnerability in the Oracle VM VirtualBox product of Oracle Virtualization (component Core). Supported versions that are affected are Prior to 5.2.44, prior to 6.0.24 and prior to 6.1.12. Difficult to exploit vulnerability allows high privileged attacker with logon to the infrastructure where Oracle VM VirtualBox executes to compromise Oracle VM VirtualBox. While the vulnerability is in Oracle VM VirtualBox, attacks may significantly impact additional products. Successful attacks of this vulnerability can result in unauthorized access to critical data or complete access to all Oracle VM VirtualBox accessible data. CVSS 3.1 Base Score 5.3 (Confidentiality impacts). CVSS Vector (CVSS3.1/AVL/ACH/PRH/UIN/SC/CH/IN/AN).",
    "keyphrases": {
        "rootcause": "",
        "weakness": "",
        "impact": [
            "unauthorized access to critical data",
            "complete access to all Oracle VM VirtualBox accessible data"
        ],
        "vector": "",
        "attacker": "high privileged attacker with logon to the infrastructure where Oracle VM VirtualBox executes",
        "product": "Oracle VM VirtualBox",
        "version": "Prior to 5.2.44, prior to 6.0.24 and prior to 6.1.12",
        "component": "Core"
    }
}
