{
  "cveId": "CVE-2020-14761",
  "version": "1.0.0",
  "timestamp": "2024-12-13T17:34:55.850537+00:00",
  "description": "Vulnerability in the Oracle Applications Manager product of Oracle E-Business Suite (component Oracle Diagnostics Interfaces). Supported versions that are affected are 12.1.3 and 12.2.3 - 12.2.7. Easily exploitable vulnerability allows unauthenticated attacker with network access via HTTP to compromise Oracle Applications Manager. Successful attacks of this vulnerability can result in unauthorized update, insert or delete access to some of Oracle Applications Manager accessible data as well as unauthorized read access to a subset of Oracle Applications Manager accessible data. CVSS 3.1 Base Score 6.5 (Confidentiality and Integrity impacts). CVSS Vector (CVSS3.1/AVN/ACL/PRN/UIN/SU/CL/IL/AN).",
  "keyphrases": {
    "rootcause": "",
    "weakness": "",
    "impact": [
      "Integrity",
      "insert or delete access",
      "unauthorized read access",
      "unauthorized update"
    ],
    "vector": "network access via HTTP",
    "attacker": "unauthenticated attacker",
    "product": "Oracle E-Business Suite",
    "version": "12.1.3 and 12.2.3 - 12.2.7",
    "component": "Oracle Applications Manager"
  },
  "mitreTechnicalImpacts": []
}