{
    "cveId": "CVE-2020-14617",
    "version": "1.0.0",
    "timestamp": "2024-12-06T11:32:07.789868+00:00",
    "description": "Vulnerability in the Primavera Unifier product of Oracle Construction and Engineering (component Platform, Mobile App). Supported versions that are affected are 16.1, 16.2, 17.7-17.12, 18.8 and 19.12 Mobile App Prior to 20.6. Easily exploitable vulnerability allows low privileged attacker with network access via HTTPS to compromise Primavera Unifier. Successful attacks require human interaction from a person other than the attacker. Successful attacks of this vulnerability can result in unauthorized access to critical data or complete access to all Primavera Unifier accessible data. CVSS 3.1 Base Score 5.7 (Confidentiality impacts). CVSS Vector (CVSS3.1/AVN/ACL/PRL/UIR/SU/CH/IN/AN).",
    "keyphrases": {
        "rootcause": "",
        "weakness": "",
        "impact": [
            "unauthorized access to critical data",
            "complete access to all Primavera Unifier accessible data"
        ],
        "vector": "low privileged attacker with network access via HTTPS",
        "attacker": "low privileged attacker",
        "product": "Primavera Unifier",
        "version": "16.1, 16.2, 17.7-17.12, 18.8 and 19.12 Mobile App Prior to 20.6",
        "component": "Platform, Mobile App"
    }
}
