{
  "cveId": "CVE-2020-14889",
  "version": "1.0.0",
  "timestamp": "2024-12-06T11:32:07.789868+00:00",
  "description": "Vulnerability in the Oracle VM VirtualBox product of Oracle Virtualization (component Core). The supported version that is affected is Prior to 6.1.16. Easily exploitable vulnerability allows high privileged attacker with logon to the infrastructure where Oracle VM VirtualBox executes to compromise Oracle VM VirtualBox. While the vulnerability is in Oracle VM VirtualBox, attacks may significantly impact additional products. Successful attacks of this vulnerability can result in unauthorized access to critical data or complete access to all Oracle VM VirtualBox accessible data. CVSS 3.1 Base Score 6.0 (Confidentiality impacts). CVSS Vector (CVSS3.1/AVL/ACL/PRH/UIN/SC/CH/IN/AN).",
  "keyphrases": {
    "rootcause": "",
    "weakness": "",
    "impact": "unauthorized access to critical data or complete access to all Oracle VM VirtualBox accessible data",
    "vector": "",
    "attacker": "high privileged attacker",
    "product": "Oracle VM VirtualBox",
    "version": "Prior to 6.1.16",
    "component": "Core"
  },
  "mitreTechnicalImpacts": []
}