{
    "cveId": "CVE-2020-14840",
    "version": "1.0.0",
    "timestamp": "2024-12-06T11:32:07.789868+00:00",
    "description": "Vulnerability in the Oracle Application Object Library product of Oracle E-Business Suite (component Diagnostics). Supported versions that are affected are 12.1.3 and 12.2.3 - 12.2.10. Easily exploitable vulnerability allows unauthenticated attacker with network access via HTTP to compromise Oracle Application Object Library. Successful attacks require human interaction from a person other than the attacker and while the vulnerability is in Oracle Application Object Library, attacks may significantly impact additional products. Successful attacks of this vulnerability can result in unauthorized update, insert or delete access to some of Oracle Application Object Library accessible data. CVSS 3.1 Base Score 4.7 (Integrity impacts). CVSS Vector (CVSS3.1/AVN/ACL/PRN/UIR/SC/CN/IL/AN).",
    "keyphrases": {
        "rootcause": "",
        "weakness": "",
        "impact": "unauthorized update, insert or delete access to some of Oracle Application Object Library accessible data",
        "vector": "",
        "attacker": "unauthenticated attacker",
        "product": "Oracle Application Object Library",
        "version": "12.1.3 and 12.2.3 - 12.2.10",
        "component": "Diagnostics"
    }
}
