{
    "cveId": "CVE-2020-14740",
    "version": "1.0.0",
    "timestamp": "2024-12-06T11:32:07.789868+00:00",
    "description": "Vulnerability in the SQL Developer Install component of Oracle Database Server. Supported versions that are affected are 11.2.0.4, 12.1.0.2, 12.2.0.1 and 18c. Easily exploitable vulnerability allows low privileged attacker having Client Computer User Account privilege with logon to the infrastructure where SQL Developer Install executes to compromise SQL Developer Install. Successful attacks require human interaction from a person other than the attacker. Successful attacks of this vulnerability can result in unauthorized read access to a subset of SQL Developer Install accessible data. CVSS 3.1 Base Score 2.8 (Confidentiality impacts). CVSS Vector (CVSS3.1/AVL/ACL/PRL/UIR/SU/CL/IN/AN).",
    "keyphrases": {
        "rootcause": "",
        "weakness": "",
        "impact": "unauthorized read access to a subset of SQL Developer Install accessible data",
        "vector": "",
        "attacker": "low privileged attacker",
        "product": "Oracle Database Server",
        "version": "11.2.0.4, 12.1.0.2, 12.2.0.1 and 18c",
        "component": "SQL Developer Install component"
    }
}
