{
    "cveId": "CVE-2020-14731",
    "version": "1.0.0",
    "timestamp": "2024-12-06T11:32:07.789868+00:00",
    "description": "Vulnerability in the Oracle Retail Customer Management and Segmentation Foundation product of Oracle Retail Applications (component Segment). Supported versions that are affected are 18.0 and 19.0. Difficult to exploit vulnerability allows low privileged attacker with network access via HTTP to compromise Oracle Retail Customer Management and Segmentation Foundation. Successful attacks of this vulnerability can result in unauthorized read access to a subset of Oracle Retail Customer Management and Segmentation Foundation accessible data. CVSS 3.1 Base Score 3.1 (Confidentiality impacts). CVSS Vector (CVSS3.1/AVN/ACH/PRL/UIN/SU/CL/IN/AN).",
    "keyphrases": {
        "rootcause": "",
        "weakness": "",
        "impact": "unauthorized read access",
        "vector": "",
        "attacker": "low privileged attacker with network access via HTTP",
        "product": "Oracle Retail Customer Management and Segmentation Foundation",
        "version": "18.0 and 19.0",
        "component": "Segment"
    }
}
