{
    "cveId": "CVE-2020-14541",
    "version": "1.0.0",
    "timestamp": "2024-12-06T11:32:07.789868+00:00",
    "description": "Vulnerability in the Hyperion Financial Close Management product of Oracle Hyperion (component Close Manager). The supported version that is affected is 11.1.2.4. Difficult to exploit vulnerability allows high privileged attacker with network access via HTTP to compromise Hyperion Financial Close Management. Successful attacks require human interaction from a person other than the attacker. Successful attacks of this vulnerability can result in unauthorized update, insert or delete access to some of Hyperion Financial Close Management accessible data. CVSS 3.1 Base Score 2.0 (Integrity impacts). CVSS Vector (CVSS3.1/AVN/ACH/PRH/UIR/SU/CN/IL/AN).",
    "keyphrases": {
        "rootcause": "",
        "weakness": "",
        "impact": "unauthorized update, insert or delete access",
        "vector": "high privileged attacker with network access via HTTP",
        "attacker": "high privileged attacker",
        "product": "Oracle Hyperion",
        "version": "11.1.2.4",
        "component": "Close Manager"
    }
}
