{
  "cveId": "CVE-2020-14823",
  "version": "1.0.0",
  "timestamp": "2024-12-06T11:32:07.789868+00:00",
  "description": "Vulnerability in the Oracle CRM Technical Foundation product of Oracle E-Business Suite (component Preferences). Supported versions that are affected are 12.2.3 - 12.2.10. Easily exploitable vulnerability allows high privileged attacker with network access via HTTP to compromise Oracle CRM Technical Foundation. Successful attacks of this vulnerability can result in unauthorized creation, deletion or modification access to critical data or all Oracle CRM Technical Foundation accessible data as well as unauthorized access to critical data or complete access to all Oracle CRM Technical Foundation accessible data. CVSS 3.1 Base Score 6.5 (Confidentiality and Integrity impacts). CVSS Vector (CVSS3.1/AVN/ACL/PRH/UIN/SU/CH/IH/AN).",
  "keyphrases": {
    "rootcause": "",
    "weakness": "",
    "impact": [
      "Integrity",
      "deletion or modification access to critical data or all Oracle CRM Technical Foundation accessible data as well as unauthorized access to critical data or complete access to all Oracle CRM Technical Foundation accessible data",
      "unauthorized creation"
    ],
    "vector": "",
    "attacker": "high privileged attacker with network access via HTTP",
    "product": "Oracle E-Business Suite",
    "version": "12.2.3 - 12.2.10",
    "component": "Oracle CRM Technical Foundation"
  },
  "mitreTechnicalImpacts": []
}