{
    "cveId": "CVE-2020-14764",
    "version": "1.0.0",
    "timestamp": "2024-12-06T11:32:07.789868+00:00",
    "description": "Vulnerability in the Hyperion Planning product of Oracle Hyperion (component Application Development Framework). The supported version that is affected is 11.1.2.4. Difficult to exploit vulnerability allows high privileged attacker with network access via HTTP to compromise Hyperion Planning. Successful attacks require human interaction from a person other than the attacker. Successful attacks of this vulnerability can result in unauthorized creation, deletion or modification access to critical data or all Hyperion Planning accessible data. CVSS 3.1 Base Score 4.2 (Integrity impacts). CVSS Vector (CVSS3.1/AVN/ACH/PRH/UIR/SU/CN/IH/AN).",
    "keyphrases": {
        "rootcause": "",
        "weakness": "",
        "impact": "unauthorized creation, deletion or modification access to critical data or all Hyperion Planning accessible data",
        "vector": "high privileged attacker with network access via HTTP",
        "attacker": "",
        "product": "Hyperion Planning",
        "version": "11.1.2.4",
        "component": "Application Development Framework"
    }
}
