{
  "cveId": "CVE-2020-14667",
  "version": "1.0.0",
  "timestamp": "2024-12-06T11:32:07.789868+00:00",
  "description": "Vulnerability in the Oracle CRM Technical Foundation product of Oracle E-Business Suite (component Preferences). Supported versions that are affected are 12.1.3 and 12.2.3-12.2.9. Easily exploitable vulnerability allows low privileged attacker with network access via HTTP to compromise Oracle CRM Technical Foundation. Successful attacks require human interaction from a person other than the attacker and while the vulnerability is in Oracle CRM Technical Foundation, attacks may significantly impact additional products. Successful attacks of this vulnerability can result in unauthorized access to critical data or complete access to all Oracle CRM Technical Foundation accessible data as well as unauthorized update, insert or delete access to some of Oracle CRM Technical Foundation accessible data. CVSS 3.1 Base Score 7.6 (Confidentiality and Integrity impacts). CVSS Vector (CVSS3.1/AVN/ACL/PRL/UIR/SC/CH/IL/AN).",
  "keyphrases": {
    "rootcause": "",
    "weakness": "",
    "impact": [
      "Integrity",
      "complete access to all Oracle CRM Technical Foundation accessible data",
      "insert or delete access to some of Oracle CRM Technical Foundation accessible data",
      "unauthorized access to critical data",
      "unauthorized update"
    ],
    "vector": "low privileged attacker with network access via HTTP",
    "attacker": "",
    "product": "Oracle E-Business Suite",
    "version": [
      "12.1.3",
      "12.2.3-12.2.9"
    ],
    "component": "Oracle CRM Technical Foundation"
  },
  "mitreTechnicalImpacts": []
}