{
  "cveId": "CVE-2020-14807",
  "version": "1.0.0",
  "timestamp": "2024-12-13T17:34:55.850537+00:00",
  "description": "Vulnerability in the Oracle Hospitality Suite8 product of Oracle Hospitality Applications (component WebConnect). Supported versions that are affected are 8.10.2 and 8.11-8.14. Easily exploitable vulnerability allows unauthenticated attacker with network access via HTTP to compromise Oracle Hospitality Suite8. Successful attacks require human interaction from a person other than the attacker. Successful attacks of this vulnerability can result in unauthorized access to critical data or complete access to all Oracle Hospitality Suite8 accessible data as well as unauthorized update, insert or delete access to some of Oracle Hospitality Suite8 accessible data. CVSS 3.1 Base Score 7.1 (Confidentiality and Integrity impacts). CVSS Vector (CVSS3.1/AVN/ACL/PRN/UIR/SU/CH/IL/AN).",
  "keyphrases": {
    "rootcause": "",
    "weakness": "",
    "impact": [
      "Integrity",
      "insert or delete access",
      "unauthorized access to critical data",
      "unauthorized update"
    ],
    "vector": "network access via HTTP",
    "attacker": "unauthenticated attacker",
    "product": "Oracle Hospitality Suite8",
    "version": [
      "8.10.2",
      "8.11-8.14"
    ],
    "component": "WebConnect"
  },
  "mitreTechnicalImpacts": []
}