{
  "cveId": "CVE-2020-14662",
  "version": "1.0.0",
  "timestamp": "2024-12-06T11:32:07.789868+00:00",
  "description": "Vulnerability in the Oracle Financial Services Analytical Applications Infrastructure product of Oracle Financial Services Applications (component Infrastructure). Supported versions that are affected are 8.0.6-8.1.0. Easily exploitable vulnerability allows low privileged attacker with network access via HTTP to compromise Oracle Financial Services Analytical Applications Infrastructure. Successful attacks of this vulnerability can result in unauthorized update, insert or delete access to some of Oracle Financial Services Analytical Applications Infrastructure accessible data as well as unauthorized read access to a subset of Oracle Financial Services Analytical Applications Infrastructure accessible data and unauthorized ability to cause a partial denial of service (partial DOS) of Oracle Financial Services Analytical Applications Infrastructure. CVSS 3.1 Base Score 6.3 (Confidentiality, Integrity and Availability impacts). CVSS Vector (CVSS3.1/AVN/ACL/PRL/UIN/SU/CL/IL/AL).",
  "keyphrases": {
    "rootcause": "",
    "weakness": "",
    "impact": [
      "DOS",
      "Integrity and Availability impacts",
      "insert or delete access to some of Oracle Financial Services Analytical Applications Infrastructure accessible data",
      "unauthorized ability to cause a partial denial of service",
      "unauthorized read access to a subset of Oracle Financial Services Analytical Applications Infrastructure accessible data",
      "unauthorized update"
    ],
    "vector": "network access via HTTP",
    "attacker": "low privileged attacker",
    "product": "Oracle Financial Services Applications",
    "version": "8.0.6-8.1.0",
    "component": "Oracle Financial Services Analytical Applications Infrastructure"
  },
  "mitreTechnicalImpacts": []
}