{
  "cveId": "CVE-2020-14768",
  "version": "1.0.0",
  "timestamp": "2024-12-06T11:32:07.789868+00:00",
  "description": "Vulnerability in the Hyperion Analytic Provider Services product of Oracle Hyperion (component Smart View Provider). The supported version that is affected is 11.1.2.4. Difficult to exploit vulnerability allows low privileged attacker with access to the physical communication segment attached to the hardware where the Hyperion Analytic Provider Services executes to compromise Hyperion Analytic Provider Services. Successful attacks require human interaction from a person other than the attacker. Successful attacks of this vulnerability can result in unauthorized update, insert or delete access to some of Hyperion Analytic Provider Services accessible data as well as unauthorized read access to a subset of Hyperion Analytic Provider Services accessible data and unauthorized ability to cause a partial denial of service (partial DOS) of Hyperion Analytic Provider Services. CVSS 3.1 Base Score 4.3 (Confidentiality, Integrity and Availability impacts). CVSS Vector (CVSS3.1/AVA/ACH/PRL/UIR/SU/CL/IL/AL).",
  "keyphrases": {
    "rootcause": "",
    "weakness": "",
    "impact": [
      "Integrity and Availability impacts",
      "insert or delete access",
      "partial denial of service (partial DOS)",
      "unauthorized read access",
      "unauthorized update"
    ],
    "vector": "",
    "attacker": "low privileged attacker",
    "product": "Hyperion Analytic Provider Services",
    "version": "11.1.2.4",
    "component": "Smart View Provider"
  },
  "mitreTechnicalImpacts": []
}