{
    "cveId": "CVE-2020-14661",
    "version": "1.0.0",
    "timestamp": "2024-12-06T11:32:07.789868+00:00",
    "description": "Vulnerability in the Oracle CRM Technical Foundation product of Oracle E-Business Suite (component Preferences). Supported versions that are affected are 12.1.3 and 12.2.3-12.2.9. Easily exploitable vulnerability allows unauthenticated attacker with network access via HTTP to compromise Oracle CRM Technical Foundation. Successful attacks require human interaction from a person other than the attacker and while the vulnerability is in Oracle CRM Technical Foundation, attacks may significantly impact additional products. Successful attacks of this vulnerability can result in unauthorized update, insert or delete access to some of Oracle CRM Technical Foundation accessible data. CVSS 3.1 Base Score 4.7 (Integrity impacts). CVSS Vector (CVSS3.1/AVN/ACL/PRN/UIR/SC/CN/IL/AN).",
    "keyphrases": {
        "rootcause": "",
        "weakness": "",
        "impact": "unauthorized update, insert or delete access",
        "vector": "",
        "attacker": "unauthenticated attacker",
        "product": "Oracle CRM Technical Foundation",
        "version": "12.1.3 and 12.2.3-12.2.9",
        "component": "Preferences"
    }
}
