{
    "cveId": "CVE-2020-14744",
    "version": "1.0.0",
    "timestamp": "2024-12-06T11:32:07.789868+00:00",
    "description": "Vulnerability in the Oracle REST Data Services product of Oracle REST Data Services (component General). Supported versions that are affected are 11.2.0.4, 12.1.0.2, 12.2.0.1, 18c and 19c Standalone ORDS prior to 20.2.1. Easily exploitable vulnerability allows low privileged attacker with network access via HTTP to compromise Oracle REST Data Services. Successful attacks of this vulnerability can result in unauthorized access to critical data or complete access to all Oracle REST Data Services accessible data. CVSS 3.1 Base Score 6.5 (Confidentiality impacts). CVSS Vector (CVSS3.1/AVN/ACL/PRL/UIN/SU/CH/IN/AN).",
    "keyphrases": {
        "rootcause": "",
        "weakness": "",
        "impact": "unauthorized access to critical data or complete access to all Oracle REST Data Services accessible data",
        "vector": "low privileged attacker with network access via HTTP",
        "attacker": "",
        "product": "Oracle REST Data Services",
        "version": "11.2.0.4, 12.1.0.2, 12.2.0.1, 18c and 19c Standalone ORDS prior to 20.2.1",
        "component": "General"
    }
}
