{
    "cveId": "CVE-2020-14566",
    "version": "1.0.0",
    "timestamp": "2024-12-06T11:32:07.789868+00:00",
    "description": "Vulnerability in the Primavera Portfolio Management product of Oracle Construction and Engineering (component Web Access). Supported versions that are affected are 16.1.0.0-16.1.5.1, 18.0.0.0-18.0.2.0 and 19.0.0.0. Easily exploitable vulnerability allows unauthenticated attacker with network access via HTTP to compromise Primavera Portfolio Management. Successful attacks require human interaction from a person other than the attacker. Successful attacks of this vulnerability can result in unauthorized update, insert or delete access to some of Primavera Portfolio Management accessible data. CVSS 3.1 Base Score 4.3 (Integrity impacts). CVSS Vector (CVSS3.1/AVN/ACL/PRN/UIR/SU/CN/IL/AN).",
    "keyphrases": {
        "rootcause": "",
        "weakness": "",
        "impact": "unauthorized update, insert or delete access",
        "vector": "HTTP",
        "attacker": "unauthenticated attacker",
        "product": "Primavera Portfolio Management",
        "version": [
            "16.1.0.0-16.1.5.1",
            "18.0.0.0-18.0.2.0",
            "19.0.0.0"
        ],
        "component": "Web Access"
    }
}
