{
    "cveId": "CVE-2011-4340",
    "version": "1.0.0",
    "timestamp": "2024-12-10T17:54:04.992951+00:00",
    "description": "Multiple cross-site scripting (XSS) vulnerabilities in Symphony CMS 2.2.3 and possibly other versions before 2.2.4 allow remote authenticated users with Author privileges to inject arbitrary web script or HTML via (1) the profile parameter to extensions/profiledevkit/content/content.profile.php, as demonstrated via requests to (a) the default URI, (b) about/, or (c) drafts/ or (2) the filter parameter in symphony/lib/core/class.symphony.php, as demonstrated via requests to (d) symphony/publish/comments or (e) symphony/publish/images. NOTE some of these details are obtained from third party information.",
    "keyphrases": {
        "rootcause": "cross-site scripting",
        "weakness": "inject arbitrary web script or HTML",
        "impact": "",
        "vector": "",
        "attacker": "remote authenticated users with Author privileges",
        "product": "Symphony CMS",
        "version": "2.2.3",
        "component": [
            "profile parameter to extensions/profiledevkit/content/content.profile.php",
            "filter parameter in symphony/lib/core/class.symphony.php"
        ]
    }
}
