{
    "cveId": "CVE-2008-6922",
    "version": "1.0.0",
    "timestamp": "2024-12-10T17:54:04.992951+00:00",
    "description": "Multiple stack-based buffer overflows in CMailCOM.dll in CMailServer 5.4.6 allow remote attackers to execute arbitrary code via a long argument to the (1) CreateUserPath, (2) Logout, (3) DeleteMailByUID, (4) MoveToInbox, (5) MoveToFolder, (6) DeleteMailEx, (7) GetMailDataEx, (8) SetReplySign, (9) SetForwardSign, and (10) SetReadSign methods, which are not properly handled by (a) the POP3 Class ActiveX control (CMailCom.POP3) or a long argument to the (11) AddAttach, (12) SetSubject, (13) SetBcc, (14) SetBody, (15) SetCc, (16) SetFrom, (17) SetTo, and (18) SetFromUID methods, which are not properly handled by the Class ActiveX control (CMailCOM.SMTP), as demonstrated via the indexOfMail parameter to mwmail.asp.",
    "keyphrases": {
        "rootcause": "stack-based buffer overflows",
        "weakness": "",
        "impact": "execute arbitrary code",
        "vector": "long argument",
        "attacker": "remote attackers",
        "product": "CMailServer",
        "version": "5.4.6",
        "component": [
            "CreateUserPath",
            "Logout",
            "DeleteMailByUID",
            "MoveToInbox",
            "MoveToFolder",
            "DeleteMailEx",
            "GetMailDataEx",
            "SetReplySign",
            "SetForwardSign",
            "SetReadSign",
            "AddAttach",
            "SetSubject",
            "SetBcc",
            "SetBody",
            "SetCc",
            "SetFrom",
            "SetTo",
            "SetFromUID"
        ]
    }
}
