{
    "cveId": "CVE-2021-23274",
    "version": "1.0.0",
    "timestamp": "2024-12-15T20:24:27.876763+00:00",
    "description": "The Config UI component of TIBCO Software Inc.s TIBCO API Exchange Gateway and TIBCO API Exchange Gateway Distribution for TIBCO Silver Fabric contains a vulnerability that theoretically allows an unauthenticated attacker with network access to execute a clickjacking attack on the affected system. A successful attack using this vulnerability does not require human interaction from a person other than the attacker. Affected releases are TIBCO Software Inc.s TIBCO API Exchange Gateway versions 2.3.3 and below and TIBCO API Exchange Gateway Distribution for TIBCO Silver Fabric versions 2.3.3 and below.",
    "keyphrases": {
        "rootcause": "",
        "weakness": "clickjacking attack",
        "impact": "",
        "vector": "",
        "attacker": "unauthenticated attacker",
        "product": [
            "TIBCO API Exchange Gateway",
            "TIBCO API Exchange Gateway Distribution for TIBCO Silver Fabric"
        ],
        "version": "2.3.3 and below",
        "component": "Config UI component"
    }
}
