{
    "cveId": "CVE-2023-25722",
    "version": "1.0.0",
    "timestamp": "2024-12-15T20:24:27.876763+00:00",
    "description": "A credential-leak issue was discovered in related Veracode products before 2023-03-27. Veracode Scan Jenkins Plugin before 23.3.19.0, when configured for remote agent jobs, invokes the Veracode Java API Wrapper in a manner that allows local users (with OS-level access of the Jenkins remote) to discover Veracode API credentials by listing the process and its arguments. Veracode Scan Jenkins Plugin before 23.3.19.0, when configured for remote agent jobs and when the Connect using proxy option is enabled and configured with proxy credentials, allows local users of the Jenkins remote to discover proxy credentials by listing the process and its arguments. Veracode Azure DevOps Extension before 3.20.0 invokes the Veracode Java API Wrapper in a manner that allows local users (with OS-level access to the Azure DevOps Services cloud infrastructure or Azure DevOps Server) to discover Veracode API credentials by listing the process and its arguments. Veracode Azure DevOps Extension before 3.20.0, when configured with proxy credentials, allows users (with shell access to the Azure DevOps Services cloud infrastructure or Azure DevOps Server) to discover proxy credentials by listing the process and its arguments.",
    "keyphrases": {
        "rootcause": "",
        "weakness": "improper access control",
        "impact": [
            "discover Veracode API credentials",
            "discover proxy credentials"
        ],
        "vector": "listing the process and its arguments",
        "attacker": "local users",
        "product": [
            "Veracode Scan Jenkins Plugin",
            "Veracode Azure DevOps Extension"
        ],
        "version": [
            "before 23.3.19.0",
            "before 3.20.0"
        ],
        "component": ""
    }
}
