{
    "cveId": "CVE-2022-25159",
    "version": "1.0.0",
    "timestamp": "2024-11-03T18:37:50.907685+00:00",
    "description": "Authentication Bypass by Capture-replay vulnerability in Mitsubishi Electric MELSEC iQ-F series FX5U(C) CPU all versions, Mitsubishi Electric MELSEC iQ-F series FX5UJ CPU all versions, Mitsubishi Electric MELSEC iQ-R series R00/01/02CPU all versions, Mitsubishi Electric MELSEC iQ-R series R04/08/16/32/120(EN)CPU all versions, Mitsubishi Electric MELSEC iQ-R series R08/16/32/120SFCPU all versions, Mitsubishi Electric MELSEC iQ-R series R08/16/32/120PCPU all versions, Mitsubishi Electric MELSEC iQ-R series R08/16/32/120PSFCPU all versions, Mitsubishi Electric MELSEC iQ-R series R16/32/64MTCPU all versions, Mitsubishi Electric MELSEC iQ-R series RJ71C24(-R2/R4) all versions, Mitsubishi Electric MELSEC iQ-R series RJ71EN71 all versions, Mitsubishi Electric MELSEC iQ-R series RJ72GF15-T2 all versions, Mitsubishi Electric MELSEC Q series Q03/04/06/13/26UDVCPU all versions, Mitsubishi Electric MELSEC Q series Q04/06/13/26UDPVCPU all versions, Mitsubishi Electric MELSEC Q series QJ71C24N(-R2/R4) all versions and Mitsubishi Electric MELSEC Q series QJ71E71-100 all versions allows a remote unauthenticated attacker to login to the product by replay attack.",
    "keyphrases": {
        "rootcause": "capture-replay",
        "weakness": "",
        "impact": "Authentication Bypass",
        "vector": "replay attack",
        "attacker": "remote unauthenticated attacker",
        "product": [
            "Mitsubishi Electric MELSEC iQ-F series FX5U(C) CPU",
            "Mitsubishi Electric MELSEC iQ-F series FX5UJ CPU",
            "Mitsubishi Electric MELSEC iQ-R series R00/01/02CPU",
            "Mitsubishi Electric MELSEC iQ-R series R04/08/16/32/120(EN)CPU",
            "Mitsubishi Electric MELSEC iQ-R series R08/16/32/120SFCPU",
            "Mitsubishi Electric MELSEC iQ-R series R08/16/32/120PCPU",
            "Mitsubishi Electric MELSEC iQ-R series R08/16/32/120PSFCPU",
            "Mitsubishi Electric MELSEC iQ-R series R16/32/64MTCPU",
            "Mitsubishi Electric MELSEC iQ-R series RJ71C24(-R2/R4)",
            "Mitsubishi Electric MELSEC iQ-R series RJ71EN71",
            "Mitsubishi Electric MELSEC iQ-R series RJ72GF15-T2",
            "Mitsubishi Electric MELSEC Q series Q03/04/06/13/26UDVCPU",
            "Mitsubishi Electric MELSEC Q series Q04/06/13/26UDPVCPU",
            "Mitsubishi Electric MELSEC Q series QJ71C24N(-R2/R4)",
            "Mitsubishi Electric MELSEC Q series QJ71E71-100"
        ],
        "version": "all versions",
        "component": ""
    },
    "mitreTechnicalImpacts": [
        "Bypass protection mechanism",
        "Gain privileges / assume identity"
    ]
}
