{
    "cveId": "CVE-2006-1767",
    "version": "1.0.0",
    "timestamp": "2024-12-10T17:54:04.992951+00:00",
    "description": "Multiple PHP remote file inclusion vulnerabilities in nicecoder.com INDEXU 5.0.0 and 5.0.1 allow remote attackers to execute arbitrary PHP code via a URL in the theme_path parameter in (1) index.php, (2) become_editor.php, (3) add.php, (4) bad_link.php, (5) browse.php, (6) detail.php, (7) fav.php, (8) get_rated.php, (9) login.php, (10) mailing_list.php, (11) new.php, (12) modify.php, (13) pick.php, (14) power_search.php, (15) rating.php, (16) register.php, (17) review.php, (18) rss.php, (19) search.php, (20) send_pwd.php, (21) sendmail.php, (22) tell_friend.php, (23) top_rated.php, (24) user_detail.php, and (25) user_search.php and the (26) base_path parameter in invoice.php.",
    "keyphrases": {
        "rootcause": "Multiple PHP remote file inclusion vulnerabilities",
        "weakness": "",
        "impact": "execute arbitrary PHP code",
        "vector": [
            "URL in the theme_path parameter",
            "base_path parameter"
        ],
        "attacker": "remote attackers",
        "product": "nicecoder.com INDEXU",
        "version": "5.0.0 and 5.0.1",
        "component": [
            "index.php",
            "become_editor.php",
            "add.php",
            "bad_link.php",
            "browse.php",
            "detail.php",
            "fav.php",
            "get_rated.php",
            "login.php",
            "mailing_list.php",
            "new.php",
            "modify.php",
            "pick.php",
            "power_search.php",
            "rating.php",
            "register.php",
            "review.php",
            "rss.php",
            "search.php",
            "send_pwd.php",
            "sendmail.php",
            "tell_friend.php",
            "top_rated.php",
            "user_detail.php",
            "user_search.php",
            "invoice.php"
        ]
    }
}
