{
  "cveId": "CVE-2020-1417",
  "version": "1.0.0",
  "timestamp": "2024-12-13T17:34:55.850537+00:00",
  "description": "An elevation of privilege vulnerability exists when the Windows kernel fails to properly handle objects in memory. An attacker who successfully exploited this vulnerability could run arbitrary code in kernel mode. An attacker could then install programs view, change, or delete data or create new accounts with full user rights.To exploit this vulnerability, an attacker would first have to log on to the system. An attacker could then run a specially crafted application to take control of an affected system.The update addresses the vulnerability by correcting how the Windows kernel handles objects in memory.",
  "keyphrases": {
    "rootcause": "Windows kernel fails to properly handle objects in memory",
    "weakness": "",
    "impact": [
      "change",
      "create new accounts with full user rights",
      "elevation of privilege",
      "install programs",
      "or delete data",
      "run arbitrary code in kernel mode",
      "take control of an affected system"
    ],
    "vector": "specially crafted application",
    "attacker": "attacker",
    "product": "Windows kernel",
    "version": "",
    "component": ""
  },
  "mitreTechnicalImpacts": []
}