{
    "cveId": "CVE-2011-1989",
    "version": "1.0.0",
    "timestamp": "2024-12-10T17:54:04.992951+00:00",
    "description": "Microsoft Excel 2003 SP3 and 2007 SP2 Excel in Office 2007 SP2 Excel 2010 Gold and SP1 Excel in Office 2010 Gold and SP1 Office 2004, 2008, and 2011 for Mac Open XML File Format Converter for Mac Excel Viewer SP2 Office Compatibility Pack for Word, Excel, and PowerPoint 2007 File Formats SP2 Excel Services on Office SharePoint Server 2007 SP2 Excel Services on Office SharePoint Server 2010 Gold and SP1 and Excel Web App 2010 Gold and SP1 do not properly parse conditional expressions associated with formatting requirements, which allows remote attackers to execute arbitrary code via a crafted spreadsheet, aka Excel Conditional Expression Parsing Vulnerability.",
    "keyphrases": {
        "rootcause": "improper parsing of conditional expressions",
        "weakness": "",
        "impact": "execute arbitrary code",
        "vector": "crafted spreadsheet",
        "attacker": "remote attackers",
        "product": [
            "Microsoft Excel",
            "Office Compatibility Pack for Word, Excel, and PowerPoint",
            "Office SharePoint Server",
            "Excel Web App"
        ],
        "version": [
            "2003 SP3",
            "2007 SP2",
            "2010 Gold and SP1",
            "2007 SP2",
            "2010 Gold and SP1",
            "2010 Gold and SP1"
        ],
        "component": ""
    }
}
