{
    "cveId": "CVE-2023-44450",
    "version": "1.0.0",
    "timestamp": "2024-12-06T11:32:07.789868+00:00",
    "description": "NETGEAR ProSAFE Network Management System getNodesByTopologyMapSearch SQL Injection Remote Code Execution Vulnerability. This vulnerability allows remote attackers to execute arbitrary code on affected installations of NETGEAR ProSAFE Network Management System. Authentication is required to exploit this vulnerability. The specific flaw exists within the getNodesByTopologyMapSearch function. The issue results from the lack of proper validation of a user-supplied string before using it to construct SQL queries. An attacker can leverage this vulnerability to execute code in the context of SYSTEM. Was ZDI-CAN-21858.",
    "keyphrases": {
        "rootcause": "lack of proper validation of a user-supplied string",
        "weakness": "SQL injection",
        "impact": "execute arbitrary code",
        "vector": "",
        "attacker": "remote attackers",
        "product": "NETGEAR ProSAFE Network Management System",
        "version": "",
        "component": "getNodesByTopologyMapSearch function"
    }
}
