{
    "cveId": "CVE-2018-3166",
    "version": "1.0.0",
    "timestamp": "2024-12-06T11:32:07.789868+00:00",
    "description": "Vulnerability in the Oracle Hospitality Cruise Fleet Management component of Oracle Hospitality Applications (subcomponent Emergency Response System). The supported version that is affected is 9.0. Easily exploitable vulnerability allows low privileged attacker with network access via HTTP to compromise Oracle Hospitality Cruise Fleet Management. Successful attacks of this vulnerability can result in unauthorized creation, deletion or modification access to critical data or all Oracle Hospitality Cruise Fleet Management accessible data. CVSS 3.0 Base Score 6.5 (Integrity impacts). CVSS Vector (CVSS3.0/AVN/ACL/PRL/UIN/SU/CN/IH/AN).",
    "keyphrases": {
        "rootcause": "",
        "weakness": "",
        "impact": "unauthorized creation, deletion or modification access to critical data or all Oracle Hospitality Cruise Fleet Management accessible data",
        "vector": "low privileged attacker with network access via HTTP",
        "attacker": "low privileged attacker",
        "product": "Oracle Hospitality Cruise Fleet Management",
        "version": "9.0",
        "component": "Emergency Response System"
    }
}
