{
    "cveId": "CVE-2018-3163",
    "version": "1.0.0",
    "timestamp": "2024-12-06T11:32:07.789868+00:00",
    "description": "Vulnerability in the Oracle Hospitality Cruise Fleet Management component of Oracle Hospitality Applications (subcomponent Emergency Response System). The supported version that is affected is 9.0. Easily exploitable vulnerability allows unauthenticated attacker with network access via HTTP to compromise Oracle Hospitality Cruise Fleet Management. Successful attacks of this vulnerability can result in unauthorized read access to a subset of Oracle Hospitality Cruise Fleet Management accessible data and unauthorized ability to cause a partial denial of service (partial DOS) of Oracle Hospitality Cruise Fleet Management. CVSS 3.0 Base Score 6.5 (Confidentiality and Availability impacts). CVSS Vector (CVSS3.0/AVN/ACL/PRN/UIN/SU/CL/IN/AL).",
    "keyphrases": {
        "rootcause": "",
        "weakness": "",
        "impact": [
            "unauthorized read access",
            "partial denial of service"
        ],
        "vector": "HTTP",
        "attacker": "unauthenticated attacker with network access",
        "product": "Oracle Hospitality Cruise Fleet Management",
        "version": "9.0",
        "component": "Emergency Response System"
    }
}
