{
    "cveId": "CVE-2018-3271",
    "version": "1.0.0",
    "timestamp": "2024-12-06T11:32:07.789868+00:00",
    "description": "Vulnerability in the Solaris component of Oracle Sun Systems Products Suite (subcomponent Kernel Zones). The supported version that is affected is 11.3. Difficult to exploit vulnerability allows high privileged attacker with logon to the infrastructure where Solaris executes to compromise Solaris. While the vulnerability is in Solaris, attacks may significantly impact additional products. Successful attacks of this vulnerability can result in unauthorized ability to cause a hang or frequently repeatable crash (complete DOS) of Solaris. CVSS 3.0 Base Score 5.3 (Availability impacts). CVSS Vector (CVSS3.0/AVL/ACH/PRH/UIN/SC/CN/IN/AH).",
    "keyphrases": {
        "rootcause": "",
        "weakness": "",
        "impact": "cause a hang or frequently repeatable crash (complete DOS) of Solaris",
        "vector": "",
        "attacker": "high privileged attacker with logon to the infrastructure where Solaris executes",
        "product": "Oracle Sun Systems Products Suite",
        "version": "11.3",
        "component": "Solaris component"
    }
}
