{
  "cveId": "CVE-2018-3264",
  "version": "1.0.0",
  "timestamp": "2024-12-06T11:32:07.789868+00:00",
  "description": "Vulnerability in the Solaris component of Oracle Sun Systems Products Suite (subcomponent Kernel). The supported version that is affected is 11.3. Easily exploitable vulnerability allows low privileged attacker with logon to the infrastructure where Solaris executes to compromise Solaris. Successful attacks of this vulnerability can result in unauthorized update, insert or delete access to some of Solaris accessible data and unauthorized ability to cause a partial denial of service (partial DOS) of Solaris. CVSS 3.0 Base Score 4.4 (Integrity and Availability impacts). CVSS Vector (CVSS3.0/AVL/ACL/PRL/UIN/SU/CN/IL/AL).",
  "keyphrases": {
    "rootcause": "",
    "weakness": "",
    "impact": [
      "Availability",
      "DOS",
      "insert or delete access",
      "partial denial of service",
      "unauthorized update"
    ],
    "vector": "",
    "attacker": "low privileged attacker",
    "product": "Oracle Sun Systems Products Suite",
    "version": "11.3",
    "component": "Solaris"
  },
  "mitreTechnicalImpacts": []
}