{
  "cveId": "CVE-2018-3111",
  "version": "1.0.0",
  "timestamp": "2024-12-06T11:32:07.789868+00:00",
  "description": "Vulnerability in the Oracle Retail Xstore Office component of Oracle Retail Applications (subcomponent Internal Operations). The supported version that is affected is 7.1. Easily exploitable vulnerability allows unauthenticated attacker with network access via HTTP to compromise Oracle Retail Xstore Office. Successful attacks require human interaction from a person other than the attacker. Successful attacks of this vulnerability can result in unauthorized access to critical data or complete access to all Oracle Retail Xstore Office accessible data as well as unauthorized update, insert or delete access to some of Oracle Retail Xstore Office accessible data and unauthorized ability to cause a partial denial of service (partial DOS) of Oracle Retail Xstore Office. CVSS 3.0 Base Score 7.6 (Confidentiality, Integrity and Availability impacts). CVSS Vector (CVSS3.0/AVN/ACL/PRN/UIR/SU/CH/IL/AL).",
  "keyphrases": {
    "rootcause": "",
    "weakness": "",
    "impact": [
      "Integrity and Availability impacts",
      "insert or delete access",
      "partial denial of service (partial DOS)",
      "unauthorized access to critical data",
      "unauthorized delete",
      "unauthorized insert",
      "unauthorized update"
    ],
    "vector": "network access via HTTP",
    "attacker": "unauthenticated attacker",
    "product": "Oracle Retail Xstore Office",
    "version": "7.1",
    "component": "Oracle Retail Xstore Office"
  },
  "mitreTechnicalImpacts": []
}