{
  "cveId": "CVE-2018-3060",
  "version": "1.0.0",
  "timestamp": "2024-12-06T11:32:07.789868+00:00",
  "description": "Vulnerability in the MySQL Server component of Oracle MySQL (subcomponent InnoDB). Supported versions that are affected are 5.7.22 and prior and 8.0.11 and prior. Easily exploitable vulnerability allows high privileged attacker with network access via multiple protocols to compromise MySQL Server. Successful attacks of this vulnerability can result in unauthorized creation, deletion or modification access to critical data or all MySQL Server accessible data and unauthorized ability to cause a hang or frequently repeatable crash (complete DOS) of MySQL Server. CVSS 3.0 Base Score 6.5 (Integrity and Availability impacts). CVSS Vector (CVSS3.0/AVN/ACL/PRH/UIN/SU/CN/IH/AH).",
  "keyphrases": {
    "rootcause": "",
    "weakness": "",
    "impact": [
      "Availability",
      "DOS",
      "cause a hang or frequently repeatable crash",
      "deletion or modification access to critical data or all MySQL Server accessible data",
      "unauthorized creation"
    ],
    "vector": "multiple protocols",
    "attacker": "high privileged attacker with network access",
    "product": "Oracle MySQL",
    "version": "5.7.22 and prior and 8.0.11 and prior",
    "component": "MySQL Server component"
  },
  "mitreTechnicalImpacts": []
}