{
  "cveId": "CVE-2018-3263",
  "version": "1.0.0",
  "timestamp": "2024-12-06T11:32:07.789868+00:00",
  "description": "Vulnerability in the Solaris component of Oracle Sun Systems Products Suite (subcomponent Sudo). The supported version that is affected is 11.3. Difficult to exploit vulnerability allows unauthenticated attacker with network access via multiple protocols to compromise Solaris. Successful attacks of this vulnerability can result in unauthorized update, insert or delete access to some of Solaris accessible data as well as unauthorized read access to a subset of Solaris accessible data and unauthorized ability to cause a partial denial of service (partial DOS) of Solaris. CVSS 3.0 Base Score 5.6 (Confidentiality, Integrity and Availability impacts). CVSS Vector (CVSS3.0/AVN/ACH/PRN/UIN/SU/CL/IL/AL).",
  "keyphrases": {
    "rootcause": "",
    "weakness": "",
    "impact": [
      "DOS",
      "Integrity and Availability impacts",
      "insert or delete access",
      "partial denial of service",
      "unauthorized read access",
      "unauthorized update"
    ],
    "vector": "multiple protocols",
    "attacker": "unauthenticated attacker with network access",
    "product": "Oracle Sun Systems Products Suite",
    "version": "11.3",
    "component": "Sudo"
  },
  "mitreTechnicalImpacts": []
}