{
  "cveId": "CVE-2018-3064",
  "version": "1.0.0",
  "timestamp": "2024-12-06T11:32:07.789868+00:00",
  "description": "Vulnerability in the MySQL Server component of Oracle MySQL (subcomponent InnoDB). Supported versions that are affected are 5.6.40 and prior, 5.7.22 and prior and 8.0.11 and prior. Easily exploitable vulnerability allows low privileged attacker with network access via multiple protocols to compromise MySQL Server. Successful attacks of this vulnerability can result in unauthorized ability to cause a hang or frequently repeatable crash (complete DOS) of MySQL Server as well as unauthorized update, insert or delete access to some of MySQL Server accessible data. CVSS 3.0 Base Score 7.1 (Integrity and Availability impacts). CVSS Vector (CVSS3.0/AVN/ACL/PRL/UIN/SU/CN/IL/AH).",
  "keyphrases": {
    "rootcause": "",
    "weakness": "",
    "impact": [
      "Availability",
      "DOS",
      "cause a hang or frequently repeatable crash",
      "insert or delete access to some of MySQL Server accessible data",
      "unauthorized update"
    ],
    "vector": "multiple protocols",
    "attacker": "low privileged attacker with network access",
    "product": "Oracle MySQL",
    "version": [
      "5.6.40 and prior",
      "5.7.22 and prior and 8.0.11 and prior"
    ],
    "component": "MySQL Server component"
  },
  "mitreTechnicalImpacts": []
}