{
  "cveId": "CVE-2018-3110",
  "version": "1.0.0",
  "timestamp": "2024-12-06T11:32:07.789868+00:00",
  "description": "A vulnerability was discovered in the Java VM component of Oracle Database Server. Supported versions that are affected are 11.2.0.4, 12.1.0.2, 12.2.0.1 and 18. Easily exploitable vulnerability allows low privileged attacker having Create Session privilege with network access via Oracle Net to compromise Java VM. While the vulnerability is in Java VM, attacks may significantly impact additional products. Successful attacks of this vulnerability can result in takeover of Java VM. CVSS 3.0 Base Score 9.9 (Confidentiality, Integrity and Availability impacts). CVSS Vector (CVSS3.0/AVN/ACL/PRL/UIN/SC/CH/IH/AH).",
  "keyphrases": {
    "rootcause": "",
    "weakness": "",
    "impact": [
      "Integrity and Availability impacts",
      "takeover of Java VM"
    ],
    "vector": "Oracle Net",
    "attacker": "low privileged attacker",
    "product": "Oracle Database Server",
    "version": [
      "11.2.0.4",
      "12.1.0.2",
      "12.2.0.1 and 18"
    ],
    "component": "Java VM component"
  },
  "mitreTechnicalImpacts": []
}