{
  "cveId": "CVE-2018-3311",
  "version": "1.0.0",
  "timestamp": "2024-12-06T11:32:07.789868+00:00",
  "description": "Vulnerability in the Oracle Retail Xstore Payment component of Oracle Retail Applications (subcomponent Security). The supported version that is affected is 3.3. Easily exploitable vulnerability allows unauthenticated attacker with network access via HTTP to compromise Oracle Retail Xstore Payment. Successful attacks of this vulnerability can result in unauthorized access to critical data or complete access to all Oracle Retail Xstore Payment accessible data as well as unauthorized update, insert or delete access to some of Oracle Retail Xstore Payment accessible data and unauthorized ability to cause a partial denial of service (partial DOS) of Oracle Retail Xstore Payment. CVSS 3.0 Base Score 8.6 (Confidentiality, Integrity and Availability impacts). CVSS Vector (CVSS3.0/AVN/ACL/PRN/UIN/SU/CH/IL/AL).",
  "keyphrases": {
    "rootcause": "",
    "weakness": "",
    "impact": [
      "DOS",
      "Integrity and Availability impacts",
      "insert or delete access",
      "partial denial of service",
      "unauthorized access to critical data",
      "unauthorized delete",
      "unauthorized insert",
      "unauthorized update"
    ],
    "vector": "network access via HTTP",
    "attacker": "unauthenticated attacker",
    "product": "Oracle Retail Xstore Payment",
    "version": "3.3",
    "component": ""
  },
  "mitreTechnicalImpacts": []
}