{
    "cveId": "CVE-2018-3167",
    "version": "1.0.0",
    "timestamp": "2024-12-06T11:32:07.789868+00:00",
    "description": "Vulnerability in the Application Management Pack for Oracle E-Business Suite component of Oracle E-Business Suite (subcomponent User Monitoring). Supported versions that are affected are 12.1.3, 12.2.3, 12.2.4, 12.2.5, 12.2.6 and 12.2.7. Easily exploitable vulnerability allows unauthenticated attacker with network access via HTTP to compromise Application Management Pack for Oracle E-Business Suite. Successful attacks of this vulnerability can result in unauthorized read access to a subset of Application Management Pack for Oracle E-Business Suite accessible data. CVSS 3.0 Base Score 5.3 (Confidentiality impacts). CVSS Vector (CVSS3.0/AVN/ACL/PRN/UIN/SU/CL/IN/AN).",
    "keyphrases": {
        "rootcause": "",
        "weakness": "",
        "impact": "unauthorized read access",
        "vector": "HTTP",
        "attacker": "unauthenticated attacker with network access",
        "product": "Oracle E-Business Suite",
        "version": "12.1.3, 12.2.3, 12.2.4, 12.2.5, 12.2.6 and 12.2.7",
        "component": "Application Management Pack for Oracle E-Business Suite"
    }
}
