{
  "cveId": "CVE-2018-3026",
  "version": "1.0.0",
  "timestamp": "2024-12-06T11:32:07.789868+00:00",
  "description": "Vulnerability in the Oracle Banking Payments component of Oracle Financial Services Applications (subcomponent Payments Core). Supported versions that are affected are 12.2.0, 12.3.0, 12.4.0, 12.5.0 and 14.1.0. Easily exploitable vulnerability allows low privileged attacker with network access via HTTP to compromise Oracle Banking Payments. Successful attacks require human interaction from a person other than the attacker and while the vulnerability is in Oracle Banking Payments, attacks may significantly impact additional products. Successful attacks of this vulnerability can result in unauthorized update, insert or delete access to some of Oracle Banking Payments accessible data as well as unauthorized read access to a subset of Oracle Banking Payments accessible data. CVSS 3.0 Base Score 5.4 (Confidentiality and Integrity impacts). CVSS Vector (CVSS3.0/AVN/ACL/PRL/UIR/SC/CL/IL/AN).",
  "keyphrases": {
    "rootcause": "",
    "weakness": "",
    "impact": [
      "Integrity",
      "insert or delete access",
      "unauthorized read access",
      "unauthorized update"
    ],
    "vector": "",
    "attacker": "low privileged attacker",
    "product": "Oracle Banking Payments",
    "version": [
      "12.2.0",
      "12.3.0",
      "12.4.0",
      "12.5.0",
      "14.1.0"
    ],
    "component": "Payments Core"
  },
  "mitreTechnicalImpacts": []
}