{
  "cveId": "CVE-2018-3148",
  "version": "1.0.0",
  "timestamp": "2024-12-06T11:32:07.789868+00:00",
  "description": "Vulnerability in the Primavera Unifier component of Oracle Construction and Engineering Suite (subcomponent Web Access). Supported versions that are affected are 15.1, 15.2, 16.1, 16.2, 17.1-17.12 and 18.1-18.8. Easily exploitable vulnerability allows unauthenticated attacker with network access via HTTP to compromise Primavera Unifier. Successful attacks require human interaction from a person other than the attacker and while the vulnerability is in Primavera Unifier, attacks may significantly impact additional products. Successful attacks of this vulnerability can result in unauthorized update, insert or delete access to some of Primavera Unifier accessible data as well as unauthorized read access to a subset of Primavera Unifier accessible data. CVSS 3.0 Base Score 6.1 (Confidentiality and Integrity impacts). CVSS Vector (CVSS3.0/AVN/ACL/PRN/UIR/SC/CL/IL/AN).",
  "keyphrases": {
    "rootcause": "",
    "weakness": "",
    "impact": [
      "Integrity",
      "insert or delete access",
      "unauthorized read access",
      "unauthorized update"
    ],
    "vector": "",
    "attacker": "unauthenticated attacker",
    "product": "Oracle Construction and Engineering Suite",
    "version": [
      "15.1",
      "15.2",
      "16.1",
      "16.2",
      "17.1-17.12 and 18.1-18.8"
    ],
    "component": "Primavera Unifier"
  },
  "mitreTechnicalImpacts": []
}