{
    "cveId": "CVE-2018-3059",
    "version": "1.0.0",
    "timestamp": "2024-12-06T11:32:07.789868+00:00",
    "description": "Vulnerability in the Siebel UI Framework component of Oracle Siebel CRM (subcomponent UIF Open UI). Supported versions that are affected are 18.7, 18.8 and 18.9. Easily exploitable vulnerability allows unauthenticated attacker with network access via HTTP to compromise Siebel UI Framework. Successful attacks require human interaction from a person other than the attacker and while the vulnerability is in Siebel UI Framework, attacks may significantly impact additional products. Successful attacks of this vulnerability can result in unauthorized update, insert or delete access to some of Siebel UI Framework accessible data as well as unauthorized read access to a subset of Siebel UI Framework accessible data. CVSS 3.0 Base Score 6.1 (Confidentiality and Integrity impacts). CVSS Vector (CVSS3.0/AVN/ACL/PRN/UIR/SC/CL/IL/AN).",
    "keyphrases": {
        "rootcause": "",
        "weakness": "",
        "impact": "unauthorized update, insert or delete access to some of Siebel UI Framework accessible data as well as unauthorized read access to a subset of Siebel UI Framework accessible data",
        "vector": "",
        "attacker": "unauthenticated attacker with network access via HTTP",
        "product": "Oracle Siebel CRM",
        "version": "18.7, 18.8 and 18.9",
        "component": "Siebel UI Framework component"
    }
}
