{
  "cveId": "CVE-2018-3177",
  "version": "1.0.0",
  "timestamp": "2024-12-06T11:32:07.789868+00:00",
  "description": "Vulnerability in the Hyperion Common Events component of Oracle Hyperion (subcomponent User Interface). The supported version that is affected is 11.1.2.4. Easily exploitable vulnerability allows unauthenticated attacker with network access via HTTP to compromise Hyperion Common Events. Successful attacks require human interaction from a person other than the attacker and while the vulnerability is in Hyperion Common Events, attacks may significantly impact additional products. Successful attacks of this vulnerability can result in unauthorized update, insert or delete access to some of Hyperion Common Events accessible data as well as unauthorized read access to a subset of Hyperion Common Events accessible data. CVSS 3.0 Base Score 6.1 (Confidentiality and Integrity impacts). CVSS Vector (CVSS3.0/AVN/ACL/PRN/UIR/SC/CL/IL/AN).",
  "keyphrases": {
    "rootcause": "",
    "weakness": "",
    "impact": [
      "Integrity",
      "insert or delete access",
      "unauthorized read access",
      "unauthorized update"
    ],
    "vector": "unauthenticated attacker with network access via HTTP",
    "attacker": "unauthenticated attacker",
    "product": "Oracle Hyperion",
    "version": "11.1.2.4",
    "component": "Hyperion Common Events"
  },
  "mitreTechnicalImpacts": []
}