{
    "cveId": "CVE-2018-3309",
    "version": "1.0.0",
    "timestamp": "2024-12-06T11:32:07.789868+00:00",
    "description": "Vulnerability in the Oracle VM VirtualBox component of Oracle Virtualization (subcomponent Core). The supported version that is affected is prior to 5.2.22. Easily exploitable vulnerability allows high privileged attacker with logon to the infrastructure where Oracle VM VirtualBox executes to compromise Oracle VM VirtualBox. While the vulnerability is in Oracle VM VirtualBox, attacks may significantly impact additional products. Successful attacks of this vulnerability can result in takeover of Oracle VM VirtualBox. CVSS 3.0 Base Score 8.2 (Confidentiality, Integrity and Availability impacts). CVSS Vector (CVSS3.0/AVL/ACL/PRH/UIN/SC/CH/IH/AH).",
    "keyphrases": {
        "rootcause": "",
        "weakness": "",
        "impact": "takeover of Oracle VM VirtualBox",
        "vector": "",
        "attacker": "high privileged attacker",
        "product": "Oracle VM VirtualBox",
        "version": "prior to 5.2.22",
        "component": "Core"
    }
}
