{
  "cveId": "CVE-2024-5335",
  "version": "1.0.0",
  "timestamp": "2024-12-06T11:32:07.789868+00:00",
  "description": "The Ultimate Store Kit Elementor Addons, Woocommerce Builder, EDD Builder, Elementor Store Builder, Product Grid, Product Table, Woocommerce Slider plugin is vulnerable to PHP Object Injection via deserialization of untrusted input via the _ultimate_store_kit_compare_products cookie in versions up to , and including, 1.6.4. This makes it possible for an unauthenticated attacker to inject a PHP Object. No POP chain is present in the vulnerable plugin. If a POP chain is present via an additional plugin or theme installed on the target system, it could allow the attacker or above to delete arbitrary files, retrieve sensitive data, or execute code.",
  "keyphrases": {
    "rootcause": [
      "PHP Object Injection",
      "deserialization of untrusted input"
    ],
    "weakness": "deserialization",
    "impact": [
      "Object Injection",
      "delete arbitrary files",
      "or execute code",
      "retrieve sensitive data"
    ],
    "vector": "deserialization of untrusted input",
    "attacker": "unauthenticated attacker",
    "product": [
      "Ultimate Store Kit Elementor Addons",
      "Woocommerce Builder",
      "EDD Builder",
      "Elementor Store Builder",
      "Product Grid",
      "Product Table",
      "Woocommerce Slider plugin"
    ],
    "version": "up to and including 1.6.4",
    "component": "_ultimate_store_kit_compare_products cookie"
  },
  "mitreTechnicalImpacts": []
}