{
  "cveId": "CVE-2024-5762",
  "version": "1.0.0",
  "timestamp": "2024-12-06T11:32:07.789868+00:00",
  "description": "Zen Cart findPluginAdminPage Local File Inclusion Remote Code Execution Vulnerability. This vulnerability allows remote attackers to execute arbitrary code on affected installations of Zen Cart. Authentication is not required to exploit this vulnerability. The specific flaw exists within the findPluginAdminPage function. The issue results from the lack of proper validation of user-supplied data prior to passing it to a PHP include function. An attacker can leverage this in conjunction with other vulnerabilities to execute arbitrary code in the context of the service account. Was ZDI-CAN-21408.",
  "keyphrases": {
    "rootcause": "lack of proper validation of user-supplied data",
    "weakness": "Local File Inclusion",
    "impact": [
      "execute arbitrary code",
      "remote code execution"
    ],
    "vector": "",
    "attacker": "remote attackers",
    "product": "Zen Cart",
    "version": "",
    "component": "findPluginAdminPage function"
  },
  "mitreTechnicalImpacts": []
}