{
  "cveId": "CVE-2025-5822",
  "version": "1.0.0",
  "timestamp": "2025-07-04T16:12:41.853043+00:00",
  "description": "Autel MaxiCharger AC Wallbox Commercial Technician API Incorrect Authorization Privilege Escalation Vulnerability. This vulnerability allows remote attackers to escalate privileges on affected installations of Autel MaxiCharger AC Wallbox Commercial charging stations. An attacker must first obtain a low-privileged authorization token in order to exploit this vulnerability. The specific flaw exists within the implementation of the Autel Technician API. The issue results from incorrect authorization. An attacker can leverage this vulnerability to escalate privileges to resources normally protected from the user. Was ZDI-CAN-26325.",
  "keyphrases": {
    "rootcause": "incorrect authorization",
    "weakness": "Privilege Escalation Vulnerability",
    "impact": [
      "Privilege Escalation",
      "escalate privileges"
    ],
    "vector": "",
    "attacker": "remote attackers",
    "product": "Autel MaxiCharger AC Wallbox Commercial",
    "version": "",
    "component": "Autel Technician API"
  },
  "mitreTechnicalImpacts": []
}