{
    "cveId": "CVE-2025-5405",
    "version": "1.0.0",
    "timestamp": "2025-07-04T16:12:41.853043+00:00",
    "description": "A vulnerability, which was classified as problematic, has been found in chaitak-gorai Blogbook up to 92f5cf90f8a7e6566b576fe0952e14e1c6736513. This issue affects some unknown processing of the file /post.php. The manipulation of the argument comment_author/comment_email/comment_content leads to cross site scripting. The attack may be initiated remotely. The exploit has been disclosed to the public and may be used. This product takes the approach of rolling releases to provide continious delivery. Therefore, version details for affected and updated releases are not available. The vendor was contacted early about this disclosure but did not respond in any way.",
    "keyphrases": {
        "rootcause": "",
        "weakness": "cross site scripting",
        "impact": "",
        "vector": "comment_author/comment_email/comment_content",
        "attacker": "",
        "product": "chaitak-gorai Blogbook",
        "version": "up to 92f5cf90f8a7e6566b576fe0952e14e1c6736513",
        "component": "/post.php"
    }
}
