{
    "cveId": "CVE-2025-5647",
    "version": "1.0.0",
    "timestamp": "2025-07-04T16:12:41.853043+00:00",
    "description": "A vulnerability was found in Radare2 5.9.9 and classified as problematic. This issue affects the function r_cons_context_break_pop in the library /libr/cons/cons.c of the component radiff2. The manipulation of the argument -T leads to memory corruption. The attack needs to be approached locally. The complexity of an attack is rather high. The exploitation is known to be difficult. The exploit has been disclosed to the public and may be used. The real existence of this vulnerability is still doubted at the moment. The patch is named 5705d99cc1f23f36f9a84aab26d1724010b97798. It is recommended to apply a patch to fix this issue. The documentation explains that the parameter -T is experimental and crashy. Further analysis has shown the race is not a real problem unless you use asan. A new warning has been added.",
    "keyphrases": {
        "rootcause": "",
        "weakness": "memory corruption",
        "impact": "",
        "vector": "manipulation of the argument -T",
        "attacker": "",
        "product": "Radare2",
        "version": "5.9.9",
        "component": "/libr/cons/cons.c"
    }
}
