{
    "cveId": "CVE-2024-28192",
    "version": "1.0.0",
    "timestamp": "2024-12-06T11:32:07.789868+00:00",
    "description": "your_spotify is an open source, self hosted Spotify tracking dashboard. YourSpotify version <1.8.0 is vulnerable to NoSQL injection in the public access token processing logic. Attackers can fully bypass the public token authentication mechanism, regardless if a public token has been generated before or not, without any user interaction or prerequisite knowledge. This vulnerability allows an attacker to fully bypass the public token authentication mechanism, regardless if a public token has been generated before or not, without any user interaction or prerequisite knowledge. This issue has been addressed in version 1.8.0. Users are advised to upgrade. There are no known workarounds for this vulnerability.",
    "keyphrases": {
        "rootcause": "",
        "weakness": "NoSQL injection",
        "impact": "fully bypass the public token authentication mechanism",
        "vector": "",
        "attacker": "",
        "product": "YourSpotify",
        "version": "<1.8.0",
        "component": "public access token processing logic"
    }
}
