{
    "cveId": "CVE-2019-13944",
    "version": "1.0.0",
    "timestamp": "2024-12-12T22:08:52.294043+00:00",
    "description": "A vulnerability has been identified in EN100 Ethernet module DNP3 variant (All versions), EN100 Ethernet module IEC 61850 variant (All versions < V4.37), EN100 Ethernet module IEC104 variant (All versions), EN100 Ethernet module Modbus TCP variant (All versions), EN100 Ethernet module PROFINET IO variant (All versions). A vulnerability in the integrated web server of the affected devices could allow unauthorized attackers to obtain sensitive information about the device, including logs and configurations. At the time of advisory publication no public exploitation of this security vulnerability was known.",
    "keyphrases": {
        "rootcause": "",
        "weakness": "",
        "impact": "obtain sensitive information about the device",
        "vector": "",
        "attacker": "unauthorized attackers",
        "product": "EN100 Ethernet module",
        "version": "IEC 61850 variant (All versions < V4.37)",
        "component": "integrated web server"
    }
}
