{
    "cveId": "CVE-2024-1369",
    "version": "1.0.0",
    "timestamp": "2024-12-06T11:32:07.789868+00:00",
    "description": "A command injection vulnerability was identified in GitHub Enterprise Server that allowed an attacker with an editor role in the Management Console to gain admin SSH access to the appliance when setting the username and password for collectd configurations. Exploitation of this vulnerability required access to the GitHub Enterprise Server instance and access to the Management Console with the editor role. This vulnerability affected all versions of GitHub Enterprise Server prior to 3.12 and was fixed in versions 3.11.5, 3.10.7, 3.9.10, and 3.8.15. This vulnerability was reported via the GitHub Bug Bounty program https//bounty.github.com .",
    "keyphrases": {
        "rootcause": "",
        "weakness": "command injection",
        "impact": "gain admin SSH access",
        "vector": "",
        "attacker": "attacker with an editor role",
        "product": "GitHub Enterprise Server",
        "version": "prior to 3.12",
        "component": ""
    }
}
