{
  "cveId": "CVE-2023-48365",
  "version": "1.0.0",
  "timestamp": "2024-12-17T08:36:27.567979+00:00",
  "description": "Qlik Sense Enterprise for Windows before August 2023 Patch 2 allows unauthenticated remote code execution, aka QB-21683. Due to improper validation of HTTP headers, a remote attacker is able to elevate their privilege by tunneling HTTP requests, allowing them to execute HTTP requests on the backend server that hosts the repository application. The fixed versions are August 2023 Patch 2, May 2023 Patch 6, February 2023 Patch 10, November 2022 Patch 12, August 2022 Patch 14, May 2022 Patch 16, February 2022 Patch 15, and November 2021 Patch 17. NOTE this issue exists because of an incomplete fix for CVE-2023-41265.",
  "keyphrases": {
    "rootcause": [
      "improper validation of HTTP headers",
      "incomplete fix"
    ],
    "weakness": "",
    "impact": "unauthenticated remote code execution",
    "vector": "tunneling HTTP requests",
    "attacker": "remote attacker",
    "product": "Qlik Sense Enterprise for Windows",
    "version": "before August 2023 Patch 2",
    "component": ""
  },
  "mitreTechnicalImpacts": []
}