{
  "cveId": "CVE-2023-48704",
  "version": "1.0.0",
  "timestamp": "2024-12-17T08:36:27.567979+00:00",
  "description": "ClickHouse is an open-source column-oriented database management system that allows generating analytical data reports in real-time. A heap buffer overflow issue was discovered in ClickHouse server. An attacker could send a specially crafted payload to the native interface exposed by default on port 9000/tcp, triggering a bug in the decompression logic of Gorilla codec that crashes the ClickHouse server process. This attack does not require authentication. This issue has been addressed in ClickHouse Cloud version 23.9.2.47551 and ClickHouse versions 23.10.5.20, 23.3.18.15, 23.8.8.20, and 23.9.6.20.",
  "keyphrases": {
    "rootcause": "does not require authentication",
    "weakness": "heap buffer overflow",
    "impact": "crash the ClickHouse server process",
    "vector": "specially crafted payload",
    "attacker": "",
    "product": "ClickHouse",
    "version": [
      "Cloud version 23.9.2.47551",
      "ClickHouse versions 23.10.5.20",
      "23.3.18.15",
      "23.8.8.20",
      "and 23.9.6.20"
    ],
    "component": "native interface"
  },
  "mitreTechnicalImpacts": []
}