{
    "cveId": "CVE-2016-8673",
    "version": "1.0.0",
    "timestamp": "2024-12-10T17:54:04.992951+00:00",
    "description": "A vulnerability has been identified in SIMATIC CP 343-1 Advanced (incl. SIPLUS NET variant) (All versions < V3.0.53), SIMATIC CP 443-1 Advanced (incl. SIPLUS NET variant) (All versions < V3.2.17), SIMATIC S7-300 PN/DP CPU family (incl. SIPLUS variants) (All versions), SIMATIC S7-400 PN/DP CPU family (incl. SIPLUS variants) (All versions). The integrated web server at port 80/TCP or port 443/TCP of the affected devices could allow remote attackers to perform actions with the permissions of an authenticated user, provided the targeted user has an active session and is induced to trigger the malicious request.",
    "keyphrases": {
        "rootcause": "",
        "weakness": "",
        "impact": "perform actions with the permissions of an authenticated user",
        "vector": "malicious request",
        "attacker": "remote attackers",
        "product": [
            "SIMATIC CP 343-1 Advanced",
            "SIMATIC CP 443-1 Advanced",
            "SIMATIC S7-300 PN/DP CPU family",
            "SIMATIC S7-400 PN/DP CPU family"
        ],
        "version": [
            "All versions < V3.0.53",
            "All versions < V3.2.17",
            "All versions",
            "All versions"
        ],
        "component": "integrated web server at port 80/TCP or port 443/TCP"
    }
}
