{
    "cveId": "CVE-2016-8313",
    "version": "1.0.0",
    "timestamp": "2024-12-06T11:32:07.789868+00:00",
    "description": "Vulnerability in the Oracle FLEXCUBE Private Banking component of Oracle Financial Services Applications (subcomponent Product / Instrument Search). Supported versions that are affected are 2.0.1, 2.2.0 and 12.0.1. Easily exploitable vulnerability allows low privileged attacker with network access via HTTP to compromise Oracle FLEXCUBE Private Banking. Successful attacks require human interaction from a person other than the attacker and while the vulnerability is in Oracle FLEXCUBE Private Banking, attacks may significantly impact additional products. Successful attacks of this vulnerability can result in unauthorized read access to a subset of Oracle FLEXCUBE Private Banking accessible data. CVSS v3.0 Base Score 4.1 (Confidentiality impacts).",
    "keyphrases": {
        "rootcause": "",
        "weakness": "",
        "impact": "unauthorized read access",
        "vector": "low privileged attacker with network access via HTTP",
        "attacker": "low privileged attacker",
        "product": "Oracle FLEXCUBE Private Banking",
        "version": "2.0.1, 2.2.0 and 12.0.1",
        "component": ""
    }
}
