{
    "cveId": "CVE-2016-8320",
    "version": "1.0.0",
    "timestamp": "2024-12-06T11:32:07.789868+00:00",
    "description": "Vulnerability in the Oracle FLEXCUBE Enterprise Limits and Collateral Management component of Oracle Financial Services Applications (subcomponent Core). Supported versions that are affected are 12.0.0 and 12.0.2. Easily exploitable vulnerability allows unauthenticated attacker with network access via HTTP to compromise Oracle FLEXCUBE Enterprise Limits and Collateral Management. Successful attacks require human interaction from a person other than the attacker and while the vulnerability is in Oracle FLEXCUBE Enterprise Limits and Collateral Management, attacks may significantly impact additional products. Successful attacks of this vulnerability can result in unauthorized update, insert or delete access to some of Oracle FLEXCUBE Enterprise Limits and Collateral Management accessible data as well as unauthorized read access to a subset of Oracle FLEXCUBE Enterprise Limits and Collateral Management accessible data. CVSS v3.0 Base Score 6.1 (Confidentiality and Integrity impacts).",
    "keyphrases": {
        "rootcause": "",
        "weakness": "",
        "impact": [
            "unauthorized update",
            "insert or delete access",
            "unauthorized read access"
        ],
        "vector": "",
        "attacker": "unauthenticated attacker",
        "product": "Oracle FLEXCUBE Enterprise Limits and Collateral Management",
        "version": "12.0.0 and 12.0.2",
        "component": "Core"
    }
}
