{
    "cveId": "CVE-2016-2926",
    "version": "1.0.0",
    "timestamp": "2024-12-10T17:54:04.992951+00:00",
    "description": "Cross-site scripting (XSS) vulnerability in IBM Rational Collaborative Lifecycle Management 4.0 before 4.0.7 iFix11, 5.0 before 5.0.2 iFix19, and 6.0 before 6.0.2 iFix3 Rational Quality Manager 4.0 before 4.0.7 iFix11, 5.0 before 5.0.2 iFix19, and 6.0 before 6.0.2 iFix3 Rational Team Concert 4.0 before 4.0.7 iFix11, 5.0 before 5.0.2 iFix19, and 6.0 before 6.0.2 iFix3 Rational DOORS Next Generation 4.0 before 4.0.7 iFix11, 5.0 before 5.0.2 iFix19, and 6.0 before 6.0.2 iFix3 Rational Engineering Lifecycle Manager 4.x before 4.0.7 iFix11, 5.0 before 5.0.2 iFix19, and 6.0 before 6.0.2 iFix3 Rational Rhapsody Design Manager 4.0 before 4.0.7 iFix11, 5.0 before 5.0.2 iFix19, and 6.0 before 6.0.2 iFix3 and Rational Software Architect Design Manager 4.0 before 4.0.7 iFix11, 5.0 before 5.0.2 iFix19, and 6.0 before 6.0.2 iFix3 allows remote authenticated users to inject arbitrary web script or HTML via a crafted URL.",
    "keyphrases": {
        "rootcause": "",
        "weakness": "cross-site scripting",
        "impact": "inject arbitrary web script or HTML",
        "vector": "crafted URL",
        "attacker": "remote authenticated users",
        "product": [
            "IBM Rational Collaborative Lifecycle Management",
            "Rational Quality Manager",
            "Rational Team Concert",
            "Rational DOORS Next Generation",
            "Rational Engineering Lifecycle Manager",
            "Rational Rhapsody Design Manager",
            "Rational Software Architect Design Manager"
        ],
        "version": "multiple versions before specific patches",
        "component": ""
    }
}
