{
    "cveId": "CVE-2023-21952",
    "version": "1.0.0",
    "timestamp": "2024-12-06T11:32:07.789868+00:00",
    "description": "Vulnerability in the Oracle Business Intelligence Enterprise Edition product of Oracle Analytics (component Analytics Server). The supported version that is affected is 6.4.0.0.0. Easily exploitable vulnerability allows low privileged attacker with network access via HTTP to compromise Oracle Business Intelligence Enterprise Edition. Successful attacks require human interaction from a person other than the attacker. Successful attacks of this vulnerability can result in unauthorized access to critical data or complete access to all Oracle Business Intelligence Enterprise Edition accessible data. CVSS 3.1 Base Score 5.7 (Confidentiality impacts). CVSS Vector (CVSS3.1/AVN/ACL/PRL/UIR/SU/CH/IN/AN).",
    "keyphrases": {
        "rootcause": "",
        "weakness": "",
        "impact": "unauthorized access to critical data or complete access to all Oracle Business Intelligence Enterprise Edition accessible data",
        "vector": "",
        "attacker": "low privileged attacker",
        "product": "Oracle Business Intelligence Enterprise Edition",
        "version": "6.4.0.0.0",
        "component": "Analytics Server"
    }
}
