{
    "cveId": "CVE-2023-21894",
    "version": "1.0.0",
    "timestamp": "2024-12-06T11:32:07.789868+00:00",
    "description": "Vulnerability in the Oracle Global Lifecycle Management NextGen OUI Framework product of Oracle Fusion Middleware (component NextGen Installer issues). Supported versions that are affected are Prior to 13.9.4.2.11. Easily exploitable vulnerability allows low privileged attacker with logon to the infrastructure where Oracle Global Lifecycle Management NextGen OUI Framework executes to compromise Oracle Global Lifecycle Management NextGen OUI Framework. Successful attacks require human interaction from a person other than the attacker. Successful attacks of this vulnerability can result in takeover of Oracle Global Lifecycle Management NextGen OUI Framework. CVSS 3.1 Base Score 7.3 (Confidentiality, Integrity and Availability impacts). CVSS Vector (CVSS3.1/AVL/ACL/PRL/UIR/SU/CH/IH/AH).",
    "keyphrases": {
        "rootcause": "",
        "weakness": "",
        "impact": "takeover of Oracle Global Lifecycle Management NextGen OUI Framework",
        "vector": "",
        "attacker": "low privileged attacker",
        "product": "Oracle Global Lifecycle Management NextGen OUI Framework",
        "version": "Prior to 13.9.4.2.11",
        "component": "NextGen Installer issues"
    }
}
