{
  "cveId": "CVE-2023-21921",
  "version": "1.0.0",
  "timestamp": "2024-12-06T11:32:07.789868+00:00",
  "description": "Vulnerability in the Oracle Health Sciences InForm product of Oracle Health Sciences Applications (component Core). Supported versions that are affected are Prior to 6.3.1.3 and Prior to 7.0.0.1. Easily exploitable vulnerability allows low privileged attacker with network access via HTTP to compromise Oracle Health Sciences InForm. Successful attacks of this vulnerability can result in unauthorized update, insert or delete access to some of Oracle Health Sciences InForm accessible data as well as unauthorized read access to a subset of Oracle Health Sciences InForm accessible data. CVSS 3.1 Base Score 5.4 (Confidentiality and Integrity impacts). CVSS Vector (CVSS3.1/AVN/ACL/PRL/UIN/SU/CL/IL/AN).",
  "keyphrases": {
    "rootcause": "",
    "weakness": "",
    "impact": [
      "Integrity",
      "insert or delete access to some of Oracle Health Sciences InForm accessible data as well as unauthorized read access to a subset of Oracle Health Sciences InForm accessible data",
      "unauthorized update"
    ],
    "vector": "low privileged attacker with network access via HTTP",
    "attacker": "",
    "product": "Oracle Health Sciences InForm",
    "version": "Prior to 6.3.1.3 and Prior to 7.0.0.1",
    "component": "Core"
  },
  "mitreTechnicalImpacts": []
}