{
    "cveId": "CVE-2023-21936",
    "version": "1.0.0",
    "timestamp": "2024-12-06T11:32:07.789868+00:00",
    "description": "Vulnerability in the JD Edwards EnterpriseOne Tools product of Oracle JD Edwards (component Web Runtime SEC). Supported versions that are affected are Prior to 9.2.7.3. Easily exploitable vulnerability allows low privileged attacker with network access via HTTP to compromise JD Edwards EnterpriseOne Tools. Successful attacks require human interaction from a person other than the attacker and while the vulnerability is in JD Edwards EnterpriseOne Tools, attacks may significantly impact additional products (scope change). Successful attacks of this vulnerability can result in unauthorized update, insert or delete access to some of JD Edwards EnterpriseOne Tools accessible data as well as unauthorized read access to a subset of JD Edwards EnterpriseOne Tools accessible data. CVSS 3.1 Base Score 5.4 (Confidentiality and Integrity impacts). CVSS Vector (CVSS3.1/AVN/ACL/PRL/UIR/SC/CL/IL/AN).",
    "keyphrases": {
        "rootcause": "",
        "weakness": "",
        "impact": [
            "unauthorized update",
            "insert or delete",
            "unauthorized read"
        ],
        "vector": "low privileged attacker with network access via HTTP",
        "attacker": "attacker",
        "product": "Oracle JD Edwards",
        "version": "Prior to 9.2.7.3",
        "component": "JD Edwards EnterpriseOne Tools"
    }
}
