{
    "cveId": "CVE-2023-21834",
    "version": "1.0.0",
    "timestamp": "2024-12-06T11:32:07.789868+00:00",
    "description": "Vulnerability in the Oracle Self-Service Human Resources product of Oracle E-Business Suite (component Workflow, Approval, Work Force Management). Supported versions that are affected are 12.2.3-12.2.12. Easily exploitable vulnerability allows low privileged attacker with network access via HTTP to compromise Oracle Self-Service Human Resources. Successful attacks of this vulnerability can result in unauthorized update, insert or delete access to some of Oracle Self-Service Human Resources accessible data. CVSS 3.1 Base Score 4.3 (Integrity impacts). CVSS Vector (CVSS3.1/AVN/ACL/PRL/UIN/SU/CN/IL/AN).",
    "keyphrases": {
        "rootcause": "",
        "weakness": "",
        "impact": "unauthorized update, insert or delete access",
        "vector": "",
        "attacker": "low privileged attacker",
        "product": "Oracle Self-Service Human Resources",
        "version": "12.2.3-12.2.12",
        "component": "Workflow, Approval, Work Force Management"
    }
}
