{
    "cveId": "CVE-2023-21829",
    "version": "1.0.0",
    "timestamp": "2024-12-06T11:32:07.789868+00:00",
    "description": "Vulnerability in the Oracle Database RDBMS Security component of Oracle Database Server. Supported versions that are affected are 19c and 21c. Easily exploitable vulnerability allows low privileged attacker having Create Session privilege with network access via Oracle Net to compromise Oracle Database RDBMS Security. Successful attacks require human interaction from a person other than the attacker. Successful attacks of this vulnerability can result in unauthorized creation, deletion or modification access to critical data or all Oracle Database RDBMS Security accessible data as well as unauthorized read access to a subset of Oracle Database RDBMS Security accessible data. CVSS 3.1 Base Score 6.3 (Confidentiality and Integrity impacts). CVSS Vector (CVSS3.1/AVN/ACL/PRL/UIR/SU/CL/IH/AN).",
    "keyphrases": {
        "rootcause": "",
        "weakness": "",
        "impact": "unauthorized creation, deletion or modification access to critical data",
        "vector": "having Create Session privilege with network access via Oracle Net",
        "attacker": "low privileged attacker",
        "product": "Oracle Database Server",
        "version": "19c and 21c",
        "component": "Oracle Database RDBMS Security component"
    }
}
