{
  "cveId": "CVE-2023-21845",
  "version": "1.0.0",
  "timestamp": "2024-12-06T11:32:07.789868+00:00",
  "description": "Vulnerability in the PeopleSoft Enterprise PeopleTools product of Oracle PeopleSoft (component Panel Processor). The supported version that is affected is 8.60. Easily exploitable vulnerability allows low privileged attacker with network access via HTTP to compromise PeopleSoft Enterprise PeopleTools. Successful attacks of this vulnerability can result in unauthorized update, insert or delete access to some of PeopleSoft Enterprise PeopleTools accessible data as well as unauthorized read access to a subset of PeopleSoft Enterprise PeopleTools accessible data. CVSS 3.1 Base Score 5.4 (Confidentiality and Integrity impacts). CVSS Vector (CVSS3.1/AVN/ACL/PRL/UIN/SU/CL/IL/AN).",
  "keyphrases": {
    "rootcause": "",
    "weakness": "",
    "impact": [
      "Integrity",
      "insert or delete access to some of PeopleSoft Enterprise PeopleTools accessible data as well as unauthorized read access to a subset of PeopleSoft Enterprise PeopleTools accessible data",
      "unauthorized update"
    ],
    "vector": "",
    "attacker": "low privileged attacker",
    "product": "Oracle PeopleSoft",
    "version": "8.60",
    "component": "Panel Processor"
  },
  "mitreTechnicalImpacts": []
}