{
  "cveId": "CVE-2023-21904",
  "version": "1.0.0",
  "timestamp": "2024-12-06T11:32:07.789868+00:00",
  "description": "Vulnerability in the Oracle Banking Virtual Account Management product of Oracle Financial Services Applications (component OBVAM Trn Journal Domain). Supported versions that are affected are 14.5, 14.6 and 14.7. Difficult to exploit vulnerability allows high privileged attacker with network access via HTTP to compromise Oracle Banking Virtual Account Management. Successful attacks require human interaction from a person other than the attacker. Successful attacks of this vulnerability can result in unauthorized access to critical data or complete access to all Oracle Banking Virtual Account Management accessible data as well as unauthorized update, insert or delete access to some of Oracle Banking Virtual Account Management accessible data and unauthorized ability to cause a partial denial of service (partial DOS) of Oracle Banking Virtual Account Management. CVSS 3.1 Base Score 5.3 (Confidentiality, Integrity and Availability impacts). CVSS Vector (CVSS3.1/AVN/ACH/PRH/UIR/SU/CH/IL/AL).",
  "keyphrases": {
    "rootcause": "",
    "weakness": "",
    "impact": [
      "DOS",
      "Integrity and Availability impacts",
      "complete access to all Oracle Banking Virtual Account Management accessible data",
      "insert or delete access",
      "partial denial of service",
      "unauthorized access to critical data",
      "unauthorized update"
    ],
    "vector": "high privileged attacker with network access via HTTP",
    "attacker": "",
    "product": "Oracle Banking Virtual Account Management",
    "version": [
      "14.5",
      "14.6 and 14.7"
    ],
    "component": "OBVAM Trn Journal Domain"
  },
  "mitreTechnicalImpacts": []
}