{
  "cveId": "CVE-2023-21973",
  "version": "1.0.0",
  "timestamp": "2024-12-06T11:32:07.789868+00:00",
  "description": "Vulnerability in the Oracle iProcurement product of Oracle E-Business Suite (component E-Content Manager Catalog). Supported versions that are affected are 12.2.3-12.2.12. Easily exploitable vulnerability allows low privileged attacker with network access via HTTP to compromise Oracle iProcurement. Successful attacks require human interaction from a person other than the attacker and while the vulnerability is in Oracle iProcurement, attacks may significantly impact additional products (scope change). Successful attacks of this vulnerability can result in unauthorized update, insert or delete access to some of Oracle iProcurement accessible data as well as unauthorized read access to a subset of Oracle iProcurement accessible data. CVSS 3.1 Base Score 5.4 (Confidentiality and Integrity impacts). CVSS Vector (CVSS3.1/AVN/ACL/PRL/UIR/SC/CL/IL/AN).",
  "keyphrases": {
    "rootcause": "",
    "weakness": "",
    "impact": [
      "Integrity",
      "insert or delete access to some of Oracle iProcurement accessible data as well as unauthorized read access to a subset of Oracle iProcurement accessible data",
      "unauthorized update"
    ],
    "vector": "low privileged attacker with network access via HTTP",
    "attacker": "",
    "product": "Oracle iProcurement",
    "version": "12.2.3-12.2.12",
    "component": "E-Content Manager Catalog"
  },
  "mitreTechnicalImpacts": []
}