{
    "cveId": "CVE-2023-21850",
    "version": "1.0.0",
    "timestamp": "2024-12-06T11:32:07.789868+00:00",
    "description": "Vulnerability in the Oracle Demantra Demand Management product of Oracle Supply Chain (component E-Business Collections). Supported versions that are affected are 12.1 and 12.2. Easily exploitable vulnerability allows unauthenticated attacker with network access via HTTP to compromise Oracle Demantra Demand Management. Successful attacks of this vulnerability can result in unauthorized creation, deletion or modification access to critical data or all Oracle Demantra Demand Management accessible data. CVSS 3.1 Base Score 7.5 (Integrity impacts). CVSS Vector (CVSS3.1/AVN/ACL/PRN/UIN/SU/CN/IH/AN).",
    "keyphrases": {
        "rootcause": "",
        "weakness": "",
        "impact": "unauthorized creation, deletion or modification access to critical data or all Oracle Demantra Demand Management accessible data",
        "vector": "",
        "attacker": "unauthenticated attacker",
        "product": "Oracle Demantra Demand Management",
        "version": "12.1 and 12.2",
        "component": "E-Business Collections"
    }
}
