{
    "cveId": "CVE-2017-8367",
    "version": "1.0.0",
    "timestamp": "2024-12-11T16:08:24.783251+00:00",
    "description": "Buffer overflow in Ether Software Easy MOV Converter 1.4.24, Easy DVD Creator, Easy MPEG/AVI/DIVX/WMV/RM to DVD, Easy Avi/Divx/Xvid to DVD Burner, Easy MPEG to DVD Burner, Easy WMV/ASF/ASX to DVD Burner, Easy RM RMVB to DVD Burner, Easy CD DVD Copy, MP3/AVI/MPEG/WMV/RM to Audio CD Burner, MP3/WAV/OGG/WMA/AC3 to CD Burner, MP3 WAV to CD Burner, My Video Converter, Easy AVI DivX Converter, Easy Video to iPod Converter, Easy Video to PSP Converter, Easy Video to 3GP Converter, Easy Video to MP4 Converter, and Easy Video to iPod/MP4/PSP/3GP Converter allows local attackers to cause a denial of service (SEH overwrite) or possibly have unspecified other impact via a long username.",
    "keyphrases": {
        "rootcause": "",
        "weakness": "buffer overflow",
        "impact": "denial of service (SEH overwrite)",
        "vector": "long username",
        "attacker": "local attackers",
        "product": "Ether Software Easy MOV Converter",
        "version": "1.4.24",
        "component": ""
    }
}
