{
    "cveId": "CVE-2022-21354",
    "version": "1.0.0",
    "timestamp": "2024-12-06T11:32:07.789868+00:00",
    "description": "Vulnerability in the Oracle iStore product of Oracle E-Business Suite (component User Interface). Supported versions that are affected are 12.2.3-12.2.11. Easily exploitable vulnerability allows unauthenticated attacker with network access via HTTP to compromise Oracle iStore. Successful attacks require human interaction from a person other than the attacker and while the vulnerability is in Oracle iStore, attacks may significantly impact additional products. Successful attacks of this vulnerability can result in unauthorized update, insert or delete access to some of Oracle iStore accessible data as well as unauthorized read access to a subset of Oracle iStore accessible data. CVSS 3.1 Base Score 6.1 (Confidentiality and Integrity impacts). CVSS Vector (CVSS3.1/AVN/ACL/PRN/UIR/SC/CL/IL/AN).",
    "keyphrases": {
        "rootcause": "",
        "weakness": "",
        "impact": [
            "unauthorized update",
            "insert or delete",
            "unauthorized read"
        ],
        "vector": "HTTP",
        "attacker": "unauthenticated attacker",
        "product": "Oracle E-Business Suite",
        "version": "12.2.3-12.2.11",
        "component": "Oracle iStore"
    }
}
