{
    "cveId": "CVE-2022-21583",
    "version": "1.0.0",
    "timestamp": "2024-12-06T11:32:07.789868+00:00",
    "description": "Vulnerability in the Oracle Banking Trade Finance product of Oracle Financial Services Applications (component Infrastructure). The supported version that is affected is 14.5. Difficult to exploit vulnerability allows low privileged attacker with network access via HTTP to compromise Oracle Banking Trade Finance. Successful attacks of this vulnerability can result in unauthorized access to critical data or complete access to all Oracle Banking Trade Finance accessible data as well as unauthorized update, insert or delete access to some of Oracle Banking Trade Finance accessible data and unauthorized ability to cause a partial denial of service (partial DOS) of Oracle Banking Trade Finance. CVSS 3.1 Base Score 6.4 (Confidentiality, Integrity and Availability impacts). CVSS Vector (CVSS3.1/AVN/ACH/PRL/UIN/SU/CH/IL/AL).",
    "keyphrases": {
        "rootcause": "",
        "weakness": "Difficult to exploit",
        "impact": "unauthorized access to critical data, complete access to all Oracle Banking Trade Finance accessible data, unauthorized update, insert or delete access, partial denial of service",
        "vector": "low privileged attacker with network access via HTTP",
        "attacker": "low privileged attacker",
        "product": "Oracle Banking Trade Finance",
        "version": "14.5",
        "component": "Infrastructure"
    }
}
