{
  "cveId": "CVE-2022-21368",
  "version": "1.0.0",
  "timestamp": "2024-12-06T11:32:07.789868+00:00",
  "description": "Vulnerability in the MySQL Server product of Oracle MySQL (component Server Components Services). Supported versions that are affected are 8.0.27 and prior. Easily exploitable vulnerability allows high privileged attacker with network access via multiple protocols to compromise MySQL Server. Successful attacks of this vulnerability can result in unauthorized update, insert or delete access to some of MySQL Server accessible data as well as unauthorized read access to a subset of MySQL Server accessible data and unauthorized ability to cause a partial denial of service (partial DOS) of MySQL Server. CVSS 3.1 Base Score 4.7 (Confidentiality, Integrity and Availability impacts). CVSS Vector (CVSS3.1/AVN/ACL/PRH/UIN/SU/CL/IL/AL).",
  "keyphrases": {
    "rootcause": "",
    "weakness": "",
    "impact": [
      "DOS",
      "Integrity and Availability impacts",
      "insert or delete access to some of MySQL Server accessible data",
      "unauthorized partial denial of service",
      "unauthorized read access to a subset of MySQL Server accessible data",
      "unauthorized update"
    ],
    "vector": "multiple protocols",
    "attacker": "high privileged attacker with network access",
    "product": "MySQL Server",
    "version": "8.0.27 and prior",
    "component": "Server Components Services"
  },
  "mitreTechnicalImpacts": []
}