{
    "cveId": "CVE-2022-21548",
    "version": "1.0.0",
    "timestamp": "2024-12-06T11:32:07.789868+00:00",
    "description": "Vulnerability in the Oracle WebLogic Server product of Oracle Fusion Middleware (component Core). Supported versions that are affected are 12.2.1.3.0, 12.2.1.4.0 and 14.1.1.0.0. Easily exploitable vulnerability allows unauthenticated attacker with network access via T3, IIOP to compromise Oracle WebLogic Server. Successful attacks of this vulnerability can result in unauthorized update, insert or delete access to some of Oracle WebLogic Server accessible data and unauthorized ability to cause a partial denial of service (partial DOS) of Oracle WebLogic Server. CVSS 3.1 Base Score 6.5 (Integrity and Availability impacts). CVSS Vector (CVSS3.1/AVN/ACL/PRN/UIN/SU/CN/IL/AL).",
    "keyphrases": {
        "rootcause": "",
        "weakness": "",
        "impact": "unauthorized update, insert or delete access to some of Oracle WebLogic Server accessible data and unauthorized ability to cause a partial denial of service (partial DOS)",
        "vector": "network access via T3, IIOP",
        "attacker": "unauthenticated attacker",
        "product": "Oracle WebLogic Server",
        "version": "12.2.1.3.0, 12.2.1.4.0 and 14.1.1.0.0",
        "component": "Core"
    }
}
