{
  "cveId": "CVE-2022-21318",
  "version": "1.0.0",
  "timestamp": "2024-12-06T11:32:07.789868+00:00",
  "description": "Vulnerability in the MySQL Cluster product of Oracle MySQL (component Cluster General). Supported versions that are affected are 7.6.20 and prior and 8.0.27 and prior. Difficult to exploit vulnerability allows high privileged attacker with logon to the infrastructure where MySQL Cluster executes to compromise MySQL Cluster. Successful attacks require human interaction from a person other than the attacker. Successful attacks of this vulnerability can result in takeover of MySQL Cluster. CVSS 3.1 Base Score 6.3 (Confidentiality, Integrity and Availability impacts). CVSS Vector (CVSS3.1/AVL/ACH/PRH/UIR/SU/CH/IH/AH).",
  "keyphrases": {
    "rootcause": "",
    "weakness": "",
    "impact": [
      "Integrity and Availability impacts",
      "takeover of MySQL Cluster"
    ],
    "vector": "",
    "attacker": "high privileged attacker",
    "product": "MySQL Cluster",
    "version": "7.6.20 and prior and 8.0.27 and prior",
    "component": "Cluster General"
  },
  "mitreTechnicalImpacts": []
}