{
    "cveId": "CVE-2022-21518",
    "version": "1.0.0",
    "timestamp": "2024-12-06T11:32:07.789868+00:00",
    "description": "Vulnerability in the Oracle Health Sciences Data Management Workbench product of Oracle Health Sciences Applications (component User Interface). Supported versions that are affected are 2.4.8.7 and 2.5.2.1. Easily exploitable vulnerability allows low privileged attacker with network access via HTTP to compromise Oracle Health Sciences Data Management Workbench. Successful attacks of this vulnerability can result in unauthorized access to critical data or complete access to all Oracle Health Sciences Data Management Workbench accessible data. CVSS 3.1 Base Score 6.5 (Confidentiality impacts). CVSS Vector (CVSS3.1/AVN/ACL/PRL/UIN/SU/CH/IN/AN).",
    "keyphrases": {
        "rootcause": "",
        "weakness": "",
        "impact": [
            "unauthorized access to critical data",
            "complete access to all Oracle Health Sciences Data Management Workbench accessible data"
        ],
        "vector": "",
        "attacker": "low privileged attacker with network access via HTTP",
        "product": "Oracle Health Sciences Data Management Workbench",
        "version": "2.4.8.7 and 2.5.2.1",
        "component": "User Interface"
    }
}
