{
  "cveId": "CVE-2022-21390",
  "version": "1.0.0",
  "timestamp": "2024-12-06T11:32:07.789868+00:00",
  "description": "Vulnerability in the Oracle Communications Billing and Revenue Management product of Oracle Communications Applications (component Webservices Manager). Supported versions that are affected are 12.0.0.3 and 12.0.0.4. Easily exploitable vulnerability allows unauthenticated attacker with network access via HTTP to compromise Oracle Communications Billing and Revenue Management. While the vulnerability is in Oracle Communications Billing and Revenue Management, attacks may significantly impact additional products. Successful attacks of this vulnerability can result in takeover of Oracle Communications Billing and Revenue Management. CVSS 3.1 Base Score 10.0 (Confidentiality, Integrity and Availability impacts). CVSS Vector (CVSS3.1/AVN/ACL/PRN/UIN/SC/CH/IH/AH).",
  "keyphrases": {
    "rootcause": "",
    "weakness": "",
    "impact": [
      "Integrity and Availability impacts",
      "takeover of Oracle Communications Billing and Revenue Management"
    ],
    "vector": "",
    "attacker": "unauthenticated attacker with network access via HTTP",
    "product": "Oracle Communications Billing and Revenue Management",
    "version": "12.0.0.3 and 12.0.0.4",
    "component": "Webservices Manager"
  },
  "mitreTechnicalImpacts": []
}