{
  "cveId": "CVE-2022-21351",
  "version": "1.0.0",
  "timestamp": "2024-12-06T11:32:07.789868+00:00",
  "description": "Vulnerability in the MySQL Server product of Oracle MySQL (component Server Optimizer). Supported versions that are affected are 8.0.27 and prior. Easily exploitable vulnerability allows low privileged attacker with network access via multiple protocols to compromise MySQL Server. Successful attacks of this vulnerability can result in unauthorized ability to cause a hang or frequently repeatable crash (complete DOS) of MySQL Server as well as unauthorized update, insert or delete access to some of MySQL Server accessible data. CVSS 3.1 Base Score 7.1 (Integrity and Availability impacts). CVSS Vector (CVSS3.1/AVN/ACL/PRL/UIN/SU/CN/IL/AH).",
  "keyphrases": {
    "rootcause": "",
    "weakness": "",
    "impact": [
      "Availability",
      "cause a hang or frequently repeatable crash (complete DOS) of MySQL Server",
      "insert or delete access to some of MySQL Server accessible data",
      "unauthorized update"
    ],
    "vector": "",
    "attacker": "low privileged attacker",
    "product": "MySQL Server",
    "version": "8.0.27 and prior",
    "component": "Server Optimizer"
  },
  "mitreTechnicalImpacts": []
}