{
    "cveId": "CVE-2022-21442",
    "version": "1.0.0",
    "timestamp": "2024-12-06T11:32:07.789868+00:00",
    "description": "Vulnerability in Oracle GoldenGate (component OGG Core Library). The supported version that is affected is Prior to 23.1. Easily exploitable vulnerability allows low privileged attacker with logon to the infrastructure where Oracle GoldenGate executes to compromise Oracle GoldenGate. While the vulnerability is in Oracle GoldenGate, attacks may significantly impact additional products (scope change). Successful attacks of this vulnerability can result in takeover of Oracle GoldenGate. CVSS 3.1 Base Score 8.8 (Confidentiality, Integrity and Availability impacts). CVSS Vector (CVSS3.1/AVL/ACL/PRL/UIN/SC/CH/IH/AH).",
    "keyphrases": {
        "rootcause": "",
        "weakness": "",
        "impact": "takeover of Oracle GoldenGate",
        "vector": "",
        "attacker": "low privileged attacker with logon",
        "product": "Oracle GoldenGate",
        "version": "Prior to 23.1",
        "component": "OGG Core Library"
    }
}
