{
    "cveId": "CVE-2022-21573",
    "version": "1.0.0",
    "timestamp": "2024-12-06T11:32:07.789868+00:00",
    "description": "Vulnerability in the Oracle Communications Billing and Revenue Management product of Oracle Communications Applications (component Billing Care). Supported versions that are affected are 12.0.0.4.0-12.0.0.6.0. Easily exploitable vulnerability allows low privileged attacker with network access via HTTP to compromise Oracle Communications Billing and Revenue Management. Successful attacks of this vulnerability can result in unauthorized ability to cause a hang or frequently repeatable crash (complete DOS) of Oracle Communications Billing and Revenue Management. CVSS 3.1 Base Score 6.5 (Availability impacts). CVSS Vector (CVSS3.1/AVN/ACL/PRL/UIN/SU/CN/IN/AH).",
    "keyphrases": {
        "rootcause": "",
        "weakness": "",
        "impact": "cause a hang or frequently repeatable crash (complete DOS)",
        "vector": "",
        "attacker": "low privileged attacker",
        "product": "Oracle Communications Billing and Revenue Management",
        "version": "12.0.0.4.0-12.0.0.6.0",
        "component": "Billing Care"
    }
}
