{
    "cveId": "CVE-2007-4588",
    "version": "1.0.0",
    "timestamp": "2024-12-10T17:54:04.992951+00:00",
    "description": "Multiple cross-site scripting (XSS) vulnerabilities in InterWorx Hosting Control Panel (InterWorx-CP) Server Admin Level (NodeWorx) 3.0.2 (1) allow remote attackers to inject arbitrary web script or HTML via the PATH_INFO to index.php and allow remote authenticated users to inject arbitrary web script or HTML via the PATH_INFO to (2) nodeworx.php, (3) users.php, (4) lang.php, (5) themes.php, (6) setup.php, (7) siteworx.php, (8) packages.php, (9) backup.php, (10) import.php, (11) scriptworx.php, (12) resellers.php, (13) reseller-packages.php, (14) http.php, (15) mail.php, (16) ftp.php, (17) mysql.php, (18) sshd.php, (19) nfs.php, (20) cron.php, (21) ip.php, (22) firewall.php, (23) updates.php, (24) rrd.php, or (25) cluster.php.",
    "keyphrases": {
        "rootcause": "cross-site scripting",
        "weakness": "",
        "impact": "inject arbitrary web script or HTML",
        "vector": "PATH_INFO",
        "attacker": "remote attackers",
        "product": "InterWorx Hosting Control Panel (InterWorx-CP) Server Admin Level (NodeWorx)",
        "version": "3.0.2",
        "component": [
            "index.php",
            "nodeworx.php",
            "users.php",
            "lang.php",
            "themes.php",
            "setup.php",
            "siteworx.php",
            "packages.php",
            "backup.php",
            "import.php",
            "scriptworx.php",
            "resellers.php",
            "reseller-packages.php",
            "http.php",
            "mail.php",
            "ftp.php",
            "mysql.php",
            "sshd.php",
            "nfs.php",
            "cron.php",
            "ip.php",
            "firewall.php",
            "updates.php",
            "rrd.php",
            "cluster.php"
        ]
    }
}
